Workbook

Sheet Disclaimer
B4: ="Project: "&Cockpit!C4 -> Project: Template
B6: Status: Working Draft
B9: Databook Financial Due Diligence
B11: BakerTilly, #city#date#
B14: Disclaimer: This Databook is confidential and has been prepared exclusively for the benefit of the Client in connection with the Transaction and may not be disclosed, quoted, used or relied on for any other purpose or by any other party than the Client without the prior written consent of BT. This Databook is made available to the Client and we consent to the disclosure, provided that the client agress to non-reliance of this work-in-progress databook. Compensation claims of the Purchaser against BT for damages caused by negligence in connection with performance of the assignment are limited to EUR 4.000.000 (in words: Euro four million) for each damage event and for all damage events in total.

Sheet Cockpit
B3: Table labels | G3: =user input -> #VALUE!
B4: Project name | C4: Template
B5: Currency base code | C5: EUR | G5: =technische hilfszelle --> nicht löschen -> #VALUE!
B7: Quelle: | C7: Datenraum/ eigene Analysen
B8: Source: | C8: Virtual Data Room/ Company Information
B10: Working Group
B11: Partner
B12: Manager
B13: Senior/Assistant
B16: Timeline parameter
B17: End of first historical period | C17: 44926
B18: Number of historical periods | C18: 3
B19: Label | C19: IST | D19: Adjust according to language(DEU/ ENG)
B21: CYT Begin Date | C21: 45658 | D21: =IF(C21<(EDATE(C17,24)),"CYT Begin Date must not be prior to historical date","ok") -> ok
B22: CYT Date | C22: 45808 | D22: =IF(TEXT($C$22,"TT.MM.")="31.12.","CYT date must not be December 31, check","ok") -> ok
B23: Label (Last twelve months) | C23: LTM
B24: Label (Current year trading) | C24: YTD
B25: Label (Year to go) | C25: YTG
B27: Label | C27: Plan
B31: Timeline (annual for PL and CF)
B32: Counter | D32: 1 | E32: =D32+1 -> 2 | F32: =E32+1 -> 3 | G32: =F32+1 -> 4 | H32: =G32+1 -> 5 | I32: =H32+1 -> 6 | J32: =I32+1 -> 7 | K32: =J32+1 -> 8 | L32: =K32+1 -> 9
B33: Date (Auto) | C33: =EDATE($C$17,-12) -> 44561 | D33: =IF(D$32<$C$18+1,EDATE($C$33,12*D$32),IF(OR(D$32=$C$18+1,D$32=$C$18+2),$C$22,IF(D$32>$C$18+2,EDATE($C$33,(D$32-2)*12)))) -> 44926 | E33: =IF(E$32<$C$18+1,EDATE($C$33,12*E$32),IF(OR(E$32=$C$18+1,E$32=$C$18+2),$C$22,IF(E$32>$C$18+2,EDATE($C$33,(E$32-2)*12)))) -> 45291 | F33: =IF(F$32<$C$18+1,EDATE($C$33,12*F$32),IF(OR(F$32=$C$18+1,F$32=$C$18+2),$C$22,IF(F$32>$C$18+2,EDATE($C$33,(F$32-2)*12)))) -> 45657 | G33: =IF(G$32<$C$18+1,EDATE($C$33,12*G$32),IF(OR(G$32=$C$18+1,G$32=$C$18+2),$C$22,IF(G$32>$C$18+2,EDATE($C$33,(G$32-2)*12)))) -> 45808 | H33: =IF(H$32<$C$18+1,EDATE($C$33,12*H$32),IF(OR(H$32=$C$18+1,H$32=$C$18+2),$C$22,IF(H$32>$C$18+2,EDATE($C$33,(H$32-2)*12)))) -> 45808 | I33: =IF(I$32<$C$18+1,EDATE($C$33,12*I$32),IF(OR(I$32=$C$18+1,I$32=$C$18+2),$C$22,IF(I$32>$C$18+2,EDATE($C$33,(I$32-2)*12)))) -> 46022 | J33: =IF(J$32<$C$18+1,EDATE($C$33,12*J$32),IF(OR(J$32=$C$18+1,J$32=$C$18+2),$C$22,IF(J$32>$C$18+2,EDATE($C$33,(J$32-2)*12)))) -> 46387 | K33: =IF(K$32<$C$18+1,EDATE($C$33,12*K$32),IF(OR(K$32=$C$18+1,K$32=$C$18+2),$C$22,IF(K$32>$C$18+2,EDATE($C$33,(K$32-2)*12)))) -> 46752 | L33: =IF(L$32<$C$18+1,EDATE($C$33,12*L$32),IF(OR(L$32=$C$18+1,L$32=$C$18+2),$C$22,IF(L$32>$C$18+2,EDATE($C$33,(L$32-2)*12)))) -> 47118
B34: Label | C34: =$C$19 -> IST | D34: =IF(D$32<=$C$18,$C$19,IF(D$32=$C$18+1,$C$23,IF(D$32=$C$18+2,$C$24,$C$27))) -> IST | E34: =IF(E$32<=$C$18,$C$19,IF(E$32=$C$18+1,$C$23,IF(E$32=$C$18+2,$C$24,$C$27))) -> IST | F34: =IF(F$32<=$C$18,$C$19,IF(F$32=$C$18+1,$C$23,IF(F$32=$C$18+2,$C$24,$C$27))) -> IST | G34: =IF(G$32<=$C$18,$C$19,IF(G$32=$C$18+1,$C$23,IF(G$32=$C$18+2,$C$24,$C$27))) -> LTM | H34: =IF(H$32<=$C$18,$C$19,IF(H$32=$C$18+1,$C$23,IF(H$32=$C$18+2,$C$24,$C$27))) -> YTD | I34: =IF(I$32<=$C$18,$C$19,IF(I$32=$C$18+1,$C$23,IF(I$32=$C$18+2,$C$24,$C$27))) -> Plan | J34: =IF(J$32<=$C$18,$C$19,IF(J$32=$C$18+1,$C$23,IF(J$32=$C$18+2,$C$24,$C$27))) -> Plan | K34: =IF(K$32<=$C$18,$C$19,IF(K$32=$C$18+1,$C$23,IF(K$32=$C$18+2,$C$24,$C$27))) -> Plan | L34: =IF(L$32<=$C$18,$C$19,IF(L$32=$C$18+1,$C$23,IF(L$32=$C$18+2,$C$24,$C$27))) -> Plan
B37: Timeline (annual for BS)
B38: Counter | D38: 1 | E38: =D38+1 -> 2 | F38: =E38+1 -> 3 | G38: =F38+1 -> 4 | H38: =G38+1 -> 5 | I38: =H38+1 -> 6 | J38: =I38+1 -> 7 | K38: =J38+1 -> 8
B39: Date | C39: =EDATE($C$17,-12) -> 44561 | D39: =IF(D$38<$C$18+1,EDATE($C$39,12*D$38),IF(D$38=$C$18+1,$C$22,IF(D$38>$C$18+1,EDATE($C$39,(D$38-1)*12)))) -> 44926 | E39: =IF(E$38<$C$18+1,EDATE($C$39,12*E$38),IF(E$38=$C$18+1,$C$22,IF(E$38>$C$18+1,EDATE($C$39,(E$38-1)*12)))) -> 45291 | F39: =IF(F$38<$C$18+1,EDATE($C$39,12*F$38),IF(F$38=$C$18+1,$C$22,IF(F$38>$C$18+1,EDATE($C$39,(F$38-1)*12)))) -> 45657 | G39: =IF(G$38<$C$18+1,EDATE($C$39,12*G$38),IF(G$38=$C$18+1,$C$22,IF(G$38>$C$18+1,EDATE($C$39,(G$38-1)*12)))) -> 45808 | H39: =IF(H$38<$C$18+1,EDATE($C$39,12*H$38),IF(H$38=$C$18+1,$C$22,IF(H$38>$C$18+1,EDATE($C$39,(H$38-1)*12)))) -> 46022 | I39: =IF(I$38<$C$18+1,EDATE($C$39,12*I$38),IF(I$38=$C$18+1,$C$22,IF(I$38>$C$18+1,EDATE($C$39,(I$38-1)*12)))) -> 46387 | J39: =IF(J$38<$C$18+1,EDATE($C$39,12*J$38),IF(J$38=$C$18+1,$C$22,IF(J$38>$C$18+1,EDATE($C$39,(J$38-1)*12)))) -> 46752 | K39: =IF(K$38<$C$18+1,EDATE($C$39,12*K$38),IF(K$38=$C$18+1,$C$22,IF(K$38>$C$18+1,EDATE($C$39,(K$38-1)*12)))) -> 47118
B40: Label | C40: =$C$19 -> IST | D40: =IF(D$38<=$C$18,$C$19,IF(D$38=$C$18+1,$C$19,$C$27)) -> IST | E40: =IF(E$38<=$C$18,$C$19,IF(E$38=$C$18+1,$C$19,$C$27)) -> IST | F40: =IF(F$38<=$C$18,$C$19,IF(F$38=$C$18+1,$C$19,$C$27)) -> IST | G40: =IF(G$38<=$C$18,$C$19,IF(G$38=$C$18+1,$C$19,$C$27)) -> IST | H40: =IF(H$38<=$C$18,$C$19,IF(H$38=$C$18+1,$C$19,$C$27)) -> Plan | I40: =IF(I$38<=$C$18,$C$19,IF(I$38=$C$18+1,$C$19,$C$27)) -> Plan | J40: =IF(J$38<=$C$18,$C$19,IF(J$38=$C$18+1,$C$19,$C$27)) -> Plan | K40: =IF(K$38<=$C$18,$C$19,IF(K$38=$C$18+1,$C$19,$C$27)) -> Plan
B43: Timeline (monthly)
B44: Counter | D44: 1 | E44: =D44+1 -> 2 | F44: =E44+1 -> 3 | G44: =F44+1 -> 4 | H44: =G44+1 -> 5 | I44: =H44+1 -> 6 | J44: =I44+1 -> 7 | K44: =J44+1 -> 8 | L44: =K44+1 -> 9 | ... CI44: =CH44+1 -> 84
B45: Date | C45: =EDATE($C$17,-12) -> 44561 | D45: =EDATE($C$45,D$44) -> 44592 | E45: =EDATE($C$45,E$44) -> 44620 | F45: =EDATE($C$45,F$44) -> 44651 | G45: =EDATE($C$45,G$44) -> 44681 | H45: =EDATE($C$45,H$44) -> 44712 | I45: =EDATE($C$45,I$44) -> 44742 | J45: =EDATE($C$45,J$44) -> 44773 | K45: =EDATE($C$45,K$44) -> 44804 | ... CI45: =EDATE($C$45,CI$44) -> 47118
B46: Label | C46: =$C$19 -> IST | D46: =IF(D$45<=$C$22,$C$19,$C$27) -> IST | E46: =IF(E$45<=$C$22,$C$19,$C$27) -> IST | F46: =IF(F$45<=$C$22,$C$19,$C$27) -> IST | G46: =IF(G$45<=$C$22,$C$19,$C$27) -> IST | H46: =IF(H$45<=$C$22,$C$19,$C$27) -> IST | I46: =IF(I$45<=$C$22,$C$19,$C$27) -> IST | J46: =IF(J$45<=$C$22,$C$19,$C$27) -> IST | K46: =IF(K$45<=$C$22,$C$19,$C$27) -> IST | ... CI46: =IF(CI$45<=$C$22,$C$19,$C$27) -> Plan

Sheet Mastersheet
A1: Konto | B1: Bezeichnung | C1: Klasse | D1: NA-Zeile | E1: Review | F1: P1 | G1: P2 | H1: P3 | I1: P4 | J1: P5 | K1: P6 | L1: P7 | M1: P8 | N1: P9 | O1: P10
B2: <Mastersheet wird je Mandat aus der SuSa befuellt. Spalten F bis O sind die Perioden in EUR.>

Sheet Datengrundlage
B2: Deutsch: | F2: Manuell Anpassen | H2: Englisch: | L2: Manuell Anpassen
B3: =Cockpit!$C$4 -> Template | C3: =Cockpit!D33 -> 44926 | D3: =Cockpit!E33 -> 45291 | E3: =Cockpit!F33 -> 45657 | F3: YTD Jan23 | H3: =Cockpit!$C$4 -> Template | I3: =Cockpit!D33 -> 44926 | J3: =Cockpit!E33 -> 45291 | K3: =Cockpit!F33 -> 45657 | L3: YTD Jan23
B6: Entity 1 | H6: Entity 1 | M6: Manuell Anpassen
B7: Jahresabschlüsse (ungeprüft) | C7: ja | D7: ja | E7: ja | F7: - | H7: Annual reports (unaudited) | I7: yes | J7: yes | K7: yes | L7: - | M7: Manuell Anpassen
B8: Summen- und Saldenlisten (SuSas) - monatlich | C8: ja | D8: ja | E8: ja | F8: ja | H8: Monthly trial balances | I8: yes | J8: yes | K8: yes | L8: yes
B9: Betriebswirtschaftliche Auswertungen (BWAs) - monatlich | C9: ja | D9: ja | E9: ja | F9: ja | H9: Revenue data and selected KPIs | I9: yes | J9: yes | K9: yes | L9: yes
B10: Umsatzdaten und ausgewählte KPIs | C10: ja | D10: ja | E10: ja | F10: ja | H10: Detailed analyes and managerial accounting reports | I10: - | J10: - | K10: - | L10: -
B11: Detailaufrisse und Controlling-/ERP-Auswertungen | C11: - | D11: - | E11: - | F11: - | H11: Further details on selected topics | J11: yes
B12: Weitere Auskünfte zu ausgewählten Sachverhalten | D12: ja
B14: Entity 2 | H14: Entity 2 | M14: Manuell Anpassen
B15: Jahresabschlüsse (ungeprüft) | C15: ja | D15: ja | E15: ja | F15: - | H15: Annual reports (unaudited) | I15: yes | J15: yes | K15: yes | L15: -
B16: Summen- und Saldenlisten (SuSas) - monatlich | C16: ja | D16: ja | E16: ja | F16: ja | H16: Monthly trial balances | I16: yes | J16: yes | K16: yes | L16: yes
B17: Betriebswirtschaftliche Auswertungen (BWAs) - monatlich | C17: ja | D17: ja | E17: ja | F17: ja | H17: Revenue data and selected KPIs | I17: yes | J17: yes | K17: yes | L17: yes
B18: Umsatzdaten und ausgewählte KPIs | C18: ja | D18: ja | E18: ja | F18: ja | H18: Detailed analyes and managerial accounting reports | I18: - | J18: - | K18: - | L18: -
B19: Detailaufrisse und Controlling-/ERP-Auswertungen | C19: - | D19: - | E19: - | F19: - | H19: Further details on selected topics | J19: yes
B20: Weitere Auskünfte zu ausgewählten Sachverhalten | D20: ja
B22: Entity 3 | H22: Entity 3 | M22: Manuell Anpassen
B23: Jahresabschlüsse (ungeprüft) | C23: ja | D23: ja | E23: ja | F23: - | H23: Annual reports (unaudited) | I23: yes | J23: yes | K23: yes | L23: -
B24: Summen- und Saldenlisten (SuSas) - monatlich | C24: ja | D24: ja | E24: ja | F24: ja | H24: Monthly trial balances | I24: yes | J24: yes | K24: yes | L24: yes
B25: Betriebswirtschaftliche Auswertungen (BWAs) - monatlich | C25: ja | D25: ja | E25: ja | F25: ja | H25: Revenue data and selected KPIs | I25: yes | J25: yes | K25: yes | L25: yes
B26: Umsatzdaten und ausgewählte KPIs | C26: ja | D26: ja | E26: ja | F26: ja | H26: Detailed analyes and managerial accounting reports | I26: - | J26: - | K26: - | L26: -
B27: Detailaufrisse und Controlling-/ERP-Auswertungen | C27: - | D27: - | E27: - | F27: - | H27: Further details on selected topics | J27: yes
B28: Weitere Auskünfte zu ausgewählten Sachverhalten | D28: ja
B30: Entity 4 | H30: Entity 4 | M30: Manuell Anpassen
B31: Jahresabschlüsse (ungeprüft) | C31: ja | D31: ja | E31: ja | F31: - | H31: Annual reports (unaudited) | I31: yes | J31: yes | K31: yes | L31: -
B32: Summen- und Saldenlisten (SuSas) - monatlich | C32: ja | D32: ja | E32: ja | F32: ja | H32: Monthly trial balances | I32: yes | J32: yes | K32: yes | L32: yes
B33: Betriebswirtschaftliche Auswertungen (BWAs) - monatlich | C33: ja | D33: ja | E33: ja | F33: ja | H33: Revenue data and selected KPIs | I33: yes | J33: yes | K33: yes | L33: yes
B34: Umsatzdaten und ausgewählte KPIs | C34: ja | D34: ja | E34: ja | F34: ja | H34: Detailed analyes and managerial accounting reports | I34: - | J34: - | K34: - | L34: -
B35: Detailaufrisse und Controlling-/ERP-Auswertungen | C35: - | D35: - | E35: - | F35: - | H35: Further details on selected topics | J35: yes
B36: Weitere Auskünfte zu ausgewählten Sachverhalten | D36: ja
B38: ="Quelle: "&Cockpit!$C$7 -> Quelle: Datenraum/ eigene Analysen | H38: ="Source: "&Cockpit!$C$8 -> Source: Virtual Data Room/ Company Information

Sheet Abkürzungsverzeichnis
A1: Deutsch | C1: kurz | D1: Lang | F1: English | H1: short | I1: long
A2: 1 | C2: Adj. | D2: Angepasst | F2: 1 | H2: Act. | I2: Actual figures
A3: 2 | C3: AO | D3: Abgabenordnung | F3: 2 | H3: Adj. | I3: Adjusted
A4: 3 | C4: BP | D4: Betriebsprüfung | F4: 3 | H4: BoP | I4: Beginning of period
A5: 4 | C5: BT | D5: Baker Tilly | F5: 4 | H5: BT | I5: Baker Tilly
A6: 5 | C6: BWA | D6: Betriebswirtschaftliche Auswertung | F6: 5 | H6: c. | I6: circa
A7: 6 | C7: ca. | D7: circa | F7: 6 | H7: CAGR | I7: Compounded Annual Growth Rate
A8: 7 | C8: CAGR | D8: Compounded Annual Growth Rate | F8: 7 | H8: CAPEX | I8: Capital Expenditures
A9: 8 | C9: CAPEX | D9: Capital Expenditures | F9: 8 | H9: CCC | I9: Cash Conversion Cycle
A10: 9 | C10: CCC | D10: Cash Conversion Cycle | F10: 9 | H10: CDD | I10: Commercial Due Diligence
A11: 10 | C11: CDD | D11: Commercial Due Diligence | F11: 10 | H11: CLI | I11: Cash-like item
A12: 11 | C12: DIO | D12: Lagerdauer | F12: 11 | H12: COGS | I12: Cost of Goods sold
A13: 12 | C13: DPO | D13: Kreditorenlaufzeit | F13: 12 | H13: cont'd | I13: continued
... A21: 20 | C21: FTE | D21: Full-Time Equivalent | F21: 20 | H21: EoP | I21: End of period
A22: 21 | B22: Spalte 1 | C22: GewSt | D22: Gewerbesteuer | F22: 21 | G22: Spalte 1 | H22: EOY | I22: End of year
A23: 1 | C23: GJ | D23: Geschäftsjahr | F23: 1 | H23: EUR | I23: Euro
A24: 2 | C24: GmbH | D24: Gesellschaft mit beschränkter Haftung | F24: 2 | H24: FC | I24: Forecast
A25: 3 | C25: h | D25: Stunde | F25: 3 | H25: FDD | I25: Financial Due Diligence
A26: 4 | C26: HGB | D26: Handelsgesetzbuch | F26: 4 | H26: FTE | I26: Full-Time Equivalent
A27: 5 | C27: i.d.R. | D27: in der Regel | F27: 5 | H27: FX | I27: Foreign exchange
A28: 6 | C28: i.H.v. | D28: in Höhe von | F28: 6 | H28: FY | I28: Fiscal year
A29: 7 | C29: KSt | D29: Körperschaftsteuer | F29: 7 | H29: GmbH | I29: Limited Company
A30: 8 | C30: KStG | D30: Körperschaftsteuergesetz | F30: 8 | H30: h | I30: hour
A31: 9 | C31: L.u.L. | D31: Lieferungen und Leistungen | F31: 9 | H31: HGB | I31: German Commercial Code
A32: 10 | C32: LTM | D32: Last Twelve Months | F32: 10 | H32: kEUR | I32: Thousand Euro
A33: 11 | C33: p.a. | D33: per annum, jährlich | F33: 11 | H33: LTM | I33: Last Twelve Months
A34: 12 | C34: PPA | D34: Purchase Price Allocation | F34: 12 | H34: OOI | I34: Other operating income
... A42: 20 | C42: SuSa | D42: Summen- und Saldenliste | F42: 20 | H42: SuSa | I42: Trial balance
A43: 21 | B43: Spalte 2 | C43: TDD | D43: Tax Due Diligence | F43: 21 | G43: Spalte 2 | H43: TDD | I43: Tax Due Diligence
A44: 1 | C44: TEUR | D44: Tausend Euro | F44: 1 | H44: TWC | I44: Trade Working Capital
A45: 2 | C45: TWC | D45: Trade Working Capital | F45: 2 | H45: USD | I45: US Dollar
A46: 3 | C46: USD | D46: US Dollar | F46: 3 | H46: VDR | I46: Virtual Dataroom
A47: 4 | C47: USt | D47: Umsatzsteuer | F47: 4 | H47: WIP | I47: Work-in-Progress
A48: 5 | C48: VdN | D48: Vorbehalt der Nachprüfung | F48: 5 | H48: YoY | I48: Year-on-Year
A49: 6 | C49: VDR | D49: Datenraum | F49: 6 | H49: YTD | I49: Year-to-Date
A50: 7 | C50: WIP | D50: Work-in-Progress | F50: 7 | H50: YTG | I50: Year-to-Go
A51: 8 | C51: WJ | D51: Wirtschaftsjahr | F51: 8
A52: 9 | C52: YTD | D52: Year-to-Date | F52: 9
A53: 10 | C53: YTG | D53: Year-to-Go | F53: 10
A54: 11 | C54: AHK | D54: Anschaffungs- und Herstellungskosten | F54: 11
A55: 12 | C55: BGA | D55: Betriebs- und Geschäftsausstattung | F55: 12
A56: 13 | F56: 13
A57: 14 | F57: 14
A58: 15 | F58: 15
A59: 16 | F59: 16
A60: 17 | F60: 17
A61: 18 | F61: 18
A62: 19 | F62: 19
A63: 20 | F63: 20
A64: 21 | B64: Spalte 3 | F64: 21 | G64: Spalte 3

Sheet Think Cell
A2: Revenue Split
B4: ='Lead PL'!F6 -> 44926 | E4: ='Lead PL'!G6 -> 45291 | H4: ='Lead PL'!H6 -> 45657 | K4: ='Lead PL'!I6 -> 45808
A5: Dummy 1
A6: Dummy 2
A7: Dummy 3
A8: Dummy 4
A13: Total Output and EBITDA
B17: ='Lead PL'!F6 -> 44926 | C17: ='Lead PL'!G6 -> 45291 | D17: ='Lead PL'!H6 -> 45657 | E17: ='Lead PL'!I6 -> 45808
B18: FY | C18: FY | D18: FY | E18: LTM
A19: EBITDA-margin (normalized) | B19: =PL_QoE!F44 -> n/a | C19: =PL_QoE!G44 -> n/a | D19: =PL_QoE!H44 -> n/a | E19: =PL_QoE!I44 -> n/a
A20: EBITDA-margin | B20: =PL_QoE!F41 -> n/a | C20: =PL_QoE!G41 -> n/a | D20: =PL_QoE!H41 -> n/a | E20: =PL_QoE!I41 -> n/a
A21: Total Output | B21: ='Lead PL'!F39 -> 0 | C21: ='Lead PL'!G39 -> 0 | D21: ='Lead PL'!H39 -> 0 | E21: ='Lead PL'!I39 -> 0
A22: EBITDA | B22: ='Lead PL'!F146 -> 0 | C22: ='Lead PL'!G146 -> 0 | D22: ='Lead PL'!H146 -> 0 | E22: ='Lead PL'!I146 -> 0
A23: Adj. EBITDA | B23: =PL_QoE!F30 -> 0 | C23: =PL_QoE!G30 -> 0 | D23: =PL_QoE!H30 -> 0 | E23: =PL_QoE!I30 -> 0
A28: EBITDA-Bridge
B31: ="EBITDA FY" & RIGHT(YEAR(Cockpit!D33),2) & " Act." -> EBITDA FY22 Act. | C31: ="∆ "&'Lead PL'!D9 -> ∆ Revenues | D31: ="∆ "&'Lead PL'!D18 -> ∆ Change in inventory | E31: ="∆ "&'Lead PL'!D27 -> ∆ Own work capitalized | F31: ="∆ "&'Lead PL'!D36 -> ∆ Dummy 1 | G31: ="∆ "&'Lead PL'!D37 -> ∆ Dummy 2 | H31: ="∆ "&'Lead PL'!D38 -> ∆ Dummy 3 | I31: ="∆ "&'Lead PL'!D40 -> ∆ Cost of materials | J31: ="∆ "&'Lead PL'!D53 -> ∆ Personnel expenses | K31: ="∆ "&'Lead PL'!D62 -> ∆ Premise costs | L31: ="∆ "&'Lead PL'!D71 -> ∆ Repair and maintenance | M31: ="∆ "&'Lead PL'!D80 -> ∆ Sales costs | N31: ="∆ "&'Lead PL'!D89 -> ∆ Delivery costs | O31: ="∆ "&'Lead PL'!D98 -> ∆ Vehicle costs | P31: ="∆ "&'Lead PL'!D107 -> ∆ Insurance, contributions and levies expenses | Q31: ="∆ "&'Lead PL'!D116 -> ∆ Advertising and travel expenses | R31: ="∆ "&'Lead PL'!D125 -> ∆ Other operating income | S31: ="∆ "&'Lead PL'!D134 -> ∆ Other operating expenses | T31: ="∆ "&'Lead PL'!D143 -> ∆ Dummy 1 | U31: ="∆ "&'Lead PL'!D144 -> ∆ Dummy 2 | V31: ="∆ "&'Lead PL'!D145 -> ∆ Dummy 3 | W31: ="EBITDA FY" & RIGHT(YEAR(Cockpit!E33),2) & " Act." -> EBITDA FY23 Act. | X31: =C31 -> ∆ Revenues | Y31: =D31 -> ∆ Change in inventory | Z31: =E31 -> ∆ Own work capitalized | AA31: =F31 -> ∆ Dummy 1 | AB31: =G31 -> ∆ Dummy 2 | AC31: =H31 -> ∆ Dummy 3 | AD31: =I31 -> ∆ Cost of materials | AE31: =J31 -> ∆ Personnel expenses | ... AQ31: =V31 -> ∆ Dummy 3 | AR31: ="EBITDA FY" & RIGHT(YEAR(Cockpit!F33),2) & " Act." -> EBITDA FY24 Act.
A33: EBITDA | B33: ='Lead PL'!F146 -> 0 | C33: ='Lead PL'!G9-'Lead PL'!F9 -> 0 | D33: ='Lead PL'!G18-'Lead PL'!F18 -> 0 | E33: ='Lead PL'!G27-'Lead PL'!F27 -> 0 | F33: ='Lead PL'!G36-'Lead PL'!F36 -> 0 | G33: ='Lead PL'!G37-'Lead PL'!F37 -> 0 | H33: ='Lead PL'!G38-'Lead PL'!F38 -> 0 | I33: ='Lead PL'!G40-'Lead PL'!F40 -> 0 | J33: ='Lead PL'!G53-'Lead PL'!F53 -> 0 | K33: ='Lead PL'!G62-'Lead PL'!F62 -> 0 | L33: ='Lead PL'!G71-'Lead PL'!F71 -> 0 | M33: ='Lead PL'!G80-'Lead PL'!F80 -> 0 | N33: ='Lead PL'!G89-'Lead PL'!F89 -> 0 | O33: ='Lead PL'!G98-'Lead PL'!F98 -> 0 | P33: ='Lead PL'!G107-'Lead PL'!F107 -> 0 | Q33: ='Lead PL'!G116-'Lead PL'!F116 -> 0 | R33: ='Lead PL'!G125-'Lead PL'!F125 -> 0 | S33: ='Lead PL'!G134-'Lead PL'!F134 -> 0 | T33: ='Lead PL'!G143-'Lead PL'!F143 -> 0 | U33: ='Lead PL'!G144-'Lead PL'!F144 -> 0 | V33: ='Lead PL'!G145-'Lead PL'!F145 -> 0 | W33: =SUM(B33:V33) -> 0 | X33: ='Lead PL'!H9-'Lead PL'!G9 -> 0 | Y33: ='Lead PL'!H18-'Lead PL'!G18 -> 0 | Z33: ='Lead PL'!H27-'Lead PL'!G27 -> 0 | AA33: ='Lead PL'!H36-'Lead PL'!G36 -> 0 | AB33: ='Lead PL'!H37-'Lead PL'!G37 -> 0 | AC33: ='Lead PL'!H38-'Lead PL'!G38 -> 0 | AD33: ='Lead PL'!H40-'Lead PL'!G40 -> 0 | AE33: ='Lead PL'!H53-'Lead PL'!G53 -> 0 | AF33: ='Lead PL'!H62-'Lead PL'!G62 -> 0 | AG33: ='Lead PL'!H71-'Lead PL'!G71 -> 0 | AH33: ='Lead PL'!H80-'Lead PL'!G80 -> 0 | AI33: ='Lead PL'!H89-'Lead PL'!G89 -> 0 | AJ33: ='Lead PL'!H98-'Lead PL'!G98 -> 0 | AK33: ='Lead PL'!H107-'Lead PL'!G107 -> 0 | AL33: ='Lead PL'!H116-'Lead PL'!G116 -> 0 | AM33: ='Lead PL'!H125-'Lead PL'!G125 -> 0 | AN33: ='Lead PL'!H134-'Lead PL'!G134 -> 0 | AO33: ='Lead PL'!H143-'Lead PL'!G143 -> 0 | AP33: ='Lead PL'!H144-'Lead PL'!G144 -> 0 | AQ33: ='Lead PL'!H145-'Lead PL'!G145 -> 0 | AR33: =SUM(W33:AQ33) -> 0
A34: Check | W34: =W33-'Lead PL'!G146 -> 0 | AR34: =AR33-'Lead PL'!H146 -> 0
A64: Monthly Trade Working Capital
B67: =NA_monthly!F6 -> 44592 | C67: =NA_monthly!G6 -> 44620 | D67: =NA_monthly!H6 -> 44651 | E67: =NA_monthly!I6 -> 44681 | F67: =NA_monthly!J6 -> 44712 | G67: =NA_monthly!K6 -> 44742 | H67: =NA_monthly!L6 -> 44773 | I67: =NA_monthly!M6 -> 44804 | ... AV67: =NA_monthly!AZ6 -> 45991
A68: =NA_monthly!D16 -> Inventories | B68: =NA_monthly!F16 -> 0 | C68: =NA_monthly!G16 -> 0 | D68: =NA_monthly!H16 -> 0 | E68: =NA_monthly!I16 -> 0 | F68: =NA_monthly!J16 -> 0 | G68: =NA_monthly!K16 -> 0 | H68: =NA_monthly!L16 -> 0 | I68: =NA_monthly!M16 -> 0 | ... AV68: =NA_monthly!AZ16 -> 0
A69: =NA_monthly!D17 -> Trade receivables | B69: =NA_monthly!F17 -> 0 | C69: =NA_monthly!G17 -> 0 | D69: =NA_monthly!H17 -> 0 | E69: =NA_monthly!I17 -> 0 | F69: =NA_monthly!J17 -> 0 | G69: =NA_monthly!K17 -> 0 | H69: =NA_monthly!L17 -> 0 | I69: =NA_monthly!M17 -> 0 | ... AV69: =NA_monthly!AZ17 -> 0
A70: =NA_monthly!D18 -> Trade payables | B70: =NA_monthly!F18 -> 0 | C70: =NA_monthly!G18 -> 0 | D70: =NA_monthly!H18 -> 0 | E70: =NA_monthly!I18 -> 0 | F70: =NA_monthly!J18 -> 0 | G70: =NA_monthly!K18 -> 0 | H70: =NA_monthly!L18 -> 0 | I70: =NA_monthly!M18 -> 0 | ... AV70: =NA_monthly!AZ18 -> 0
A71: =NA_monthly!D19 -> Advance payments received | B71: =NA_monthly!F19 -> 0 | C71: =NA_monthly!G19 -> 0 | D71: =NA_monthly!H19 -> 0 | E71: =NA_monthly!I19 -> 0 | F71: =NA_monthly!J19 -> 0 | G71: =NA_monthly!K19 -> 0 | H71: =NA_monthly!L19 -> 0 | I71: =NA_monthly!M19 -> 0 | ... AV71: =NA_monthly!AZ19 -> 0
A72: =NA_monthly!D23 -> Trade working capital | B72: =NA_monthly!F23 -> 0 | C72: =NA_monthly!G23 -> 0 | D72: =NA_monthly!H23 -> 0 | E72: =NA_monthly!I23 -> 0 | F72: =NA_monthly!J23 -> 0 | G72: =NA_monthly!K23 -> 0 | H72: =NA_monthly!L23 -> 0 | I72: =NA_monthly!M23 -> 0 | ... AV72: =NA_monthly!AZ23 -> 0
A73: =NA_monthly!D43 -> Net working capital | B73: =NA_monthly!F43 -> 0 | C73: =NA_monthly!G43 -> 0 | D73: =NA_monthly!H43 -> 0 | E73: =NA_monthly!I43 -> 0 | F73: =NA_monthly!J43 -> 0 | G73: =NA_monthly!K43 -> 0 | H73: =NA_monthly!L43 -> 0 | I73: =NA_monthly!M43 -> 0 | ... AV73: =NA_monthly!AZ43 -> 0
A74: =NA_monthly!D44 -> Cash | B74: =NA_monthly!F44 -> 0 | C74: =NA_monthly!G44 -> 0 | D74: =NA_monthly!H44 -> 0 | E74: =NA_monthly!I44 -> 0 | F74: =NA_monthly!J44 -> 0 | G74: =NA_monthly!K44 -> 0 | H74: =NA_monthly!L44 -> 0 | I74: =NA_monthly!M44 -> 0 | ... AV74: =NA_monthly!AZ44 -> 0
A75: =PL_monthly!D9 -> Revenues | B75: =PL_monthly!F9 -> 0 | C75: =PL_monthly!G9 -> 0 | D75: =PL_monthly!H9 -> 0 | E75: =PL_monthly!I9 -> 0 | F75: =PL_monthly!J9 -> 0 | G75: =PL_monthly!K9 -> 0 | H75: =PL_monthly!L9 -> 0 | I75: =PL_monthly!M9 -> 0 | ... AV75: =PL_monthly!AZ9 -> 0
A76: TWC in % LTM Revenue | B76: =IF(NA_monthly!F108="n.a.",0,NA_monthly!F108) -> 0 | C76: =IF(NA_monthly!G108="n.a.",0,NA_monthly!G108) -> 0 | D76: =IF(NA_monthly!H108="n.a.",0,NA_monthly!H108) -> 0 | E76: =IF(NA_monthly!I108="n.a.",0,NA_monthly!I108) -> 0 | F76: =IF(NA_monthly!J108="n.a.",0,NA_monthly!J108) -> 0 | G76: =IF(NA_monthly!K108="n.a.",0,NA_monthly!K108) -> 0 | H76: =IF(NA_monthly!L108="n.a.",0,NA_monthly!L108) -> 0 | I76: =IF(NA_monthly!M108="n.a.",0,NA_monthly!M108) -> 0 | ... AV76: =IF(NA_monthly!AZ108="n.a.",0,NA_monthly!AZ108) -> 0
A100: Cash Conversion Cycle
B103: =NA_TWC!F6 -> 44926 | C103: =NA_TWC!G6 -> 45291 | D103: =NA_TWC!H6 -> 45657 | E103: =NA_TWC!I6 -> 45808
A105: Ø Days inventory outstanding (DIO) | B105: =NA_TWC!F70 -> n/a | C105: =NA_TWC!G70 -> n/a | D105: =NA_TWC!H70 -> n/a | E105: =NA_TWC!I70 -> n/a
A106: Ø Days sales outstanding (DSO) | B106: =NA_TWC!F71 -> n/a | C106: =NA_TWC!G71 -> n/a | D106: =NA_TWC!H71 -> n/a | E106: =NA_TWC!I71 -> n/a
A107: Ø Days payables outstanding (DPO) | B107: =NA_TWC!F72 -> n/a | C107: =NA_TWC!G72 -> n/a | D107: =NA_TWC!H72 -> n/a | E107: =NA_TWC!I72 -> n/a
A108: Cash conversion cycle | B108: =NA_TWC!F73 -> 0 | C108: =NA_TWC!G73 -> 0 | D108: =NA_TWC!H73 -> 0 | E108: =NA_TWC!I73 -> 0
A115: TOP Customer Analyse
B117: Customer 1 | C117: Customer 2 | D117: Customer 3 | E117: Customer 4 | F117: Customer 5
A119: FYXX
A120: FYXX
A121: FYXX
A122: FYXX
A133: Contribution Margin
A135: 44196
B136: Revenue | C136: Contribution margin 1 in % | D136: Revenue
A137: Dummy 1
A138: Dummy 2
A139: Dummy 3
A140: Dummy 4
A141: Total output

Sheet Lead >>

Sheet Trial Balance Dropdown
A1: Mapping_Dropdown_as_reported | C1: BT_adjustment_Dropdown
A2: /profit and loss | C2: /btadjustment/QOE/normalization_1
A3: /profit and loss/income | C3: /btadjustment/QOE/normalization_2
A4: /profit and loss/income/sales | C4: /btadjustment/QOE/normalization_3
A5: /profit and loss/income/increase in inventory | C5: /btadjustment/QOE/normalization_4
A6: /profit and loss/income/change in inventory | C6: /btadjustment/QOE/normalization_5
A7: /profit and loss/income/own work capitalised | C7: /btadjustment/QOE/normalization_6
A8: /profit and loss/income/income from investments | C8: /btadjustment/QOE/proforma_1
A9: /profit and loss/income/income from other securities and loans of financial assets | C9: /btadjustment/QOE/proforma_2
A10: /profit and loss/income/interest income | C10: /btadjustment/QOE/proforma_3
A11: /profit and loss/income/other income | C11: /btadjustment/QOE/proforma_4
A12: /profit and loss/expense | C12: /btadjustment/QOE/other items_1
... A49: /net debt/securities | C49: /btadjustment/net deb/other items_6
A50: /net debt/cash and cash equivalent
A51: /net debt/provisions for pensions and similar obligations
A52: /net debt/tax provisions
A53: /net debt/other provisions
A54: /net debt/bonds issued
A55: /net debt/liabilities to credit institutions
A56: /net debt/liabilities to shareholders
A57: /net debt/debt like item
A58: /fixed assets
A59: /fixed assets/intangible assets
A60: /fixed assets/intangible assets/self developed intangible assets
A61: /fixed assets/intangible assets/patents, licenses, trademarks and other
... A93: /other/deferred tax liabilities

Sheet Lead PL
C1: Technische Zeile --> nicht löschen | D1: Technische Zeile --> nicht löschen | E1: =IFERROR(E4,E6) -> 44561 | F1: =IFERROR(F4,F6) -> 44926 | G1: =IFERROR(G4,G6) -> 45291 | H1: =IFERROR(H4,H6) -> 45657 | I1: =IFERROR(I4,I6) -> 45808 | J1: =IFERROR(J4,J6) -> 45808 | K1: =IFERROR(K4,K6) -> 46022 | L1: =IFERROR(L4,L6) -> 46387 | ... N1: =IFERROR(N4,N6) -> 47118
C4: =Cockpit!$C$4 -> Template | E4: =Cockpit!C33 -> 44561 | F4: =Cockpit!D33 -> 44926 | G4: =Cockpit!E33 -> 45291 | H4: =Cockpit!F33 -> 45657 | I4: =Cockpit!G33 -> 45808 | J4: =Cockpit!H33 -> 45808 | K4: =Cockpit!I33 -> 46022 | L4: =Cockpit!J33 -> 46387 | ... N4: =Cockpit!L33 -> 47118 | P4: CAGR | Q4: CAGR
C5: ="in T"&Cockpit!$C$5 -> in TEUR | E5: =Cockpit!C34 -> IST | F5: =Cockpit!D34 -> IST | G5: =Cockpit!E34 -> IST | H5: =Cockpit!F34 -> IST | I5: =Cockpit!G34 -> LTM | J5: =Cockpit!H34 -> YTD | K5: =Cockpit!I34 -> Plan | L5: =Cockpit!J34 -> Plan | ... N5: =Cockpit!L34 -> Plan | P5: IST | Q5: =Cockpit!$C$27 -> Plan | T5: Ticker 1 (NA-Zeile / Konto) | U5: Ticker 2 (Klasse) | V5: Zeilentyp
D6: =Cockpit!$C$4 -> Template | E6: =Cockpit!C33 -> 44561 | F6: =Cockpit!D33 -> 44926 | G6: =Cockpit!E33 -> 45291 | H6: =Cockpit!F33 -> 45657 | I6: =Cockpit!G33 -> 45808 | J6: =Cockpit!H33 -> 45808 | K6: =Cockpit!I33 -> 46022 | L6: =Cockpit!J33 -> 46387 | ... N6: =Cockpit!L33 -> 47118 | P6: CAGR | Q6: CAGR
D7: ="in k"&Cockpit!$C$5 -> in kEUR | E7: =Cockpit!C34 -> IST | F7: =Cockpit!D34 -> IST | G7: =Cockpit!E34 -> IST | H7: =Cockpit!F34 -> IST | I7: =Cockpit!G34 -> LTM | J7: =Cockpit!H34 -> YTD | K7: =Cockpit!I34 -> Plan | L7: =Cockpit!J34 -> Plan | ... N7: =Cockpit!L34 -> Plan | P7: =Cockpit!$C$19 -> IST | Q7: =Cockpit!$C$27 -> Plan | T7: Classification BT
C9: Umsatzerlöse | D9: Revenues | E9: =SUMIFS(Mastersheet!$F$2:$F$400,Mastersheet!$D$2:$D$400,$T9,Mastersheet!$C$2:$C$400,$U9)/1000 -> 0 | F9: =SUMIFS(Mastersheet!$G$2:$G$400,Mastersheet!$D$2:$D$400,$T9,Mastersheet!$C$2:$C$400,$U9)/1000 -> 0 | G9: =SUMIFS(Mastersheet!$H$2:$H$400,Mastersheet!$D$2:$D$400,$T9,Mastersheet!$C$2:$C$400,$U9)/1000 -> 0 | H9: =SUMIFS(Mastersheet!$I$2:$I$400,Mastersheet!$D$2:$D$400,$T9,Mastersheet!$C$2:$C$400,$U9)/1000 -> 0 | I9: =SUMIFS(Mastersheet!$J$2:$J$400,Mastersheet!$D$2:$D$400,$T9,Mastersheet!$C$2:$C$400,$U9)/1000 -> 0 | J9: =SUMIFS(Mastersheet!$K$2:$K$400,Mastersheet!$D$2:$D$400,$T9,Mastersheet!$C$2:$C$400,$U9)/1000 -> 0 | K9: =SUMIFS(Mastersheet!$L$2:$L$400,Mastersheet!$D$2:$D$400,$T9,Mastersheet!$C$2:$C$400,$U9)/1000 -> 0 | L9: =SUMIFS(Mastersheet!$M$2:$M$400,Mastersheet!$D$2:$D$400,$T9,Mastersheet!$C$2:$C$400,$U9)/1000 -> 0 | M9: =SUMIFS(Mastersheet!$N$2:$N$400,Mastersheet!$D$2:$D$400,$T9,Mastersheet!$C$2:$C$400,$U9)/1000 -> 0 | N9: =SUMIFS(Mastersheet!$O$2:$O$400,Mastersheet!$D$2:$D$400,$T9,Mastersheet!$C$2:$C$400,$U9)/1000 -> 0 | P9: =IFERROR(((H9/F9)^(1/(($H$1-$F$1)/365)))-1,"n/a") -> n/a | Q9: =IFERROR(((N9/H9)^(1/(($N$1-$H$1)/365)))-1,"n/a") -> n/a | T9: Umsatzerloese | U9: PL | V9: POS
E10: =IF($T$10="","",SUMIFS(Mastersheet!$F$2:$F$400,Mastersheet!$A$2:$A$400,$T$10)/1000) | F10: =IF($T$10="","",SUMIFS(Mastersheet!$G$2:$G$400,Mastersheet!$A$2:$A$400,$T$10)/1000) | G10: =IF($T$10="","",SUMIFS(Mastersheet!$H$2:$H$400,Mastersheet!$A$2:$A$400,$T$10)/1000) | H10: =IF($T$10="","",SUMIFS(Mastersheet!$I$2:$I$400,Mastersheet!$A$2:$A$400,$T$10)/1000) | I10: =IF($T$10="","",SUMIFS(Mastersheet!$J$2:$J$400,Mastersheet!$A$2:$A$400,$T$10)/1000) | J10: =IF($T$10="","",SUMIFS(Mastersheet!$K$2:$K$400,Mastersheet!$A$2:$A$400,$T$10)/1000) | K10: =IF($T$10="","",SUMIFS(Mastersheet!$L$2:$L$400,Mastersheet!$A$2:$A$400,$T$10)/1000) | L10: =IF($T$10="","",SUMIFS(Mastersheet!$M$2:$M$400,Mastersheet!$A$2:$A$400,$T$10)/1000) | M10: =IF($T$10="","",SUMIFS(Mastersheet!$N$2:$N$400,Mastersheet!$A$2:$A$400,$T$10)/1000) | N10: =IF($T$10="","",SUMIFS(Mastersheet!$O$2:$O$400,Mastersheet!$A$2:$A$400,$T$10)/1000) | U10: Account | V10: KTO
E11: =IF($T$11="","",SUMIFS(Mastersheet!$F$2:$F$400,Mastersheet!$A$2:$A$400,$T$11)/1000) | F11: =IF($T$11="","",SUMIFS(Mastersheet!$G$2:$G$400,Mastersheet!$A$2:$A$400,$T$11)/1000) | G11: =IF($T$11="","",SUMIFS(Mastersheet!$H$2:$H$400,Mastersheet!$A$2:$A$400,$T$11)/1000) | H11: =IF($T$11="","",SUMIFS(Mastersheet!$I$2:$I$400,Mastersheet!$A$2:$A$400,$T$11)/1000) | I11: =IF($T$11="","",SUMIFS(Mastersheet!$J$2:$J$400,Mastersheet!$A$2:$A$400,$T$11)/1000) | J11: =IF($T$11="","",SUMIFS(Mastersheet!$K$2:$K$400,Mastersheet!$A$2:$A$400,$T$11)/1000) | K11: =IF($T$11="","",SUMIFS(Mastersheet!$L$2:$L$400,Mastersheet!$A$2:$A$400,$T$11)/1000) | L11: =IF($T$11="","",SUMIFS(Mastersheet!$M$2:$M$400,Mastersheet!$A$2:$A$400,$T$11)/1000) | M11: =IF($T$11="","",SUMIFS(Mastersheet!$N$2:$N$400,Mastersheet!$A$2:$A$400,$T$11)/1000) | N11: =IF($T$11="","",SUMIFS(Mastersheet!$O$2:$O$400,Mastersheet!$A$2:$A$400,$T$11)/1000) | U11: Account | V11: KTO
E12: =IF($T$12="","",SUMIFS(Mastersheet!$F$2:$F$400,Mastersheet!$A$2:$A$400,$T$12)/1000) | F12: =IF($T$12="","",SUMIFS(Mastersheet!$G$2:$G$400,Mastersheet!$A$2:$A$400,$T$12)/1000) | G12: =IF($T$12="","",SUMIFS(Mastersheet!$H$2:$H$400,Mastersheet!$A$2:$A$400,$T$12)/1000) | H12: =IF($T$12="","",SUMIFS(Mastersheet!$I$2:$I$400,Mastersheet!$A$2:$A$400,$T$12)/1000) | I12: =IF($T$12="","",SUMIFS(Mastersheet!$J$2:$J$400,Mastersheet!$A$2:$A$400,$T$12)/1000) | J12: =IF($T$12="","",SUMIFS(Mastersheet!$K$2:$K$400,Mastersheet!$A$2:$A$400,$T$12)/1000) | K12: =IF($T$12="","",SUMIFS(Mastersheet!$L$2:$L$400,Mastersheet!$A$2:$A$400,$T$12)/1000) | L12: =IF($T$12="","",SUMIFS(Mastersheet!$M$2:$M$400,Mastersheet!$A$2:$A$400,$T$12)/1000) | M12: =IF($T$12="","",SUMIFS(Mastersheet!$N$2:$N$400,Mastersheet!$A$2:$A$400,$T$12)/1000) | N12: =IF($T$12="","",SUMIFS(Mastersheet!$O$2:$O$400,Mastersheet!$A$2:$A$400,$T$12)/1000) | U12: Account | V12: KTO
E13: =IF($T$13="","",SUMIFS(Mastersheet!$F$2:$F$400,Mastersheet!$A$2:$A$400,$T$13)/1000) | F13: =IF($T$13="","",SUMIFS(Mastersheet!$G$2:$G$400,Mastersheet!$A$2:$A$400,$T$13)/1000) | G13: =IF($T$13="","",SUMIFS(Mastersheet!$H$2:$H$400,Mastersheet!$A$2:$A$400,$T$13)/1000) | H13: =IF($T$13="","",SUMIFS(Mastersheet!$I$2:$I$400,Mastersheet!$A$2:$A$400,$T$13)/1000) | I13: =IF($T$13="","",SUMIFS(Mastersheet!$J$2:$J$400,Mastersheet!$A$2:$A$400,$T$13)/1000) | J13: =IF($T$13="","",SUMIFS(Mastersheet!$K$2:$K$400,Mastersheet!$A$2:$A$400,$T$13)/1000) | K13: =IF($T$13="","",SUMIFS(Mastersheet!$L$2:$L$400,Mastersheet!$A$2:$A$400,$T$13)/1000) | L13: =IF($T$13="","",SUMIFS(Mastersheet!$M$2:$M$400,Mastersheet!$A$2:$A$400,$T$13)/1000) | M13: =IF($T$13="","",SUMIFS(Mastersheet!$N$2:$N$400,Mastersheet!$A$2:$A$400,$T$13)/1000) | N13: =IF($T$13="","",SUMIFS(Mastersheet!$O$2:$O$400,Mastersheet!$A$2:$A$400,$T$13)/1000) | U13: Account | V13: KTO
E14: =IF($T$14="","",SUMIFS(Mastersheet!$F$2:$F$400,Mastersheet!$A$2:$A$400,$T$14)/1000) | F14: =IF($T$14="","",SUMIFS(Mastersheet!$G$2:$G$400,Mastersheet!$A$2:$A$400,$T$14)/1000) | G14: =IF($T$14="","",SUMIFS(Mastersheet!$H$2:$H$400,Mastersheet!$A$2:$A$400,$T$14)/1000) | H14: =IF($T$14="","",SUMIFS(Mastersheet!$I$2:$I$400,Mastersheet!$A$2:$A$400,$T$14)/1000) | I14: =IF($T$14="","",SUMIFS(Mastersheet!$J$2:$J$400,Mastersheet!$A$2:$A$400,$T$14)/1000) | J14: =IF($T$14="","",SUMIFS(Mastersheet!$K$2:$K$400,Mastersheet!$A$2:$A$400,$T$14)/1000) | K14: =IF($T$14="","",SUMIFS(Mastersheet!$L$2:$L$400,Mastersheet!$A$2:$A$400,$T$14)/1000) | L14: =IF($T$14="","",SUMIFS(Mastersheet!$M$2:$M$400,Mastersheet!$A$2:$A$400,$T$14)/1000) | M14: =IF($T$14="","",SUMIFS(Mastersheet!$N$2:$N$400,Mastersheet!$A$2:$A$400,$T$14)/1000) | N14: =IF($T$14="","",SUMIFS(Mastersheet!$O$2:$O$400,Mastersheet!$A$2:$A$400,$T$14)/1000) | U14: Account | V14: KTO
E15: =IF($T$15="","",SUMIFS(Mastersheet!$F$2:$F$400,Mastersheet!$A$2:$A$400,$T$15)/1000) | F15: =IF($T$15="","",SUMIFS(Mastersheet!$G$2:$G$400,Mastersheet!$A$2:$A$400,$T$15)/1000) | G15: =IF($T$15="","",SUMIFS(Mastersheet!$H$2:$H$400,Mastersheet!$A$2:$A$400,$T$15)/1000) | H15: =IF($T$15="","",SUMIFS(Mastersheet!$I$2:$I$400,Mastersheet!$A$2:$A$400,$T$15)/1000) | I15: =IF($T$15="","",SUMIFS(Mastersheet!$J$2:$J$400,Mastersheet!$A$2:$A$400,$T$15)/1000) | J15: =IF($T$15="","",SUMIFS(Mastersheet!$K$2:$K$400,Mastersheet!$A$2:$A$400,$T$15)/1000) | K15: =IF($T$15="","",SUMIFS(Mastersheet!$L$2:$L$400,Mastersheet!$A$2:$A$400,$T$15)/1000) | L15: =IF($T$15="","",SUMIFS(Mastersheet!$M$2:$M$400,Mastersheet!$A$2:$A$400,$T$15)/1000) | M15: =IF($T$15="","",SUMIFS(Mastersheet!$N$2:$N$400,Mastersheet!$A$2:$A$400,$T$15)/1000) | N15: =IF($T$15="","",SUMIFS(Mastersheet!$O$2:$O$400,Mastersheet!$A$2:$A$400,$T$15)/1000) | U15: Account | V15: KTO
E16: =IF($T$16="","",SUMIFS(Mastersheet!$F$2:$F$400,Mastersheet!$A$2:$A$400,$T$16)/1000) | F16: =IF($T$16="","",SUMIFS(Mastersheet!$G$2:$G$400,Mastersheet!$A$2:$A$400,$T$16)/1000) | G16: =IF($T$16="","",SUMIFS(Mastersheet!$H$2:$H$400,Mastersheet!$A$2:$A$400,$T$16)/1000) | H16: =IF($T$16="","",SUMIFS(Mastersheet!$I$2:$I$400,Mastersheet!$A$2:$A$400,$T$16)/1000) | I16: =IF($T$16="","",SUMIFS(Mastersheet!$J$2:$J$400,Mastersheet!$A$2:$A$400,$T$16)/1000) | J16: =IF($T$16="","",SUMIFS(Mastersheet!$K$2:$K$400,Mastersheet!$A$2:$A$400,$T$16)/1000) | K16: =IF($T$16="","",SUMIFS(Mastersheet!$L$2:$L$400,Mastersheet!$A$2:$A$400,$T$16)/1000) | L16: =IF($T$16="","",SUMIFS(Mastersheet!$M$2:$M$400,Mastersheet!$A$2:$A$400,$T$16)/1000) | M16: =IF($T$16="","",SUMIFS(Mastersheet!$N$2:$N$400,Mastersheet!$A$2:$A$400,$T$16)/1000) | N16: =IF($T$16="","",SUMIFS(Mastersheet!$O$2:$O$400,Mastersheet!$A$2:$A$400,$T$16)/1000) | U16: Account | V16: KTO
E17: =IF($T$17="","",SUMIFS(Mastersheet!$F$2:$F$400,Mastersheet!$A$2:$A$400,$T$17)/1000) | F17: =IF($T$17="","",SUMIFS(Mastersheet!$G$2:$G$400,Mastersheet!$A$2:$A$400,$T$17)/1000) | G17: =IF($T$17="","",SUMIFS(Mastersheet!$H$2:$H$400,Mastersheet!$A$2:$A$400,$T$17)/1000) | H17: =IF($T$17="","",SUMIFS(Mastersheet!$I$2:$I$400,Mastersheet!$A$2:$A$400,$T$17)/1000) | I17: =IF($T$17="","",SUMIFS(Mastersheet!$J$2:$J$400,Mastersheet!$A$2:$A$400,$T$17)/1000) | J17: =IF($T$17="","",SUMIFS(Mastersheet!$K$2:$K$400,Mastersheet!$A$2:$A$400,$T$17)/1000) | K17: =IF($T$17="","",SUMIFS(Mastersheet!$L$2:$L$400,Mastersheet!$A$2:$A$400,$T$17)/1000) | L17: =IF($T$17="","",SUMIFS(Mastersheet!$M$2:$M$400,Mastersheet!$A$2:$A$400,$T$17)/1000) | M17: =IF($T$17="","",SUMIFS(Mastersheet!$N$2:$N$400,Mastersheet!$A$2:$A$400,$T$17)/1000) | N17: =IF($T$17="","",SUMIFS(Mastersheet!$O$2:$O$400,Mastersheet!$A$2:$A$400,$T$17)/1000) | U17: Account | V17: KTO
C18: Bestandsveränderung | D18: Change in inventory | E18: =SUMIFS(Mastersheet!$F$2:$F$400,Mastersheet!$D$2:$D$400,$T18,Mastersheet!$C$2:$C$400,$U18)/1000 -> 0 | F18: =SUMIFS(Mastersheet!$G$2:$G$400,Mastersheet!$D$2:$D$400,$T18,Mastersheet!$C$2:$C$400,$U18)/1000 -> 0 | G18: =SUMIFS(Mastersheet!$H$2:$H$400,Mastersheet!$D$2:$D$400,$T18,Mastersheet!$C$2:$C$400,$U18)/1000 -> 0 | H18: =SUMIFS(Mastersheet!$I$2:$I$400,Mastersheet!$D$2:$D$400,$T18,Mastersheet!$C$2:$C$400,$U18)/1000 -> 0 | I18: =SUMIFS(Mastersheet!$J$2:$J$400,Mastersheet!$D$2:$D$400,$T18,Mastersheet!$C$2:$C$400,$U18)/1000 -> 0 | J18: =SUMIFS(Mastersheet!$K$2:$K$400,Mastersheet!$D$2:$D$400,$T18,Mastersheet!$C$2:$C$400,$U18)/1000 -> 0 | K18: =SUMIFS(Mastersheet!$L$2:$L$400,Mastersheet!$D$2:$D$400,$T18,Mastersheet!$C$2:$C$400,$U18)/1000 -> 0 | L18: =SUMIFS(Mastersheet!$M$2:$M$400,Mastersheet!$D$2:$D$400,$T18,Mastersheet!$C$2:$C$400,$U18)/1000 -> 0 | M18: =SUMIFS(Mastersheet!$N$2:$N$400,Mastersheet!$D$2:$D$400,$T18,Mastersheet!$C$2:$C$400,$U18)/1000 -> 0 | N18: =SUMIFS(Mastersheet!$O$2:$O$400,Mastersheet!$D$2:$D$400,$T18,Mastersheet!$C$2:$C$400,$U18)/1000 -> 0 | P18: =IFERROR(((H18/F18)^(1/(($H$1-$F$1)/365)))-1,"n/a") -> n/a | Q18: =IFERROR(((N18/H18)^(1/(($N$1-$H$1)/365)))-1,"n/a") -> n/a | T18: Bestandsveraenderung | U18: PL | V18: POS
E19: =IF($T$19="","",SUMIFS(Mastersheet!$F$2:$F$400,Mastersheet!$A$2:$A$400,$T$19)/1000) | F19: =IF($T$19="","",SUMIFS(Mastersheet!$G$2:$G$400,Mastersheet!$A$2:$A$400,$T$19)/1000) | G19: =IF($T$19="","",SUMIFS(Mastersheet!$H$2:$H$400,Mastersheet!$A$2:$A$400,$T$19)/1000) | H19: =IF($T$19="","",SUMIFS(Mastersheet!$I$2:$I$400,Mastersheet!$A$2:$A$400,$T$19)/1000) | I19: =IF($T$19="","",SUMIFS(Mastersheet!$J$2:$J$400,Mastersheet!$A$2:$A$400,$T$19)/1000) | J19: =IF($T$19="","",SUMIFS(Mastersheet!$K$2:$K$400,Mastersheet!$A$2:$A$400,$T$19)/1000) | K19: =IF($T$19="","",SUMIFS(Mastersheet!$L$2:$L$400,Mastersheet!$A$2:$A$400,$T$19)/1000) | L19: =IF($T$19="","",SUMIFS(Mastersheet!$M$2:$M$400,Mastersheet!$A$2:$A$400,$T$19)/1000) | M19: =IF($T$19="","",SUMIFS(Mastersheet!$N$2:$N$400,Mastersheet!$A$2:$A$400,$T$19)/1000) | N19: =IF($T$19="","",SUMIFS(Mastersheet!$O$2:$O$400,Mastersheet!$A$2:$A$400,$T$19)/1000) | U19: Account | V19: KTO
E20: =IF($T$20="","",SUMIFS(Mastersheet!$F$2:$F$400,Mastersheet!$A$2:$A$400,$T$20)/1000) | F20: =IF($T$20="","",SUMIFS(Mastersheet!$G$2:$G$400,Mastersheet!$A$2:$A$400,$T$20)/1000) | G20: =IF($T$20="","",SUMIFS(Mastersheet!$H$2:$H$400,Mastersheet!$A$2:$A$400,$T$20)/1000) | H20: =IF($T$20="","",SUMIFS(Mastersheet!$I$2:$I$400,Mastersheet!$A$2:$A$400,$T$20)/1000) | I20: =IF($T$20="","",SUMIFS(Mastersheet!$J$2:$J$400,Mastersheet!$A$2:$A$400,$T$20)/1000) | J20: =IF($T$20="","",SUMIFS(Mastersheet!$K$2:$K$400,Mastersheet!$A$2:$A$400,$T$20)/1000) | K20: =IF($T$20="","",SUMIFS(Mastersheet!$L$2:$L$400,Mastersheet!$A$2:$A$400,$T$20)/1000) | L20: =IF($T$20="","",SUMIFS(Mastersheet!$M$2:$M$400,Mastersheet!$A$2:$A$400,$T$20)/1000) | M20: =IF($T$20="","",SUMIFS(Mastersheet!$N$2:$N$400,Mastersheet!$A$2:$A$400,$T$20)/1000) | N20: =IF($T$20="","",SUMIFS(Mastersheet!$O$2:$O$400,Mastersheet!$A$2:$A$400,$T$20)/1000) | U20: Account | V20: KTO
E21: =IF($T$21="","",SUMIFS(Mastersheet!$F$2:$F$400,Mastersheet!$A$2:$A$400,$T$21)/1000) | F21: =IF($T$21="","",SUMIFS(Mastersheet!$G$2:$G$400,Mastersheet!$A$2:$A$400,$T$21)/1000) | G21: =IF($T$21="","",SUMIFS(Mastersheet!$H$2:$H$400,Mastersheet!$A$2:$A$400,$T$21)/1000) | H21: =IF($T$21="","",SUMIFS(Mastersheet!$I$2:$I$400,Mastersheet!$A$2:$A$400,$T$21)/1000) | I21: =IF($T$21="","",SUMIFS(Mastersheet!$J$2:$J$400,Mastersheet!$A$2:$A$400,$T$21)/1000) | J21: =IF($T$21="","",SUMIFS(Mastersheet!$K$2:$K$400,Mastersheet!$A$2:$A$400,$T$21)/1000) | K21: =IF($T$21="","",SUMIFS(Mastersheet!$L$2:$L$400,Mastersheet!$A$2:$A$400,$T$21)/1000) | L21: =IF($T$21="","",SUMIFS(Mastersheet!$M$2:$M$400,Mastersheet!$A$2:$A$400,$T$21)/1000) | M21: =IF($T$21="","",SUMIFS(Mastersheet!$N$2:$N$400,Mastersheet!$A$2:$A$400,$T$21)/1000) | N21: =IF($T$21="","",SUMIFS(Mastersheet!$O$2:$O$400,Mastersheet!$A$2:$A$400,$T$21)/1000) | U21: Account | V21: KTO
E22: =IF($T$22="","",SUMIFS(Mastersheet!$F$2:$F$400,Mastersheet!$A$2:$A$400,$T$22)/1000) | F22: =IF($T$22="","",SUMIFS(Mastersheet!$G$2:$G$400,Mastersheet!$A$2:$A$400,$T$22)/1000) | G22: =IF($T$22="","",SUMIFS(Mastersheet!$H$2:$H$400,Mastersheet!$A$2:$A$400,$T$22)/1000) | H22: =IF($T$22="","",SUMIFS(Mastersheet!$I$2:$I$400,Mastersheet!$A$2:$A$400,$T$22)/1000) | I22: =IF($T$22="","",SUMIFS(Mastersheet!$J$2:$J$400,Mastersheet!$A$2:$A$400,$T$22)/1000) | J22: =IF($T$22="","",SUMIFS(Mastersheet!$K$2:$K$400,Mastersheet!$A$2:$A$400,$T$22)/1000) | K22: =IF($T$22="","",SUMIFS(Mastersheet!$L$2:$L$400,Mastersheet!$A$2:$A$400,$T$22)/1000) | L22: =IF($T$22="","",SUMIFS(Mastersheet!$M$2:$M$400,Mastersheet!$A$2:$A$400,$T$22)/1000) | M22: =IF($T$22="","",SUMIFS(Mastersheet!$N$2:$N$400,Mastersheet!$A$2:$A$400,$T$22)/1000) | N22: =IF($T$22="","",SUMIFS(Mastersheet!$O$2:$O$400,Mastersheet!$A$2:$A$400,$T$22)/1000) | U22: Account | V22: KTO
E23: =IF($T$23="","",SUMIFS(Mastersheet!$F$2:$F$400,Mastersheet!$A$2:$A$400,$T$23)/1000) | F23: =IF($T$23="","",SUMIFS(Mastersheet!$G$2:$G$400,Mastersheet!$A$2:$A$400,$T$23)/1000) | G23: =IF($T$23="","",SUMIFS(Mastersheet!$H$2:$H$400,Mastersheet!$A$2:$A$400,$T$23)/1000) | H23: =IF($T$23="","",SUMIFS(Mastersheet!$I$2:$I$400,Mastersheet!$A$2:$A$400,$T$23)/1000) | I23: =IF($T$23="","",SUMIFS(Mastersheet!$J$2:$J$400,Mastersheet!$A$2:$A$400,$T$23)/1000) | J23: =IF($T$23="","",SUMIFS(Mastersheet!$K$2:$K$400,Mastersheet!$A$2:$A$400,$T$23)/1000) | K23: =IF($T$23="","",SUMIFS(Mastersheet!$L$2:$L$400,Mastersheet!$A$2:$A$400,$T$23)/1000) | L23: =IF($T$23="","",SUMIFS(Mastersheet!$M$2:$M$400,Mastersheet!$A$2:$A$400,$T$23)/1000) | M23: =IF($T$23="","",SUMIFS(Mastersheet!$N$2:$N$400,Mastersheet!$A$2:$A$400,$T$23)/1000) | N23: =IF($T$23="","",SUMIFS(Mastersheet!$O$2:$O$400,Mastersheet!$A$2:$A$400,$T$23)/1000) | U23: Account | V23: KTO
E24: =IF($T$24="","",SUMIFS(Mastersheet!$F$2:$F$400,Mastersheet!$A$2:$A$400,$T$24)/1000) | F24: =IF($T$24="","",SUMIFS(Mastersheet!$G$2:$G$400,Mastersheet!$A$2:$A$400,$T$24)/1000) | G24: =IF($T$24="","",SUMIFS(Mastersheet!$H$2:$H$400,Mastersheet!$A$2:$A$400,$T$24)/1000) | H24: =IF($T$24="","",SUMIFS(Mastersheet!$I$2:$I$400,Mastersheet!$A$2:$A$400,$T$24)/1000) | I24: =IF($T$24="","",SUMIFS(Mastersheet!$J$2:$J$400,Mastersheet!$A$2:$A$400,$T$24)/1000) | J24: =IF($T$24="","",SUMIFS(Mastersheet!$K$2:$K$400,Mastersheet!$A$2:$A$400,$T$24)/1000) | K24: =IF($T$24="","",SUMIFS(Mastersheet!$L$2:$L$400,Mastersheet!$A$2:$A$400,$T$24)/1000) | L24: =IF($T$24="","",SUMIFS(Mastersheet!$M$2:$M$400,Mastersheet!$A$2:$A$400,$T$24)/1000) | M24: =IF($T$24="","",SUMIFS(Mastersheet!$N$2:$N$400,Mastersheet!$A$2:$A$400,$T$24)/1000) | N24: =IF($T$24="","",SUMIFS(Mastersheet!$O$2:$O$400,Mastersheet!$A$2:$A$400,$T$24)/1000) | U24: Account | V24: KTO
E25: =IF($T$25="","",SUMIFS(Mastersheet!$F$2:$F$400,Mastersheet!$A$2:$A$400,$T$25)/1000) | F25: =IF($T$25="","",SUMIFS(Mastersheet!$G$2:$G$400,Mastersheet!$A$2:$A$400,$T$25)/1000) | G25: =IF($T$25="","",SUMIFS(Mastersheet!$H$2:$H$400,Mastersheet!$A$2:$A$400,$T$25)/1000) | H25: =IF($T$25="","",SUMIFS(Mastersheet!$I$2:$I$400,Mastersheet!$A$2:$A$400,$T$25)/1000) | I25: =IF($T$25="","",SUMIFS(Mastersheet!$J$2:$J$400,Mastersheet!$A$2:$A$400,$T$25)/1000) | J25: =IF($T$25="","",SUMIFS(Mastersheet!$K$2:$K$400,Mastersheet!$A$2:$A$400,$T$25)/1000) | K25: =IF($T$25="","",SUMIFS(Mastersheet!$L$2:$L$400,Mastersheet!$A$2:$A$400,$T$25)/1000) | L25: =IF($T$25="","",SUMIFS(Mastersheet!$M$2:$M$400,Mastersheet!$A$2:$A$400,$T$25)/1000) | M25: =IF($T$25="","",SUMIFS(Mastersheet!$N$2:$N$400,Mastersheet!$A$2:$A$400,$T$25)/1000) | N25: =IF($T$25="","",SUMIFS(Mastersheet!$O$2:$O$400,Mastersheet!$A$2:$A$400,$T$25)/1000) | U25: Account | V25: KTO
E26: =IF($T$26="","",SUMIFS(Mastersheet!$F$2:$F$400,Mastersheet!$A$2:$A$400,$T$26)/1000) | F26: =IF($T$26="","",SUMIFS(Mastersheet!$G$2:$G$400,Mastersheet!$A$2:$A$400,$T$26)/1000) | G26: =IF($T$26="","",SUMIFS(Mastersheet!$H$2:$H$400,Mastersheet!$A$2:$A$400,$T$26)/1000) | H26: =IF($T$26="","",SUMIFS(Mastersheet!$I$2:$I$400,Mastersheet!$A$2:$A$400,$T$26)/1000) | I26: =IF($T$26="","",SUMIFS(Mastersheet!$J$2:$J$400,Mastersheet!$A$2:$A$400,$T$26)/1000) | J26: =IF($T$26="","",SUMIFS(Mastersheet!$K$2:$K$400,Mastersheet!$A$2:$A$400,$T$26)/1000) | K26: =IF($T$26="","",SUMIFS(Mastersheet!$L$2:$L$400,Mastersheet!$A$2:$A$400,$T$26)/1000) | L26: =IF($T$26="","",SUMIFS(Mastersheet!$M$2:$M$400,Mastersheet!$A$2:$A$400,$T$26)/1000) | M26: =IF($T$26="","",SUMIFS(Mastersheet!$N$2:$N$400,Mastersheet!$A$2:$A$400,$T$26)/1000) | N26: =IF($T$26="","",SUMIFS(Mastersheet!$O$2:$O$400,Mastersheet!$A$2:$A$400,$T$26)/1000) | U26: Account | V26: KTO
C27: Aktivierte Eigenleistungen | D27: Own work capitalized | E27: =SUMIFS(Mastersheet!$F$2:$F$400,Mastersheet!$D$2:$D$400,$T27,Mastersheet!$C$2:$C$400,$U27)/1000 -> 0 | F27: =SUMIFS(Mastersheet!$G$2:$G$400,Mastersheet!$D$2:$D$400,$T27,Mastersheet!$C$2:$C$400,$U27)/1000 -> 0 | G27: =SUMIFS(Mastersheet!$H$2:$H$400,Mastersheet!$D$2:$D$400,$T27,Mastersheet!$C$2:$C$400,$U27)/1000 -> 0 | H27: =SUMIFS(Mastersheet!$I$2:$I$400,Mastersheet!$D$2:$D$400,$T27,Mastersheet!$C$2:$C$400,$U27)/1000 -> 0 | I27: =SUMIFS(Mastersheet!$J$2:$J$400,Mastersheet!$D$2:$D$400,$T27,Mastersheet!$C$2:$C$400,$U27)/1000 -> 0 | J27: =SUMIFS(Mastersheet!$K$2:$K$400,Mastersheet!$D$2:$D$400,$T27,Mastersheet!$C$2:$C$400,$U27)/1000 -> 0 | K27: =SUMIFS(Mastersheet!$L$2:$L$400,Mastersheet!$D$2:$D$400,$T27,Mastersheet!$C$2:$C$400,$U27)/1000 -> 0 | L27: =SUMIFS(Mastersheet!$M$2:$M$400,Mastersheet!$D$2:$D$400,$T27,Mastersheet!$C$2:$C$400,$U27)/1000 -> 0 | M27: =SUMIFS(Mastersheet!$N$2:$N$400,Mastersheet!$D$2:$D$400,$T27,Mastersheet!$C$2:$C$400,$U27)/1000 -> 0 | N27: =SUMIFS(Mastersheet!$O$2:$O$400,Mastersheet!$D$2:$D$400,$T27,Mastersheet!$C$2:$C$400,$U27)/1000 -> 0 | P27: =IFERROR(((H27/F27)^(1/(($H$1-$F$1)/365)))-1,"n/a") -> n/a | Q27: =IFERROR(((N27/H27)^(1/(($N$1-$H$1)/365)))-1,"n/a") -> n/a | T27: Aktivierte Eigenleistungen | U27: PL | V27: POS
E28: =IF($T$28="","",SUMIFS(Mastersheet!$F$2:$F$400,Mastersheet!$A$2:$A$400,$T$28)/1000) | F28: =IF($T$28="","",SUMIFS(Mastersheet!$G$2:$G$400,Mastersheet!$A$2:$A$400,$T$28)/1000) | G28: =IF($T$28="","",SUMIFS(Mastersheet!$H$2:$H$400,Mastersheet!$A$2:$A$400,$T$28)/1000) | H28: =IF($T$28="","",SUMIFS(Mastersheet!$I$2:$I$400,Mastersheet!$A$2:$A$400,$T$28)/1000) | I28: =IF($T$28="","",SUMIFS(Mastersheet!$J$2:$J$400,Mastersheet!$A$2:$A$400,$T$28)/1000) | J28: =IF($T$28="","",SUMIFS(Mastersheet!$K$2:$K$400,Mastersheet!$A$2:$A$400,$T$28)/1000) | K28: =IF($T$28="","",SUMIFS(Mastersheet!$L$2:$L$400,Mastersheet!$A$2:$A$400,$T$28)/1000) | L28: =IF($T$28="","",SUMIFS(Mastersheet!$M$2:$M$400,Mastersheet!$A$2:$A$400,$T$28)/1000) | M28: =IF($T$28="","",SUMIFS(Mastersheet!$N$2:$N$400,Mastersheet!$A$2:$A$400,$T$28)/1000) | N28: =IF($T$28="","",SUMIFS(Mastersheet!$O$2:$O$400,Mastersheet!$A$2:$A$400,$T$28)/1000) | U28: Account | V28: KTO
E29: =IF($T$29="","",SUMIFS(Mastersheet!$F$2:$F$400,Mastersheet!$A$2:$A$400,$T$29)/1000) | F29: =IF($T$29="","",SUMIFS(Mastersheet!$G$2:$G$400,Mastersheet!$A$2:$A$400,$T$29)/1000) | G29: =IF($T$29="","",SUMIFS(Mastersheet!$H$2:$H$400,Mastersheet!$A$2:$A$400,$T$29)/1000) | H29: =IF($T$29="","",SUMIFS(Mastersheet!$I$2:$I$400,Mastersheet!$A$2:$A$400,$T$29)/1000) | I29: =IF($T$29="","",SUMIFS(Mastersheet!$J$2:$J$400,Mastersheet!$A$2:$A$400,$T$29)/1000) | J29: =IF($T$29="","",SUMIFS(Mastersheet!$K$2:$K$400,Mastersheet!$A$2:$A$400,$T$29)/1000) | K29: =IF($T$29="","",SUMIFS(Mastersheet!$L$2:$L$400,Mastersheet!$A$2:$A$400,$T$29)/1000) | L29: =IF($T$29="","",SUMIFS(Mastersheet!$M$2:$M$400,Mastersheet!$A$2:$A$400,$T$29)/1000) | M29: =IF($T$29="","",SUMIFS(Mastersheet!$N$2:$N$400,Mastersheet!$A$2:$A$400,$T$29)/1000) | N29: =IF($T$29="","",SUMIFS(Mastersheet!$O$2:$O$400,Mastersheet!$A$2:$A$400,$T$29)/1000) | U29: Account | V29: KTO
E30: =IF($T$30="","",SUMIFS(Mastersheet!$F$2:$F$400,Mastersheet!$A$2:$A$400,$T$30)/1000) | F30: =IF($T$30="","",SUMIFS(Mastersheet!$G$2:$G$400,Mastersheet!$A$2:$A$400,$T$30)/1000) | G30: =IF($T$30="","",SUMIFS(Mastersheet!$H$2:$H$400,Mastersheet!$A$2:$A$400,$T$30)/1000) | H30: =IF($T$30="","",SUMIFS(Mastersheet!$I$2:$I$400,Mastersheet!$A$2:$A$400,$T$30)/1000) | I30: =IF($T$30="","",SUMIFS(Mastersheet!$J$2:$J$400,Mastersheet!$A$2:$A$400,$T$30)/1000) | J30: =IF($T$30="","",SUMIFS(Mastersheet!$K$2:$K$400,Mastersheet!$A$2:$A$400,$T$30)/1000) | K30: =IF($T$30="","",SUMIFS(Mastersheet!$L$2:$L$400,Mastersheet!$A$2:$A$400,$T$30)/1000) | L30: =IF($T$30="","",SUMIFS(Mastersheet!$M$2:$M$400,Mastersheet!$A$2:$A$400,$T$30)/1000) | M30: =IF($T$30="","",SUMIFS(Mastersheet!$N$2:$N$400,Mastersheet!$A$2:$A$400,$T$30)/1000) | N30: =IF($T$30="","",SUMIFS(Mastersheet!$O$2:$O$400,Mastersheet!$A$2:$A$400,$T$30)/1000) | U30: Account | V30: KTO
E31: =IF($T$31="","",SUMIFS(Mastersheet!$F$2:$F$400,Mastersheet!$A$2:$A$400,$T$31)/1000) | F31: =IF($T$31="","",SUMIFS(Mastersheet!$G$2:$G$400,Mastersheet!$A$2:$A$400,$T$31)/1000) | G31: =IF($T$31="","",SUMIFS(Mastersheet!$H$2:$H$400,Mastersheet!$A$2:$A$400,$T$31)/1000) | H31: =IF($T$31="","",SUMIFS(Mastersheet!$I$2:$I$400,Mastersheet!$A$2:$A$400,$T$31)/1000) | I31: =IF($T$31="","",SUMIFS(Mastersheet!$J$2:$J$400,Mastersheet!$A$2:$A$400,$T$31)/1000) | J31: =IF($T$31="","",SUMIFS(Mastersheet!$K$2:$K$400,Mastersheet!$A$2:$A$400,$T$31)/1000) | K31: =IF($T$31="","",SUMIFS(Mastersheet!$L$2:$L$400,Mastersheet!$A$2:$A$400,$T$31)/1000) | L31: =IF($T$31="","",SUMIFS(Mastersheet!$M$2:$M$400,Mastersheet!$A$2:$A$400,$T$31)/1000) | M31: =IF($T$31="","",SUMIFS(Mastersheet!$N$2:$N$400,Mastersheet!$A$2:$A$400,$T$31)/1000) | N31: =IF($T$31="","",SUMIFS(Mastersheet!$O$2:$O$400,Mastersheet!$A$2:$A$400,$T$31)/1000) | U31: Account | V31: KTO
E32: =IF($T$32="","",SUMIFS(Mastersheet!$F$2:$F$400,Mastersheet!$A$2:$A$400,$T$32)/1000) | F32: =IF($T$32="","",SUMIFS(Mastersheet!$G$2:$G$400,Mastersheet!$A$2:$A$400,$T$32)/1000) | G32: =IF($T$32="","",SUMIFS(Mastersheet!$H$2:$H$400,Mastersheet!$A$2:$A$400,$T$32)/1000) | H32: =IF($T$32="","",SUMIFS(Mastersheet!$I$2:$I$400,Mastersheet!$A$2:$A$400,$T$32)/1000) | I32: =IF($T$32="","",SUMIFS(Mastersheet!$J$2:$J$400,Mastersheet!$A$2:$A$400,$T$32)/1000) | J32: =IF($T$32="","",SUMIFS(Mastersheet!$K$2:$K$400,Mastersheet!$A$2:$A$400,$T$32)/1000) | K32: =IF($T$32="","",SUMIFS(Mastersheet!$L$2:$L$400,Mastersheet!$A$2:$A$400,$T$32)/1000) | L32: =IF($T$32="","",SUMIFS(Mastersheet!$M$2:$M$400,Mastersheet!$A$2:$A$400,$T$32)/1000) | M32: =IF($T$32="","",SUMIFS(Mastersheet!$N$2:$N$400,Mastersheet!$A$2:$A$400,$T$32)/1000) | N32: =IF($T$32="","",SUMIFS(Mastersheet!$O$2:$O$400,Mastersheet!$A$2:$A$400,$T$32)/1000) | U32: Account | V32: KTO
E33: =IF($T$33="","",SUMIFS(Mastersheet!$F$2:$F$400,Mastersheet!$A$2:$A$400,$T$33)/1000) | F33: =IF($T$33="","",SUMIFS(Mastersheet!$G$2:$G$400,Mastersheet!$A$2:$A$400,$T$33)/1000) | G33: =IF($T$33="","",SUMIFS(Mastersheet!$H$2:$H$400,Mastersheet!$A$2:$A$400,$T$33)/1000) | H33: =IF($T$33="","",SUMIFS(Mastersheet!$I$2:$I$400,Mastersheet!$A$2:$A$400,$T$33)/1000) | I33: =IF($T$33="","",SUMIFS(Mastersheet!$J$2:$J$400,Mastersheet!$A$2:$A$400,$T$33)/1000) | J33: =IF($T$33="","",SUMIFS(Mastersheet!$K$2:$K$400,Mastersheet!$A$2:$A$400,$T$33)/1000) | K33: =IF($T$33="","",SUMIFS(Mastersheet!$L$2:$L$400,Mastersheet!$A$2:$A$400,$T$33)/1000) | L33: =IF($T$33="","",SUMIFS(Mastersheet!$M$2:$M$400,Mastersheet!$A$2:$A$400,$T$33)/1000) | M33: =IF($T$33="","",SUMIFS(Mastersheet!$N$2:$N$400,Mastersheet!$A$2:$A$400,$T$33)/1000) | N33: =IF($T$33="","",SUMIFS(Mastersheet!$O$2:$O$400,Mastersheet!$A$2:$A$400,$T$33)/1000) | U33: Account | V33: KTO
E34: =IF($T$34="","",SUMIFS(Mastersheet!$F$2:$F$400,Mastersheet!$A$2:$A$400,$T$34)/1000) | F34: =IF($T$34="","",SUMIFS(Mastersheet!$G$2:$G$400,Mastersheet!$A$2:$A$400,$T$34)/1000) | G34: =IF($T$34="","",SUMIFS(Mastersheet!$H$2:$H$400,Mastersheet!$A$2:$A$400,$T$34)/1000) | H34: =IF($T$34="","",SUMIFS(Mastersheet!$I$2:$I$400,Mastersheet!$A$2:$A$400,$T$34)/1000) | I34: =IF($T$34="","",SUMIFS(Mastersheet!$J$2:$J$400,Mastersheet!$A$2:$A$400,$T$34)/1000) | J34: =IF($T$34="","",SUMIFS(Mastersheet!$K$2:$K$400,Mastersheet!$A$2:$A$400,$T$34)/1000) | K34: =IF($T$34="","",SUMIFS(Mastersheet!$L$2:$L$400,Mastersheet!$A$2:$A$400,$T$34)/1000) | L34: =IF($T$34="","",SUMIFS(Mastersheet!$M$2:$M$400,Mastersheet!$A$2:$A$400,$T$34)/1000) | M34: =IF($T$34="","",SUMIFS(Mastersheet!$N$2:$N$400,Mastersheet!$A$2:$A$400,$T$34)/1000) | N34: =IF($T$34="","",SUMIFS(Mastersheet!$O$2:$O$400,Mastersheet!$A$2:$A$400,$T$34)/1000) | U34: Account | V34: KTO
E35: =IF($T$35="","",SUMIFS(Mastersheet!$F$2:$F$400,Mastersheet!$A$2:$A$400,$T$35)/1000) | F35: =IF($T$35="","",SUMIFS(Mastersheet!$G$2:$G$400,Mastersheet!$A$2:$A$400,$T$35)/1000) | G35: =IF($T$35="","",SUMIFS(Mastersheet!$H$2:$H$400,Mastersheet!$A$2:$A$400,$T$35)/1000) | H35: =IF($T$35="","",SUMIFS(Mastersheet!$I$2:$I$400,Mastersheet!$A$2:$A$400,$T$35)/1000) | I35: =IF($T$35="","",SUMIFS(Mastersheet!$J$2:$J$400,Mastersheet!$A$2:$A$400,$T$35)/1000) | J35: =IF($T$35="","",SUMIFS(Mastersheet!$K$2:$K$400,Mastersheet!$A$2:$A$400,$T$35)/1000) | K35: =IF($T$35="","",SUMIFS(Mastersheet!$L$2:$L$400,Mastersheet!$A$2:$A$400,$T$35)/1000) | L35: =IF($T$35="","",SUMIFS(Mastersheet!$M$2:$M$400,Mastersheet!$A$2:$A$400,$T$35)/1000) | M35: =IF($T$35="","",SUMIFS(Mastersheet!$N$2:$N$400,Mastersheet!$A$2:$A$400,$T$35)/1000) | N35: =IF($T$35="","",SUMIFS(Mastersheet!$O$2:$O$400,Mastersheet!$A$2:$A$400,$T$35)/1000) | U35: Account | V35: KTO
C36: Dummy 1 | D36: Dummy 1 | P36: =IFERROR(((H36/F36)^(1/(($H$1-$F$1)/365)))-1,"n/a") -> n/a | Q36: =IFERROR(((N36/H36)^(1/(($N$1-$H$1)/365)))-1,"n/a") -> n/a
C37: Dummy 2 | D37: Dummy 2 | P37: =IFERROR(((H37/F37)^(1/(($H$1-$F$1)/365)))-1,"n/a") -> n/a | Q37: =IFERROR(((N37/H37)^(1/(($N$1-$H$1)/365)))-1,"n/a") -> n/a
C38: Dummy 3 | D38: Dummy 3 | P38: =IFERROR(((H38/F38)^(1/(($H$1-$F$1)/365)))-1,"n/a") -> n/a | Q38: =IFERROR(((N38/H38)^(1/(($N$1-$H$1)/365)))-1,"n/a") -> n/a
C39: Gesamtleistung | D39: Total output | E39: =SUMIF($V$9:$V$38,"<>KTO",E9:E38) -> 0 | F39: =SUMIF($V$9:$V$38,"<>KTO",F9:F38) -> 0 | G39: =SUMIF($V$9:$V$38,"<>KTO",G9:G38) -> 0 | H39: =SUMIF($V$9:$V$38,"<>KTO",H9:H38) -> 0 | I39: =SUMIF($V$9:$V$38,"<>KTO",I9:I38) -> 0 | J39: =SUMIF($V$9:$V$38,"<>KTO",J9:J38) -> 0 | K39: =SUMIF($V$9:$V$38,"<>KTO",K9:K38) -> 0 | L39: =SUMIF($V$9:$V$38,"<>KTO",L9:L38) -> 0 | ... N39: =SUMIF($V$9:$V$38,"<>KTO",N9:N38) -> 0 | P39: =IFERROR(((H39/F39)^(1/(($H$1-$F$1)/365)))-1,"n/a") -> n/a | Q39: =IFERROR(((N39/H39)^(1/(($N$1-$H$1)/365)))-1,"n/a") -> n/a
C40: Materialaufwand | D40: Cost of materials | E40: =SUMIFS(Mastersheet!$F$2:$F$400,Mastersheet!$D$2:$D$400,$T40,Mastersheet!$C$2:$C$400,$U40)/1000 -> 0 | F40: =SUMIFS(Mastersheet!$G$2:$G$400,Mastersheet!$D$2:$D$400,$T40,Mastersheet!$C$2:$C$400,$U40)/1000 -> 0 | G40: =SUMIFS(Mastersheet!$H$2:$H$400,Mastersheet!$D$2:$D$400,$T40,Mastersheet!$C$2:$C$400,$U40)/1000 -> 0 | H40: =SUMIFS(Mastersheet!$I$2:$I$400,Mastersheet!$D$2:$D$400,$T40,Mastersheet!$C$2:$C$400,$U40)/1000 -> 0 | I40: =SUMIFS(Mastersheet!$J$2:$J$400,Mastersheet!$D$2:$D$400,$T40,Mastersheet!$C$2:$C$400,$U40)/1000 -> 0 | J40: =SUMIFS(Mastersheet!$K$2:$K$400,Mastersheet!$D$2:$D$400,$T40,Mastersheet!$C$2:$C$400,$U40)/1000 -> 0 | K40: =SUMIFS(Mastersheet!$L$2:$L$400,Mastersheet!$D$2:$D$400,$T40,Mastersheet!$C$2:$C$400,$U40)/1000 -> 0 | L40: =SUMIFS(Mastersheet!$M$2:$M$400,Mastersheet!$D$2:$D$400,$T40,Mastersheet!$C$2:$C$400,$U40)/1000 -> 0 | M40: =SUMIFS(Mastersheet!$N$2:$N$400,Mastersheet!$D$2:$D$400,$T40,Mastersheet!$C$2:$C$400,$U40)/1000 -> 0 | N40: =SUMIFS(Mastersheet!$O$2:$O$400,Mastersheet!$D$2:$D$400,$T40,Mastersheet!$C$2:$C$400,$U40)/1000 -> 0 | P40: =IFERROR(((H40/F40)^(1/(($H$1-$F$1)/365)))-1,"n/a") -> n/a | Q40: =IFERROR(((N40/H40)^(1/(($N$1-$H$1)/365)))-1,"n/a") -> n/a | T40: Materialaufwand | U40: PL | V40: POS
E41: =IF($T$41="","",SUMIFS(Mastersheet!$F$2:$F$400,Mastersheet!$A$2:$A$400,$T$41)/1000) | F41: =IF($T$41="","",SUMIFS(Mastersheet!$G$2:$G$400,Mastersheet!$A$2:$A$400,$T$41)/1000) | G41: =IF($T$41="","",SUMIFS(Mastersheet!$H$2:$H$400,Mastersheet!$A$2:$A$400,$T$41)/1000) | H41: =IF($T$41="","",SUMIFS(Mastersheet!$I$2:$I$400,Mastersheet!$A$2:$A$400,$T$41)/1000) | I41: =IF($T$41="","",SUMIFS(Mastersheet!$J$2:$J$400,Mastersheet!$A$2:$A$400,$T$41)/1000) | J41: =IF($T$41="","",SUMIFS(Mastersheet!$K$2:$K$400,Mastersheet!$A$2:$A$400,$T$41)/1000) | K41: =IF($T$41="","",SUMIFS(Mastersheet!$L$2:$L$400,Mastersheet!$A$2:$A$400,$T$41)/1000) | L41: =IF($T$41="","",SUMIFS(Mastersheet!$M$2:$M$400,Mastersheet!$A$2:$A$400,$T$41)/1000) | M41: =IF($T$41="","",SUMIFS(Mastersheet!$N$2:$N$400,Mastersheet!$A$2:$A$400,$T$41)/1000) | N41: =IF($T$41="","",SUMIFS(Mastersheet!$O$2:$O$400,Mastersheet!$A$2:$A$400,$T$41)/1000) | U41: Account | V41: KTO
E42: =IF($T$42="","",SUMIFS(Mastersheet!$F$2:$F$400,Mastersheet!$A$2:$A$400,$T$42)/1000) | F42: =IF($T$42="","",SUMIFS(Mastersheet!$G$2:$G$400,Mastersheet!$A$2:$A$400,$T$42)/1000) | G42: =IF($T$42="","",SUMIFS(Mastersheet!$H$2:$H$400,Mastersheet!$A$2:$A$400,$T$42)/1000) | H42: =IF($T$42="","",SUMIFS(Mastersheet!$I$2:$I$400,Mastersheet!$A$2:$A$400,$T$42)/1000) | I42: =IF($T$42="","",SUMIFS(Mastersheet!$J$2:$J$400,Mastersheet!$A$2:$A$400,$T$42)/1000) | J42: =IF($T$42="","",SUMIFS(Mastersheet!$K$2:$K$400,Mastersheet!$A$2:$A$400,$T$42)/1000) | K42: =IF($T$42="","",SUMIFS(Mastersheet!$L$2:$L$400,Mastersheet!$A$2:$A$400,$T$42)/1000) | L42: =IF($T$42="","",SUMIFS(Mastersheet!$M$2:$M$400,Mastersheet!$A$2:$A$400,$T$42)/1000) | M42: =IF($T$42="","",SUMIFS(Mastersheet!$N$2:$N$400,Mastersheet!$A$2:$A$400,$T$42)/1000) | N42: =IF($T$42="","",SUMIFS(Mastersheet!$O$2:$O$400,Mastersheet!$A$2:$A$400,$T$42)/1000) | U42: Account | V42: KTO
E43: =IF($T$43="","",SUMIFS(Mastersheet!$F$2:$F$400,Mastersheet!$A$2:$A$400,$T$43)/1000) | F43: =IF($T$43="","",SUMIFS(Mastersheet!$G$2:$G$400,Mastersheet!$A$2:$A$400,$T$43)/1000) | G43: =IF($T$43="","",SUMIFS(Mastersheet!$H$2:$H$400,Mastersheet!$A$2:$A$400,$T$43)/1000) | H43: =IF($T$43="","",SUMIFS(Mastersheet!$I$2:$I$400,Mastersheet!$A$2:$A$400,$T$43)/1000) | I43: =IF($T$43="","",SUMIFS(Mastersheet!$J$2:$J$400,Mastersheet!$A$2:$A$400,$T$43)/1000) | J43: =IF($T$43="","",SUMIFS(Mastersheet!$K$2:$K$400,Mastersheet!$A$2:$A$400,$T$43)/1000) | K43: =IF($T$43="","",SUMIFS(Mastersheet!$L$2:$L$400,Mastersheet!$A$2:$A$400,$T$43)/1000) | L43: =IF($T$43="","",SUMIFS(Mastersheet!$M$2:$M$400,Mastersheet!$A$2:$A$400,$T$43)/1000) | M43: =IF($T$43="","",SUMIFS(Mastersheet!$N$2:$N$400,Mastersheet!$A$2:$A$400,$T$43)/1000) | N43: =IF($T$43="","",SUMIFS(Mastersheet!$O$2:$O$400,Mastersheet!$A$2:$A$400,$T$43)/1000) | U43: Account | V43: KTO
E44: =IF($T$44="","",SUMIFS(Mastersheet!$F$2:$F$400,Mastersheet!$A$2:$A$400,$T$44)/1000) | F44: =IF($T$44="","",SUMIFS(Mastersheet!$G$2:$G$400,Mastersheet!$A$2:$A$400,$T$44)/1000) | G44: =IF($T$44="","",SUMIFS(Mastersheet!$H$2:$H$400,Mastersheet!$A$2:$A$400,$T$44)/1000) | H44: =IF($T$44="","",SUMIFS(Mastersheet!$I$2:$I$400,Mastersheet!$A$2:$A$400,$T$44)/1000) | I44: =IF($T$44="","",SUMIFS(Mastersheet!$J$2:$J$400,Mastersheet!$A$2:$A$400,$T$44)/1000) | J44: =IF($T$44="","",SUMIFS(Mastersheet!$K$2:$K$400,Mastersheet!$A$2:$A$400,$T$44)/1000) | K44: =IF($T$44="","",SUMIFS(Mastersheet!$L$2:$L$400,Mastersheet!$A$2:$A$400,$T$44)/1000) | L44: =IF($T$44="","",SUMIFS(Mastersheet!$M$2:$M$400,Mastersheet!$A$2:$A$400,$T$44)/1000) | M44: =IF($T$44="","",SUMIFS(Mastersheet!$N$2:$N$400,Mastersheet!$A$2:$A$400,$T$44)/1000) | N44: =IF($T$44="","",SUMIFS(Mastersheet!$O$2:$O$400,Mastersheet!$A$2:$A$400,$T$44)/1000) | U44: Account | V44: KTO
E45: =IF($T$45="","",SUMIFS(Mastersheet!$F$2:$F$400,Mastersheet!$A$2:$A$400,$T$45)/1000) | F45: =IF($T$45="","",SUMIFS(Mastersheet!$G$2:$G$400,Mastersheet!$A$2:$A$400,$T$45)/1000) | G45: =IF($T$45="","",SUMIFS(Mastersheet!$H$2:$H$400,Mastersheet!$A$2:$A$400,$T$45)/1000) | H45: =IF($T$45="","",SUMIFS(Mastersheet!$I$2:$I$400,Mastersheet!$A$2:$A$400,$T$45)/1000) | I45: =IF($T$45="","",SUMIFS(Mastersheet!$J$2:$J$400,Mastersheet!$A$2:$A$400,$T$45)/1000) | J45: =IF($T$45="","",SUMIFS(Mastersheet!$K$2:$K$400,Mastersheet!$A$2:$A$400,$T$45)/1000) | K45: =IF($T$45="","",SUMIFS(Mastersheet!$L$2:$L$400,Mastersheet!$A$2:$A$400,$T$45)/1000) | L45: =IF($T$45="","",SUMIFS(Mastersheet!$M$2:$M$400,Mastersheet!$A$2:$A$400,$T$45)/1000) | M45: =IF($T$45="","",SUMIFS(Mastersheet!$N$2:$N$400,Mastersheet!$A$2:$A$400,$T$45)/1000) | N45: =IF($T$45="","",SUMIFS(Mastersheet!$O$2:$O$400,Mastersheet!$A$2:$A$400,$T$45)/1000) | U45: Account | V45: KTO
E46: =IF($T$46="","",SUMIFS(Mastersheet!$F$2:$F$400,Mastersheet!$A$2:$A$400,$T$46)/1000) | F46: =IF($T$46="","",SUMIFS(Mastersheet!$G$2:$G$400,Mastersheet!$A$2:$A$400,$T$46)/1000) | G46: =IF($T$46="","",SUMIFS(Mastersheet!$H$2:$H$400,Mastersheet!$A$2:$A$400,$T$46)/1000) | H46: =IF($T$46="","",SUMIFS(Mastersheet!$I$2:$I$400,Mastersheet!$A$2:$A$400,$T$46)/1000) | I46: =IF($T$46="","",SUMIFS(Mastersheet!$J$2:$J$400,Mastersheet!$A$2:$A$400,$T$46)/1000) | J46: =IF($T$46="","",SUMIFS(Mastersheet!$K$2:$K$400,Mastersheet!$A$2:$A$400,$T$46)/1000) | K46: =IF($T$46="","",SUMIFS(Mastersheet!$L$2:$L$400,Mastersheet!$A$2:$A$400,$T$46)/1000) | L46: =IF($T$46="","",SUMIFS(Mastersheet!$M$2:$M$400,Mastersheet!$A$2:$A$400,$T$46)/1000) | M46: =IF($T$46="","",SUMIFS(Mastersheet!$N$2:$N$400,Mastersheet!$A$2:$A$400,$T$46)/1000) | N46: =IF($T$46="","",SUMIFS(Mastersheet!$O$2:$O$400,Mastersheet!$A$2:$A$400,$T$46)/1000) | U46: Account | V46: KTO
E47: =IF($T$47="","",SUMIFS(Mastersheet!$F$2:$F$400,Mastersheet!$A$2:$A$400,$T$47)/1000) | F47: =IF($T$47="","",SUMIFS(Mastersheet!$G$2:$G$400,Mastersheet!$A$2:$A$400,$T$47)/1000) | G47: =IF($T$47="","",SUMIFS(Mastersheet!$H$2:$H$400,Mastersheet!$A$2:$A$400,$T$47)/1000) | H47: =IF($T$47="","",SUMIFS(Mastersheet!$I$2:$I$400,Mastersheet!$A$2:$A$400,$T$47)/1000) | I47: =IF($T$47="","",SUMIFS(Mastersheet!$J$2:$J$400,Mastersheet!$A$2:$A$400,$T$47)/1000) | J47: =IF($T$47="","",SUMIFS(Mastersheet!$K$2:$K$400,Mastersheet!$A$2:$A$400,$T$47)/1000) | K47: =IF($T$47="","",SUMIFS(Mastersheet!$L$2:$L$400,Mastersheet!$A$2:$A$400,$T$47)/1000) | L47: =IF($T$47="","",SUMIFS(Mastersheet!$M$2:$M$400,Mastersheet!$A$2:$A$400,$T$47)/1000) | M47: =IF($T$47="","",SUMIFS(Mastersheet!$N$2:$N$400,Mastersheet!$A$2:$A$400,$T$47)/1000) | N47: =IF($T$47="","",SUMIFS(Mastersheet!$O$2:$O$400,Mastersheet!$A$2:$A$400,$T$47)/1000) | U47: Account | V47: KTO
E48: =IF($T$48="","",SUMIFS(Mastersheet!$F$2:$F$400,Mastersheet!$A$2:$A$400,$T$48)/1000) | F48: =IF($T$48="","",SUMIFS(Mastersheet!$G$2:$G$400,Mastersheet!$A$2:$A$400,$T$48)/1000) | G48: =IF($T$48="","",SUMIFS(Mastersheet!$H$2:$H$400,Mastersheet!$A$2:$A$400,$T$48)/1000) | H48: =IF($T$48="","",SUMIFS(Mastersheet!$I$2:$I$400,Mastersheet!$A$2:$A$400,$T$48)/1000) | I48: =IF($T$48="","",SUMIFS(Mastersheet!$J$2:$J$400,Mastersheet!$A$2:$A$400,$T$48)/1000) | J48: =IF($T$48="","",SUMIFS(Mastersheet!$K$2:$K$400,Mastersheet!$A$2:$A$400,$T$48)/1000) | K48: =IF($T$48="","",SUMIFS(Mastersheet!$L$2:$L$400,Mastersheet!$A$2:$A$400,$T$48)/1000) | L48: =IF($T$48="","",SUMIFS(Mastersheet!$M$2:$M$400,Mastersheet!$A$2:$A$400,$T$48)/1000) | M48: =IF($T$48="","",SUMIFS(Mastersheet!$N$2:$N$400,Mastersheet!$A$2:$A$400,$T$48)/1000) | N48: =IF($T$48="","",SUMIFS(Mastersheet!$O$2:$O$400,Mastersheet!$A$2:$A$400,$T$48)/1000) | U48: Account | V48: KTO
C49: Dummy 1 | D49: Dummy 1 | P49: =IFERROR(((H49/F49)^(1/(($H$1-$F$1)/365)))-1,"n/a") -> n/a | Q49: =IFERROR(((N49/H49)^(1/(($N$1-$H$1)/365)))-1,"n/a") -> n/a
C50: Dummy 2 | D50: Dummy 2 | P50: =IFERROR(((H50/F50)^(1/(($H$1-$F$1)/365)))-1,"n/a") -> n/a | Q50: =IFERROR(((N50/H50)^(1/(($N$1-$H$1)/365)))-1,"n/a") -> n/a
C51: Dummy 3 | D51: Dummy 3 | P51: =IFERROR(((H51/F51)^(1/(($H$1-$F$1)/365)))-1,"n/a") -> n/a | Q51: =IFERROR(((N51/H51)^(1/(($N$1-$H$1)/365)))-1,"n/a") -> n/a
C52: Rohergebnis | D52: Gross profit | E52: =SUMIF($V$39:$V$51,"<>KTO",E39:E51) -> 0 | F52: =SUMIF($V$39:$V$51,"<>KTO",F39:F51) -> 0 | G52: =SUMIF($V$39:$V$51,"<>KTO",G39:G51) -> 0 | H52: =SUMIF($V$39:$V$51,"<>KTO",H39:H51) -> 0 | I52: =SUMIF($V$39:$V$51,"<>KTO",I39:I51) -> 0 | J52: =SUMIF($V$39:$V$51,"<>KTO",J39:J51) -> 0 | K52: =SUMIF($V$39:$V$51,"<>KTO",K39:K51) -> 0 | L52: =SUMIF($V$39:$V$51,"<>KTO",L39:L51) -> 0 | ... N52: =SUMIF($V$39:$V$51,"<>KTO",N39:N51) -> 0 | P52: =IFERROR(((H52/F52)^(1/(($H$1-$F$1)/365)))-1,"n/a") -> n/a | Q52: =IFERROR(((N52/H52)^(1/(($N$1-$H$1)/365)))-1,"n/a") -> n/a
C53: Personalaufwand | D53: Personnel expenses | E53: =SUMIFS(Mastersheet!$F$2:$F$400,Mastersheet!$D$2:$D$400,$T53,Mastersheet!$C$2:$C$400,$U53)/1000 -> 0 | F53: =SUMIFS(Mastersheet!$G$2:$G$400,Mastersheet!$D$2:$D$400,$T53,Mastersheet!$C$2:$C$400,$U53)/1000 -> 0 | G53: =SUMIFS(Mastersheet!$H$2:$H$400,Mastersheet!$D$2:$D$400,$T53,Mastersheet!$C$2:$C$400,$U53)/1000 -> 0 | H53: =SUMIFS(Mastersheet!$I$2:$I$400,Mastersheet!$D$2:$D$400,$T53,Mastersheet!$C$2:$C$400,$U53)/1000 -> 0 | I53: =SUMIFS(Mastersheet!$J$2:$J$400,Mastersheet!$D$2:$D$400,$T53,Mastersheet!$C$2:$C$400,$U53)/1000 -> 0 | J53: =SUMIFS(Mastersheet!$K$2:$K$400,Mastersheet!$D$2:$D$400,$T53,Mastersheet!$C$2:$C$400,$U53)/1000 -> 0 | K53: =SUMIFS(Mastersheet!$L$2:$L$400,Mastersheet!$D$2:$D$400,$T53,Mastersheet!$C$2:$C$400,$U53)/1000 -> 0 | L53: =SUMIFS(Mastersheet!$M$2:$M$400,Mastersheet!$D$2:$D$400,$T53,Mastersheet!$C$2:$C$400,$U53)/1000 -> 0 | M53: =SUMIFS(Mastersheet!$N$2:$N$400,Mastersheet!$D$2:$D$400,$T53,Mastersheet!$C$2:$C$400,$U53)/1000 -> 0 | N53: =SUMIFS(Mastersheet!$O$2:$O$400,Mastersheet!$D$2:$D$400,$T53,Mastersheet!$C$2:$C$400,$U53)/1000 -> 0 | P53: =IFERROR(((H53/F53)^(1/(($H$1-$F$1)/365)))-1,"n/a") -> n/a | Q53: =IFERROR(((N53/H53)^(1/(($N$1-$H$1)/365)))-1,"n/a") -> n/a | T53: Personalaufwand | U53: PL | V53: POS
E54: =IF($T$54="","",SUMIFS(Mastersheet!$F$2:$F$400,Mastersheet!$A$2:$A$400,$T$54)/1000) | F54: =IF($T$54="","",SUMIFS(Mastersheet!$G$2:$G$400,Mastersheet!$A$2:$A$400,$T$54)/1000) | G54: =IF($T$54="","",SUMIFS(Mastersheet!$H$2:$H$400,Mastersheet!$A$2:$A$400,$T$54)/1000) | H54: =IF($T$54="","",SUMIFS(Mastersheet!$I$2:$I$400,Mastersheet!$A$2:$A$400,$T$54)/1000) | I54: =IF($T$54="","",SUMIFS(Mastersheet!$J$2:$J$400,Mastersheet!$A$2:$A$400,$T$54)/1000) | J54: =IF($T$54="","",SUMIFS(Mastersheet!$K$2:$K$400,Mastersheet!$A$2:$A$400,$T$54)/1000) | K54: =IF($T$54="","",SUMIFS(Mastersheet!$L$2:$L$400,Mastersheet!$A$2:$A$400,$T$54)/1000) | L54: =IF($T$54="","",SUMIFS(Mastersheet!$M$2:$M$400,Mastersheet!$A$2:$A$400,$T$54)/1000) | M54: =IF($T$54="","",SUMIFS(Mastersheet!$N$2:$N$400,Mastersheet!$A$2:$A$400,$T$54)/1000) | N54: =IF($T$54="","",SUMIFS(Mastersheet!$O$2:$O$400,Mastersheet!$A$2:$A$400,$T$54)/1000) | U54: Account | V54: KTO
E55: =IF($T$55="","",SUMIFS(Mastersheet!$F$2:$F$400,Mastersheet!$A$2:$A$400,$T$55)/1000) | F55: =IF($T$55="","",SUMIFS(Mastersheet!$G$2:$G$400,Mastersheet!$A$2:$A$400,$T$55)/1000) | G55: =IF($T$55="","",SUMIFS(Mastersheet!$H$2:$H$400,Mastersheet!$A$2:$A$400,$T$55)/1000) | H55: =IF($T$55="","",SUMIFS(Mastersheet!$I$2:$I$400,Mastersheet!$A$2:$A$400,$T$55)/1000) | I55: =IF($T$55="","",SUMIFS(Mastersheet!$J$2:$J$400,Mastersheet!$A$2:$A$400,$T$55)/1000) | J55: =IF($T$55="","",SUMIFS(Mastersheet!$K$2:$K$400,Mastersheet!$A$2:$A$400,$T$55)/1000) | K55: =IF($T$55="","",SUMIFS(Mastersheet!$L$2:$L$400,Mastersheet!$A$2:$A$400,$T$55)/1000) | L55: =IF($T$55="","",SUMIFS(Mastersheet!$M$2:$M$400,Mastersheet!$A$2:$A$400,$T$55)/1000) | M55: =IF($T$55="","",SUMIFS(Mastersheet!$N$2:$N$400,Mastersheet!$A$2:$A$400,$T$55)/1000) | N55: =IF($T$55="","",SUMIFS(Mastersheet!$O$2:$O$400,Mastersheet!$A$2:$A$400,$T$55)/1000) | U55: Account | V55: KTO
E56: =IF($T$56="","",SUMIFS(Mastersheet!$F$2:$F$400,Mastersheet!$A$2:$A$400,$T$56)/1000) | F56: =IF($T$56="","",SUMIFS(Mastersheet!$G$2:$G$400,Mastersheet!$A$2:$A$400,$T$56)/1000) | G56: =IF($T$56="","",SUMIFS(Mastersheet!$H$2:$H$400,Mastersheet!$A$2:$A$400,$T$56)/1000) | H56: =IF($T$56="","",SUMIFS(Mastersheet!$I$2:$I$400,Mastersheet!$A$2:$A$400,$T$56)/1000) | I56: =IF($T$56="","",SUMIFS(Mastersheet!$J$2:$J$400,Mastersheet!$A$2:$A$400,$T$56)/1000) | J56: =IF($T$56="","",SUMIFS(Mastersheet!$K$2:$K$400,Mastersheet!$A$2:$A$400,$T$56)/1000) | K56: =IF($T$56="","",SUMIFS(Mastersheet!$L$2:$L$400,Mastersheet!$A$2:$A$400,$T$56)/1000) | L56: =IF($T$56="","",SUMIFS(Mastersheet!$M$2:$M$400,Mastersheet!$A$2:$A$400,$T$56)/1000) | M56: =IF($T$56="","",SUMIFS(Mastersheet!$N$2:$N$400,Mastersheet!$A$2:$A$400,$T$56)/1000) | N56: =IF($T$56="","",SUMIFS(Mastersheet!$O$2:$O$400,Mastersheet!$A$2:$A$400,$T$56)/1000) | U56: Account | V56: KTO
E57: =IF($T$57="","",SUMIFS(Mastersheet!$F$2:$F$400,Mastersheet!$A$2:$A$400,$T$57)/1000) | F57: =IF($T$57="","",SUMIFS(Mastersheet!$G$2:$G$400,Mastersheet!$A$2:$A$400,$T$57)/1000) | G57: =IF($T$57="","",SUMIFS(Mastersheet!$H$2:$H$400,Mastersheet!$A$2:$A$400,$T$57)/1000) | H57: =IF($T$57="","",SUMIFS(Mastersheet!$I$2:$I$400,Mastersheet!$A$2:$A$400,$T$57)/1000) | I57: =IF($T$57="","",SUMIFS(Mastersheet!$J$2:$J$400,Mastersheet!$A$2:$A$400,$T$57)/1000) | J57: =IF($T$57="","",SUMIFS(Mastersheet!$K$2:$K$400,Mastersheet!$A$2:$A$400,$T$57)/1000) | K57: =IF($T$57="","",SUMIFS(Mastersheet!$L$2:$L$400,Mastersheet!$A$2:$A$400,$T$57)/1000) | L57: =IF($T$57="","",SUMIFS(Mastersheet!$M$2:$M$400,Mastersheet!$A$2:$A$400,$T$57)/1000) | M57: =IF($T$57="","",SUMIFS(Mastersheet!$N$2:$N$400,Mastersheet!$A$2:$A$400,$T$57)/1000) | N57: =IF($T$57="","",SUMIFS(Mastersheet!$O$2:$O$400,Mastersheet!$A$2:$A$400,$T$57)/1000) | U57: Account | V57: KTO
E58: =IF($T$58="","",SUMIFS(Mastersheet!$F$2:$F$400,Mastersheet!$A$2:$A$400,$T$58)/1000) | F58: =IF($T$58="","",SUMIFS(Mastersheet!$G$2:$G$400,Mastersheet!$A$2:$A$400,$T$58)/1000) | G58: =IF($T$58="","",SUMIFS(Mastersheet!$H$2:$H$400,Mastersheet!$A$2:$A$400,$T$58)/1000) | H58: =IF($T$58="","",SUMIFS(Mastersheet!$I$2:$I$400,Mastersheet!$A$2:$A$400,$T$58)/1000) | I58: =IF($T$58="","",SUMIFS(Mastersheet!$J$2:$J$400,Mastersheet!$A$2:$A$400,$T$58)/1000) | J58: =IF($T$58="","",SUMIFS(Mastersheet!$K$2:$K$400,Mastersheet!$A$2:$A$400,$T$58)/1000) | K58: =IF($T$58="","",SUMIFS(Mastersheet!$L$2:$L$400,Mastersheet!$A$2:$A$400,$T$58)/1000) | L58: =IF($T$58="","",SUMIFS(Mastersheet!$M$2:$M$400,Mastersheet!$A$2:$A$400,$T$58)/1000) | M58: =IF($T$58="","",SUMIFS(Mastersheet!$N$2:$N$400,Mastersheet!$A$2:$A$400,$T$58)/1000) | N58: =IF($T$58="","",SUMIFS(Mastersheet!$O$2:$O$400,Mastersheet!$A$2:$A$400,$T$58)/1000) | U58: Account | V58: KTO
E59: =IF($T$59="","",SUMIFS(Mastersheet!$F$2:$F$400,Mastersheet!$A$2:$A$400,$T$59)/1000) | F59: =IF($T$59="","",SUMIFS(Mastersheet!$G$2:$G$400,Mastersheet!$A$2:$A$400,$T$59)/1000) | G59: =IF($T$59="","",SUMIFS(Mastersheet!$H$2:$H$400,Mastersheet!$A$2:$A$400,$T$59)/1000) | H59: =IF($T$59="","",SUMIFS(Mastersheet!$I$2:$I$400,Mastersheet!$A$2:$A$400,$T$59)/1000) | I59: =IF($T$59="","",SUMIFS(Mastersheet!$J$2:$J$400,Mastersheet!$A$2:$A$400,$T$59)/1000) | J59: =IF($T$59="","",SUMIFS(Mastersheet!$K$2:$K$400,Mastersheet!$A$2:$A$400,$T$59)/1000) | K59: =IF($T$59="","",SUMIFS(Mastersheet!$L$2:$L$400,Mastersheet!$A$2:$A$400,$T$59)/1000) | L59: =IF($T$59="","",SUMIFS(Mastersheet!$M$2:$M$400,Mastersheet!$A$2:$A$400,$T$59)/1000) | M59: =IF($T$59="","",SUMIFS(Mastersheet!$N$2:$N$400,Mastersheet!$A$2:$A$400,$T$59)/1000) | N59: =IF($T$59="","",SUMIFS(Mastersheet!$O$2:$O$400,Mastersheet!$A$2:$A$400,$T$59)/1000) | U59: Account | V59: KTO
E60: =IF($T$60="","",SUMIFS(Mastersheet!$F$2:$F$400,Mastersheet!$A$2:$A$400,$T$60)/1000) | F60: =IF($T$60="","",SUMIFS(Mastersheet!$G$2:$G$400,Mastersheet!$A$2:$A$400,$T$60)/1000) | G60: =IF($T$60="","",SUMIFS(Mastersheet!$H$2:$H$400,Mastersheet!$A$2:$A$400,$T$60)/1000) | H60: =IF($T$60="","",SUMIFS(Mastersheet!$I$2:$I$400,Mastersheet!$A$2:$A$400,$T$60)/1000) | I60: =IF($T$60="","",SUMIFS(Mastersheet!$J$2:$J$400,Mastersheet!$A$2:$A$400,$T$60)/1000) | J60: =IF($T$60="","",SUMIFS(Mastersheet!$K$2:$K$400,Mastersheet!$A$2:$A$400,$T$60)/1000) | K60: =IF($T$60="","",SUMIFS(Mastersheet!$L$2:$L$400,Mastersheet!$A$2:$A$400,$T$60)/1000) | L60: =IF($T$60="","",SUMIFS(Mastersheet!$M$2:$M$400,Mastersheet!$A$2:$A$400,$T$60)/1000) | M60: =IF($T$60="","",SUMIFS(Mastersheet!$N$2:$N$400,Mastersheet!$A$2:$A$400,$T$60)/1000) | N60: =IF($T$60="","",SUMIFS(Mastersheet!$O$2:$O$400,Mastersheet!$A$2:$A$400,$T$60)/1000) | U60: Account | V60: KTO
E61: =IF($T$61="","",SUMIFS(Mastersheet!$F$2:$F$400,Mastersheet!$A$2:$A$400,$T$61)/1000) | F61: =IF($T$61="","",SUMIFS(Mastersheet!$G$2:$G$400,Mastersheet!$A$2:$A$400,$T$61)/1000) | G61: =IF($T$61="","",SUMIFS(Mastersheet!$H$2:$H$400,Mastersheet!$A$2:$A$400,$T$61)/1000) | H61: =IF($T$61="","",SUMIFS(Mastersheet!$I$2:$I$400,Mastersheet!$A$2:$A$400,$T$61)/1000) | I61: =IF($T$61="","",SUMIFS(Mastersheet!$J$2:$J$400,Mastersheet!$A$2:$A$400,$T$61)/1000) | J61: =IF($T$61="","",SUMIFS(Mastersheet!$K$2:$K$400,Mastersheet!$A$2:$A$400,$T$61)/1000) | K61: =IF($T$61="","",SUMIFS(Mastersheet!$L$2:$L$400,Mastersheet!$A$2:$A$400,$T$61)/1000) | L61: =IF($T$61="","",SUMIFS(Mastersheet!$M$2:$M$400,Mastersheet!$A$2:$A$400,$T$61)/1000) | M61: =IF($T$61="","",SUMIFS(Mastersheet!$N$2:$N$400,Mastersheet!$A$2:$A$400,$T$61)/1000) | N61: =IF($T$61="","",SUMIFS(Mastersheet!$O$2:$O$400,Mastersheet!$A$2:$A$400,$T$61)/1000) | U61: Account | V61: KTO
C62: Raumkosten | D62: Premise costs | E62: =SUMIFS(Mastersheet!$F$2:$F$400,Mastersheet!$D$2:$D$400,$T62,Mastersheet!$C$2:$C$400,$U62)/1000 -> 0 | F62: =SUMIFS(Mastersheet!$G$2:$G$400,Mastersheet!$D$2:$D$400,$T62,Mastersheet!$C$2:$C$400,$U62)/1000 -> 0 | G62: =SUMIFS(Mastersheet!$H$2:$H$400,Mastersheet!$D$2:$D$400,$T62,Mastersheet!$C$2:$C$400,$U62)/1000 -> 0 | H62: =SUMIFS(Mastersheet!$I$2:$I$400,Mastersheet!$D$2:$D$400,$T62,Mastersheet!$C$2:$C$400,$U62)/1000 -> 0 | I62: =SUMIFS(Mastersheet!$J$2:$J$400,Mastersheet!$D$2:$D$400,$T62,Mastersheet!$C$2:$C$400,$U62)/1000 -> 0 | J62: =SUMIFS(Mastersheet!$K$2:$K$400,Mastersheet!$D$2:$D$400,$T62,Mastersheet!$C$2:$C$400,$U62)/1000 -> 0 | K62: =SUMIFS(Mastersheet!$L$2:$L$400,Mastersheet!$D$2:$D$400,$T62,Mastersheet!$C$2:$C$400,$U62)/1000 -> 0 | L62: =SUMIFS(Mastersheet!$M$2:$M$400,Mastersheet!$D$2:$D$400,$T62,Mastersheet!$C$2:$C$400,$U62)/1000 -> 0 | M62: =SUMIFS(Mastersheet!$N$2:$N$400,Mastersheet!$D$2:$D$400,$T62,Mastersheet!$C$2:$C$400,$U62)/1000 -> 0 | N62: =SUMIFS(Mastersheet!$O$2:$O$400,Mastersheet!$D$2:$D$400,$T62,Mastersheet!$C$2:$C$400,$U62)/1000 -> 0 | P62: =IFERROR(((H62/F62)^(1/(($H$1-$F$1)/365)))-1,"n/a") -> n/a | Q62: =IFERROR(((N62/H62)^(1/(($N$1-$H$1)/365)))-1,"n/a") -> n/a | T62: Raumkosten | U62: PL | V62: POS
E63: =IF($T$63="","",SUMIFS(Mastersheet!$F$2:$F$400,Mastersheet!$A$2:$A$400,$T$63)/1000) | F63: =IF($T$63="","",SUMIFS(Mastersheet!$G$2:$G$400,Mastersheet!$A$2:$A$400,$T$63)/1000) | G63: =IF($T$63="","",SUMIFS(Mastersheet!$H$2:$H$400,Mastersheet!$A$2:$A$400,$T$63)/1000) | H63: =IF($T$63="","",SUMIFS(Mastersheet!$I$2:$I$400,Mastersheet!$A$2:$A$400,$T$63)/1000) | I63: =IF($T$63="","",SUMIFS(Mastersheet!$J$2:$J$400,Mastersheet!$A$2:$A$400,$T$63)/1000) | J63: =IF($T$63="","",SUMIFS(Mastersheet!$K$2:$K$400,Mastersheet!$A$2:$A$400,$T$63)/1000) | K63: =IF($T$63="","",SUMIFS(Mastersheet!$L$2:$L$400,Mastersheet!$A$2:$A$400,$T$63)/1000) | L63: =IF($T$63="","",SUMIFS(Mastersheet!$M$2:$M$400,Mastersheet!$A$2:$A$400,$T$63)/1000) | M63: =IF($T$63="","",SUMIFS(Mastersheet!$N$2:$N$400,Mastersheet!$A$2:$A$400,$T$63)/1000) | N63: =IF($T$63="","",SUMIFS(Mastersheet!$O$2:$O$400,Mastersheet!$A$2:$A$400,$T$63)/1000) | U63: Account | V63: KTO
E64: =IF($T$64="","",SUMIFS(Mastersheet!$F$2:$F$400,Mastersheet!$A$2:$A$400,$T$64)/1000) | F64: =IF($T$64="","",SUMIFS(Mastersheet!$G$2:$G$400,Mastersheet!$A$2:$A$400,$T$64)/1000) | G64: =IF($T$64="","",SUMIFS(Mastersheet!$H$2:$H$400,Mastersheet!$A$2:$A$400,$T$64)/1000) | H64: =IF($T$64="","",SUMIFS(Mastersheet!$I$2:$I$400,Mastersheet!$A$2:$A$400,$T$64)/1000) | I64: =IF($T$64="","",SUMIFS(Mastersheet!$J$2:$J$400,Mastersheet!$A$2:$A$400,$T$64)/1000) | J64: =IF($T$64="","",SUMIFS(Mastersheet!$K$2:$K$400,Mastersheet!$A$2:$A$400,$T$64)/1000) | K64: =IF($T$64="","",SUMIFS(Mastersheet!$L$2:$L$400,Mastersheet!$A$2:$A$400,$T$64)/1000) | L64: =IF($T$64="","",SUMIFS(Mastersheet!$M$2:$M$400,Mastersheet!$A$2:$A$400,$T$64)/1000) | M64: =IF($T$64="","",SUMIFS(Mastersheet!$N$2:$N$400,Mastersheet!$A$2:$A$400,$T$64)/1000) | N64: =IF($T$64="","",SUMIFS(Mastersheet!$O$2:$O$400,Mastersheet!$A$2:$A$400,$T$64)/1000) | U64: Account | V64: KTO
E65: =IF($T$65="","",SUMIFS(Mastersheet!$F$2:$F$400,Mastersheet!$A$2:$A$400,$T$65)/1000) | F65: =IF($T$65="","",SUMIFS(Mastersheet!$G$2:$G$400,Mastersheet!$A$2:$A$400,$T$65)/1000) | G65: =IF($T$65="","",SUMIFS(Mastersheet!$H$2:$H$400,Mastersheet!$A$2:$A$400,$T$65)/1000) | H65: =IF($T$65="","",SUMIFS(Mastersheet!$I$2:$I$400,Mastersheet!$A$2:$A$400,$T$65)/1000) | I65: =IF($T$65="","",SUMIFS(Mastersheet!$J$2:$J$400,Mastersheet!$A$2:$A$400,$T$65)/1000) | J65: =IF($T$65="","",SUMIFS(Mastersheet!$K$2:$K$400,Mastersheet!$A$2:$A$400,$T$65)/1000) | K65: =IF($T$65="","",SUMIFS(Mastersheet!$L$2:$L$400,Mastersheet!$A$2:$A$400,$T$65)/1000) | L65: =IF($T$65="","",SUMIFS(Mastersheet!$M$2:$M$400,Mastersheet!$A$2:$A$400,$T$65)/1000) | M65: =IF($T$65="","",SUMIFS(Mastersheet!$N$2:$N$400,Mastersheet!$A$2:$A$400,$T$65)/1000) | N65: =IF($T$65="","",SUMIFS(Mastersheet!$O$2:$O$400,Mastersheet!$A$2:$A$400,$T$65)/1000) | U65: Account | V65: KTO
E66: =IF($T$66="","",SUMIFS(Mastersheet!$F$2:$F$400,Mastersheet!$A$2:$A$400,$T$66)/1000) | F66: =IF($T$66="","",SUMIFS(Mastersheet!$G$2:$G$400,Mastersheet!$A$2:$A$400,$T$66)/1000) | G66: =IF($T$66="","",SUMIFS(Mastersheet!$H$2:$H$400,Mastersheet!$A$2:$A$400,$T$66)/1000) | H66: =IF($T$66="","",SUMIFS(Mastersheet!$I$2:$I$400,Mastersheet!$A$2:$A$400,$T$66)/1000) | I66: =IF($T$66="","",SUMIFS(Mastersheet!$J$2:$J$400,Mastersheet!$A$2:$A$400,$T$66)/1000) | J66: =IF($T$66="","",SUMIFS(Mastersheet!$K$2:$K$400,Mastersheet!$A$2:$A$400,$T$66)/1000) | K66: =IF($T$66="","",SUMIFS(Mastersheet!$L$2:$L$400,Mastersheet!$A$2:$A$400,$T$66)/1000) | L66: =IF($T$66="","",SUMIFS(Mastersheet!$M$2:$M$400,Mastersheet!$A$2:$A$400,$T$66)/1000) | M66: =IF($T$66="","",SUMIFS(Mastersheet!$N$2:$N$400,Mastersheet!$A$2:$A$400,$T$66)/1000) | N66: =IF($T$66="","",SUMIFS(Mastersheet!$O$2:$O$400,Mastersheet!$A$2:$A$400,$T$66)/1000) | U66: Account | V66: KTO
E67: =IF($T$67="","",SUMIFS(Mastersheet!$F$2:$F$400,Mastersheet!$A$2:$A$400,$T$67)/1000) | F67: =IF($T$67="","",SUMIFS(Mastersheet!$G$2:$G$400,Mastersheet!$A$2:$A$400,$T$67)/1000) | G67: =IF($T$67="","",SUMIFS(Mastersheet!$H$2:$H$400,Mastersheet!$A$2:$A$400,$T$67)/1000) | H67: =IF($T$67="","",SUMIFS(Mastersheet!$I$2:$I$400,Mastersheet!$A$2:$A$400,$T$67)/1000) | I67: =IF($T$67="","",SUMIFS(Mastersheet!$J$2:$J$400,Mastersheet!$A$2:$A$400,$T$67)/1000) | J67: =IF($T$67="","",SUMIFS(Mastersheet!$K$2:$K$400,Mastersheet!$A$2:$A$400,$T$67)/1000) | K67: =IF($T$67="","",SUMIFS(Mastersheet!$L$2:$L$400,Mastersheet!$A$2:$A$400,$T$67)/1000) | L67: =IF($T$67="","",SUMIFS(Mastersheet!$M$2:$M$400,Mastersheet!$A$2:$A$400,$T$67)/1000) | M67: =IF($T$67="","",SUMIFS(Mastersheet!$N$2:$N$400,Mastersheet!$A$2:$A$400,$T$67)/1000) | N67: =IF($T$67="","",SUMIFS(Mastersheet!$O$2:$O$400,Mastersheet!$A$2:$A$400,$T$67)/1000) | U67: Account | V67: KTO
E68: =IF($T$68="","",SUMIFS(Mastersheet!$F$2:$F$400,Mastersheet!$A$2:$A$400,$T$68)/1000) | F68: =IF($T$68="","",SUMIFS(Mastersheet!$G$2:$G$400,Mastersheet!$A$2:$A$400,$T$68)/1000) | G68: =IF($T$68="","",SUMIFS(Mastersheet!$H$2:$H$400,Mastersheet!$A$2:$A$400,$T$68)/1000) | H68: =IF($T$68="","",SUMIFS(Mastersheet!$I$2:$I$400,Mastersheet!$A$2:$A$400,$T$68)/1000) | I68: =IF($T$68="","",SUMIFS(Mastersheet!$J$2:$J$400,Mastersheet!$A$2:$A$400,$T$68)/1000) | J68: =IF($T$68="","",SUMIFS(Mastersheet!$K$2:$K$400,Mastersheet!$A$2:$A$400,$T$68)/1000) | K68: =IF($T$68="","",SUMIFS(Mastersheet!$L$2:$L$400,Mastersheet!$A$2:$A$400,$T$68)/1000) | L68: =IF($T$68="","",SUMIFS(Mastersheet!$M$2:$M$400,Mastersheet!$A$2:$A$400,$T$68)/1000) | M68: =IF($T$68="","",SUMIFS(Mastersheet!$N$2:$N$400,Mastersheet!$A$2:$A$400,$T$68)/1000) | N68: =IF($T$68="","",SUMIFS(Mastersheet!$O$2:$O$400,Mastersheet!$A$2:$A$400,$T$68)/1000) | U68: Account | V68: KTO
E69: =IF($T$69="","",SUMIFS(Mastersheet!$F$2:$F$400,Mastersheet!$A$2:$A$400,$T$69)/1000) | F69: =IF($T$69="","",SUMIFS(Mastersheet!$G$2:$G$400,Mastersheet!$A$2:$A$400,$T$69)/1000) | G69: =IF($T$69="","",SUMIFS(Mastersheet!$H$2:$H$400,Mastersheet!$A$2:$A$400,$T$69)/1000) | H69: =IF($T$69="","",SUMIFS(Mastersheet!$I$2:$I$400,Mastersheet!$A$2:$A$400,$T$69)/1000) | I69: =IF($T$69="","",SUMIFS(Mastersheet!$J$2:$J$400,Mastersheet!$A$2:$A$400,$T$69)/1000) | J69: =IF($T$69="","",SUMIFS(Mastersheet!$K$2:$K$400,Mastersheet!$A$2:$A$400,$T$69)/1000) | K69: =IF($T$69="","",SUMIFS(Mastersheet!$L$2:$L$400,Mastersheet!$A$2:$A$400,$T$69)/1000) | L69: =IF($T$69="","",SUMIFS(Mastersheet!$M$2:$M$400,Mastersheet!$A$2:$A$400,$T$69)/1000) | M69: =IF($T$69="","",SUMIFS(Mastersheet!$N$2:$N$400,Mastersheet!$A$2:$A$400,$T$69)/1000) | N69: =IF($T$69="","",SUMIFS(Mastersheet!$O$2:$O$400,Mastersheet!$A$2:$A$400,$T$69)/1000) | U69: Account | V69: KTO
E70: =IF($T$70="","",SUMIFS(Mastersheet!$F$2:$F$400,Mastersheet!$A$2:$A$400,$T$70)/1000) | F70: =IF($T$70="","",SUMIFS(Mastersheet!$G$2:$G$400,Mastersheet!$A$2:$A$400,$T$70)/1000) | G70: =IF($T$70="","",SUMIFS(Mastersheet!$H$2:$H$400,Mastersheet!$A$2:$A$400,$T$70)/1000) | H70: =IF($T$70="","",SUMIFS(Mastersheet!$I$2:$I$400,Mastersheet!$A$2:$A$400,$T$70)/1000) | I70: =IF($T$70="","",SUMIFS(Mastersheet!$J$2:$J$400,Mastersheet!$A$2:$A$400,$T$70)/1000) | J70: =IF($T$70="","",SUMIFS(Mastersheet!$K$2:$K$400,Mastersheet!$A$2:$A$400,$T$70)/1000) | K70: =IF($T$70="","",SUMIFS(Mastersheet!$L$2:$L$400,Mastersheet!$A$2:$A$400,$T$70)/1000) | L70: =IF($T$70="","",SUMIFS(Mastersheet!$M$2:$M$400,Mastersheet!$A$2:$A$400,$T$70)/1000) | M70: =IF($T$70="","",SUMIFS(Mastersheet!$N$2:$N$400,Mastersheet!$A$2:$A$400,$T$70)/1000) | N70: =IF($T$70="","",SUMIFS(Mastersheet!$O$2:$O$400,Mastersheet!$A$2:$A$400,$T$70)/1000) | U70: Account | V70: KTO
C71: Reparaturen und Instandhaltungen | D71: Repair and maintenance | E71: =SUMIFS(Mastersheet!$F$2:$F$400,Mastersheet!$D$2:$D$400,$T71,Mastersheet!$C$2:$C$400,$U71)/1000 -> 0 | F71: =SUMIFS(Mastersheet!$G$2:$G$400,Mastersheet!$D$2:$D$400,$T71,Mastersheet!$C$2:$C$400,$U71)/1000 -> 0 | G71: =SUMIFS(Mastersheet!$H$2:$H$400,Mastersheet!$D$2:$D$400,$T71,Mastersheet!$C$2:$C$400,$U71)/1000 -> 0 | H71: =SUMIFS(Mastersheet!$I$2:$I$400,Mastersheet!$D$2:$D$400,$T71,Mastersheet!$C$2:$C$400,$U71)/1000 -> 0 | I71: =SUMIFS(Mastersheet!$J$2:$J$400,Mastersheet!$D$2:$D$400,$T71,Mastersheet!$C$2:$C$400,$U71)/1000 -> 0 | J71: =SUMIFS(Mastersheet!$K$2:$K$400,Mastersheet!$D$2:$D$400,$T71,Mastersheet!$C$2:$C$400,$U71)/1000 -> 0 | K71: =SUMIFS(Mastersheet!$L$2:$L$400,Mastersheet!$D$2:$D$400,$T71,Mastersheet!$C$2:$C$400,$U71)/1000 -> 0 | L71: =SUMIFS(Mastersheet!$M$2:$M$400,Mastersheet!$D$2:$D$400,$T71,Mastersheet!$C$2:$C$400,$U71)/1000 -> 0 | M71: =SUMIFS(Mastersheet!$N$2:$N$400,Mastersheet!$D$2:$D$400,$T71,Mastersheet!$C$2:$C$400,$U71)/1000 -> 0 | N71: =SUMIFS(Mastersheet!$O$2:$O$400,Mastersheet!$D$2:$D$400,$T71,Mastersheet!$C$2:$C$400,$U71)/1000 -> 0 | P71: =IFERROR(((H71/F71)^(1/(($H$1-$F$1)/365)))-1,"n/a") -> n/a | Q71: =IFERROR(((N71/H71)^(1/(($N$1-$H$1)/365)))-1,"n/a") -> n/a | T71: Reparaturen und Instandhaltungen | U71: PL | V71: POS
E72: =IF($T$72="","",SUMIFS(Mastersheet!$F$2:$F$400,Mastersheet!$A$2:$A$400,$T$72)/1000) | F72: =IF($T$72="","",SUMIFS(Mastersheet!$G$2:$G$400,Mastersheet!$A$2:$A$400,$T$72)/1000) | G72: =IF($T$72="","",SUMIFS(Mastersheet!$H$2:$H$400,Mastersheet!$A$2:$A$400,$T$72)/1000) | H72: =IF($T$72="","",SUMIFS(Mastersheet!$I$2:$I$400,Mastersheet!$A$2:$A$400,$T$72)/1000) | I72: =IF($T$72="","",SUMIFS(Mastersheet!$J$2:$J$400,Mastersheet!$A$2:$A$400,$T$72)/1000) | J72: =IF($T$72="","",SUMIFS(Mastersheet!$K$2:$K$400,Mastersheet!$A$2:$A$400,$T$72)/1000) | K72: =IF($T$72="","",SUMIFS(Mastersheet!$L$2:$L$400,Mastersheet!$A$2:$A$400,$T$72)/1000) | L72: =IF($T$72="","",SUMIFS(Mastersheet!$M$2:$M$400,Mastersheet!$A$2:$A$400,$T$72)/1000) | M72: =IF($T$72="","",SUMIFS(Mastersheet!$N$2:$N$400,Mastersheet!$A$2:$A$400,$T$72)/1000) | N72: =IF($T$72="","",SUMIFS(Mastersheet!$O$2:$O$400,Mastersheet!$A$2:$A$400,$T$72)/1000) | U72: Account | V72: KTO
E73: =IF($T$73="","",SUMIFS(Mastersheet!$F$2:$F$400,Mastersheet!$A$2:$A$400,$T$73)/1000) | F73: =IF($T$73="","",SUMIFS(Mastersheet!$G$2:$G$400,Mastersheet!$A$2:$A$400,$T$73)/1000) | G73: =IF($T$73="","",SUMIFS(Mastersheet!$H$2:$H$400,Mastersheet!$A$2:$A$400,$T$73)/1000) | H73: =IF($T$73="","",SUMIFS(Mastersheet!$I$2:$I$400,Mastersheet!$A$2:$A$400,$T$73)/1000) | I73: =IF($T$73="","",SUMIFS(Mastersheet!$J$2:$J$400,Mastersheet!$A$2:$A$400,$T$73)/1000) | J73: =IF($T$73="","",SUMIFS(Mastersheet!$K$2:$K$400,Mastersheet!$A$2:$A$400,$T$73)/1000) | K73: =IF($T$73="","",SUMIFS(Mastersheet!$L$2:$L$400,Mastersheet!$A$2:$A$400,$T$73)/1000) | L73: =IF($T$73="","",SUMIFS(Mastersheet!$M$2:$M$400,Mastersheet!$A$2:$A$400,$T$73)/1000) | M73: =IF($T$73="","",SUMIFS(Mastersheet!$N$2:$N$400,Mastersheet!$A$2:$A$400,$T$73)/1000) | N73: =IF($T$73="","",SUMIFS(Mastersheet!$O$2:$O$400,Mastersheet!$A$2:$A$400,$T$73)/1000) | U73: Account | V73: KTO
E74: =IF($T$74="","",SUMIFS(Mastersheet!$F$2:$F$400,Mastersheet!$A$2:$A$400,$T$74)/1000) | F74: =IF($T$74="","",SUMIFS(Mastersheet!$G$2:$G$400,Mastersheet!$A$2:$A$400,$T$74)/1000) | G74: =IF($T$74="","",SUMIFS(Mastersheet!$H$2:$H$400,Mastersheet!$A$2:$A$400,$T$74)/1000) | H74: =IF($T$74="","",SUMIFS(Mastersheet!$I$2:$I$400,Mastersheet!$A$2:$A$400,$T$74)/1000) | I74: =IF($T$74="","",SUMIFS(Mastersheet!$J$2:$J$400,Mastersheet!$A$2:$A$400,$T$74)/1000) | J74: =IF($T$74="","",SUMIFS(Mastersheet!$K$2:$K$400,Mastersheet!$A$2:$A$400,$T$74)/1000) | K74: =IF($T$74="","",SUMIFS(Mastersheet!$L$2:$L$400,Mastersheet!$A$2:$A$400,$T$74)/1000) | L74: =IF($T$74="","",SUMIFS(Mastersheet!$M$2:$M$400,Mastersheet!$A$2:$A$400,$T$74)/1000) | M74: =IF($T$74="","",SUMIFS(Mastersheet!$N$2:$N$400,Mastersheet!$A$2:$A$400,$T$74)/1000) | N74: =IF($T$74="","",SUMIFS(Mastersheet!$O$2:$O$400,Mastersheet!$A$2:$A$400,$T$74)/1000) | U74: Account | V74: KTO
E75: =IF($T$75="","",SUMIFS(Mastersheet!$F$2:$F$400,Mastersheet!$A$2:$A$400,$T$75)/1000) | F75: =IF($T$75="","",SUMIFS(Mastersheet!$G$2:$G$400,Mastersheet!$A$2:$A$400,$T$75)/1000) | G75: =IF($T$75="","",SUMIFS(Mastersheet!$H$2:$H$400,Mastersheet!$A$2:$A$400,$T$75)/1000) | H75: =IF($T$75="","",SUMIFS(Mastersheet!$I$2:$I$400,Mastersheet!$A$2:$A$400,$T$75)/1000) | I75: =IF($T$75="","",SUMIFS(Mastersheet!$J$2:$J$400,Mastersheet!$A$2:$A$400,$T$75)/1000) | J75: =IF($T$75="","",SUMIFS(Mastersheet!$K$2:$K$400,Mastersheet!$A$2:$A$400,$T$75)/1000) | K75: =IF($T$75="","",SUMIFS(Mastersheet!$L$2:$L$400,Mastersheet!$A$2:$A$400,$T$75)/1000) | L75: =IF($T$75="","",SUMIFS(Mastersheet!$M$2:$M$400,Mastersheet!$A$2:$A$400,$T$75)/1000) | M75: =IF($T$75="","",SUMIFS(Mastersheet!$N$2:$N$400,Mastersheet!$A$2:$A$400,$T$75)/1000) | N75: =IF($T$75="","",SUMIFS(Mastersheet!$O$2:$O$400,Mastersheet!$A$2:$A$400,$T$75)/1000) | U75: Account | V75: KTO
E76: =IF($T$76="","",SUMIFS(Mastersheet!$F$2:$F$400,Mastersheet!$A$2:$A$400,$T$76)/1000) | F76: =IF($T$76="","",SUMIFS(Mastersheet!$G$2:$G$400,Mastersheet!$A$2:$A$400,$T$76)/1000) | G76: =IF($T$76="","",SUMIFS(Mastersheet!$H$2:$H$400,Mastersheet!$A$2:$A$400,$T$76)/1000) | H76: =IF($T$76="","",SUMIFS(Mastersheet!$I$2:$I$400,Mastersheet!$A$2:$A$400,$T$76)/1000) | I76: =IF($T$76="","",SUMIFS(Mastersheet!$J$2:$J$400,Mastersheet!$A$2:$A$400,$T$76)/1000) | J76: =IF($T$76="","",SUMIFS(Mastersheet!$K$2:$K$400,Mastersheet!$A$2:$A$400,$T$76)/1000) | K76: =IF($T$76="","",SUMIFS(Mastersheet!$L$2:$L$400,Mastersheet!$A$2:$A$400,$T$76)/1000) | L76: =IF($T$76="","",SUMIFS(Mastersheet!$M$2:$M$400,Mastersheet!$A$2:$A$400,$T$76)/1000) | M76: =IF($T$76="","",SUMIFS(Mastersheet!$N$2:$N$400,Mastersheet!$A$2:$A$400,$T$76)/1000) | N76: =IF($T$76="","",SUMIFS(Mastersheet!$O$2:$O$400,Mastersheet!$A$2:$A$400,$T$76)/1000) | U76: Account | V76: KTO
E77: =IF($T$77="","",SUMIFS(Mastersheet!$F$2:$F$400,Mastersheet!$A$2:$A$400,$T$77)/1000) | F77: =IF($T$77="","",SUMIFS(Mastersheet!$G$2:$G$400,Mastersheet!$A$2:$A$400,$T$77)/1000) | G77: =IF($T$77="","",SUMIFS(Mastersheet!$H$2:$H$400,Mastersheet!$A$2:$A$400,$T$77)/1000) | H77: =IF($T$77="","",SUMIFS(Mastersheet!$I$2:$I$400,Mastersheet!$A$2:$A$400,$T$77)/1000) | I77: =IF($T$77="","",SUMIFS(Mastersheet!$J$2:$J$400,Mastersheet!$A$2:$A$400,$T$77)/1000) | J77: =IF($T$77="","",SUMIFS(Mastersheet!$K$2:$K$400,Mastersheet!$A$2:$A$400,$T$77)/1000) | K77: =IF($T$77="","",SUMIFS(Mastersheet!$L$2:$L$400,Mastersheet!$A$2:$A$400,$T$77)/1000) | L77: =IF($T$77="","",SUMIFS(Mastersheet!$M$2:$M$400,Mastersheet!$A$2:$A$400,$T$77)/1000) | M77: =IF($T$77="","",SUMIFS(Mastersheet!$N$2:$N$400,Mastersheet!$A$2:$A$400,$T$77)/1000) | N77: =IF($T$77="","",SUMIFS(Mastersheet!$O$2:$O$400,Mastersheet!$A$2:$A$400,$T$77)/1000) | U77: Account | V77: KTO
E78: =IF($T$78="","",SUMIFS(Mastersheet!$F$2:$F$400,Mastersheet!$A$2:$A$400,$T$78)/1000) | F78: =IF($T$78="","",SUMIFS(Mastersheet!$G$2:$G$400,Mastersheet!$A$2:$A$400,$T$78)/1000) | G78: =IF($T$78="","",SUMIFS(Mastersheet!$H$2:$H$400,Mastersheet!$A$2:$A$400,$T$78)/1000) | H78: =IF($T$78="","",SUMIFS(Mastersheet!$I$2:$I$400,Mastersheet!$A$2:$A$400,$T$78)/1000) | I78: =IF($T$78="","",SUMIFS(Mastersheet!$J$2:$J$400,Mastersheet!$A$2:$A$400,$T$78)/1000) | J78: =IF($T$78="","",SUMIFS(Mastersheet!$K$2:$K$400,Mastersheet!$A$2:$A$400,$T$78)/1000) | K78: =IF($T$78="","",SUMIFS(Mastersheet!$L$2:$L$400,Mastersheet!$A$2:$A$400,$T$78)/1000) | L78: =IF($T$78="","",SUMIFS(Mastersheet!$M$2:$M$400,Mastersheet!$A$2:$A$400,$T$78)/1000) | M78: =IF($T$78="","",SUMIFS(Mastersheet!$N$2:$N$400,Mastersheet!$A$2:$A$400,$T$78)/1000) | N78: =IF($T$78="","",SUMIFS(Mastersheet!$O$2:$O$400,Mastersheet!$A$2:$A$400,$T$78)/1000) | U78: Account | V78: KTO
E79: =IF($T$79="","",SUMIFS(Mastersheet!$F$2:$F$400,Mastersheet!$A$2:$A$400,$T$79)/1000) | F79: =IF($T$79="","",SUMIFS(Mastersheet!$G$2:$G$400,Mastersheet!$A$2:$A$400,$T$79)/1000) | G79: =IF($T$79="","",SUMIFS(Mastersheet!$H$2:$H$400,Mastersheet!$A$2:$A$400,$T$79)/1000) | H79: =IF($T$79="","",SUMIFS(Mastersheet!$I$2:$I$400,Mastersheet!$A$2:$A$400,$T$79)/1000) | I79: =IF($T$79="","",SUMIFS(Mastersheet!$J$2:$J$400,Mastersheet!$A$2:$A$400,$T$79)/1000) | J79: =IF($T$79="","",SUMIFS(Mastersheet!$K$2:$K$400,Mastersheet!$A$2:$A$400,$T$79)/1000) | K79: =IF($T$79="","",SUMIFS(Mastersheet!$L$2:$L$400,Mastersheet!$A$2:$A$400,$T$79)/1000) | L79: =IF($T$79="","",SUMIFS(Mastersheet!$M$2:$M$400,Mastersheet!$A$2:$A$400,$T$79)/1000) | M79: =IF($T$79="","",SUMIFS(Mastersheet!$N$2:$N$400,Mastersheet!$A$2:$A$400,$T$79)/1000) | N79: =IF($T$79="","",SUMIFS(Mastersheet!$O$2:$O$400,Mastersheet!$A$2:$A$400,$T$79)/1000) | U79: Account | V79: KTO
C80: Vertriebskosten | D80: Sales costs | E80: =SUMIFS(Mastersheet!$F$2:$F$400,Mastersheet!$D$2:$D$400,$T80,Mastersheet!$C$2:$C$400,$U80)/1000 -> 0 | F80: =SUMIFS(Mastersheet!$G$2:$G$400,Mastersheet!$D$2:$D$400,$T80,Mastersheet!$C$2:$C$400,$U80)/1000 -> 0 | G80: =SUMIFS(Mastersheet!$H$2:$H$400,Mastersheet!$D$2:$D$400,$T80,Mastersheet!$C$2:$C$400,$U80)/1000 -> 0 | H80: =SUMIFS(Mastersheet!$I$2:$I$400,Mastersheet!$D$2:$D$400,$T80,Mastersheet!$C$2:$C$400,$U80)/1000 -> 0 | I80: =SUMIFS(Mastersheet!$J$2:$J$400,Mastersheet!$D$2:$D$400,$T80,Mastersheet!$C$2:$C$400,$U80)/1000 -> 0 | J80: =SUMIFS(Mastersheet!$K$2:$K$400,Mastersheet!$D$2:$D$400,$T80,Mastersheet!$C$2:$C$400,$U80)/1000 -> 0 | K80: =SUMIFS(Mastersheet!$L$2:$L$400,Mastersheet!$D$2:$D$400,$T80,Mastersheet!$C$2:$C$400,$U80)/1000 -> 0 | L80: =SUMIFS(Mastersheet!$M$2:$M$400,Mastersheet!$D$2:$D$400,$T80,Mastersheet!$C$2:$C$400,$U80)/1000 -> 0 | M80: =SUMIFS(Mastersheet!$N$2:$N$400,Mastersheet!$D$2:$D$400,$T80,Mastersheet!$C$2:$C$400,$U80)/1000 -> 0 | N80: =SUMIFS(Mastersheet!$O$2:$O$400,Mastersheet!$D$2:$D$400,$T80,Mastersheet!$C$2:$C$400,$U80)/1000 -> 0 | P80: =IFERROR(((H80/F80)^(1/(($H$1-$F$1)/365)))-1,"n/a") -> n/a | Q80: =IFERROR(((N80/H80)^(1/(($N$1-$H$1)/365)))-1,"n/a") -> n/a | T80: Vertriebskosten | U80: PL | V80: POS
E81: =IF($T$81="","",SUMIFS(Mastersheet!$F$2:$F$400,Mastersheet!$A$2:$A$400,$T$81)/1000) | F81: =IF($T$81="","",SUMIFS(Mastersheet!$G$2:$G$400,Mastersheet!$A$2:$A$400,$T$81)/1000) | G81: =IF($T$81="","",SUMIFS(Mastersheet!$H$2:$H$400,Mastersheet!$A$2:$A$400,$T$81)/1000) | H81: =IF($T$81="","",SUMIFS(Mastersheet!$I$2:$I$400,Mastersheet!$A$2:$A$400,$T$81)/1000) | I81: =IF($T$81="","",SUMIFS(Mastersheet!$J$2:$J$400,Mastersheet!$A$2:$A$400,$T$81)/1000) | J81: =IF($T$81="","",SUMIFS(Mastersheet!$K$2:$K$400,Mastersheet!$A$2:$A$400,$T$81)/1000) | K81: =IF($T$81="","",SUMIFS(Mastersheet!$L$2:$L$400,Mastersheet!$A$2:$A$400,$T$81)/1000) | L81: =IF($T$81="","",SUMIFS(Mastersheet!$M$2:$M$400,Mastersheet!$A$2:$A$400,$T$81)/1000) | M81: =IF($T$81="","",SUMIFS(Mastersheet!$N$2:$N$400,Mastersheet!$A$2:$A$400,$T$81)/1000) | N81: =IF($T$81="","",SUMIFS(Mastersheet!$O$2:$O$400,Mastersheet!$A$2:$A$400,$T$81)/1000) | U81: Account | V81: KTO
E82: =IF($T$82="","",SUMIFS(Mastersheet!$F$2:$F$400,Mastersheet!$A$2:$A$400,$T$82)/1000) | F82: =IF($T$82="","",SUMIFS(Mastersheet!$G$2:$G$400,Mastersheet!$A$2:$A$400,$T$82)/1000) | G82: =IF($T$82="","",SUMIFS(Mastersheet!$H$2:$H$400,Mastersheet!$A$2:$A$400,$T$82)/1000) | H82: =IF($T$82="","",SUMIFS(Mastersheet!$I$2:$I$400,Mastersheet!$A$2:$A$400,$T$82)/1000) | I82: =IF($T$82="","",SUMIFS(Mastersheet!$J$2:$J$400,Mastersheet!$A$2:$A$400,$T$82)/1000) | J82: =IF($T$82="","",SUMIFS(Mastersheet!$K$2:$K$400,Mastersheet!$A$2:$A$400,$T$82)/1000) | K82: =IF($T$82="","",SUMIFS(Mastersheet!$L$2:$L$400,Mastersheet!$A$2:$A$400,$T$82)/1000) | L82: =IF($T$82="","",SUMIFS(Mastersheet!$M$2:$M$400,Mastersheet!$A$2:$A$400,$T$82)/1000) | M82: =IF($T$82="","",SUMIFS(Mastersheet!$N$2:$N$400,Mastersheet!$A$2:$A$400,$T$82)/1000) | N82: =IF($T$82="","",SUMIFS(Mastersheet!$O$2:$O$400,Mastersheet!$A$2:$A$400,$T$82)/1000) | U82: Account | V82: KTO
E83: =IF($T$83="","",SUMIFS(Mastersheet!$F$2:$F$400,Mastersheet!$A$2:$A$400,$T$83)/1000) | F83: =IF($T$83="","",SUMIFS(Mastersheet!$G$2:$G$400,Mastersheet!$A$2:$A$400,$T$83)/1000) | G83: =IF($T$83="","",SUMIFS(Mastersheet!$H$2:$H$400,Mastersheet!$A$2:$A$400,$T$83)/1000) | H83: =IF($T$83="","",SUMIFS(Mastersheet!$I$2:$I$400,Mastersheet!$A$2:$A$400,$T$83)/1000) | I83: =IF($T$83="","",SUMIFS(Mastersheet!$J$2:$J$400,Mastersheet!$A$2:$A$400,$T$83)/1000) | J83: =IF($T$83="","",SUMIFS(Mastersheet!$K$2:$K$400,Mastersheet!$A$2:$A$400,$T$83)/1000) | K83: =IF($T$83="","",SUMIFS(Mastersheet!$L$2:$L$400,Mastersheet!$A$2:$A$400,$T$83)/1000) | L83: =IF($T$83="","",SUMIFS(Mastersheet!$M$2:$M$400,Mastersheet!$A$2:$A$400,$T$83)/1000) | M83: =IF($T$83="","",SUMIFS(Mastersheet!$N$2:$N$400,Mastersheet!$A$2:$A$400,$T$83)/1000) | N83: =IF($T$83="","",SUMIFS(Mastersheet!$O$2:$O$400,Mastersheet!$A$2:$A$400,$T$83)/1000) | U83: Account | V83: KTO
E84: =IF($T$84="","",SUMIFS(Mastersheet!$F$2:$F$400,Mastersheet!$A$2:$A$400,$T$84)/1000) | F84: =IF($T$84="","",SUMIFS(Mastersheet!$G$2:$G$400,Mastersheet!$A$2:$A$400,$T$84)/1000) | G84: =IF($T$84="","",SUMIFS(Mastersheet!$H$2:$H$400,Mastersheet!$A$2:$A$400,$T$84)/1000) | H84: =IF($T$84="","",SUMIFS(Mastersheet!$I$2:$I$400,Mastersheet!$A$2:$A$400,$T$84)/1000) | I84: =IF($T$84="","",SUMIFS(Mastersheet!$J$2:$J$400,Mastersheet!$A$2:$A$400,$T$84)/1000) | J84: =IF($T$84="","",SUMIFS(Mastersheet!$K$2:$K$400,Mastersheet!$A$2:$A$400,$T$84)/1000) | K84: =IF($T$84="","",SUMIFS(Mastersheet!$L$2:$L$400,Mastersheet!$A$2:$A$400,$T$84)/1000) | L84: =IF($T$84="","",SUMIFS(Mastersheet!$M$2:$M$400,Mastersheet!$A$2:$A$400,$T$84)/1000) | M84: =IF($T$84="","",SUMIFS(Mastersheet!$N$2:$N$400,Mastersheet!$A$2:$A$400,$T$84)/1000) | N84: =IF($T$84="","",SUMIFS(Mastersheet!$O$2:$O$400,Mastersheet!$A$2:$A$400,$T$84)/1000) | U84: Account | V84: KTO
E85: =IF($T$85="","",SUMIFS(Mastersheet!$F$2:$F$400,Mastersheet!$A$2:$A$400,$T$85)/1000) | F85: =IF($T$85="","",SUMIFS(Mastersheet!$G$2:$G$400,Mastersheet!$A$2:$A$400,$T$85)/1000) | G85: =IF($T$85="","",SUMIFS(Mastersheet!$H$2:$H$400,Mastersheet!$A$2:$A$400,$T$85)/1000) | H85: =IF($T$85="","",SUMIFS(Mastersheet!$I$2:$I$400,Mastersheet!$A$2:$A$400,$T$85)/1000) | I85: =IF($T$85="","",SUMIFS(Mastersheet!$J$2:$J$400,Mastersheet!$A$2:$A$400,$T$85)/1000) | J85: =IF($T$85="","",SUMIFS(Mastersheet!$K$2:$K$400,Mastersheet!$A$2:$A$400,$T$85)/1000) | K85: =IF($T$85="","",SUMIFS(Mastersheet!$L$2:$L$400,Mastersheet!$A$2:$A$400,$T$85)/1000) | L85: =IF($T$85="","",SUMIFS(Mastersheet!$M$2:$M$400,Mastersheet!$A$2:$A$400,$T$85)/1000) | M85: =IF($T$85="","",SUMIFS(Mastersheet!$N$2:$N$400,Mastersheet!$A$2:$A$400,$T$85)/1000) | N85: =IF($T$85="","",SUMIFS(Mastersheet!$O$2:$O$400,Mastersheet!$A$2:$A$400,$T$85)/1000) | U85: Account | V85: KTO
E86: =IF($T$86="","",SUMIFS(Mastersheet!$F$2:$F$400,Mastersheet!$A$2:$A$400,$T$86)/1000) | F86: =IF($T$86="","",SUMIFS(Mastersheet!$G$2:$G$400,Mastersheet!$A$2:$A$400,$T$86)/1000) | G86: =IF($T$86="","",SUMIFS(Mastersheet!$H$2:$H$400,Mastersheet!$A$2:$A$400,$T$86)/1000) | H86: =IF($T$86="","",SUMIFS(Mastersheet!$I$2:$I$400,Mastersheet!$A$2:$A$400,$T$86)/1000) | I86: =IF($T$86="","",SUMIFS(Mastersheet!$J$2:$J$400,Mastersheet!$A$2:$A$400,$T$86)/1000) | J86: =IF($T$86="","",SUMIFS(Mastersheet!$K$2:$K$400,Mastersheet!$A$2:$A$400,$T$86)/1000) | K86: =IF($T$86="","",SUMIFS(Mastersheet!$L$2:$L$400,Mastersheet!$A$2:$A$400,$T$86)/1000) | L86: =IF($T$86="","",SUMIFS(Mastersheet!$M$2:$M$400,Mastersheet!$A$2:$A$400,$T$86)/1000) | M86: =IF($T$86="","",SUMIFS(Mastersheet!$N$2:$N$400,Mastersheet!$A$2:$A$400,$T$86)/1000) | N86: =IF($T$86="","",SUMIFS(Mastersheet!$O$2:$O$400,Mastersheet!$A$2:$A$400,$T$86)/1000) | U86: Account | V86: KTO
E87: =IF($T$87="","",SUMIFS(Mastersheet!$F$2:$F$400,Mastersheet!$A$2:$A$400,$T$87)/1000) | F87: =IF($T$87="","",SUMIFS(Mastersheet!$G$2:$G$400,Mastersheet!$A$2:$A$400,$T$87)/1000) | G87: =IF($T$87="","",SUMIFS(Mastersheet!$H$2:$H$400,Mastersheet!$A$2:$A$400,$T$87)/1000) | H87: =IF($T$87="","",SUMIFS(Mastersheet!$I$2:$I$400,Mastersheet!$A$2:$A$400,$T$87)/1000) | I87: =IF($T$87="","",SUMIFS(Mastersheet!$J$2:$J$400,Mastersheet!$A$2:$A$400,$T$87)/1000) | J87: =IF($T$87="","",SUMIFS(Mastersheet!$K$2:$K$400,Mastersheet!$A$2:$A$400,$T$87)/1000) | K87: =IF($T$87="","",SUMIFS(Mastersheet!$L$2:$L$400,Mastersheet!$A$2:$A$400,$T$87)/1000) | L87: =IF($T$87="","",SUMIFS(Mastersheet!$M$2:$M$400,Mastersheet!$A$2:$A$400,$T$87)/1000) | M87: =IF($T$87="","",SUMIFS(Mastersheet!$N$2:$N$400,Mastersheet!$A$2:$A$400,$T$87)/1000) | N87: =IF($T$87="","",SUMIFS(Mastersheet!$O$2:$O$400,Mastersheet!$A$2:$A$400,$T$87)/1000) | U87: Account | V87: KTO
E88: =IF($T$88="","",SUMIFS(Mastersheet!$F$2:$F$400,Mastersheet!$A$2:$A$400,$T$88)/1000) | F88: =IF($T$88="","",SUMIFS(Mastersheet!$G$2:$G$400,Mastersheet!$A$2:$A$400,$T$88)/1000) | G88: =IF($T$88="","",SUMIFS(Mastersheet!$H$2:$H$400,Mastersheet!$A$2:$A$400,$T$88)/1000) | H88: =IF($T$88="","",SUMIFS(Mastersheet!$I$2:$I$400,Mastersheet!$A$2:$A$400,$T$88)/1000) | I88: =IF($T$88="","",SUMIFS(Mastersheet!$J$2:$J$400,Mastersheet!$A$2:$A$400,$T$88)/1000) | J88: =IF($T$88="","",SUMIFS(Mastersheet!$K$2:$K$400,Mastersheet!$A$2:$A$400,$T$88)/1000) | K88: =IF($T$88="","",SUMIFS(Mastersheet!$L$2:$L$400,Mastersheet!$A$2:$A$400,$T$88)/1000) | L88: =IF($T$88="","",SUMIFS(Mastersheet!$M$2:$M$400,Mastersheet!$A$2:$A$400,$T$88)/1000) | M88: =IF($T$88="","",SUMIFS(Mastersheet!$N$2:$N$400,Mastersheet!$A$2:$A$400,$T$88)/1000) | N88: =IF($T$88="","",SUMIFS(Mastersheet!$O$2:$O$400,Mastersheet!$A$2:$A$400,$T$88)/1000) | U88: Account | V88: KTO
C89: Kosten der Warenabgabe | D89: Delivery costs | E89: =SUMIFS(Mastersheet!$F$2:$F$400,Mastersheet!$D$2:$D$400,$T89,Mastersheet!$C$2:$C$400,$U89)/1000 -> 0 | F89: =SUMIFS(Mastersheet!$G$2:$G$400,Mastersheet!$D$2:$D$400,$T89,Mastersheet!$C$2:$C$400,$U89)/1000 -> 0 | G89: =SUMIFS(Mastersheet!$H$2:$H$400,Mastersheet!$D$2:$D$400,$T89,Mastersheet!$C$2:$C$400,$U89)/1000 -> 0 | H89: =SUMIFS(Mastersheet!$I$2:$I$400,Mastersheet!$D$2:$D$400,$T89,Mastersheet!$C$2:$C$400,$U89)/1000 -> 0 | I89: =SUMIFS(Mastersheet!$J$2:$J$400,Mastersheet!$D$2:$D$400,$T89,Mastersheet!$C$2:$C$400,$U89)/1000 -> 0 | J89: =SUMIFS(Mastersheet!$K$2:$K$400,Mastersheet!$D$2:$D$400,$T89,Mastersheet!$C$2:$C$400,$U89)/1000 -> 0 | K89: =SUMIFS(Mastersheet!$L$2:$L$400,Mastersheet!$D$2:$D$400,$T89,Mastersheet!$C$2:$C$400,$U89)/1000 -> 0 | L89: =SUMIFS(Mastersheet!$M$2:$M$400,Mastersheet!$D$2:$D$400,$T89,Mastersheet!$C$2:$C$400,$U89)/1000 -> 0 | M89: =SUMIFS(Mastersheet!$N$2:$N$400,Mastersheet!$D$2:$D$400,$T89,Mastersheet!$C$2:$C$400,$U89)/1000 -> 0 | N89: =SUMIFS(Mastersheet!$O$2:$O$400,Mastersheet!$D$2:$D$400,$T89,Mastersheet!$C$2:$C$400,$U89)/1000 -> 0 | P89: =IFERROR(((H89/F89)^(1/(($H$1-$F$1)/365)))-1,"n/a") -> n/a | Q89: =IFERROR(((N89/H89)^(1/(($N$1-$H$1)/365)))-1,"n/a") -> n/a | T89: Kosten der Warenabgabe | U89: PL | V89: POS
E90: =IF($T$90="","",SUMIFS(Mastersheet!$F$2:$F$400,Mastersheet!$A$2:$A$400,$T$90)/1000) | F90: =IF($T$90="","",SUMIFS(Mastersheet!$G$2:$G$400,Mastersheet!$A$2:$A$400,$T$90)/1000) | G90: =IF($T$90="","",SUMIFS(Mastersheet!$H$2:$H$400,Mastersheet!$A$2:$A$400,$T$90)/1000) | H90: =IF($T$90="","",SUMIFS(Mastersheet!$I$2:$I$400,Mastersheet!$A$2:$A$400,$T$90)/1000) | I90: =IF($T$90="","",SUMIFS(Mastersheet!$J$2:$J$400,Mastersheet!$A$2:$A$400,$T$90)/1000) | J90: =IF($T$90="","",SUMIFS(Mastersheet!$K$2:$K$400,Mastersheet!$A$2:$A$400,$T$90)/1000) | K90: =IF($T$90="","",SUMIFS(Mastersheet!$L$2:$L$400,Mastersheet!$A$2:$A$400,$T$90)/1000) | L90: =IF($T$90="","",SUMIFS(Mastersheet!$M$2:$M$400,Mastersheet!$A$2:$A$400,$T$90)/1000) | M90: =IF($T$90="","",SUMIFS(Mastersheet!$N$2:$N$400,Mastersheet!$A$2:$A$400,$T$90)/1000) | N90: =IF($T$90="","",SUMIFS(Mastersheet!$O$2:$O$400,Mastersheet!$A$2:$A$400,$T$90)/1000) | U90: Account | V90: KTO
E91: =IF($T$91="","",SUMIFS(Mastersheet!$F$2:$F$400,Mastersheet!$A$2:$A$400,$T$91)/1000) | F91: =IF($T$91="","",SUMIFS(Mastersheet!$G$2:$G$400,Mastersheet!$A$2:$A$400,$T$91)/1000) | G91: =IF($T$91="","",SUMIFS(Mastersheet!$H$2:$H$400,Mastersheet!$A$2:$A$400,$T$91)/1000) | H91: =IF($T$91="","",SUMIFS(Mastersheet!$I$2:$I$400,Mastersheet!$A$2:$A$400,$T$91)/1000) | I91: =IF($T$91="","",SUMIFS(Mastersheet!$J$2:$J$400,Mastersheet!$A$2:$A$400,$T$91)/1000) | J91: =IF($T$91="","",SUMIFS(Mastersheet!$K$2:$K$400,Mastersheet!$A$2:$A$400,$T$91)/1000) | K91: =IF($T$91="","",SUMIFS(Mastersheet!$L$2:$L$400,Mastersheet!$A$2:$A$400,$T$91)/1000) | L91: =IF($T$91="","",SUMIFS(Mastersheet!$M$2:$M$400,Mastersheet!$A$2:$A$400,$T$91)/1000) | M91: =IF($T$91="","",SUMIFS(Mastersheet!$N$2:$N$400,Mastersheet!$A$2:$A$400,$T$91)/1000) | N91: =IF($T$91="","",SUMIFS(Mastersheet!$O$2:$O$400,Mastersheet!$A$2:$A$400,$T$91)/1000) | U91: Account | V91: KTO
E92: =IF($T$92="","",SUMIFS(Mastersheet!$F$2:$F$400,Mastersheet!$A$2:$A$400,$T$92)/1000) | F92: =IF($T$92="","",SUMIFS(Mastersheet!$G$2:$G$400,Mastersheet!$A$2:$A$400,$T$92)/1000) | G92: =IF($T$92="","",SUMIFS(Mastersheet!$H$2:$H$400,Mastersheet!$A$2:$A$400,$T$92)/1000) | H92: =IF($T$92="","",SUMIFS(Mastersheet!$I$2:$I$400,Mastersheet!$A$2:$A$400,$T$92)/1000) | I92: =IF($T$92="","",SUMIFS(Mastersheet!$J$2:$J$400,Mastersheet!$A$2:$A$400,$T$92)/1000) | J92: =IF($T$92="","",SUMIFS(Mastersheet!$K$2:$K$400,Mastersheet!$A$2:$A$400,$T$92)/1000) | K92: =IF($T$92="","",SUMIFS(Mastersheet!$L$2:$L$400,Mastersheet!$A$2:$A$400,$T$92)/1000) | L92: =IF($T$92="","",SUMIFS(Mastersheet!$M$2:$M$400,Mastersheet!$A$2:$A$400,$T$92)/1000) | M92: =IF($T$92="","",SUMIFS(Mastersheet!$N$2:$N$400,Mastersheet!$A$2:$A$400,$T$92)/1000) | N92: =IF($T$92="","",SUMIFS(Mastersheet!$O$2:$O$400,Mastersheet!$A$2:$A$400,$T$92)/1000) | U92: Account | V92: KTO
E93: =IF($T$93="","",SUMIFS(Mastersheet!$F$2:$F$400,Mastersheet!$A$2:$A$400,$T$93)/1000) | F93: =IF($T$93="","",SUMIFS(Mastersheet!$G$2:$G$400,Mastersheet!$A$2:$A$400,$T$93)/1000) | G93: =IF($T$93="","",SUMIFS(Mastersheet!$H$2:$H$400,Mastersheet!$A$2:$A$400,$T$93)/1000) | H93: =IF($T$93="","",SUMIFS(Mastersheet!$I$2:$I$400,Mastersheet!$A$2:$A$400,$T$93)/1000) | I93: =IF($T$93="","",SUMIFS(Mastersheet!$J$2:$J$400,Mastersheet!$A$2:$A$400,$T$93)/1000) | J93: =IF($T$93="","",SUMIFS(Mastersheet!$K$2:$K$400,Mastersheet!$A$2:$A$400,$T$93)/1000) | K93: =IF($T$93="","",SUMIFS(Mastersheet!$L$2:$L$400,Mastersheet!$A$2:$A$400,$T$93)/1000) | L93: =IF($T$93="","",SUMIFS(Mastersheet!$M$2:$M$400,Mastersheet!$A$2:$A$400,$T$93)/1000) | M93: =IF($T$93="","",SUMIFS(Mastersheet!$N$2:$N$400,Mastersheet!$A$2:$A$400,$T$93)/1000) | N93: =IF($T$93="","",SUMIFS(Mastersheet!$O$2:$O$400,Mastersheet!$A$2:$A$400,$T$93)/1000) | U93: Account | V93: KTO
E94: =IF($T$94="","",SUMIFS(Mastersheet!$F$2:$F$400,Mastersheet!$A$2:$A$400,$T$94)/1000) | F94: =IF($T$94="","",SUMIFS(Mastersheet!$G$2:$G$400,Mastersheet!$A$2:$A$400,$T$94)/1000) | G94: =IF($T$94="","",SUMIFS(Mastersheet!$H$2:$H$400,Mastersheet!$A$2:$A$400,$T$94)/1000) | H94: =IF($T$94="","",SUMIFS(Mastersheet!$I$2:$I$400,Mastersheet!$A$2:$A$400,$T$94)/1000) | I94: =IF($T$94="","",SUMIFS(Mastersheet!$J$2:$J$400,Mastersheet!$A$2:$A$400,$T$94)/1000) | J94: =IF($T$94="","",SUMIFS(Mastersheet!$K$2:$K$400,Mastersheet!$A$2:$A$400,$T$94)/1000) | K94: =IF($T$94="","",SUMIFS(Mastersheet!$L$2:$L$400,Mastersheet!$A$2:$A$400,$T$94)/1000) | L94: =IF($T$94="","",SUMIFS(Mastersheet!$M$2:$M$400,Mastersheet!$A$2:$A$400,$T$94)/1000) | M94: =IF($T$94="","",SUMIFS(Mastersheet!$N$2:$N$400,Mastersheet!$A$2:$A$400,$T$94)/1000) | N94: =IF($T$94="","",SUMIFS(Mastersheet!$O$2:$O$400,Mastersheet!$A$2:$A$400,$T$94)/1000) | U94: Account | V94: KTO
E95: =IF($T$95="","",SUMIFS(Mastersheet!$F$2:$F$400,Mastersheet!$A$2:$A$400,$T$95)/1000) | F95: =IF($T$95="","",SUMIFS(Mastersheet!$G$2:$G$400,Mastersheet!$A$2:$A$400,$T$95)/1000) | G95: =IF($T$95="","",SUMIFS(Mastersheet!$H$2:$H$400,Mastersheet!$A$2:$A$400,$T$95)/1000) | H95: =IF($T$95="","",SUMIFS(Mastersheet!$I$2:$I$400,Mastersheet!$A$2:$A$400,$T$95)/1000) | I95: =IF($T$95="","",SUMIFS(Mastersheet!$J$2:$J$400,Mastersheet!$A$2:$A$400,$T$95)/1000) | J95: =IF($T$95="","",SUMIFS(Mastersheet!$K$2:$K$400,Mastersheet!$A$2:$A$400,$T$95)/1000) | K95: =IF($T$95="","",SUMIFS(Mastersheet!$L$2:$L$400,Mastersheet!$A$2:$A$400,$T$95)/1000) | L95: =IF($T$95="","",SUMIFS(Mastersheet!$M$2:$M$400,Mastersheet!$A$2:$A$400,$T$95)/1000) | M95: =IF($T$95="","",SUMIFS(Mastersheet!$N$2:$N$400,Mastersheet!$A$2:$A$400,$T$95)/1000) | N95: =IF($T$95="","",SUMIFS(Mastersheet!$O$2:$O$400,Mastersheet!$A$2:$A$400,$T$95)/1000) | U95: Account | V95: KTO
E96: =IF($T$96="","",SUMIFS(Mastersheet!$F$2:$F$400,Mastersheet!$A$2:$A$400,$T$96)/1000) | F96: =IF($T$96="","",SUMIFS(Mastersheet!$G$2:$G$400,Mastersheet!$A$2:$A$400,$T$96)/1000) | G96: =IF($T$96="","",SUMIFS(Mastersheet!$H$2:$H$400,Mastersheet!$A$2:$A$400,$T$96)/1000) | H96: =IF($T$96="","",SUMIFS(Mastersheet!$I$2:$I$400,Mastersheet!$A$2:$A$400,$T$96)/1000) | I96: =IF($T$96="","",SUMIFS(Mastersheet!$J$2:$J$400,Mastersheet!$A$2:$A$400,$T$96)/1000) | J96: =IF($T$96="","",SUMIFS(Mastersheet!$K$2:$K$400,Mastersheet!$A$2:$A$400,$T$96)/1000) | K96: =IF($T$96="","",SUMIFS(Mastersheet!$L$2:$L$400,Mastersheet!$A$2:$A$400,$T$96)/1000) | L96: =IF($T$96="","",SUMIFS(Mastersheet!$M$2:$M$400,Mastersheet!$A$2:$A$400,$T$96)/1000) | M96: =IF($T$96="","",SUMIFS(Mastersheet!$N$2:$N$400,Mastersheet!$A$2:$A$400,$T$96)/1000) | N96: =IF($T$96="","",SUMIFS(Mastersheet!$O$2:$O$400,Mastersheet!$A$2:$A$400,$T$96)/1000) | U96: Account | V96: KTO
E97: =IF($T$97="","",SUMIFS(Mastersheet!$F$2:$F$400,Mastersheet!$A$2:$A$400,$T$97)/1000) | F97: =IF($T$97="","",SUMIFS(Mastersheet!$G$2:$G$400,Mastersheet!$A$2:$A$400,$T$97)/1000) | G97: =IF($T$97="","",SUMIFS(Mastersheet!$H$2:$H$400,Mastersheet!$A$2:$A$400,$T$97)/1000) | H97: =IF($T$97="","",SUMIFS(Mastersheet!$I$2:$I$400,Mastersheet!$A$2:$A$400,$T$97)/1000) | I97: =IF($T$97="","",SUMIFS(Mastersheet!$J$2:$J$400,Mastersheet!$A$2:$A$400,$T$97)/1000) | J97: =IF($T$97="","",SUMIFS(Mastersheet!$K$2:$K$400,Mastersheet!$A$2:$A$400,$T$97)/1000) | K97: =IF($T$97="","",SUMIFS(Mastersheet!$L$2:$L$400,Mastersheet!$A$2:$A$400,$T$97)/1000) | L97: =IF($T$97="","",SUMIFS(Mastersheet!$M$2:$M$400,Mastersheet!$A$2:$A$400,$T$97)/1000) | M97: =IF($T$97="","",SUMIFS(Mastersheet!$N$2:$N$400,Mastersheet!$A$2:$A$400,$T$97)/1000) | N97: =IF($T$97="","",SUMIFS(Mastersheet!$O$2:$O$400,Mastersheet!$A$2:$A$400,$T$97)/1000) | U97: Account | V97: KTO
C98: Fahrzeugkosten | D98: Vehicle costs | E98: =SUMIFS(Mastersheet!$F$2:$F$400,Mastersheet!$D$2:$D$400,$T98,Mastersheet!$C$2:$C$400,$U98)/1000 -> 0 | F98: =SUMIFS(Mastersheet!$G$2:$G$400,Mastersheet!$D$2:$D$400,$T98,Mastersheet!$C$2:$C$400,$U98)/1000 -> 0 | G98: =SUMIFS(Mastersheet!$H$2:$H$400,Mastersheet!$D$2:$D$400,$T98,Mastersheet!$C$2:$C$400,$U98)/1000 -> 0 | H98: =SUMIFS(Mastersheet!$I$2:$I$400,Mastersheet!$D$2:$D$400,$T98,Mastersheet!$C$2:$C$400,$U98)/1000 -> 0 | I98: =SUMIFS(Mastersheet!$J$2:$J$400,Mastersheet!$D$2:$D$400,$T98,Mastersheet!$C$2:$C$400,$U98)/1000 -> 0 | J98: =SUMIFS(Mastersheet!$K$2:$K$400,Mastersheet!$D$2:$D$400,$T98,Mastersheet!$C$2:$C$400,$U98)/1000 -> 0 | K98: =SUMIFS(Mastersheet!$L$2:$L$400,Mastersheet!$D$2:$D$400,$T98,Mastersheet!$C$2:$C$400,$U98)/1000 -> 0 | L98: =SUMIFS(Mastersheet!$M$2:$M$400,Mastersheet!$D$2:$D$400,$T98,Mastersheet!$C$2:$C$400,$U98)/1000 -> 0 | M98: =SUMIFS(Mastersheet!$N$2:$N$400,Mastersheet!$D$2:$D$400,$T98,Mastersheet!$C$2:$C$400,$U98)/1000 -> 0 | N98: =SUMIFS(Mastersheet!$O$2:$O$400,Mastersheet!$D$2:$D$400,$T98,Mastersheet!$C$2:$C$400,$U98)/1000 -> 0 | P98: =IFERROR(((H98/F98)^(1/(($H$1-$F$1)/365)))-1,"n/a") -> n/a | Q98: =IFERROR(((N98/H98)^(1/(($N$1-$H$1)/365)))-1,"n/a") -> n/a | T98: Fahrzeugkosten | U98: PL | V98: POS
E99: =IF($T$99="","",SUMIFS(Mastersheet!$F$2:$F$400,Mastersheet!$A$2:$A$400,$T$99)/1000) | F99: =IF($T$99="","",SUMIFS(Mastersheet!$G$2:$G$400,Mastersheet!$A$2:$A$400,$T$99)/1000) | G99: =IF($T$99="","",SUMIFS(Mastersheet!$H$2:$H$400,Mastersheet!$A$2:$A$400,$T$99)/1000) | H99: =IF($T$99="","",SUMIFS(Mastersheet!$I$2:$I$400,Mastersheet!$A$2:$A$400,$T$99)/1000) | I99: =IF($T$99="","",SUMIFS(Mastersheet!$J$2:$J$400,Mastersheet!$A$2:$A$400,$T$99)/1000) | J99: =IF($T$99="","",SUMIFS(Mastersheet!$K$2:$K$400,Mastersheet!$A$2:$A$400,$T$99)/1000) | K99: =IF($T$99="","",SUMIFS(Mastersheet!$L$2:$L$400,Mastersheet!$A$2:$A$400,$T$99)/1000) | L99: =IF($T$99="","",SUMIFS(Mastersheet!$M$2:$M$400,Mastersheet!$A$2:$A$400,$T$99)/1000) | M99: =IF($T$99="","",SUMIFS(Mastersheet!$N$2:$N$400,Mastersheet!$A$2:$A$400,$T$99)/1000) | N99: =IF($T$99="","",SUMIFS(Mastersheet!$O$2:$O$400,Mastersheet!$A$2:$A$400,$T$99)/1000) | U99: Account | V99: KTO
E100: =IF($T$100="","",SUMIFS(Mastersheet!$F$2:$F$400,Mastersheet!$A$2:$A$400,$T$100)/1000) | F100: =IF($T$100="","",SUMIFS(Mastersheet!$G$2:$G$400,Mastersheet!$A$2:$A$400,$T$100)/1000) | G100: =IF($T$100="","",SUMIFS(Mastersheet!$H$2:$H$400,Mastersheet!$A$2:$A$400,$T$100)/1000) | H100: =IF($T$100="","",SUMIFS(Mastersheet!$I$2:$I$400,Mastersheet!$A$2:$A$400,$T$100)/1000) | I100: =IF($T$100="","",SUMIFS(Mastersheet!$J$2:$J$400,Mastersheet!$A$2:$A$400,$T$100)/1000) | J100: =IF($T$100="","",SUMIFS(Mastersheet!$K$2:$K$400,Mastersheet!$A$2:$A$400,$T$100)/1000) | K100: =IF($T$100="","",SUMIFS(Mastersheet!$L$2:$L$400,Mastersheet!$A$2:$A$400,$T$100)/1000) | L100: =IF($T$100="","",SUMIFS(Mastersheet!$M$2:$M$400,Mastersheet!$A$2:$A$400,$T$100)/1000) | M100: =IF($T$100="","",SUMIFS(Mastersheet!$N$2:$N$400,Mastersheet!$A$2:$A$400,$T$100)/1000) | N100: =IF($T$100="","",SUMIFS(Mastersheet!$O$2:$O$400,Mastersheet!$A$2:$A$400,$T$100)/1000) | U100: Account | V100: KTO
E101: =IF($T$101="","",SUMIFS(Mastersheet!$F$2:$F$400,Mastersheet!$A$2:$A$400,$T$101)/1000) | F101: =IF($T$101="","",SUMIFS(Mastersheet!$G$2:$G$400,Mastersheet!$A$2:$A$400,$T$101)/1000) | G101: =IF($T$101="","",SUMIFS(Mastersheet!$H$2:$H$400,Mastersheet!$A$2:$A$400,$T$101)/1000) | H101: =IF($T$101="","",SUMIFS(Mastersheet!$I$2:$I$400,Mastersheet!$A$2:$A$400,$T$101)/1000) | I101: =IF($T$101="","",SUMIFS(Mastersheet!$J$2:$J$400,Mastersheet!$A$2:$A$400,$T$101)/1000) | J101: =IF($T$101="","",SUMIFS(Mastersheet!$K$2:$K$400,Mastersheet!$A$2:$A$400,$T$101)/1000) | K101: =IF($T$101="","",SUMIFS(Mastersheet!$L$2:$L$400,Mastersheet!$A$2:$A$400,$T$101)/1000) | L101: =IF($T$101="","",SUMIFS(Mastersheet!$M$2:$M$400,Mastersheet!$A$2:$A$400,$T$101)/1000) | M101: =IF($T$101="","",SUMIFS(Mastersheet!$N$2:$N$400,Mastersheet!$A$2:$A$400,$T$101)/1000) | N101: =IF($T$101="","",SUMIFS(Mastersheet!$O$2:$O$400,Mastersheet!$A$2:$A$400,$T$101)/1000) | U101: Account | V101: KTO
E102: =IF($T$102="","",SUMIFS(Mastersheet!$F$2:$F$400,Mastersheet!$A$2:$A$400,$T$102)/1000) | F102: =IF($T$102="","",SUMIFS(Mastersheet!$G$2:$G$400,Mastersheet!$A$2:$A$400,$T$102)/1000) | G102: =IF($T$102="","",SUMIFS(Mastersheet!$H$2:$H$400,Mastersheet!$A$2:$A$400,$T$102)/1000) | H102: =IF($T$102="","",SUMIFS(Mastersheet!$I$2:$I$400,Mastersheet!$A$2:$A$400,$T$102)/1000) | I102: =IF($T$102="","",SUMIFS(Mastersheet!$J$2:$J$400,Mastersheet!$A$2:$A$400,$T$102)/1000) | J102: =IF($T$102="","",SUMIFS(Mastersheet!$K$2:$K$400,Mastersheet!$A$2:$A$400,$T$102)/1000) | K102: =IF($T$102="","",SUMIFS(Mastersheet!$L$2:$L$400,Mastersheet!$A$2:$A$400,$T$102)/1000) | L102: =IF($T$102="","",SUMIFS(Mastersheet!$M$2:$M$400,Mastersheet!$A$2:$A$400,$T$102)/1000) | M102: =IF($T$102="","",SUMIFS(Mastersheet!$N$2:$N$400,Mastersheet!$A$2:$A$400,$T$102)/1000) | N102: =IF($T$102="","",SUMIFS(Mastersheet!$O$2:$O$400,Mastersheet!$A$2:$A$400,$T$102)/1000) | U102: Account | V102: KTO
E103: =IF($T$103="","",SUMIFS(Mastersheet!$F$2:$F$400,Mastersheet!$A$2:$A$400,$T$103)/1000) | F103: =IF($T$103="","",SUMIFS(Mastersheet!$G$2:$G$400,Mastersheet!$A$2:$A$400,$T$103)/1000) | G103: =IF($T$103="","",SUMIFS(Mastersheet!$H$2:$H$400,Mastersheet!$A$2:$A$400,$T$103)/1000) | H103: =IF($T$103="","",SUMIFS(Mastersheet!$I$2:$I$400,Mastersheet!$A$2:$A$400,$T$103)/1000) | I103: =IF($T$103="","",SUMIFS(Mastersheet!$J$2:$J$400,Mastersheet!$A$2:$A$400,$T$103)/1000) | J103: =IF($T$103="","",SUMIFS(Mastersheet!$K$2:$K$400,Mastersheet!$A$2:$A$400,$T$103)/1000) | K103: =IF($T$103="","",SUMIFS(Mastersheet!$L$2:$L$400,Mastersheet!$A$2:$A$400,$T$103)/1000) | L103: =IF($T$103="","",SUMIFS(Mastersheet!$M$2:$M$400,Mastersheet!$A$2:$A$400,$T$103)/1000) | M103: =IF($T$103="","",SUMIFS(Mastersheet!$N$2:$N$400,Mastersheet!$A$2:$A$400,$T$103)/1000) | N103: =IF($T$103="","",SUMIFS(Mastersheet!$O$2:$O$400,Mastersheet!$A$2:$A$400,$T$103)/1000) | U103: Account | V103: KTO
...

Sheet Lead NA
C4: =Cockpit!$C$4 -> Template | E4: =Cockpit!C39 -> 44561 | F4: =Cockpit!D39 -> 44926 | G4: =Cockpit!E39 -> 45291 | H4: =Cockpit!F39 -> 45657 | I4: =Cockpit!G39 -> 45808 | J4: =Cockpit!H39 -> 46022 | K4: =Cockpit!I39 -> 46387 | L4: =Cockpit!J39 -> 46752 | M4: =Cockpit!K39 -> 47118
C5: ="in T"&Cockpit!$C$5 -> in TEUR | E5: IST | F5: IST | G5: IST | H5: IST | I5: IST | J5: =Cockpit!H40 -> Plan | K5: =Cockpit!I40 -> Plan | L5: =Cockpit!J40 -> Plan | M5: =Cockpit!K40 -> Plan | P5: Ticker 1 (NA-Zeile / Konto) | Q5: Ticker 2 (Klasse) | R5: Zeilentyp
D6: =Cockpit!$C$4 -> Template | E6: =Cockpit!C39 -> 44561 | F6: =Cockpit!D39 -> 44926 | G6: =Cockpit!E39 -> 45291 | H6: =Cockpit!F39 -> 45657 | I6: =Cockpit!G39 -> 45808 | J6: =Cockpit!H39 -> 46022 | K6: =Cockpit!I39 -> 46387 | L6: =Cockpit!J39 -> 46752 | M6: =Cockpit!K39 -> 47118
D7: ="in k"&Cockpit!$C$5 -> in kEUR | E7: =Cockpit!C40 -> IST | F7: =Cockpit!D40 -> IST | G7: =Cockpit!E40 -> IST | H7: =Cockpit!F40 -> IST | I7: =Cockpit!G40 -> IST | J7: =Cockpit!H40 -> Plan | K7: =Cockpit!I40 -> Plan | L7: =Cockpit!J40 -> Plan | M7: =Cockpit!K40 -> Plan | P7: Classification BT
C9: Immaterielle Vermögensgegenstände | D9: Intangible assets | E9: =SUMIFS(Mastersheet!$F$2:$F$400,Mastersheet!$D$2:$D$400,$P9,Mastersheet!$C$2:$C$400,$Q9)/1000 -> 0 | F9: =SUMIFS(Mastersheet!$G$2:$G$400,Mastersheet!$D$2:$D$400,$P9,Mastersheet!$C$2:$C$400,$Q9)/1000 -> 0 | G9: =SUMIFS(Mastersheet!$H$2:$H$400,Mastersheet!$D$2:$D$400,$P9,Mastersheet!$C$2:$C$400,$Q9)/1000 -> 0 | H9: =SUMIFS(Mastersheet!$I$2:$I$400,Mastersheet!$D$2:$D$400,$P9,Mastersheet!$C$2:$C$400,$Q9)/1000 -> 0 | I9: =SUMIFS(Mastersheet!$J$2:$J$400,Mastersheet!$D$2:$D$400,$P9,Mastersheet!$C$2:$C$400,$Q9)/1000 -> 0 | J9: =SUMIFS(Mastersheet!$K$2:$K$400,Mastersheet!$D$2:$D$400,$P9,Mastersheet!$C$2:$C$400,$Q9)/1000 -> 0 | K9: =SUMIFS(Mastersheet!$L$2:$L$400,Mastersheet!$D$2:$D$400,$P9,Mastersheet!$C$2:$C$400,$Q9)/1000 -> 0 | L9: =SUMIFS(Mastersheet!$M$2:$M$400,Mastersheet!$D$2:$D$400,$P9,Mastersheet!$C$2:$C$400,$Q9)/1000 -> 0 | M9: =SUMIFS(Mastersheet!$N$2:$N$400,Mastersheet!$D$2:$D$400,$P9,Mastersheet!$C$2:$C$400,$Q9)/1000 -> 0 | P9: Immaterielle Vermoegensgegenstaende | Q9: FA | R9: POS
E10: =IF($P$10="","",SUMIFS(Mastersheet!$F$2:$F$400,Mastersheet!$A$2:$A$400,$P$10)/1000) | F10: =IF($P$10="","",SUMIFS(Mastersheet!$G$2:$G$400,Mastersheet!$A$2:$A$400,$P$10)/1000) | G10: =IF($P$10="","",SUMIFS(Mastersheet!$H$2:$H$400,Mastersheet!$A$2:$A$400,$P$10)/1000) | H10: =IF($P$10="","",SUMIFS(Mastersheet!$I$2:$I$400,Mastersheet!$A$2:$A$400,$P$10)/1000) | I10: =IF($P$10="","",SUMIFS(Mastersheet!$J$2:$J$400,Mastersheet!$A$2:$A$400,$P$10)/1000) | J10: =IF($P$10="","",SUMIFS(Mastersheet!$K$2:$K$400,Mastersheet!$A$2:$A$400,$P$10)/1000) | K10: =IF($P$10="","",SUMIFS(Mastersheet!$L$2:$L$400,Mastersheet!$A$2:$A$400,$P$10)/1000) | L10: =IF($P$10="","",SUMIFS(Mastersheet!$M$2:$M$400,Mastersheet!$A$2:$A$400,$P$10)/1000) | M10: =IF($P$10="","",SUMIFS(Mastersheet!$N$2:$N$400,Mastersheet!$A$2:$A$400,$P$10)/1000) | Q10: Account | R10: KTO
E11: =IF($P$11="","",SUMIFS(Mastersheet!$F$2:$F$400,Mastersheet!$A$2:$A$400,$P$11)/1000) | F11: =IF($P$11="","",SUMIFS(Mastersheet!$G$2:$G$400,Mastersheet!$A$2:$A$400,$P$11)/1000) | G11: =IF($P$11="","",SUMIFS(Mastersheet!$H$2:$H$400,Mastersheet!$A$2:$A$400,$P$11)/1000) | H11: =IF($P$11="","",SUMIFS(Mastersheet!$I$2:$I$400,Mastersheet!$A$2:$A$400,$P$11)/1000) | I11: =IF($P$11="","",SUMIFS(Mastersheet!$J$2:$J$400,Mastersheet!$A$2:$A$400,$P$11)/1000) | J11: =IF($P$11="","",SUMIFS(Mastersheet!$K$2:$K$400,Mastersheet!$A$2:$A$400,$P$11)/1000) | K11: =IF($P$11="","",SUMIFS(Mastersheet!$L$2:$L$400,Mastersheet!$A$2:$A$400,$P$11)/1000) | L11: =IF($P$11="","",SUMIFS(Mastersheet!$M$2:$M$400,Mastersheet!$A$2:$A$400,$P$11)/1000) | M11: =IF($P$11="","",SUMIFS(Mastersheet!$N$2:$N$400,Mastersheet!$A$2:$A$400,$P$11)/1000) | Q11: Account | R11: KTO
E12: =IF($P$12="","",SUMIFS(Mastersheet!$F$2:$F$400,Mastersheet!$A$2:$A$400,$P$12)/1000) | F12: =IF($P$12="","",SUMIFS(Mastersheet!$G$2:$G$400,Mastersheet!$A$2:$A$400,$P$12)/1000) | G12: =IF($P$12="","",SUMIFS(Mastersheet!$H$2:$H$400,Mastersheet!$A$2:$A$400,$P$12)/1000) | H12: =IF($P$12="","",SUMIFS(Mastersheet!$I$2:$I$400,Mastersheet!$A$2:$A$400,$P$12)/1000) | I12: =IF($P$12="","",SUMIFS(Mastersheet!$J$2:$J$400,Mastersheet!$A$2:$A$400,$P$12)/1000) | J12: =IF($P$12="","",SUMIFS(Mastersheet!$K$2:$K$400,Mastersheet!$A$2:$A$400,$P$12)/1000) | K12: =IF($P$12="","",SUMIFS(Mastersheet!$L$2:$L$400,Mastersheet!$A$2:$A$400,$P$12)/1000) | L12: =IF($P$12="","",SUMIFS(Mastersheet!$M$2:$M$400,Mastersheet!$A$2:$A$400,$P$12)/1000) | M12: =IF($P$12="","",SUMIFS(Mastersheet!$N$2:$N$400,Mastersheet!$A$2:$A$400,$P$12)/1000) | Q12: Account | R12: KTO
E13: =IF($P$13="","",SUMIFS(Mastersheet!$F$2:$F$400,Mastersheet!$A$2:$A$400,$P$13)/1000) | F13: =IF($P$13="","",SUMIFS(Mastersheet!$G$2:$G$400,Mastersheet!$A$2:$A$400,$P$13)/1000) | G13: =IF($P$13="","",SUMIFS(Mastersheet!$H$2:$H$400,Mastersheet!$A$2:$A$400,$P$13)/1000) | H13: =IF($P$13="","",SUMIFS(Mastersheet!$I$2:$I$400,Mastersheet!$A$2:$A$400,$P$13)/1000) | I13: =IF($P$13="","",SUMIFS(Mastersheet!$J$2:$J$400,Mastersheet!$A$2:$A$400,$P$13)/1000) | J13: =IF($P$13="","",SUMIFS(Mastersheet!$K$2:$K$400,Mastersheet!$A$2:$A$400,$P$13)/1000) | K13: =IF($P$13="","",SUMIFS(Mastersheet!$L$2:$L$400,Mastersheet!$A$2:$A$400,$P$13)/1000) | L13: =IF($P$13="","",SUMIFS(Mastersheet!$M$2:$M$400,Mastersheet!$A$2:$A$400,$P$13)/1000) | M13: =IF($P$13="","",SUMIFS(Mastersheet!$N$2:$N$400,Mastersheet!$A$2:$A$400,$P$13)/1000) | Q13: Account | R13: KTO
E14: =IF($P$14="","",SUMIFS(Mastersheet!$F$2:$F$400,Mastersheet!$A$2:$A$400,$P$14)/1000) | F14: =IF($P$14="","",SUMIFS(Mastersheet!$G$2:$G$400,Mastersheet!$A$2:$A$400,$P$14)/1000) | G14: =IF($P$14="","",SUMIFS(Mastersheet!$H$2:$H$400,Mastersheet!$A$2:$A$400,$P$14)/1000) | H14: =IF($P$14="","",SUMIFS(Mastersheet!$I$2:$I$400,Mastersheet!$A$2:$A$400,$P$14)/1000) | I14: =IF($P$14="","",SUMIFS(Mastersheet!$J$2:$J$400,Mastersheet!$A$2:$A$400,$P$14)/1000) | J14: =IF($P$14="","",SUMIFS(Mastersheet!$K$2:$K$400,Mastersheet!$A$2:$A$400,$P$14)/1000) | K14: =IF($P$14="","",SUMIFS(Mastersheet!$L$2:$L$400,Mastersheet!$A$2:$A$400,$P$14)/1000) | L14: =IF($P$14="","",SUMIFS(Mastersheet!$M$2:$M$400,Mastersheet!$A$2:$A$400,$P$14)/1000) | M14: =IF($P$14="","",SUMIFS(Mastersheet!$N$2:$N$400,Mastersheet!$A$2:$A$400,$P$14)/1000) | Q14: Account | R14: KTO
E15: =IF($P$15="","",SUMIFS(Mastersheet!$F$2:$F$400,Mastersheet!$A$2:$A$400,$P$15)/1000) | F15: =IF($P$15="","",SUMIFS(Mastersheet!$G$2:$G$400,Mastersheet!$A$2:$A$400,$P$15)/1000) | G15: =IF($P$15="","",SUMIFS(Mastersheet!$H$2:$H$400,Mastersheet!$A$2:$A$400,$P$15)/1000) | H15: =IF($P$15="","",SUMIFS(Mastersheet!$I$2:$I$400,Mastersheet!$A$2:$A$400,$P$15)/1000) | I15: =IF($P$15="","",SUMIFS(Mastersheet!$J$2:$J$400,Mastersheet!$A$2:$A$400,$P$15)/1000) | J15: =IF($P$15="","",SUMIFS(Mastersheet!$K$2:$K$400,Mastersheet!$A$2:$A$400,$P$15)/1000) | K15: =IF($P$15="","",SUMIFS(Mastersheet!$L$2:$L$400,Mastersheet!$A$2:$A$400,$P$15)/1000) | L15: =IF($P$15="","",SUMIFS(Mastersheet!$M$2:$M$400,Mastersheet!$A$2:$A$400,$P$15)/1000) | M15: =IF($P$15="","",SUMIFS(Mastersheet!$N$2:$N$400,Mastersheet!$A$2:$A$400,$P$15)/1000) | Q15: Account | R15: KTO
E16: =IF($P$16="","",SUMIFS(Mastersheet!$F$2:$F$400,Mastersheet!$A$2:$A$400,$P$16)/1000) | F16: =IF($P$16="","",SUMIFS(Mastersheet!$G$2:$G$400,Mastersheet!$A$2:$A$400,$P$16)/1000) | G16: =IF($P$16="","",SUMIFS(Mastersheet!$H$2:$H$400,Mastersheet!$A$2:$A$400,$P$16)/1000) | H16: =IF($P$16="","",SUMIFS(Mastersheet!$I$2:$I$400,Mastersheet!$A$2:$A$400,$P$16)/1000) | I16: =IF($P$16="","",SUMIFS(Mastersheet!$J$2:$J$400,Mastersheet!$A$2:$A$400,$P$16)/1000) | J16: =IF($P$16="","",SUMIFS(Mastersheet!$K$2:$K$400,Mastersheet!$A$2:$A$400,$P$16)/1000) | K16: =IF($P$16="","",SUMIFS(Mastersheet!$L$2:$L$400,Mastersheet!$A$2:$A$400,$P$16)/1000) | L16: =IF($P$16="","",SUMIFS(Mastersheet!$M$2:$M$400,Mastersheet!$A$2:$A$400,$P$16)/1000) | M16: =IF($P$16="","",SUMIFS(Mastersheet!$N$2:$N$400,Mastersheet!$A$2:$A$400,$P$16)/1000) | Q16: Account | R16: KTO
E17: =IF($P$17="","",SUMIFS(Mastersheet!$F$2:$F$400,Mastersheet!$A$2:$A$400,$P$17)/1000) | F17: =IF($P$17="","",SUMIFS(Mastersheet!$G$2:$G$400,Mastersheet!$A$2:$A$400,$P$17)/1000) | G17: =IF($P$17="","",SUMIFS(Mastersheet!$H$2:$H$400,Mastersheet!$A$2:$A$400,$P$17)/1000) | H17: =IF($P$17="","",SUMIFS(Mastersheet!$I$2:$I$400,Mastersheet!$A$2:$A$400,$P$17)/1000) | I17: =IF($P$17="","",SUMIFS(Mastersheet!$J$2:$J$400,Mastersheet!$A$2:$A$400,$P$17)/1000) | J17: =IF($P$17="","",SUMIFS(Mastersheet!$K$2:$K$400,Mastersheet!$A$2:$A$400,$P$17)/1000) | K17: =IF($P$17="","",SUMIFS(Mastersheet!$L$2:$L$400,Mastersheet!$A$2:$A$400,$P$17)/1000) | L17: =IF($P$17="","",SUMIFS(Mastersheet!$M$2:$M$400,Mastersheet!$A$2:$A$400,$P$17)/1000) | M17: =IF($P$17="","",SUMIFS(Mastersheet!$N$2:$N$400,Mastersheet!$A$2:$A$400,$P$17)/1000) | Q17: Account | R17: KTO
C18: Sachanlagen | D18: Tangible assets | E18: =SUMIFS(Mastersheet!$F$2:$F$400,Mastersheet!$D$2:$D$400,$P18,Mastersheet!$C$2:$C$400,$Q18)/1000 -> 0 | F18: =SUMIFS(Mastersheet!$G$2:$G$400,Mastersheet!$D$2:$D$400,$P18,Mastersheet!$C$2:$C$400,$Q18)/1000 -> 0 | G18: =SUMIFS(Mastersheet!$H$2:$H$400,Mastersheet!$D$2:$D$400,$P18,Mastersheet!$C$2:$C$400,$Q18)/1000 -> 0 | H18: =SUMIFS(Mastersheet!$I$2:$I$400,Mastersheet!$D$2:$D$400,$P18,Mastersheet!$C$2:$C$400,$Q18)/1000 -> 0 | I18: =SUMIFS(Mastersheet!$J$2:$J$400,Mastersheet!$D$2:$D$400,$P18,Mastersheet!$C$2:$C$400,$Q18)/1000 -> 0 | J18: =SUMIFS(Mastersheet!$K$2:$K$400,Mastersheet!$D$2:$D$400,$P18,Mastersheet!$C$2:$C$400,$Q18)/1000 -> 0 | K18: =SUMIFS(Mastersheet!$L$2:$L$400,Mastersheet!$D$2:$D$400,$P18,Mastersheet!$C$2:$C$400,$Q18)/1000 -> 0 | L18: =SUMIFS(Mastersheet!$M$2:$M$400,Mastersheet!$D$2:$D$400,$P18,Mastersheet!$C$2:$C$400,$Q18)/1000 -> 0 | M18: =SUMIFS(Mastersheet!$N$2:$N$400,Mastersheet!$D$2:$D$400,$P18,Mastersheet!$C$2:$C$400,$Q18)/1000 -> 0 | P18: Sachanlagen | Q18: FA | R18: POS
E19: =IF($P$19="","",SUMIFS(Mastersheet!$F$2:$F$400,Mastersheet!$A$2:$A$400,$P$19)/1000) | F19: =IF($P$19="","",SUMIFS(Mastersheet!$G$2:$G$400,Mastersheet!$A$2:$A$400,$P$19)/1000) | G19: =IF($P$19="","",SUMIFS(Mastersheet!$H$2:$H$400,Mastersheet!$A$2:$A$400,$P$19)/1000) | H19: =IF($P$19="","",SUMIFS(Mastersheet!$I$2:$I$400,Mastersheet!$A$2:$A$400,$P$19)/1000) | I19: =IF($P$19="","",SUMIFS(Mastersheet!$J$2:$J$400,Mastersheet!$A$2:$A$400,$P$19)/1000) | J19: =IF($P$19="","",SUMIFS(Mastersheet!$K$2:$K$400,Mastersheet!$A$2:$A$400,$P$19)/1000) | K19: =IF($P$19="","",SUMIFS(Mastersheet!$L$2:$L$400,Mastersheet!$A$2:$A$400,$P$19)/1000) | L19: =IF($P$19="","",SUMIFS(Mastersheet!$M$2:$M$400,Mastersheet!$A$2:$A$400,$P$19)/1000) | M19: =IF($P$19="","",SUMIFS(Mastersheet!$N$2:$N$400,Mastersheet!$A$2:$A$400,$P$19)/1000) | Q19: Account | R19: KTO
E20: =IF($P$20="","",SUMIFS(Mastersheet!$F$2:$F$400,Mastersheet!$A$2:$A$400,$P$20)/1000) | F20: =IF($P$20="","",SUMIFS(Mastersheet!$G$2:$G$400,Mastersheet!$A$2:$A$400,$P$20)/1000) | G20: =IF($P$20="","",SUMIFS(Mastersheet!$H$2:$H$400,Mastersheet!$A$2:$A$400,$P$20)/1000) | H20: =IF($P$20="","",SUMIFS(Mastersheet!$I$2:$I$400,Mastersheet!$A$2:$A$400,$P$20)/1000) | I20: =IF($P$20="","",SUMIFS(Mastersheet!$J$2:$J$400,Mastersheet!$A$2:$A$400,$P$20)/1000) | J20: =IF($P$20="","",SUMIFS(Mastersheet!$K$2:$K$400,Mastersheet!$A$2:$A$400,$P$20)/1000) | K20: =IF($P$20="","",SUMIFS(Mastersheet!$L$2:$L$400,Mastersheet!$A$2:$A$400,$P$20)/1000) | L20: =IF($P$20="","",SUMIFS(Mastersheet!$M$2:$M$400,Mastersheet!$A$2:$A$400,$P$20)/1000) | M20: =IF($P$20="","",SUMIFS(Mastersheet!$N$2:$N$400,Mastersheet!$A$2:$A$400,$P$20)/1000) | Q20: Account | R20: KTO
E21: =IF($P$21="","",SUMIFS(Mastersheet!$F$2:$F$400,Mastersheet!$A$2:$A$400,$P$21)/1000) | F21: =IF($P$21="","",SUMIFS(Mastersheet!$G$2:$G$400,Mastersheet!$A$2:$A$400,$P$21)/1000) | G21: =IF($P$21="","",SUMIFS(Mastersheet!$H$2:$H$400,Mastersheet!$A$2:$A$400,$P$21)/1000) | H21: =IF($P$21="","",SUMIFS(Mastersheet!$I$2:$I$400,Mastersheet!$A$2:$A$400,$P$21)/1000) | I21: =IF($P$21="","",SUMIFS(Mastersheet!$J$2:$J$400,Mastersheet!$A$2:$A$400,$P$21)/1000) | J21: =IF($P$21="","",SUMIFS(Mastersheet!$K$2:$K$400,Mastersheet!$A$2:$A$400,$P$21)/1000) | K21: =IF($P$21="","",SUMIFS(Mastersheet!$L$2:$L$400,Mastersheet!$A$2:$A$400,$P$21)/1000) | L21: =IF($P$21="","",SUMIFS(Mastersheet!$M$2:$M$400,Mastersheet!$A$2:$A$400,$P$21)/1000) | M21: =IF($P$21="","",SUMIFS(Mastersheet!$N$2:$N$400,Mastersheet!$A$2:$A$400,$P$21)/1000) | Q21: Account | R21: KTO
E22: =IF($P$22="","",SUMIFS(Mastersheet!$F$2:$F$400,Mastersheet!$A$2:$A$400,$P$22)/1000) | F22: =IF($P$22="","",SUMIFS(Mastersheet!$G$2:$G$400,Mastersheet!$A$2:$A$400,$P$22)/1000) | G22: =IF($P$22="","",SUMIFS(Mastersheet!$H$2:$H$400,Mastersheet!$A$2:$A$400,$P$22)/1000) | H22: =IF($P$22="","",SUMIFS(Mastersheet!$I$2:$I$400,Mastersheet!$A$2:$A$400,$P$22)/1000) | I22: =IF($P$22="","",SUMIFS(Mastersheet!$J$2:$J$400,Mastersheet!$A$2:$A$400,$P$22)/1000) | J22: =IF($P$22="","",SUMIFS(Mastersheet!$K$2:$K$400,Mastersheet!$A$2:$A$400,$P$22)/1000) | K22: =IF($P$22="","",SUMIFS(Mastersheet!$L$2:$L$400,Mastersheet!$A$2:$A$400,$P$22)/1000) | L22: =IF($P$22="","",SUMIFS(Mastersheet!$M$2:$M$400,Mastersheet!$A$2:$A$400,$P$22)/1000) | M22: =IF($P$22="","",SUMIFS(Mastersheet!$N$2:$N$400,Mastersheet!$A$2:$A$400,$P$22)/1000) | Q22: Account | R22: KTO
E23: =IF($P$23="","",SUMIFS(Mastersheet!$F$2:$F$400,Mastersheet!$A$2:$A$400,$P$23)/1000) | F23: =IF($P$23="","",SUMIFS(Mastersheet!$G$2:$G$400,Mastersheet!$A$2:$A$400,$P$23)/1000) | G23: =IF($P$23="","",SUMIFS(Mastersheet!$H$2:$H$400,Mastersheet!$A$2:$A$400,$P$23)/1000) | H23: =IF($P$23="","",SUMIFS(Mastersheet!$I$2:$I$400,Mastersheet!$A$2:$A$400,$P$23)/1000) | I23: =IF($P$23="","",SUMIFS(Mastersheet!$J$2:$J$400,Mastersheet!$A$2:$A$400,$P$23)/1000) | J23: =IF($P$23="","",SUMIFS(Mastersheet!$K$2:$K$400,Mastersheet!$A$2:$A$400,$P$23)/1000) | K23: =IF($P$23="","",SUMIFS(Mastersheet!$L$2:$L$400,Mastersheet!$A$2:$A$400,$P$23)/1000) | L23: =IF($P$23="","",SUMIFS(Mastersheet!$M$2:$M$400,Mastersheet!$A$2:$A$400,$P$23)/1000) | M23: =IF($P$23="","",SUMIFS(Mastersheet!$N$2:$N$400,Mastersheet!$A$2:$A$400,$P$23)/1000) | Q23: Account | R23: KTO
E24: =IF($P$24="","",SUMIFS(Mastersheet!$F$2:$F$400,Mastersheet!$A$2:$A$400,$P$24)/1000) | F24: =IF($P$24="","",SUMIFS(Mastersheet!$G$2:$G$400,Mastersheet!$A$2:$A$400,$P$24)/1000) | G24: =IF($P$24="","",SUMIFS(Mastersheet!$H$2:$H$400,Mastersheet!$A$2:$A$400,$P$24)/1000) | H24: =IF($P$24="","",SUMIFS(Mastersheet!$I$2:$I$400,Mastersheet!$A$2:$A$400,$P$24)/1000) | I24: =IF($P$24="","",SUMIFS(Mastersheet!$J$2:$J$400,Mastersheet!$A$2:$A$400,$P$24)/1000) | J24: =IF($P$24="","",SUMIFS(Mastersheet!$K$2:$K$400,Mastersheet!$A$2:$A$400,$P$24)/1000) | K24: =IF($P$24="","",SUMIFS(Mastersheet!$L$2:$L$400,Mastersheet!$A$2:$A$400,$P$24)/1000) | L24: =IF($P$24="","",SUMIFS(Mastersheet!$M$2:$M$400,Mastersheet!$A$2:$A$400,$P$24)/1000) | M24: =IF($P$24="","",SUMIFS(Mastersheet!$N$2:$N$400,Mastersheet!$A$2:$A$400,$P$24)/1000) | Q24: Account | R24: KTO
E25: =IF($P$25="","",SUMIFS(Mastersheet!$F$2:$F$400,Mastersheet!$A$2:$A$400,$P$25)/1000) | F25: =IF($P$25="","",SUMIFS(Mastersheet!$G$2:$G$400,Mastersheet!$A$2:$A$400,$P$25)/1000) | G25: =IF($P$25="","",SUMIFS(Mastersheet!$H$2:$H$400,Mastersheet!$A$2:$A$400,$P$25)/1000) | H25: =IF($P$25="","",SUMIFS(Mastersheet!$I$2:$I$400,Mastersheet!$A$2:$A$400,$P$25)/1000) | I25: =IF($P$25="","",SUMIFS(Mastersheet!$J$2:$J$400,Mastersheet!$A$2:$A$400,$P$25)/1000) | J25: =IF($P$25="","",SUMIFS(Mastersheet!$K$2:$K$400,Mastersheet!$A$2:$A$400,$P$25)/1000) | K25: =IF($P$25="","",SUMIFS(Mastersheet!$L$2:$L$400,Mastersheet!$A$2:$A$400,$P$25)/1000) | L25: =IF($P$25="","",SUMIFS(Mastersheet!$M$2:$M$400,Mastersheet!$A$2:$A$400,$P$25)/1000) | M25: =IF($P$25="","",SUMIFS(Mastersheet!$N$2:$N$400,Mastersheet!$A$2:$A$400,$P$25)/1000) | Q25: Account | R25: KTO
E26: =IF($P$26="","",SUMIFS(Mastersheet!$F$2:$F$400,Mastersheet!$A$2:$A$400,$P$26)/1000) | F26: =IF($P$26="","",SUMIFS(Mastersheet!$G$2:$G$400,Mastersheet!$A$2:$A$400,$P$26)/1000) | G26: =IF($P$26="","",SUMIFS(Mastersheet!$H$2:$H$400,Mastersheet!$A$2:$A$400,$P$26)/1000) | H26: =IF($P$26="","",SUMIFS(Mastersheet!$I$2:$I$400,Mastersheet!$A$2:$A$400,$P$26)/1000) | I26: =IF($P$26="","",SUMIFS(Mastersheet!$J$2:$J$400,Mastersheet!$A$2:$A$400,$P$26)/1000) | J26: =IF($P$26="","",SUMIFS(Mastersheet!$K$2:$K$400,Mastersheet!$A$2:$A$400,$P$26)/1000) | K26: =IF($P$26="","",SUMIFS(Mastersheet!$L$2:$L$400,Mastersheet!$A$2:$A$400,$P$26)/1000) | L26: =IF($P$26="","",SUMIFS(Mastersheet!$M$2:$M$400,Mastersheet!$A$2:$A$400,$P$26)/1000) | M26: =IF($P$26="","",SUMIFS(Mastersheet!$N$2:$N$400,Mastersheet!$A$2:$A$400,$P$26)/1000) | Q26: Account | R26: KTO
C27: Finanzanlagen | D27: Financial assets | E27: =SUMIFS(Mastersheet!$F$2:$F$400,Mastersheet!$D$2:$D$400,$P27,Mastersheet!$C$2:$C$400,$Q27)/1000 -> 0 | F27: =SUMIFS(Mastersheet!$G$2:$G$400,Mastersheet!$D$2:$D$400,$P27,Mastersheet!$C$2:$C$400,$Q27)/1000 -> 0 | G27: =SUMIFS(Mastersheet!$H$2:$H$400,Mastersheet!$D$2:$D$400,$P27,Mastersheet!$C$2:$C$400,$Q27)/1000 -> 0 | H27: =SUMIFS(Mastersheet!$I$2:$I$400,Mastersheet!$D$2:$D$400,$P27,Mastersheet!$C$2:$C$400,$Q27)/1000 -> 0 | I27: =SUMIFS(Mastersheet!$J$2:$J$400,Mastersheet!$D$2:$D$400,$P27,Mastersheet!$C$2:$C$400,$Q27)/1000 -> 0 | J27: =SUMIFS(Mastersheet!$K$2:$K$400,Mastersheet!$D$2:$D$400,$P27,Mastersheet!$C$2:$C$400,$Q27)/1000 -> 0 | K27: =SUMIFS(Mastersheet!$L$2:$L$400,Mastersheet!$D$2:$D$400,$P27,Mastersheet!$C$2:$C$400,$Q27)/1000 -> 0 | L27: =SUMIFS(Mastersheet!$M$2:$M$400,Mastersheet!$D$2:$D$400,$P27,Mastersheet!$C$2:$C$400,$Q27)/1000 -> 0 | M27: =SUMIFS(Mastersheet!$N$2:$N$400,Mastersheet!$D$2:$D$400,$P27,Mastersheet!$C$2:$C$400,$Q27)/1000 -> 0 | P27: Finanzanlagen | Q27: FA | R27: POS
E28: =IF($P$28="","",SUMIFS(Mastersheet!$F$2:$F$400,Mastersheet!$A$2:$A$400,$P$28)/1000) | F28: =IF($P$28="","",SUMIFS(Mastersheet!$G$2:$G$400,Mastersheet!$A$2:$A$400,$P$28)/1000) | G28: =IF($P$28="","",SUMIFS(Mastersheet!$H$2:$H$400,Mastersheet!$A$2:$A$400,$P$28)/1000) | H28: =IF($P$28="","",SUMIFS(Mastersheet!$I$2:$I$400,Mastersheet!$A$2:$A$400,$P$28)/1000) | I28: =IF($P$28="","",SUMIFS(Mastersheet!$J$2:$J$400,Mastersheet!$A$2:$A$400,$P$28)/1000) | J28: =IF($P$28="","",SUMIFS(Mastersheet!$K$2:$K$400,Mastersheet!$A$2:$A$400,$P$28)/1000) | K28: =IF($P$28="","",SUMIFS(Mastersheet!$L$2:$L$400,Mastersheet!$A$2:$A$400,$P$28)/1000) | L28: =IF($P$28="","",SUMIFS(Mastersheet!$M$2:$M$400,Mastersheet!$A$2:$A$400,$P$28)/1000) | M28: =IF($P$28="","",SUMIFS(Mastersheet!$N$2:$N$400,Mastersheet!$A$2:$A$400,$P$28)/1000) | Q28: Account | R28: KTO
E29: =IF($P$29="","",SUMIFS(Mastersheet!$F$2:$F$400,Mastersheet!$A$2:$A$400,$P$29)/1000) | F29: =IF($P$29="","",SUMIFS(Mastersheet!$G$2:$G$400,Mastersheet!$A$2:$A$400,$P$29)/1000) | G29: =IF($P$29="","",SUMIFS(Mastersheet!$H$2:$H$400,Mastersheet!$A$2:$A$400,$P$29)/1000) | H29: =IF($P$29="","",SUMIFS(Mastersheet!$I$2:$I$400,Mastersheet!$A$2:$A$400,$P$29)/1000) | I29: =IF($P$29="","",SUMIFS(Mastersheet!$J$2:$J$400,Mastersheet!$A$2:$A$400,$P$29)/1000) | J29: =IF($P$29="","",SUMIFS(Mastersheet!$K$2:$K$400,Mastersheet!$A$2:$A$400,$P$29)/1000) | K29: =IF($P$29="","",SUMIFS(Mastersheet!$L$2:$L$400,Mastersheet!$A$2:$A$400,$P$29)/1000) | L29: =IF($P$29="","",SUMIFS(Mastersheet!$M$2:$M$400,Mastersheet!$A$2:$A$400,$P$29)/1000) | M29: =IF($P$29="","",SUMIFS(Mastersheet!$N$2:$N$400,Mastersheet!$A$2:$A$400,$P$29)/1000) | Q29: Account | R29: KTO
E30: =IF($P$30="","",SUMIFS(Mastersheet!$F$2:$F$400,Mastersheet!$A$2:$A$400,$P$30)/1000) | F30: =IF($P$30="","",SUMIFS(Mastersheet!$G$2:$G$400,Mastersheet!$A$2:$A$400,$P$30)/1000) | G30: =IF($P$30="","",SUMIFS(Mastersheet!$H$2:$H$400,Mastersheet!$A$2:$A$400,$P$30)/1000) | H30: =IF($P$30="","",SUMIFS(Mastersheet!$I$2:$I$400,Mastersheet!$A$2:$A$400,$P$30)/1000) | I30: =IF($P$30="","",SUMIFS(Mastersheet!$J$2:$J$400,Mastersheet!$A$2:$A$400,$P$30)/1000) | J30: =IF($P$30="","",SUMIFS(Mastersheet!$K$2:$K$400,Mastersheet!$A$2:$A$400,$P$30)/1000) | K30: =IF($P$30="","",SUMIFS(Mastersheet!$L$2:$L$400,Mastersheet!$A$2:$A$400,$P$30)/1000) | L30: =IF($P$30="","",SUMIFS(Mastersheet!$M$2:$M$400,Mastersheet!$A$2:$A$400,$P$30)/1000) | M30: =IF($P$30="","",SUMIFS(Mastersheet!$N$2:$N$400,Mastersheet!$A$2:$A$400,$P$30)/1000) | Q30: Account | R30: KTO
E31: =IF($P$31="","",SUMIFS(Mastersheet!$F$2:$F$400,Mastersheet!$A$2:$A$400,$P$31)/1000) | F31: =IF($P$31="","",SUMIFS(Mastersheet!$G$2:$G$400,Mastersheet!$A$2:$A$400,$P$31)/1000) | G31: =IF($P$31="","",SUMIFS(Mastersheet!$H$2:$H$400,Mastersheet!$A$2:$A$400,$P$31)/1000) | H31: =IF($P$31="","",SUMIFS(Mastersheet!$I$2:$I$400,Mastersheet!$A$2:$A$400,$P$31)/1000) | I31: =IF($P$31="","",SUMIFS(Mastersheet!$J$2:$J$400,Mastersheet!$A$2:$A$400,$P$31)/1000) | J31: =IF($P$31="","",SUMIFS(Mastersheet!$K$2:$K$400,Mastersheet!$A$2:$A$400,$P$31)/1000) | K31: =IF($P$31="","",SUMIFS(Mastersheet!$L$2:$L$400,Mastersheet!$A$2:$A$400,$P$31)/1000) | L31: =IF($P$31="","",SUMIFS(Mastersheet!$M$2:$M$400,Mastersheet!$A$2:$A$400,$P$31)/1000) | M31: =IF($P$31="","",SUMIFS(Mastersheet!$N$2:$N$400,Mastersheet!$A$2:$A$400,$P$31)/1000) | Q31: Account | R31: KTO
E32: =IF($P$32="","",SUMIFS(Mastersheet!$F$2:$F$400,Mastersheet!$A$2:$A$400,$P$32)/1000) | F32: =IF($P$32="","",SUMIFS(Mastersheet!$G$2:$G$400,Mastersheet!$A$2:$A$400,$P$32)/1000) | G32: =IF($P$32="","",SUMIFS(Mastersheet!$H$2:$H$400,Mastersheet!$A$2:$A$400,$P$32)/1000) | H32: =IF($P$32="","",SUMIFS(Mastersheet!$I$2:$I$400,Mastersheet!$A$2:$A$400,$P$32)/1000) | I32: =IF($P$32="","",SUMIFS(Mastersheet!$J$2:$J$400,Mastersheet!$A$2:$A$400,$P$32)/1000) | J32: =IF($P$32="","",SUMIFS(Mastersheet!$K$2:$K$400,Mastersheet!$A$2:$A$400,$P$32)/1000) | K32: =IF($P$32="","",SUMIFS(Mastersheet!$L$2:$L$400,Mastersheet!$A$2:$A$400,$P$32)/1000) | L32: =IF($P$32="","",SUMIFS(Mastersheet!$M$2:$M$400,Mastersheet!$A$2:$A$400,$P$32)/1000) | M32: =IF($P$32="","",SUMIFS(Mastersheet!$N$2:$N$400,Mastersheet!$A$2:$A$400,$P$32)/1000) | Q32: Account | R32: KTO
E33: =IF($P$33="","",SUMIFS(Mastersheet!$F$2:$F$400,Mastersheet!$A$2:$A$400,$P$33)/1000) | F33: =IF($P$33="","",SUMIFS(Mastersheet!$G$2:$G$400,Mastersheet!$A$2:$A$400,$P$33)/1000) | G33: =IF($P$33="","",SUMIFS(Mastersheet!$H$2:$H$400,Mastersheet!$A$2:$A$400,$P$33)/1000) | H33: =IF($P$33="","",SUMIFS(Mastersheet!$I$2:$I$400,Mastersheet!$A$2:$A$400,$P$33)/1000) | I33: =IF($P$33="","",SUMIFS(Mastersheet!$J$2:$J$400,Mastersheet!$A$2:$A$400,$P$33)/1000) | J33: =IF($P$33="","",SUMIFS(Mastersheet!$K$2:$K$400,Mastersheet!$A$2:$A$400,$P$33)/1000) | K33: =IF($P$33="","",SUMIFS(Mastersheet!$L$2:$L$400,Mastersheet!$A$2:$A$400,$P$33)/1000) | L33: =IF($P$33="","",SUMIFS(Mastersheet!$M$2:$M$400,Mastersheet!$A$2:$A$400,$P$33)/1000) | M33: =IF($P$33="","",SUMIFS(Mastersheet!$N$2:$N$400,Mastersheet!$A$2:$A$400,$P$33)/1000) | Q33: Account | R33: KTO
E34: =IF($P$34="","",SUMIFS(Mastersheet!$F$2:$F$400,Mastersheet!$A$2:$A$400,$P$34)/1000) | F34: =IF($P$34="","",SUMIFS(Mastersheet!$G$2:$G$400,Mastersheet!$A$2:$A$400,$P$34)/1000) | G34: =IF($P$34="","",SUMIFS(Mastersheet!$H$2:$H$400,Mastersheet!$A$2:$A$400,$P$34)/1000) | H34: =IF($P$34="","",SUMIFS(Mastersheet!$I$2:$I$400,Mastersheet!$A$2:$A$400,$P$34)/1000) | I34: =IF($P$34="","",SUMIFS(Mastersheet!$J$2:$J$400,Mastersheet!$A$2:$A$400,$P$34)/1000) | J34: =IF($P$34="","",SUMIFS(Mastersheet!$K$2:$K$400,Mastersheet!$A$2:$A$400,$P$34)/1000) | K34: =IF($P$34="","",SUMIFS(Mastersheet!$L$2:$L$400,Mastersheet!$A$2:$A$400,$P$34)/1000) | L34: =IF($P$34="","",SUMIFS(Mastersheet!$M$2:$M$400,Mastersheet!$A$2:$A$400,$P$34)/1000) | M34: =IF($P$34="","",SUMIFS(Mastersheet!$N$2:$N$400,Mastersheet!$A$2:$A$400,$P$34)/1000) | Q34: Account | R34: KTO
E35: =IF($P$35="","",SUMIFS(Mastersheet!$F$2:$F$400,Mastersheet!$A$2:$A$400,$P$35)/1000) | F35: =IF($P$35="","",SUMIFS(Mastersheet!$G$2:$G$400,Mastersheet!$A$2:$A$400,$P$35)/1000) | G35: =IF($P$35="","",SUMIFS(Mastersheet!$H$2:$H$400,Mastersheet!$A$2:$A$400,$P$35)/1000) | H35: =IF($P$35="","",SUMIFS(Mastersheet!$I$2:$I$400,Mastersheet!$A$2:$A$400,$P$35)/1000) | I35: =IF($P$35="","",SUMIFS(Mastersheet!$J$2:$J$400,Mastersheet!$A$2:$A$400,$P$35)/1000) | J35: =IF($P$35="","",SUMIFS(Mastersheet!$K$2:$K$400,Mastersheet!$A$2:$A$400,$P$35)/1000) | K35: =IF($P$35="","",SUMIFS(Mastersheet!$L$2:$L$400,Mastersheet!$A$2:$A$400,$P$35)/1000) | L35: =IF($P$35="","",SUMIFS(Mastersheet!$M$2:$M$400,Mastersheet!$A$2:$A$400,$P$35)/1000) | M35: =IF($P$35="","",SUMIFS(Mastersheet!$N$2:$N$400,Mastersheet!$A$2:$A$400,$P$35)/1000) | Q35: Account | R35: KTO
C36: Dummy 1 | D36: Dummy 1
C37: Dummy 2 | D37: Dummy 2
C38: Dummy 3 | D38: Dummy 3
C39: Anlagevermögen | D39: Fixed assets | E39: =SUMIF($R$9:$R$38,"<>KTO",E9:E38) -> 0 | F39: =SUMIF($R$9:$R$38,"<>KTO",F9:F38) -> 0 | G39: =SUMIF($R$9:$R$38,"<>KTO",G9:G38) -> 0 | H39: =SUMIF($R$9:$R$38,"<>KTO",H9:H38) -> 0 | I39: =SUMIF($R$9:$R$38,"<>KTO",I9:I38) -> 0 | J39: =SUMIF($R$9:$R$38,"<>KTO",J9:J38) -> 0 | K39: =SUMIF($R$9:$R$38,"<>KTO",K9:K38) -> 0 | L39: =SUMIF($R$9:$R$38,"<>KTO",L9:L38) -> 0 | M39: =SUMIF($R$9:$R$38,"<>KTO",M9:M38) -> 0
C40: Vorräte | D40: Inventories | E40: =SUMIFS(Mastersheet!$F$2:$F$400,Mastersheet!$D$2:$D$400,$P40,Mastersheet!$C$2:$C$400,$Q40)/1000 -> 0 | F40: =SUMIFS(Mastersheet!$G$2:$G$400,Mastersheet!$D$2:$D$400,$P40,Mastersheet!$C$2:$C$400,$Q40)/1000 -> 0 | G40: =SUMIFS(Mastersheet!$H$2:$H$400,Mastersheet!$D$2:$D$400,$P40,Mastersheet!$C$2:$C$400,$Q40)/1000 -> 0 | H40: =SUMIFS(Mastersheet!$I$2:$I$400,Mastersheet!$D$2:$D$400,$P40,Mastersheet!$C$2:$C$400,$Q40)/1000 -> 0 | I40: =SUMIFS(Mastersheet!$J$2:$J$400,Mastersheet!$D$2:$D$400,$P40,Mastersheet!$C$2:$C$400,$Q40)/1000 -> 0 | J40: =SUMIFS(Mastersheet!$K$2:$K$400,Mastersheet!$D$2:$D$400,$P40,Mastersheet!$C$2:$C$400,$Q40)/1000 -> 0 | K40: =SUMIFS(Mastersheet!$L$2:$L$400,Mastersheet!$D$2:$D$400,$P40,Mastersheet!$C$2:$C$400,$Q40)/1000 -> 0 | L40: =SUMIFS(Mastersheet!$M$2:$M$400,Mastersheet!$D$2:$D$400,$P40,Mastersheet!$C$2:$C$400,$Q40)/1000 -> 0 | M40: =SUMIFS(Mastersheet!$N$2:$N$400,Mastersheet!$D$2:$D$400,$P40,Mastersheet!$C$2:$C$400,$Q40)/1000 -> 0 | P40: Vorraete | Q40: TWC | R40: POS
E41: =IF($P$41="","",SUMIFS(Mastersheet!$F$2:$F$400,Mastersheet!$A$2:$A$400,$P$41)/1000) | F41: =IF($P$41="","",SUMIFS(Mastersheet!$G$2:$G$400,Mastersheet!$A$2:$A$400,$P$41)/1000) | G41: =IF($P$41="","",SUMIFS(Mastersheet!$H$2:$H$400,Mastersheet!$A$2:$A$400,$P$41)/1000) | H41: =IF($P$41="","",SUMIFS(Mastersheet!$I$2:$I$400,Mastersheet!$A$2:$A$400,$P$41)/1000) | I41: =IF($P$41="","",SUMIFS(Mastersheet!$J$2:$J$400,Mastersheet!$A$2:$A$400,$P$41)/1000) | J41: =IF($P$41="","",SUMIFS(Mastersheet!$K$2:$K$400,Mastersheet!$A$2:$A$400,$P$41)/1000) | K41: =IF($P$41="","",SUMIFS(Mastersheet!$L$2:$L$400,Mastersheet!$A$2:$A$400,$P$41)/1000) | L41: =IF($P$41="","",SUMIFS(Mastersheet!$M$2:$M$400,Mastersheet!$A$2:$A$400,$P$41)/1000) | M41: =IF($P$41="","",SUMIFS(Mastersheet!$N$2:$N$400,Mastersheet!$A$2:$A$400,$P$41)/1000) | Q41: Account | R41: KTO
E42: =IF($P$42="","",SUMIFS(Mastersheet!$F$2:$F$400,Mastersheet!$A$2:$A$400,$P$42)/1000) | F42: =IF($P$42="","",SUMIFS(Mastersheet!$G$2:$G$400,Mastersheet!$A$2:$A$400,$P$42)/1000) | G42: =IF($P$42="","",SUMIFS(Mastersheet!$H$2:$H$400,Mastersheet!$A$2:$A$400,$P$42)/1000) | H42: =IF($P$42="","",SUMIFS(Mastersheet!$I$2:$I$400,Mastersheet!$A$2:$A$400,$P$42)/1000) | I42: =IF($P$42="","",SUMIFS(Mastersheet!$J$2:$J$400,Mastersheet!$A$2:$A$400,$P$42)/1000) | J42: =IF($P$42="","",SUMIFS(Mastersheet!$K$2:$K$400,Mastersheet!$A$2:$A$400,$P$42)/1000) | K42: =IF($P$42="","",SUMIFS(Mastersheet!$L$2:$L$400,Mastersheet!$A$2:$A$400,$P$42)/1000) | L42: =IF($P$42="","",SUMIFS(Mastersheet!$M$2:$M$400,Mastersheet!$A$2:$A$400,$P$42)/1000) | M42: =IF($P$42="","",SUMIFS(Mastersheet!$N$2:$N$400,Mastersheet!$A$2:$A$400,$P$42)/1000) | Q42: Account | R42: KTO
E43: =IF($P$43="","",SUMIFS(Mastersheet!$F$2:$F$400,Mastersheet!$A$2:$A$400,$P$43)/1000) | F43: =IF($P$43="","",SUMIFS(Mastersheet!$G$2:$G$400,Mastersheet!$A$2:$A$400,$P$43)/1000) | G43: =IF($P$43="","",SUMIFS(Mastersheet!$H$2:$H$400,Mastersheet!$A$2:$A$400,$P$43)/1000) | H43: =IF($P$43="","",SUMIFS(Mastersheet!$I$2:$I$400,Mastersheet!$A$2:$A$400,$P$43)/1000) | I43: =IF($P$43="","",SUMIFS(Mastersheet!$J$2:$J$400,Mastersheet!$A$2:$A$400,$P$43)/1000) | J43: =IF($P$43="","",SUMIFS(Mastersheet!$K$2:$K$400,Mastersheet!$A$2:$A$400,$P$43)/1000) | K43: =IF($P$43="","",SUMIFS(Mastersheet!$L$2:$L$400,Mastersheet!$A$2:$A$400,$P$43)/1000) | L43: =IF($P$43="","",SUMIFS(Mastersheet!$M$2:$M$400,Mastersheet!$A$2:$A$400,$P$43)/1000) | M43: =IF($P$43="","",SUMIFS(Mastersheet!$N$2:$N$400,Mastersheet!$A$2:$A$400,$P$43)/1000) | Q43: Account | R43: KTO
E44: =IF($P$44="","",SUMIFS(Mastersheet!$F$2:$F$400,Mastersheet!$A$2:$A$400,$P$44)/1000) | F44: =IF($P$44="","",SUMIFS(Mastersheet!$G$2:$G$400,Mastersheet!$A$2:$A$400,$P$44)/1000) | G44: =IF($P$44="","",SUMIFS(Mastersheet!$H$2:$H$400,Mastersheet!$A$2:$A$400,$P$44)/1000) | H44: =IF($P$44="","",SUMIFS(Mastersheet!$I$2:$I$400,Mastersheet!$A$2:$A$400,$P$44)/1000) | I44: =IF($P$44="","",SUMIFS(Mastersheet!$J$2:$J$400,Mastersheet!$A$2:$A$400,$P$44)/1000) | J44: =IF($P$44="","",SUMIFS(Mastersheet!$K$2:$K$400,Mastersheet!$A$2:$A$400,$P$44)/1000) | K44: =IF($P$44="","",SUMIFS(Mastersheet!$L$2:$L$400,Mastersheet!$A$2:$A$400,$P$44)/1000) | L44: =IF($P$44="","",SUMIFS(Mastersheet!$M$2:$M$400,Mastersheet!$A$2:$A$400,$P$44)/1000) | M44: =IF($P$44="","",SUMIFS(Mastersheet!$N$2:$N$400,Mastersheet!$A$2:$A$400,$P$44)/1000) | Q44: Account | R44: KTO
E45: =IF($P$45="","",SUMIFS(Mastersheet!$F$2:$F$400,Mastersheet!$A$2:$A$400,$P$45)/1000) | F45: =IF($P$45="","",SUMIFS(Mastersheet!$G$2:$G$400,Mastersheet!$A$2:$A$400,$P$45)/1000) | G45: =IF($P$45="","",SUMIFS(Mastersheet!$H$2:$H$400,Mastersheet!$A$2:$A$400,$P$45)/1000) | H45: =IF($P$45="","",SUMIFS(Mastersheet!$I$2:$I$400,Mastersheet!$A$2:$A$400,$P$45)/1000) | I45: =IF($P$45="","",SUMIFS(Mastersheet!$J$2:$J$400,Mastersheet!$A$2:$A$400,$P$45)/1000) | J45: =IF($P$45="","",SUMIFS(Mastersheet!$K$2:$K$400,Mastersheet!$A$2:$A$400,$P$45)/1000) | K45: =IF($P$45="","",SUMIFS(Mastersheet!$L$2:$L$400,Mastersheet!$A$2:$A$400,$P$45)/1000) | L45: =IF($P$45="","",SUMIFS(Mastersheet!$M$2:$M$400,Mastersheet!$A$2:$A$400,$P$45)/1000) | M45: =IF($P$45="","",SUMIFS(Mastersheet!$N$2:$N$400,Mastersheet!$A$2:$A$400,$P$45)/1000) | Q45: Account | R45: KTO
E46: =IF($P$46="","",SUMIFS(Mastersheet!$F$2:$F$400,Mastersheet!$A$2:$A$400,$P$46)/1000) | F46: =IF($P$46="","",SUMIFS(Mastersheet!$G$2:$G$400,Mastersheet!$A$2:$A$400,$P$46)/1000) | G46: =IF($P$46="","",SUMIFS(Mastersheet!$H$2:$H$400,Mastersheet!$A$2:$A$400,$P$46)/1000) | H46: =IF($P$46="","",SUMIFS(Mastersheet!$I$2:$I$400,Mastersheet!$A$2:$A$400,$P$46)/1000) | I46: =IF($P$46="","",SUMIFS(Mastersheet!$J$2:$J$400,Mastersheet!$A$2:$A$400,$P$46)/1000) | J46: =IF($P$46="","",SUMIFS(Mastersheet!$K$2:$K$400,Mastersheet!$A$2:$A$400,$P$46)/1000) | K46: =IF($P$46="","",SUMIFS(Mastersheet!$L$2:$L$400,Mastersheet!$A$2:$A$400,$P$46)/1000) | L46: =IF($P$46="","",SUMIFS(Mastersheet!$M$2:$M$400,Mastersheet!$A$2:$A$400,$P$46)/1000) | M46: =IF($P$46="","",SUMIFS(Mastersheet!$N$2:$N$400,Mastersheet!$A$2:$A$400,$P$46)/1000) | Q46: Account | R46: KTO
E47: =IF($P$47="","",SUMIFS(Mastersheet!$F$2:$F$400,Mastersheet!$A$2:$A$400,$P$47)/1000) | F47: =IF($P$47="","",SUMIFS(Mastersheet!$G$2:$G$400,Mastersheet!$A$2:$A$400,$P$47)/1000) | G47: =IF($P$47="","",SUMIFS(Mastersheet!$H$2:$H$400,Mastersheet!$A$2:$A$400,$P$47)/1000) | H47: =IF($P$47="","",SUMIFS(Mastersheet!$I$2:$I$400,Mastersheet!$A$2:$A$400,$P$47)/1000) | I47: =IF($P$47="","",SUMIFS(Mastersheet!$J$2:$J$400,Mastersheet!$A$2:$A$400,$P$47)/1000) | J47: =IF($P$47="","",SUMIFS(Mastersheet!$K$2:$K$400,Mastersheet!$A$2:$A$400,$P$47)/1000) | K47: =IF($P$47="","",SUMIFS(Mastersheet!$L$2:$L$400,Mastersheet!$A$2:$A$400,$P$47)/1000) | L47: =IF($P$47="","",SUMIFS(Mastersheet!$M$2:$M$400,Mastersheet!$A$2:$A$400,$P$47)/1000) | M47: =IF($P$47="","",SUMIFS(Mastersheet!$N$2:$N$400,Mastersheet!$A$2:$A$400,$P$47)/1000) | Q47: Account | R47: KTO
E48: =IF($P$48="","",SUMIFS(Mastersheet!$F$2:$F$400,Mastersheet!$A$2:$A$400,$P$48)/1000) | F48: =IF($P$48="","",SUMIFS(Mastersheet!$G$2:$G$400,Mastersheet!$A$2:$A$400,$P$48)/1000) | G48: =IF($P$48="","",SUMIFS(Mastersheet!$H$2:$H$400,Mastersheet!$A$2:$A$400,$P$48)/1000) | H48: =IF($P$48="","",SUMIFS(Mastersheet!$I$2:$I$400,Mastersheet!$A$2:$A$400,$P$48)/1000) | I48: =IF($P$48="","",SUMIFS(Mastersheet!$J$2:$J$400,Mastersheet!$A$2:$A$400,$P$48)/1000) | J48: =IF($P$48="","",SUMIFS(Mastersheet!$K$2:$K$400,Mastersheet!$A$2:$A$400,$P$48)/1000) | K48: =IF($P$48="","",SUMIFS(Mastersheet!$L$2:$L$400,Mastersheet!$A$2:$A$400,$P$48)/1000) | L48: =IF($P$48="","",SUMIFS(Mastersheet!$M$2:$M$400,Mastersheet!$A$2:$A$400,$P$48)/1000) | M48: =IF($P$48="","",SUMIFS(Mastersheet!$N$2:$N$400,Mastersheet!$A$2:$A$400,$P$48)/1000) | Q48: Account | R48: KTO
C49: Forderungen aus LuL | D49: Trade receivables | E49: =SUMIFS(Mastersheet!$F$2:$F$400,Mastersheet!$D$2:$D$400,$P49,Mastersheet!$C$2:$C$400,$Q49)/1000 -> 0 | F49: =SUMIFS(Mastersheet!$G$2:$G$400,Mastersheet!$D$2:$D$400,$P49,Mastersheet!$C$2:$C$400,$Q49)/1000 -> 0 | G49: =SUMIFS(Mastersheet!$H$2:$H$400,Mastersheet!$D$2:$D$400,$P49,Mastersheet!$C$2:$C$400,$Q49)/1000 -> 0 | H49: =SUMIFS(Mastersheet!$I$2:$I$400,Mastersheet!$D$2:$D$400,$P49,Mastersheet!$C$2:$C$400,$Q49)/1000 -> 0 | I49: =SUMIFS(Mastersheet!$J$2:$J$400,Mastersheet!$D$2:$D$400,$P49,Mastersheet!$C$2:$C$400,$Q49)/1000 -> 0 | J49: =SUMIFS(Mastersheet!$K$2:$K$400,Mastersheet!$D$2:$D$400,$P49,Mastersheet!$C$2:$C$400,$Q49)/1000 -> 0 | K49: =SUMIFS(Mastersheet!$L$2:$L$400,Mastersheet!$D$2:$D$400,$P49,Mastersheet!$C$2:$C$400,$Q49)/1000 -> 0 | L49: =SUMIFS(Mastersheet!$M$2:$M$400,Mastersheet!$D$2:$D$400,$P49,Mastersheet!$C$2:$C$400,$Q49)/1000 -> 0 | M49: =SUMIFS(Mastersheet!$N$2:$N$400,Mastersheet!$D$2:$D$400,$P49,Mastersheet!$C$2:$C$400,$Q49)/1000 -> 0 | P49: Forderungen aus L+L | Q49: TWC | R49: POS
E50: =IF($P$50="","",SUMIFS(Mastersheet!$F$2:$F$400,Mastersheet!$A$2:$A$400,$P$50)/1000) | F50: =IF($P$50="","",SUMIFS(Mastersheet!$G$2:$G$400,Mastersheet!$A$2:$A$400,$P$50)/1000) | G50: =IF($P$50="","",SUMIFS(Mastersheet!$H$2:$H$400,Mastersheet!$A$2:$A$400,$P$50)/1000) | H50: =IF($P$50="","",SUMIFS(Mastersheet!$I$2:$I$400,Mastersheet!$A$2:$A$400,$P$50)/1000) | I50: =IF($P$50="","",SUMIFS(Mastersheet!$J$2:$J$400,Mastersheet!$A$2:$A$400,$P$50)/1000) | J50: =IF($P$50="","",SUMIFS(Mastersheet!$K$2:$K$400,Mastersheet!$A$2:$A$400,$P$50)/1000) | K50: =IF($P$50="","",SUMIFS(Mastersheet!$L$2:$L$400,Mastersheet!$A$2:$A$400,$P$50)/1000) | L50: =IF($P$50="","",SUMIFS(Mastersheet!$M$2:$M$400,Mastersheet!$A$2:$A$400,$P$50)/1000) | M50: =IF($P$50="","",SUMIFS(Mastersheet!$N$2:$N$400,Mastersheet!$A$2:$A$400,$P$50)/1000) | Q50: Account | R50: KTO
E51: =IF($P$51="","",SUMIFS(Mastersheet!$F$2:$F$400,Mastersheet!$A$2:$A$400,$P$51)/1000) | F51: =IF($P$51="","",SUMIFS(Mastersheet!$G$2:$G$400,Mastersheet!$A$2:$A$400,$P$51)/1000) | G51: =IF($P$51="","",SUMIFS(Mastersheet!$H$2:$H$400,Mastersheet!$A$2:$A$400,$P$51)/1000) | H51: =IF($P$51="","",SUMIFS(Mastersheet!$I$2:$I$400,Mastersheet!$A$2:$A$400,$P$51)/1000) | I51: =IF($P$51="","",SUMIFS(Mastersheet!$J$2:$J$400,Mastersheet!$A$2:$A$400,$P$51)/1000) | J51: =IF($P$51="","",SUMIFS(Mastersheet!$K$2:$K$400,Mastersheet!$A$2:$A$400,$P$51)/1000) | K51: =IF($P$51="","",SUMIFS(Mastersheet!$L$2:$L$400,Mastersheet!$A$2:$A$400,$P$51)/1000) | L51: =IF($P$51="","",SUMIFS(Mastersheet!$M$2:$M$400,Mastersheet!$A$2:$A$400,$P$51)/1000) | M51: =IF($P$51="","",SUMIFS(Mastersheet!$N$2:$N$400,Mastersheet!$A$2:$A$400,$P$51)/1000) | Q51: Account | R51: KTO
E52: =IF($P$52="","",SUMIFS(Mastersheet!$F$2:$F$400,Mastersheet!$A$2:$A$400,$P$52)/1000) | F52: =IF($P$52="","",SUMIFS(Mastersheet!$G$2:$G$400,Mastersheet!$A$2:$A$400,$P$52)/1000) | G52: =IF($P$52="","",SUMIFS(Mastersheet!$H$2:$H$400,Mastersheet!$A$2:$A$400,$P$52)/1000) | H52: =IF($P$52="","",SUMIFS(Mastersheet!$I$2:$I$400,Mastersheet!$A$2:$A$400,$P$52)/1000) | I52: =IF($P$52="","",SUMIFS(Mastersheet!$J$2:$J$400,Mastersheet!$A$2:$A$400,$P$52)/1000) | J52: =IF($P$52="","",SUMIFS(Mastersheet!$K$2:$K$400,Mastersheet!$A$2:$A$400,$P$52)/1000) | K52: =IF($P$52="","",SUMIFS(Mastersheet!$L$2:$L$400,Mastersheet!$A$2:$A$400,$P$52)/1000) | L52: =IF($P$52="","",SUMIFS(Mastersheet!$M$2:$M$400,Mastersheet!$A$2:$A$400,$P$52)/1000) | M52: =IF($P$52="","",SUMIFS(Mastersheet!$N$2:$N$400,Mastersheet!$A$2:$A$400,$P$52)/1000) | Q52: Account | R52: KTO
E53: =IF($P$53="","",SUMIFS(Mastersheet!$F$2:$F$400,Mastersheet!$A$2:$A$400,$P$53)/1000) | F53: =IF($P$53="","",SUMIFS(Mastersheet!$G$2:$G$400,Mastersheet!$A$2:$A$400,$P$53)/1000) | G53: =IF($P$53="","",SUMIFS(Mastersheet!$H$2:$H$400,Mastersheet!$A$2:$A$400,$P$53)/1000) | H53: =IF($P$53="","",SUMIFS(Mastersheet!$I$2:$I$400,Mastersheet!$A$2:$A$400,$P$53)/1000) | I53: =IF($P$53="","",SUMIFS(Mastersheet!$J$2:$J$400,Mastersheet!$A$2:$A$400,$P$53)/1000) | J53: =IF($P$53="","",SUMIFS(Mastersheet!$K$2:$K$400,Mastersheet!$A$2:$A$400,$P$53)/1000) | K53: =IF($P$53="","",SUMIFS(Mastersheet!$L$2:$L$400,Mastersheet!$A$2:$A$400,$P$53)/1000) | L53: =IF($P$53="","",SUMIFS(Mastersheet!$M$2:$M$400,Mastersheet!$A$2:$A$400,$P$53)/1000) | M53: =IF($P$53="","",SUMIFS(Mastersheet!$N$2:$N$400,Mastersheet!$A$2:$A$400,$P$53)/1000) | Q53: Account | R53: KTO
E54: =IF($P$54="","",SUMIFS(Mastersheet!$F$2:$F$400,Mastersheet!$A$2:$A$400,$P$54)/1000) | F54: =IF($P$54="","",SUMIFS(Mastersheet!$G$2:$G$400,Mastersheet!$A$2:$A$400,$P$54)/1000) | G54: =IF($P$54="","",SUMIFS(Mastersheet!$H$2:$H$400,Mastersheet!$A$2:$A$400,$P$54)/1000) | H54: =IF($P$54="","",SUMIFS(Mastersheet!$I$2:$I$400,Mastersheet!$A$2:$A$400,$P$54)/1000) | I54: =IF($P$54="","",SUMIFS(Mastersheet!$J$2:$J$400,Mastersheet!$A$2:$A$400,$P$54)/1000) | J54: =IF($P$54="","",SUMIFS(Mastersheet!$K$2:$K$400,Mastersheet!$A$2:$A$400,$P$54)/1000) | K54: =IF($P$54="","",SUMIFS(Mastersheet!$L$2:$L$400,Mastersheet!$A$2:$A$400,$P$54)/1000) | L54: =IF($P$54="","",SUMIFS(Mastersheet!$M$2:$M$400,Mastersheet!$A$2:$A$400,$P$54)/1000) | M54: =IF($P$54="","",SUMIFS(Mastersheet!$N$2:$N$400,Mastersheet!$A$2:$A$400,$P$54)/1000) | Q54: Account | R54: KTO
E55: =IF($P$55="","",SUMIFS(Mastersheet!$F$2:$F$400,Mastersheet!$A$2:$A$400,$P$55)/1000) | F55: =IF($P$55="","",SUMIFS(Mastersheet!$G$2:$G$400,Mastersheet!$A$2:$A$400,$P$55)/1000) | G55: =IF($P$55="","",SUMIFS(Mastersheet!$H$2:$H$400,Mastersheet!$A$2:$A$400,$P$55)/1000) | H55: =IF($P$55="","",SUMIFS(Mastersheet!$I$2:$I$400,Mastersheet!$A$2:$A$400,$P$55)/1000) | I55: =IF($P$55="","",SUMIFS(Mastersheet!$J$2:$J$400,Mastersheet!$A$2:$A$400,$P$55)/1000) | J55: =IF($P$55="","",SUMIFS(Mastersheet!$K$2:$K$400,Mastersheet!$A$2:$A$400,$P$55)/1000) | K55: =IF($P$55="","",SUMIFS(Mastersheet!$L$2:$L$400,Mastersheet!$A$2:$A$400,$P$55)/1000) | L55: =IF($P$55="","",SUMIFS(Mastersheet!$M$2:$M$400,Mastersheet!$A$2:$A$400,$P$55)/1000) | M55: =IF($P$55="","",SUMIFS(Mastersheet!$N$2:$N$400,Mastersheet!$A$2:$A$400,$P$55)/1000) | Q55: Account | R55: KTO
E56: =IF($P$56="","",SUMIFS(Mastersheet!$F$2:$F$400,Mastersheet!$A$2:$A$400,$P$56)/1000) | F56: =IF($P$56="","",SUMIFS(Mastersheet!$G$2:$G$400,Mastersheet!$A$2:$A$400,$P$56)/1000) | G56: =IF($P$56="","",SUMIFS(Mastersheet!$H$2:$H$400,Mastersheet!$A$2:$A$400,$P$56)/1000) | H56: =IF($P$56="","",SUMIFS(Mastersheet!$I$2:$I$400,Mastersheet!$A$2:$A$400,$P$56)/1000) | I56: =IF($P$56="","",SUMIFS(Mastersheet!$J$2:$J$400,Mastersheet!$A$2:$A$400,$P$56)/1000) | J56: =IF($P$56="","",SUMIFS(Mastersheet!$K$2:$K$400,Mastersheet!$A$2:$A$400,$P$56)/1000) | K56: =IF($P$56="","",SUMIFS(Mastersheet!$L$2:$L$400,Mastersheet!$A$2:$A$400,$P$56)/1000) | L56: =IF($P$56="","",SUMIFS(Mastersheet!$M$2:$M$400,Mastersheet!$A$2:$A$400,$P$56)/1000) | M56: =IF($P$56="","",SUMIFS(Mastersheet!$N$2:$N$400,Mastersheet!$A$2:$A$400,$P$56)/1000) | Q56: Account | R56: KTO
E57: =IF($P$57="","",SUMIFS(Mastersheet!$F$2:$F$400,Mastersheet!$A$2:$A$400,$P$57)/1000) | F57: =IF($P$57="","",SUMIFS(Mastersheet!$G$2:$G$400,Mastersheet!$A$2:$A$400,$P$57)/1000) | G57: =IF($P$57="","",SUMIFS(Mastersheet!$H$2:$H$400,Mastersheet!$A$2:$A$400,$P$57)/1000) | H57: =IF($P$57="","",SUMIFS(Mastersheet!$I$2:$I$400,Mastersheet!$A$2:$A$400,$P$57)/1000) | I57: =IF($P$57="","",SUMIFS(Mastersheet!$J$2:$J$400,Mastersheet!$A$2:$A$400,$P$57)/1000) | J57: =IF($P$57="","",SUMIFS(Mastersheet!$K$2:$K$400,Mastersheet!$A$2:$A$400,$P$57)/1000) | K57: =IF($P$57="","",SUMIFS(Mastersheet!$L$2:$L$400,Mastersheet!$A$2:$A$400,$P$57)/1000) | L57: =IF($P$57="","",SUMIFS(Mastersheet!$M$2:$M$400,Mastersheet!$A$2:$A$400,$P$57)/1000) | M57: =IF($P$57="","",SUMIFS(Mastersheet!$N$2:$N$400,Mastersheet!$A$2:$A$400,$P$57)/1000) | Q57: Account | R57: KTO
C58: Verbindlichkeiten aus LuL | D58: Trade payables | E58: =SUMIFS(Mastersheet!$F$2:$F$400,Mastersheet!$D$2:$D$400,$P58,Mastersheet!$C$2:$C$400,$Q58)/1000 -> 0 | F58: =SUMIFS(Mastersheet!$G$2:$G$400,Mastersheet!$D$2:$D$400,$P58,Mastersheet!$C$2:$C$400,$Q58)/1000 -> 0 | G58: =SUMIFS(Mastersheet!$H$2:$H$400,Mastersheet!$D$2:$D$400,$P58,Mastersheet!$C$2:$C$400,$Q58)/1000 -> 0 | H58: =SUMIFS(Mastersheet!$I$2:$I$400,Mastersheet!$D$2:$D$400,$P58,Mastersheet!$C$2:$C$400,$Q58)/1000 -> 0 | I58: =SUMIFS(Mastersheet!$J$2:$J$400,Mastersheet!$D$2:$D$400,$P58,Mastersheet!$C$2:$C$400,$Q58)/1000 -> 0 | J58: =SUMIFS(Mastersheet!$K$2:$K$400,Mastersheet!$D$2:$D$400,$P58,Mastersheet!$C$2:$C$400,$Q58)/1000 -> 0 | K58: =SUMIFS(Mastersheet!$L$2:$L$400,Mastersheet!$D$2:$D$400,$P58,Mastersheet!$C$2:$C$400,$Q58)/1000 -> 0 | L58: =SUMIFS(Mastersheet!$M$2:$M$400,Mastersheet!$D$2:$D$400,$P58,Mastersheet!$C$2:$C$400,$Q58)/1000 -> 0 | M58: =SUMIFS(Mastersheet!$N$2:$N$400,Mastersheet!$D$2:$D$400,$P58,Mastersheet!$C$2:$C$400,$Q58)/1000 -> 0 | P58: Verbindlichkeiten aus L+L | Q58: TWC | R58: POS
E59: =IF($P$59="","",SUMIFS(Mastersheet!$F$2:$F$400,Mastersheet!$A$2:$A$400,$P$59)/1000) | F59: =IF($P$59="","",SUMIFS(Mastersheet!$G$2:$G$400,Mastersheet!$A$2:$A$400,$P$59)/1000) | G59: =IF($P$59="","",SUMIFS(Mastersheet!$H$2:$H$400,Mastersheet!$A$2:$A$400,$P$59)/1000) | H59: =IF($P$59="","",SUMIFS(Mastersheet!$I$2:$I$400,Mastersheet!$A$2:$A$400,$P$59)/1000) | I59: =IF($P$59="","",SUMIFS(Mastersheet!$J$2:$J$400,Mastersheet!$A$2:$A$400,$P$59)/1000) | J59: =IF($P$59="","",SUMIFS(Mastersheet!$K$2:$K$400,Mastersheet!$A$2:$A$400,$P$59)/1000) | K59: =IF($P$59="","",SUMIFS(Mastersheet!$L$2:$L$400,Mastersheet!$A$2:$A$400,$P$59)/1000) | L59: =IF($P$59="","",SUMIFS(Mastersheet!$M$2:$M$400,Mastersheet!$A$2:$A$400,$P$59)/1000) | M59: =IF($P$59="","",SUMIFS(Mastersheet!$N$2:$N$400,Mastersheet!$A$2:$A$400,$P$59)/1000) | Q59: Account | R59: KTO
E60: =IF($P$60="","",SUMIFS(Mastersheet!$F$2:$F$400,Mastersheet!$A$2:$A$400,$P$60)/1000) | F60: =IF($P$60="","",SUMIFS(Mastersheet!$G$2:$G$400,Mastersheet!$A$2:$A$400,$P$60)/1000) | G60: =IF($P$60="","",SUMIFS(Mastersheet!$H$2:$H$400,Mastersheet!$A$2:$A$400,$P$60)/1000) | H60: =IF($P$60="","",SUMIFS(Mastersheet!$I$2:$I$400,Mastersheet!$A$2:$A$400,$P$60)/1000) | I60: =IF($P$60="","",SUMIFS(Mastersheet!$J$2:$J$400,Mastersheet!$A$2:$A$400,$P$60)/1000) | J60: =IF($P$60="","",SUMIFS(Mastersheet!$K$2:$K$400,Mastersheet!$A$2:$A$400,$P$60)/1000) | K60: =IF($P$60="","",SUMIFS(Mastersheet!$L$2:$L$400,Mastersheet!$A$2:$A$400,$P$60)/1000) | L60: =IF($P$60="","",SUMIFS(Mastersheet!$M$2:$M$400,Mastersheet!$A$2:$A$400,$P$60)/1000) | M60: =IF($P$60="","",SUMIFS(Mastersheet!$N$2:$N$400,Mastersheet!$A$2:$A$400,$P$60)/1000) | Q60: Account | R60: KTO
E61: =IF($P$61="","",SUMIFS(Mastersheet!$F$2:$F$400,Mastersheet!$A$2:$A$400,$P$61)/1000) | F61: =IF($P$61="","",SUMIFS(Mastersheet!$G$2:$G$400,Mastersheet!$A$2:$A$400,$P$61)/1000) | G61: =IF($P$61="","",SUMIFS(Mastersheet!$H$2:$H$400,Mastersheet!$A$2:$A$400,$P$61)/1000) | H61: =IF($P$61="","",SUMIFS(Mastersheet!$I$2:$I$400,Mastersheet!$A$2:$A$400,$P$61)/1000) | I61: =IF($P$61="","",SUMIFS(Mastersheet!$J$2:$J$400,Mastersheet!$A$2:$A$400,$P$61)/1000) | J61: =IF($P$61="","",SUMIFS(Mastersheet!$K$2:$K$400,Mastersheet!$A$2:$A$400,$P$61)/1000) | K61: =IF($P$61="","",SUMIFS(Mastersheet!$L$2:$L$400,Mastersheet!$A$2:$A$400,$P$61)/1000) | L61: =IF($P$61="","",SUMIFS(Mastersheet!$M$2:$M$400,Mastersheet!$A$2:$A$400,$P$61)/1000) | M61: =IF($P$61="","",SUMIFS(Mastersheet!$N$2:$N$400,Mastersheet!$A$2:$A$400,$P$61)/1000) | Q61: Account | R61: KTO
E62: =IF($P$62="","",SUMIFS(Mastersheet!$F$2:$F$400,Mastersheet!$A$2:$A$400,$P$62)/1000) | F62: =IF($P$62="","",SUMIFS(Mastersheet!$G$2:$G$400,Mastersheet!$A$2:$A$400,$P$62)/1000) | G62: =IF($P$62="","",SUMIFS(Mastersheet!$H$2:$H$400,Mastersheet!$A$2:$A$400,$P$62)/1000) | H62: =IF($P$62="","",SUMIFS(Mastersheet!$I$2:$I$400,Mastersheet!$A$2:$A$400,$P$62)/1000) | I62: =IF($P$62="","",SUMIFS(Mastersheet!$J$2:$J$400,Mastersheet!$A$2:$A$400,$P$62)/1000) | J62: =IF($P$62="","",SUMIFS(Mastersheet!$K$2:$K$400,Mastersheet!$A$2:$A$400,$P$62)/1000) | K62: =IF($P$62="","",SUMIFS(Mastersheet!$L$2:$L$400,Mastersheet!$A$2:$A$400,$P$62)/1000) | L62: =IF($P$62="","",SUMIFS(Mastersheet!$M$2:$M$400,Mastersheet!$A$2:$A$400,$P$62)/1000) | M62: =IF($P$62="","",SUMIFS(Mastersheet!$N$2:$N$400,Mastersheet!$A$2:$A$400,$P$62)/1000) | Q62: Account | R62: KTO
E63: =IF($P$63="","",SUMIFS(Mastersheet!$F$2:$F$400,Mastersheet!$A$2:$A$400,$P$63)/1000) | F63: =IF($P$63="","",SUMIFS(Mastersheet!$G$2:$G$400,Mastersheet!$A$2:$A$400,$P$63)/1000) | G63: =IF($P$63="","",SUMIFS(Mastersheet!$H$2:$H$400,Mastersheet!$A$2:$A$400,$P$63)/1000) | H63: =IF($P$63="","",SUMIFS(Mastersheet!$I$2:$I$400,Mastersheet!$A$2:$A$400,$P$63)/1000) | I63: =IF($P$63="","",SUMIFS(Mastersheet!$J$2:$J$400,Mastersheet!$A$2:$A$400,$P$63)/1000) | J63: =IF($P$63="","",SUMIFS(Mastersheet!$K$2:$K$400,Mastersheet!$A$2:$A$400,$P$63)/1000) | K63: =IF($P$63="","",SUMIFS(Mastersheet!$L$2:$L$400,Mastersheet!$A$2:$A$400,$P$63)/1000) | L63: =IF($P$63="","",SUMIFS(Mastersheet!$M$2:$M$400,Mastersheet!$A$2:$A$400,$P$63)/1000) | M63: =IF($P$63="","",SUMIFS(Mastersheet!$N$2:$N$400,Mastersheet!$A$2:$A$400,$P$63)/1000) | Q63: Account | R63: KTO
E64: =IF($P$64="","",SUMIFS(Mastersheet!$F$2:$F$400,Mastersheet!$A$2:$A$400,$P$64)/1000) | F64: =IF($P$64="","",SUMIFS(Mastersheet!$G$2:$G$400,Mastersheet!$A$2:$A$400,$P$64)/1000) | G64: =IF($P$64="","",SUMIFS(Mastersheet!$H$2:$H$400,Mastersheet!$A$2:$A$400,$P$64)/1000) | H64: =IF($P$64="","",SUMIFS(Mastersheet!$I$2:$I$400,Mastersheet!$A$2:$A$400,$P$64)/1000) | I64: =IF($P$64="","",SUMIFS(Mastersheet!$J$2:$J$400,Mastersheet!$A$2:$A$400,$P$64)/1000) | J64: =IF($P$64="","",SUMIFS(Mastersheet!$K$2:$K$400,Mastersheet!$A$2:$A$400,$P$64)/1000) | K64: =IF($P$64="","",SUMIFS(Mastersheet!$L$2:$L$400,Mastersheet!$A$2:$A$400,$P$64)/1000) | L64: =IF($P$64="","",SUMIFS(Mastersheet!$M$2:$M$400,Mastersheet!$A$2:$A$400,$P$64)/1000) | M64: =IF($P$64="","",SUMIFS(Mastersheet!$N$2:$N$400,Mastersheet!$A$2:$A$400,$P$64)/1000) | Q64: Account | R64: KTO
E65: =IF($P$65="","",SUMIFS(Mastersheet!$F$2:$F$400,Mastersheet!$A$2:$A$400,$P$65)/1000) | F65: =IF($P$65="","",SUMIFS(Mastersheet!$G$2:$G$400,Mastersheet!$A$2:$A$400,$P$65)/1000) | G65: =IF($P$65="","",SUMIFS(Mastersheet!$H$2:$H$400,Mastersheet!$A$2:$A$400,$P$65)/1000) | H65: =IF($P$65="","",SUMIFS(Mastersheet!$I$2:$I$400,Mastersheet!$A$2:$A$400,$P$65)/1000) | I65: =IF($P$65="","",SUMIFS(Mastersheet!$J$2:$J$400,Mastersheet!$A$2:$A$400,$P$65)/1000) | J65: =IF($P$65="","",SUMIFS(Mastersheet!$K$2:$K$400,Mastersheet!$A$2:$A$400,$P$65)/1000) | K65: =IF($P$65="","",SUMIFS(Mastersheet!$L$2:$L$400,Mastersheet!$A$2:$A$400,$P$65)/1000) | L65: =IF($P$65="","",SUMIFS(Mastersheet!$M$2:$M$400,Mastersheet!$A$2:$A$400,$P$65)/1000) | M65: =IF($P$65="","",SUMIFS(Mastersheet!$N$2:$N$400,Mastersheet!$A$2:$A$400,$P$65)/1000) | Q65: Account | R65: KTO
E66: =IF($P$66="","",SUMIFS(Mastersheet!$F$2:$F$400,Mastersheet!$A$2:$A$400,$P$66)/1000) | F66: =IF($P$66="","",SUMIFS(Mastersheet!$G$2:$G$400,Mastersheet!$A$2:$A$400,$P$66)/1000) | G66: =IF($P$66="","",SUMIFS(Mastersheet!$H$2:$H$400,Mastersheet!$A$2:$A$400,$P$66)/1000) | H66: =IF($P$66="","",SUMIFS(Mastersheet!$I$2:$I$400,Mastersheet!$A$2:$A$400,$P$66)/1000) | I66: =IF($P$66="","",SUMIFS(Mastersheet!$J$2:$J$400,Mastersheet!$A$2:$A$400,$P$66)/1000) | J66: =IF($P$66="","",SUMIFS(Mastersheet!$K$2:$K$400,Mastersheet!$A$2:$A$400,$P$66)/1000) | K66: =IF($P$66="","",SUMIFS(Mastersheet!$L$2:$L$400,Mastersheet!$A$2:$A$400,$P$66)/1000) | L66: =IF($P$66="","",SUMIFS(Mastersheet!$M$2:$M$400,Mastersheet!$A$2:$A$400,$P$66)/1000) | M66: =IF($P$66="","",SUMIFS(Mastersheet!$N$2:$N$400,Mastersheet!$A$2:$A$400,$P$66)/1000) | Q66: Account | R66: KTO
C67: Erhaltene Anzahlungen | D67: Advance payments received | E67: =SUMIFS(Mastersheet!$F$2:$F$400,Mastersheet!$D$2:$D$400,$P67,Mastersheet!$C$2:$C$400,$Q67)/1000 -> 0 | F67: =SUMIFS(Mastersheet!$G$2:$G$400,Mastersheet!$D$2:$D$400,$P67,Mastersheet!$C$2:$C$400,$Q67)/1000 -> 0 | G67: =SUMIFS(Mastersheet!$H$2:$H$400,Mastersheet!$D$2:$D$400,$P67,Mastersheet!$C$2:$C$400,$Q67)/1000 -> 0 | H67: =SUMIFS(Mastersheet!$I$2:$I$400,Mastersheet!$D$2:$D$400,$P67,Mastersheet!$C$2:$C$400,$Q67)/1000 -> 0 | I67: =SUMIFS(Mastersheet!$J$2:$J$400,Mastersheet!$D$2:$D$400,$P67,Mastersheet!$C$2:$C$400,$Q67)/1000 -> 0 | J67: =SUMIFS(Mastersheet!$K$2:$K$400,Mastersheet!$D$2:$D$400,$P67,Mastersheet!$C$2:$C$400,$Q67)/1000 -> 0 | K67: =SUMIFS(Mastersheet!$L$2:$L$400,Mastersheet!$D$2:$D$400,$P67,Mastersheet!$C$2:$C$400,$Q67)/1000 -> 0 | L67: =SUMIFS(Mastersheet!$M$2:$M$400,Mastersheet!$D$2:$D$400,$P67,Mastersheet!$C$2:$C$400,$Q67)/1000 -> 0 | M67: =SUMIFS(Mastersheet!$N$2:$N$400,Mastersheet!$D$2:$D$400,$P67,Mastersheet!$C$2:$C$400,$Q67)/1000 -> 0 | P67: Erhaltene Anzahlungen | Q67: TWC | R67: POS
E68: =IF($P$68="","",SUMIFS(Mastersheet!$F$2:$F$400,Mastersheet!$A$2:$A$400,$P$68)/1000) | F68: =IF($P$68="","",SUMIFS(Mastersheet!$G$2:$G$400,Mastersheet!$A$2:$A$400,$P$68)/1000) | G68: =IF($P$68="","",SUMIFS(Mastersheet!$H$2:$H$400,Mastersheet!$A$2:$A$400,$P$68)/1000) | H68: =IF($P$68="","",SUMIFS(Mastersheet!$I$2:$I$400,Mastersheet!$A$2:$A$400,$P$68)/1000) | I68: =IF($P$68="","",SUMIFS(Mastersheet!$J$2:$J$400,Mastersheet!$A$2:$A$400,$P$68)/1000) | J68: =IF($P$68="","",SUMIFS(Mastersheet!$K$2:$K$400,Mastersheet!$A$2:$A$400,$P$68)/1000) | K68: =IF($P$68="","",SUMIFS(Mastersheet!$L$2:$L$400,Mastersheet!$A$2:$A$400,$P$68)/1000) | L68: =IF($P$68="","",SUMIFS(Mastersheet!$M$2:$M$400,Mastersheet!$A$2:$A$400,$P$68)/1000) | M68: =IF($P$68="","",SUMIFS(Mastersheet!$N$2:$N$400,Mastersheet!$A$2:$A$400,$P$68)/1000) | Q68: Account | R68: KTO
E69: =IF($P$69="","",SUMIFS(Mastersheet!$F$2:$F$400,Mastersheet!$A$2:$A$400,$P$69)/1000) | F69: =IF($P$69="","",SUMIFS(Mastersheet!$G$2:$G$400,Mastersheet!$A$2:$A$400,$P$69)/1000) | G69: =IF($P$69="","",SUMIFS(Mastersheet!$H$2:$H$400,Mastersheet!$A$2:$A$400,$P$69)/1000) | H69: =IF($P$69="","",SUMIFS(Mastersheet!$I$2:$I$400,Mastersheet!$A$2:$A$400,$P$69)/1000) | I69: =IF($P$69="","",SUMIFS(Mastersheet!$J$2:$J$400,Mastersheet!$A$2:$A$400,$P$69)/1000) | J69: =IF($P$69="","",SUMIFS(Mastersheet!$K$2:$K$400,Mastersheet!$A$2:$A$400,$P$69)/1000) | K69: =IF($P$69="","",SUMIFS(Mastersheet!$L$2:$L$400,Mastersheet!$A$2:$A$400,$P$69)/1000) | L69: =IF($P$69="","",SUMIFS(Mastersheet!$M$2:$M$400,Mastersheet!$A$2:$A$400,$P$69)/1000) | M69: =IF($P$69="","",SUMIFS(Mastersheet!$N$2:$N$400,Mastersheet!$A$2:$A$400,$P$69)/1000) | Q69: Account | R69: KTO
E70: =IF($P$70="","",SUMIFS(Mastersheet!$F$2:$F$400,Mastersheet!$A$2:$A$400,$P$70)/1000) | F70: =IF($P$70="","",SUMIFS(Mastersheet!$G$2:$G$400,Mastersheet!$A$2:$A$400,$P$70)/1000) | G70: =IF($P$70="","",SUMIFS(Mastersheet!$H$2:$H$400,Mastersheet!$A$2:$A$400,$P$70)/1000) | H70: =IF($P$70="","",SUMIFS(Mastersheet!$I$2:$I$400,Mastersheet!$A$2:$A$400,$P$70)/1000) | I70: =IF($P$70="","",SUMIFS(Mastersheet!$J$2:$J$400,Mastersheet!$A$2:$A$400,$P$70)/1000) | J70: =IF($P$70="","",SUMIFS(Mastersheet!$K$2:$K$400,Mastersheet!$A$2:$A$400,$P$70)/1000) | K70: =IF($P$70="","",SUMIFS(Mastersheet!$L$2:$L$400,Mastersheet!$A$2:$A$400,$P$70)/1000) | L70: =IF($P$70="","",SUMIFS(Mastersheet!$M$2:$M$400,Mastersheet!$A$2:$A$400,$P$70)/1000) | M70: =IF($P$70="","",SUMIFS(Mastersheet!$N$2:$N$400,Mastersheet!$A$2:$A$400,$P$70)/1000) | Q70: Account | R70: KTO
E71: =IF($P$71="","",SUMIFS(Mastersheet!$F$2:$F$400,Mastersheet!$A$2:$A$400,$P$71)/1000) | F71: =IF($P$71="","",SUMIFS(Mastersheet!$G$2:$G$400,Mastersheet!$A$2:$A$400,$P$71)/1000) | G71: =IF($P$71="","",SUMIFS(Mastersheet!$H$2:$H$400,Mastersheet!$A$2:$A$400,$P$71)/1000) | H71: =IF($P$71="","",SUMIFS(Mastersheet!$I$2:$I$400,Mastersheet!$A$2:$A$400,$P$71)/1000) | I71: =IF($P$71="","",SUMIFS(Mastersheet!$J$2:$J$400,Mastersheet!$A$2:$A$400,$P$71)/1000) | J71: =IF($P$71="","",SUMIFS(Mastersheet!$K$2:$K$400,Mastersheet!$A$2:$A$400,$P$71)/1000) | K71: =IF($P$71="","",SUMIFS(Mastersheet!$L$2:$L$400,Mastersheet!$A$2:$A$400,$P$71)/1000) | L71: =IF($P$71="","",SUMIFS(Mastersheet!$M$2:$M$400,Mastersheet!$A$2:$A$400,$P$71)/1000) | M71: =IF($P$71="","",SUMIFS(Mastersheet!$N$2:$N$400,Mastersheet!$A$2:$A$400,$P$71)/1000) | Q71: Account | R71: KTO
E72: =IF($P$72="","",SUMIFS(Mastersheet!$F$2:$F$400,Mastersheet!$A$2:$A$400,$P$72)/1000) | F72: =IF($P$72="","",SUMIFS(Mastersheet!$G$2:$G$400,Mastersheet!$A$2:$A$400,$P$72)/1000) | G72: =IF($P$72="","",SUMIFS(Mastersheet!$H$2:$H$400,Mastersheet!$A$2:$A$400,$P$72)/1000) | H72: =IF($P$72="","",SUMIFS(Mastersheet!$I$2:$I$400,Mastersheet!$A$2:$A$400,$P$72)/1000) | I72: =IF($P$72="","",SUMIFS(Mastersheet!$J$2:$J$400,Mastersheet!$A$2:$A$400,$P$72)/1000) | J72: =IF($P$72="","",SUMIFS(Mastersheet!$K$2:$K$400,Mastersheet!$A$2:$A$400,$P$72)/1000) | K72: =IF($P$72="","",SUMIFS(Mastersheet!$L$2:$L$400,Mastersheet!$A$2:$A$400,$P$72)/1000) | L72: =IF($P$72="","",SUMIFS(Mastersheet!$M$2:$M$400,Mastersheet!$A$2:$A$400,$P$72)/1000) | M72: =IF($P$72="","",SUMIFS(Mastersheet!$N$2:$N$400,Mastersheet!$A$2:$A$400,$P$72)/1000) | Q72: Account | R72: KTO
E73: =IF($P$73="","",SUMIFS(Mastersheet!$F$2:$F$400,Mastersheet!$A$2:$A$400,$P$73)/1000) | F73: =IF($P$73="","",SUMIFS(Mastersheet!$G$2:$G$400,Mastersheet!$A$2:$A$400,$P$73)/1000) | G73: =IF($P$73="","",SUMIFS(Mastersheet!$H$2:$H$400,Mastersheet!$A$2:$A$400,$P$73)/1000) | H73: =IF($P$73="","",SUMIFS(Mastersheet!$I$2:$I$400,Mastersheet!$A$2:$A$400,$P$73)/1000) | I73: =IF($P$73="","",SUMIFS(Mastersheet!$J$2:$J$400,Mastersheet!$A$2:$A$400,$P$73)/1000) | J73: =IF($P$73="","",SUMIFS(Mastersheet!$K$2:$K$400,Mastersheet!$A$2:$A$400,$P$73)/1000) | K73: =IF($P$73="","",SUMIFS(Mastersheet!$L$2:$L$400,Mastersheet!$A$2:$A$400,$P$73)/1000) | L73: =IF($P$73="","",SUMIFS(Mastersheet!$M$2:$M$400,Mastersheet!$A$2:$A$400,$P$73)/1000) | M73: =IF($P$73="","",SUMIFS(Mastersheet!$N$2:$N$400,Mastersheet!$A$2:$A$400,$P$73)/1000) | Q73: Account | R73: KTO
E74: =IF($P$74="","",SUMIFS(Mastersheet!$F$2:$F$400,Mastersheet!$A$2:$A$400,$P$74)/1000) | F74: =IF($P$74="","",SUMIFS(Mastersheet!$G$2:$G$400,Mastersheet!$A$2:$A$400,$P$74)/1000) | G74: =IF($P$74="","",SUMIFS(Mastersheet!$H$2:$H$400,Mastersheet!$A$2:$A$400,$P$74)/1000) | H74: =IF($P$74="","",SUMIFS(Mastersheet!$I$2:$I$400,Mastersheet!$A$2:$A$400,$P$74)/1000) | I74: =IF($P$74="","",SUMIFS(Mastersheet!$J$2:$J$400,Mastersheet!$A$2:$A$400,$P$74)/1000) | J74: =IF($P$74="","",SUMIFS(Mastersheet!$K$2:$K$400,Mastersheet!$A$2:$A$400,$P$74)/1000) | K74: =IF($P$74="","",SUMIFS(Mastersheet!$L$2:$L$400,Mastersheet!$A$2:$A$400,$P$74)/1000) | L74: =IF($P$74="","",SUMIFS(Mastersheet!$M$2:$M$400,Mastersheet!$A$2:$A$400,$P$74)/1000) | M74: =IF($P$74="","",SUMIFS(Mastersheet!$N$2:$N$400,Mastersheet!$A$2:$A$400,$P$74)/1000) | Q74: Account | R74: KTO
E75: =IF($P$75="","",SUMIFS(Mastersheet!$F$2:$F$400,Mastersheet!$A$2:$A$400,$P$75)/1000) | F75: =IF($P$75="","",SUMIFS(Mastersheet!$G$2:$G$400,Mastersheet!$A$2:$A$400,$P$75)/1000) | G75: =IF($P$75="","",SUMIFS(Mastersheet!$H$2:$H$400,Mastersheet!$A$2:$A$400,$P$75)/1000) | H75: =IF($P$75="","",SUMIFS(Mastersheet!$I$2:$I$400,Mastersheet!$A$2:$A$400,$P$75)/1000) | I75: =IF($P$75="","",SUMIFS(Mastersheet!$J$2:$J$400,Mastersheet!$A$2:$A$400,$P$75)/1000) | J75: =IF($P$75="","",SUMIFS(Mastersheet!$K$2:$K$400,Mastersheet!$A$2:$A$400,$P$75)/1000) | K75: =IF($P$75="","",SUMIFS(Mastersheet!$L$2:$L$400,Mastersheet!$A$2:$A$400,$P$75)/1000) | L75: =IF($P$75="","",SUMIFS(Mastersheet!$M$2:$M$400,Mastersheet!$A$2:$A$400,$P$75)/1000) | M75: =IF($P$75="","",SUMIFS(Mastersheet!$N$2:$N$400,Mastersheet!$A$2:$A$400,$P$75)/1000) | Q75: Account | R75: KTO
C76: Dummy 1 | D76: Dummy 1
C77: Dummy 2 | D77: Dummy 2
C78: Dummy 3 | D78: Dummy 3
C79: Trade Working Capital | D79: Trade working capital | E79: =SUMIF($R$40:$R$78,"<>KTO",E40:E78) -> 0 | F79: =SUMIF($R$40:$R$78,"<>KTO",F40:F78) -> 0 | G79: =SUMIF($R$40:$R$78,"<>KTO",G40:G78) -> 0 | H79: =SUMIF($R$40:$R$78,"<>KTO",H40:H78) -> 0 | I79: =SUMIF($R$40:$R$78,"<>KTO",I40:I78) -> 0 | J79: =SUMIF($R$40:$R$78,"<>KTO",J40:J78) -> 0 | K79: =SUMIF($R$40:$R$78,"<>KTO",K40:K78) -> 0 | L79: =SUMIF($R$40:$R$78,"<>KTO",L40:L78) -> 0 | M79: =SUMIF($R$40:$R$78,"<>KTO",M40:M78) -> 0
C80: Sonstige Vermögensgegenstände | D80: Other assets | E80: =SUMIFS(Mastersheet!$F$2:$F$400,Mastersheet!$D$2:$D$400,$P80,Mastersheet!$C$2:$C$400,$Q80)/1000 -> 0 | F80: =SUMIFS(Mastersheet!$G$2:$G$400,Mastersheet!$D$2:$D$400,$P80,Mastersheet!$C$2:$C$400,$Q80)/1000 -> 0 | G80: =SUMIFS(Mastersheet!$H$2:$H$400,Mastersheet!$D$2:$D$400,$P80,Mastersheet!$C$2:$C$400,$Q80)/1000 -> 0 | H80: =SUMIFS(Mastersheet!$I$2:$I$400,Mastersheet!$D$2:$D$400,$P80,Mastersheet!$C$2:$C$400,$Q80)/1000 -> 0 | I80: =SUMIFS(Mastersheet!$J$2:$J$400,Mastersheet!$D$2:$D$400,$P80,Mastersheet!$C$2:$C$400,$Q80)/1000 -> 0 | J80: =SUMIFS(Mastersheet!$K$2:$K$400,Mastersheet!$D$2:$D$400,$P80,Mastersheet!$C$2:$C$400,$Q80)/1000 -> 0 | K80: =SUMIFS(Mastersheet!$L$2:$L$400,Mastersheet!$D$2:$D$400,$P80,Mastersheet!$C$2:$C$400,$Q80)/1000 -> 0 | L80: =SUMIFS(Mastersheet!$M$2:$M$400,Mastersheet!$D$2:$D$400,$P80,Mastersheet!$C$2:$C$400,$Q80)/1000 -> 0 | M80: =SUMIFS(Mastersheet!$N$2:$N$400,Mastersheet!$D$2:$D$400,$P80,Mastersheet!$C$2:$C$400,$Q80)/1000 -> 0 | P80: Sonstige Vermoegensgegenstaende | Q80: OA | R80: POS
E81: =IF($P$81="","",SUMIFS(Mastersheet!$F$2:$F$400,Mastersheet!$A$2:$A$400,$P$81)/1000) | F81: =IF($P$81="","",SUMIFS(Mastersheet!$G$2:$G$400,Mastersheet!$A$2:$A$400,$P$81)/1000) | G81: =IF($P$81="","",SUMIFS(Mastersheet!$H$2:$H$400,Mastersheet!$A$2:$A$400,$P$81)/1000) | H81: =IF($P$81="","",SUMIFS(Mastersheet!$I$2:$I$400,Mastersheet!$A$2:$A$400,$P$81)/1000) | I81: =IF($P$81="","",SUMIFS(Mastersheet!$J$2:$J$400,Mastersheet!$A$2:$A$400,$P$81)/1000) | J81: =IF($P$81="","",SUMIFS(Mastersheet!$K$2:$K$400,Mastersheet!$A$2:$A$400,$P$81)/1000) | K81: =IF($P$81="","",SUMIFS(Mastersheet!$L$2:$L$400,Mastersheet!$A$2:$A$400,$P$81)/1000) | L81: =IF($P$81="","",SUMIFS(Mastersheet!$M$2:$M$400,Mastersheet!$A$2:$A$400,$P$81)/1000) | M81: =IF($P$81="","",SUMIFS(Mastersheet!$N$2:$N$400,Mastersheet!$A$2:$A$400,$P$81)/1000) | Q81: Account | R81: KTO
E82: =IF($P$82="","",SUMIFS(Mastersheet!$F$2:$F$400,Mastersheet!$A$2:$A$400,$P$82)/1000) | F82: =IF($P$82="","",SUMIFS(Mastersheet!$G$2:$G$400,Mastersheet!$A$2:$A$400,$P$82)/1000) | G82: =IF($P$82="","",SUMIFS(Mastersheet!$H$2:$H$400,Mastersheet!$A$2:$A$400,$P$82)/1000) | H82: =IF($P$82="","",SUMIFS(Mastersheet!$I$2:$I$400,Mastersheet!$A$2:$A$400,$P$82)/1000) | I82: =IF($P$82="","",SUMIFS(Mastersheet!$J$2:$J$400,Mastersheet!$A$2:$A$400,$P$82)/1000) | J82: =IF($P$82="","",SUMIFS(Mastersheet!$K$2:$K$400,Mastersheet!$A$2:$A$400,$P$82)/1000) | K82: =IF($P$82="","",SUMIFS(Mastersheet!$L$2:$L$400,Mastersheet!$A$2:$A$400,$P$82)/1000) | L82: =IF($P$82="","",SUMIFS(Mastersheet!$M$2:$M$400,Mastersheet!$A$2:$A$400,$P$82)/1000) | M82: =IF($P$82="","",SUMIFS(Mastersheet!$N$2:$N$400,Mastersheet!$A$2:$A$400,$P$82)/1000) | Q82: Account | R82: KTO
E83: =IF($P$83="","",SUMIFS(Mastersheet!$F$2:$F$400,Mastersheet!$A$2:$A$400,$P$83)/1000) | F83: =IF($P$83="","",SUMIFS(Mastersheet!$G$2:$G$400,Mastersheet!$A$2:$A$400,$P$83)/1000) | G83: =IF($P$83="","",SUMIFS(Mastersheet!$H$2:$H$400,Mastersheet!$A$2:$A$400,$P$83)/1000) | H83: =IF($P$83="","",SUMIFS(Mastersheet!$I$2:$I$400,Mastersheet!$A$2:$A$400,$P$83)/1000) | I83: =IF($P$83="","",SUMIFS(Mastersheet!$J$2:$J$400,Mastersheet!$A$2:$A$400,$P$83)/1000) | J83: =IF($P$83="","",SUMIFS(Mastersheet!$K$2:$K$400,Mastersheet!$A$2:$A$400,$P$83)/1000) | K83: =IF($P$83="","",SUMIFS(Mastersheet!$L$2:$L$400,Mastersheet!$A$2:$A$400,$P$83)/1000) | L83: =IF($P$83="","",SUMIFS(Mastersheet!$M$2:$M$400,Mastersheet!$A$2:$A$400,$P$83)/1000) | M83: =IF($P$83="","",SUMIFS(Mastersheet!$N$2:$N$400,Mastersheet!$A$2:$A$400,$P$83)/1000) | Q83: Account | R83: KTO
E84: =IF($P$84="","",SUMIFS(Mastersheet!$F$2:$F$400,Mastersheet!$A$2:$A$400,$P$84)/1000) | F84: =IF($P$84="","",SUMIFS(Mastersheet!$G$2:$G$400,Mastersheet!$A$2:$A$400,$P$84)/1000) | G84: =IF($P$84="","",SUMIFS(Mastersheet!$H$2:$H$400,Mastersheet!$A$2:$A$400,$P$84)/1000) | H84: =IF($P$84="","",SUMIFS(Mastersheet!$I$2:$I$400,Mastersheet!$A$2:$A$400,$P$84)/1000) | I84: =IF($P$84="","",SUMIFS(Mastersheet!$J$2:$J$400,Mastersheet!$A$2:$A$400,$P$84)/1000) | J84: =IF($P$84="","",SUMIFS(Mastersheet!$K$2:$K$400,Mastersheet!$A$2:$A$400,$P$84)/1000) | K84: =IF($P$84="","",SUMIFS(Mastersheet!$L$2:$L$400,Mastersheet!$A$2:$A$400,$P$84)/1000) | L84: =IF($P$84="","",SUMIFS(Mastersheet!$M$2:$M$400,Mastersheet!$A$2:$A$400,$P$84)/1000) | M84: =IF($P$84="","",SUMIFS(Mastersheet!$N$2:$N$400,Mastersheet!$A$2:$A$400,$P$84)/1000) | Q84: Account | R84: KTO
E85: =IF($P$85="","",SUMIFS(Mastersheet!$F$2:$F$400,Mastersheet!$A$2:$A$400,$P$85)/1000) | F85: =IF($P$85="","",SUMIFS(Mastersheet!$G$2:$G$400,Mastersheet!$A$2:$A$400,$P$85)/1000) | G85: =IF($P$85="","",SUMIFS(Mastersheet!$H$2:$H$400,Mastersheet!$A$2:$A$400,$P$85)/1000) | H85: =IF($P$85="","",SUMIFS(Mastersheet!$I$2:$I$400,Mastersheet!$A$2:$A$400,$P$85)/1000) | I85: =IF($P$85="","",SUMIFS(Mastersheet!$J$2:$J$400,Mastersheet!$A$2:$A$400,$P$85)/1000) | J85: =IF($P$85="","",SUMIFS(Mastersheet!$K$2:$K$400,Mastersheet!$A$2:$A$400,$P$85)/1000) | K85: =IF($P$85="","",SUMIFS(Mastersheet!$L$2:$L$400,Mastersheet!$A$2:$A$400,$P$85)/1000) | L85: =IF($P$85="","",SUMIFS(Mastersheet!$M$2:$M$400,Mastersheet!$A$2:$A$400,$P$85)/1000) | M85: =IF($P$85="","",SUMIFS(Mastersheet!$N$2:$N$400,Mastersheet!$A$2:$A$400,$P$85)/1000) | Q85: Account | R85: KTO
E86: =IF($P$86="","",SUMIFS(Mastersheet!$F$2:$F$400,Mastersheet!$A$2:$A$400,$P$86)/1000) | F86: =IF($P$86="","",SUMIFS(Mastersheet!$G$2:$G$400,Mastersheet!$A$2:$A$400,$P$86)/1000) | G86: =IF($P$86="","",SUMIFS(Mastersheet!$H$2:$H$400,Mastersheet!$A$2:$A$400,$P$86)/1000) | H86: =IF($P$86="","",SUMIFS(Mastersheet!$I$2:$I$400,Mastersheet!$A$2:$A$400,$P$86)/1000) | I86: =IF($P$86="","",SUMIFS(Mastersheet!$J$2:$J$400,Mastersheet!$A$2:$A$400,$P$86)/1000) | J86: =IF($P$86="","",SUMIFS(Mastersheet!$K$2:$K$400,Mastersheet!$A$2:$A$400,$P$86)/1000) | K86: =IF($P$86="","",SUMIFS(Mastersheet!$L$2:$L$400,Mastersheet!$A$2:$A$400,$P$86)/1000) | L86: =IF($P$86="","",SUMIFS(Mastersheet!$M$2:$M$400,Mastersheet!$A$2:$A$400,$P$86)/1000) | M86: =IF($P$86="","",SUMIFS(Mastersheet!$N$2:$N$400,Mastersheet!$A$2:$A$400,$P$86)/1000) | Q86: Account | R86: KTO
E87: =IF($P$87="","",SUMIFS(Mastersheet!$F$2:$F$400,Mastersheet!$A$2:$A$400,$P$87)/1000) | F87: =IF($P$87="","",SUMIFS(Mastersheet!$G$2:$G$400,Mastersheet!$A$2:$A$400,$P$87)/1000) | G87: =IF($P$87="","",SUMIFS(Mastersheet!$H$2:$H$400,Mastersheet!$A$2:$A$400,$P$87)/1000) | H87: =IF($P$87="","",SUMIFS(Mastersheet!$I$2:$I$400,Mastersheet!$A$2:$A$400,$P$87)/1000) | I87: =IF($P$87="","",SUMIFS(Mastersheet!$J$2:$J$400,Mastersheet!$A$2:$A$400,$P$87)/1000) | J87: =IF($P$87="","",SUMIFS(Mastersheet!$K$2:$K$400,Mastersheet!$A$2:$A$400,$P$87)/1000) | K87: =IF($P$87="","",SUMIFS(Mastersheet!$L$2:$L$400,Mastersheet!$A$2:$A$400,$P$87)/1000) | L87: =IF($P$87="","",SUMIFS(Mastersheet!$M$2:$M$400,Mastersheet!$A$2:$A$400,$P$87)/1000) | M87: =IF($P$87="","",SUMIFS(Mastersheet!$N$2:$N$400,Mastersheet!$A$2:$A$400,$P$87)/1000) | Q87: Account | R87: KTO
E88: =IF($P$88="","",SUMIFS(Mastersheet!$F$2:$F$400,Mastersheet!$A$2:$A$400,$P$88)/1000) | F88: =IF($P$88="","",SUMIFS(Mastersheet!$G$2:$G$400,Mastersheet!$A$2:$A$400,$P$88)/1000) | G88: =IF($P$88="","",SUMIFS(Mastersheet!$H$2:$H$400,Mastersheet!$A$2:$A$400,$P$88)/1000) | H88: =IF($P$88="","",SUMIFS(Mastersheet!$I$2:$I$400,Mastersheet!$A$2:$A$400,$P$88)/1000) | I88: =IF($P$88="","",SUMIFS(Mastersheet!$J$2:$J$400,Mastersheet!$A$2:$A$400,$P$88)/1000) | J88: =IF($P$88="","",SUMIFS(Mastersheet!$K$2:$K$400,Mastersheet!$A$2:$A$400,$P$88)/1000) | K88: =IF($P$88="","",SUMIFS(Mastersheet!$L$2:$L$400,Mastersheet!$A$2:$A$400,$P$88)/1000) | L88: =IF($P$88="","",SUMIFS(Mastersheet!$M$2:$M$400,Mastersheet!$A$2:$A$400,$P$88)/1000) | M88: =IF($P$88="","",SUMIFS(Mastersheet!$N$2:$N$400,Mastersheet!$A$2:$A$400,$P$88)/1000) | Q88: Account | R88: KTO
C89: Aktive Rechnungsabgrenzungsposten | D89: Prepaid expenses | E89: =SUMIFS(Mastersheet!$F$2:$F$400,Mastersheet!$D$2:$D$400,$P89,Mastersheet!$C$2:$C$400,$Q89)/1000 -> 0 | F89: =SUMIFS(Mastersheet!$G$2:$G$400,Mastersheet!$D$2:$D$400,$P89,Mastersheet!$C$2:$C$400,$Q89)/1000 -> 0 | G89: =SUMIFS(Mastersheet!$H$2:$H$400,Mastersheet!$D$2:$D$400,$P89,Mastersheet!$C$2:$C$400,$Q89)/1000 -> 0 | H89: =SUMIFS(Mastersheet!$I$2:$I$400,Mastersheet!$D$2:$D$400,$P89,Mastersheet!$C$2:$C$400,$Q89)/1000 -> 0 | I89: =SUMIFS(Mastersheet!$J$2:$J$400,Mastersheet!$D$2:$D$400,$P89,Mastersheet!$C$2:$C$400,$Q89)/1000 -> 0 | J89: =SUMIFS(Mastersheet!$K$2:$K$400,Mastersheet!$D$2:$D$400,$P89,Mastersheet!$C$2:$C$400,$Q89)/1000 -> 0 | K89: =SUMIFS(Mastersheet!$L$2:$L$400,Mastersheet!$D$2:$D$400,$P89,Mastersheet!$C$2:$C$400,$Q89)/1000 -> 0 | L89: =SUMIFS(Mastersheet!$M$2:$M$400,Mastersheet!$D$2:$D$400,$P89,Mastersheet!$C$2:$C$400,$Q89)/1000 -> 0 | M89: =SUMIFS(Mastersheet!$N$2:$N$400,Mastersheet!$D$2:$D$400,$P89,Mastersheet!$C$2:$C$400,$Q89)/1000 -> 0 | P89: Aktive Rechnungsabgrenzung | Q89: OA | R89: POS
E90: =IF($P$90="","",SUMIFS(Mastersheet!$F$2:$F$400,Mastersheet!$A$2:$A$400,$P$90)/1000) | F90: =IF($P$90="","",SUMIFS(Mastersheet!$G$2:$G$400,Mastersheet!$A$2:$A$400,$P$90)/1000) | G90: =IF($P$90="","",SUMIFS(Mastersheet!$H$2:$H$400,Mastersheet!$A$2:$A$400,$P$90)/1000) | H90: =IF($P$90="","",SUMIFS(Mastersheet!$I$2:$I$400,Mastersheet!$A$2:$A$400,$P$90)/1000) | I90: =IF($P$90="","",SUMIFS(Mastersheet!$J$2:$J$400,Mastersheet!$A$2:$A$400,$P$90)/1000) | J90: =IF($P$90="","",SUMIFS(Mastersheet!$K$2:$K$400,Mastersheet!$A$2:$A$400,$P$90)/1000) | K90: =IF($P$90="","",SUMIFS(Mastersheet!$L$2:$L$400,Mastersheet!$A$2:$A$400,$P$90)/1000) | L90: =IF($P$90="","",SUMIFS(Mastersheet!$M$2:$M$400,Mastersheet!$A$2:$A$400,$P$90)/1000) | M90: =IF($P$90="","",SUMIFS(Mastersheet!$N$2:$N$400,Mastersheet!$A$2:$A$400,$P$90)/1000) | Q90: Account | R90: KTO
E91: =IF($P$91="","",SUMIFS(Mastersheet!$F$2:$F$400,Mastersheet!$A$2:$A$400,$P$91)/1000) | F91: =IF($P$91="","",SUMIFS(Mastersheet!$G$2:$G$400,Mastersheet!$A$2:$A$400,$P$91)/1000) | G91: =IF($P$91="","",SUMIFS(Mastersheet!$H$2:$H$400,Mastersheet!$A$2:$A$400,$P$91)/1000) | H91: =IF($P$91="","",SUMIFS(Mastersheet!$I$2:$I$400,Mastersheet!$A$2:$A$400,$P$91)/1000) | I91: =IF($P$91="","",SUMIFS(Mastersheet!$J$2:$J$400,Mastersheet!$A$2:$A$400,$P$91)/1000) | J91: =IF($P$91="","",SUMIFS(Mastersheet!$K$2:$K$400,Mastersheet!$A$2:$A$400,$P$91)/1000) | K91: =IF($P$91="","",SUMIFS(Mastersheet!$L$2:$L$400,Mastersheet!$A$2:$A$400,$P$91)/1000) | L91: =IF($P$91="","",SUMIFS(Mastersheet!$M$2:$M$400,Mastersheet!$A$2:$A$400,$P$91)/1000) | M91: =IF($P$91="","",SUMIFS(Mastersheet!$N$2:$N$400,Mastersheet!$A$2:$A$400,$P$91)/1000) | Q91: Account | R91: KTO
E92: =IF($P$92="","",SUMIFS(Mastersheet!$F$2:$F$400,Mastersheet!$A$2:$A$400,$P$92)/1000) | F92: =IF($P$92="","",SUMIFS(Mastersheet!$G$2:$G$400,Mastersheet!$A$2:$A$400,$P$92)/1000) | G92: =IF($P$92="","",SUMIFS(Mastersheet!$H$2:$H$400,Mastersheet!$A$2:$A$400,$P$92)/1000) | H92: =IF($P$92="","",SUMIFS(Mastersheet!$I$2:$I$400,Mastersheet!$A$2:$A$400,$P$92)/1000) | I92: =IF($P$92="","",SUMIFS(Mastersheet!$J$2:$J$400,Mastersheet!$A$2:$A$400,$P$92)/1000) | J92: =IF($P$92="","",SUMIFS(Mastersheet!$K$2:$K$400,Mastersheet!$A$2:$A$400,$P$92)/1000) | K92: =IF($P$92="","",SUMIFS(Mastersheet!$L$2:$L$400,Mastersheet!$A$2:$A$400,$P$92)/1000) | L92: =IF($P$92="","",SUMIFS(Mastersheet!$M$2:$M$400,Mastersheet!$A$2:$A$400,$P$92)/1000) | M92: =IF($P$92="","",SUMIFS(Mastersheet!$N$2:$N$400,Mastersheet!$A$2:$A$400,$P$92)/1000) | Q92: Account | R92: KTO
E93: =IF($P$93="","",SUMIFS(Mastersheet!$F$2:$F$400,Mastersheet!$A$2:$A$400,$P$93)/1000) | F93: =IF($P$93="","",SUMIFS(Mastersheet!$G$2:$G$400,Mastersheet!$A$2:$A$400,$P$93)/1000) | G93: =IF($P$93="","",SUMIFS(Mastersheet!$H$2:$H$400,Mastersheet!$A$2:$A$400,$P$93)/1000) | H93: =IF($P$93="","",SUMIFS(Mastersheet!$I$2:$I$400,Mastersheet!$A$2:$A$400,$P$93)/1000) | I93: =IF($P$93="","",SUMIFS(Mastersheet!$J$2:$J$400,Mastersheet!$A$2:$A$400,$P$93)/1000) | J93: =IF($P$93="","",SUMIFS(Mastersheet!$K$2:$K$400,Mastersheet!$A$2:$A$400,$P$93)/1000) | K93: =IF($P$93="","",SUMIFS(Mastersheet!$L$2:$L$400,Mastersheet!$A$2:$A$400,$P$93)/1000) | L93: =IF($P$93="","",SUMIFS(Mastersheet!$M$2:$M$400,Mastersheet!$A$2:$A$400,$P$93)/1000) | M93: =IF($P$93="","",SUMIFS(Mastersheet!$N$2:$N$400,Mastersheet!$A$2:$A$400,$P$93)/1000) | Q93: Account | R93: KTO
E94: =IF($P$94="","",SUMIFS(Mastersheet!$F$2:$F$400,Mastersheet!$A$2:$A$400,$P$94)/1000) | F94: =IF($P$94="","",SUMIFS(Mastersheet!$G$2:$G$400,Mastersheet!$A$2:$A$400,$P$94)/1000) | G94: =IF($P$94="","",SUMIFS(Mastersheet!$H$2:$H$400,Mastersheet!$A$2:$A$400,$P$94)/1000) | H94: =IF($P$94="","",SUMIFS(Mastersheet!$I$2:$I$400,Mastersheet!$A$2:$A$400,$P$94)/1000) | I94: =IF($P$94="","",SUMIFS(Mastersheet!$J$2:$J$400,Mastersheet!$A$2:$A$400,$P$94)/1000) | J94: =IF($P$94="","",SUMIFS(Mastersheet!$K$2:$K$400,Mastersheet!$A$2:$A$400,$P$94)/1000) | K94: =IF($P$94="","",SUMIFS(Mastersheet!$L$2:$L$400,Mastersheet!$A$2:$A$400,$P$94)/1000) | L94: =IF($P$94="","",SUMIFS(Mastersheet!$M$2:$M$400,Mastersheet!$A$2:$A$400,$P$94)/1000) | M94: =IF($P$94="","",SUMIFS(Mastersheet!$N$2:$N$400,Mastersheet!$A$2:$A$400,$P$94)/1000) | Q94: Account | R94: KTO
E95: =IF($P$95="","",SUMIFS(Mastersheet!$F$2:$F$400,Mastersheet!$A$2:$A$400,$P$95)/1000) | F95: =IF($P$95="","",SUMIFS(Mastersheet!$G$2:$G$400,Mastersheet!$A$2:$A$400,$P$95)/1000) | G95: =IF($P$95="","",SUMIFS(Mastersheet!$H$2:$H$400,Mastersheet!$A$2:$A$400,$P$95)/1000) | H95: =IF($P$95="","",SUMIFS(Mastersheet!$I$2:$I$400,Mastersheet!$A$2:$A$400,$P$95)/1000) | I95: =IF($P$95="","",SUMIFS(Mastersheet!$J$2:$J$400,Mastersheet!$A$2:$A$400,$P$95)/1000) | J95: =IF($P$95="","",SUMIFS(Mastersheet!$K$2:$K$400,Mastersheet!$A$2:$A$400,$P$95)/1000) | K95: =IF($P$95="","",SUMIFS(Mastersheet!$L$2:$L$400,Mastersheet!$A$2:$A$400,$P$95)/1000) | L95: =IF($P$95="","",SUMIFS(Mastersheet!$M$2:$M$400,Mastersheet!$A$2:$A$400,$P$95)/1000) | M95: =IF($P$95="","",SUMIFS(Mastersheet!$N$2:$N$400,Mastersheet!$A$2:$A$400,$P$95)/1000) | Q95: Account | R95: KTO
E96: =IF($P$96="","",SUMIFS(Mastersheet!$F$2:$F$400,Mastersheet!$A$2:$A$400,$P$96)/1000) | F96: =IF($P$96="","",SUMIFS(Mastersheet!$G$2:$G$400,Mastersheet!$A$2:$A$400,$P$96)/1000) | G96: =IF($P$96="","",SUMIFS(Mastersheet!$H$2:$H$400,Mastersheet!$A$2:$A$400,$P$96)/1000) | H96: =IF($P$96="","",SUMIFS(Mastersheet!$I$2:$I$400,Mastersheet!$A$2:$A$400,$P$96)/1000) | I96: =IF($P$96="","",SUMIFS(Mastersheet!$J$2:$J$400,Mastersheet!$A$2:$A$400,$P$96)/1000) | J96: =IF($P$96="","",SUMIFS(Mastersheet!$K$2:$K$400,Mastersheet!$A$2:$A$400,$P$96)/1000) | K96: =IF($P$96="","",SUMIFS(Mastersheet!$L$2:$L$400,Mastersheet!$A$2:$A$400,$P$96)/1000) | L96: =IF($P$96="","",SUMIFS(Mastersheet!$M$2:$M$400,Mastersheet!$A$2:$A$400,$P$96)/1000) | M96: =IF($P$96="","",SUMIFS(Mastersheet!$N$2:$N$400,Mastersheet!$A$2:$A$400,$P$96)/1000) | Q96: Account | R96: KTO
E97: =IF($P$97="","",SUMIFS(Mastersheet!$F$2:$F$400,Mastersheet!$A$2:$A$400,$P$97)/1000) | F97: =IF($P$97="","",SUMIFS(Mastersheet!$G$2:$G$400,Mastersheet!$A$2:$A$400,$P$97)/1000) | G97: =IF($P$97="","",SUMIFS(Mastersheet!$H$2:$H$400,Mastersheet!$A$2:$A$400,$P$97)/1000) | H97: =IF($P$97="","",SUMIFS(Mastersheet!$I$2:$I$400,Mastersheet!$A$2:$A$400,$P$97)/1000) | I97: =IF($P$97="","",SUMIFS(Mastersheet!$J$2:$J$400,Mastersheet!$A$2:$A$400,$P$97)/1000) | J97: =IF($P$97="","",SUMIFS(Mastersheet!$K$2:$K$400,Mastersheet!$A$2:$A$400,$P$97)/1000) | K97: =IF($P$97="","",SUMIFS(Mastersheet!$L$2:$L$400,Mastersheet!$A$2:$A$400,$P$97)/1000) | L97: =IF($P$97="","",SUMIFS(Mastersheet!$M$2:$M$400,Mastersheet!$A$2:$A$400,$P$97)/1000) | M97: =IF($P$97="","",SUMIFS(Mastersheet!$N$2:$N$400,Mastersheet!$A$2:$A$400,$P$97)/1000) | Q97: Account | R97: KTO
C98: Forderungen gegenüber verbundenen/beteiligten Unternehmen | D98: Receivables from affiliated/ participating companies | E98: =SUMIFS(Mastersheet!$F$2:$F$400,Mastersheet!$D$2:$D$400,$P98,Mastersheet!$C$2:$C$400,$Q98)/1000 -> 0 | F98: =SUMIFS(Mastersheet!$G$2:$G$400,Mastersheet!$D$2:$D$400,$P98,Mastersheet!$C$2:$C$400,$Q98)/1000 -> 0 | G98: =SUMIFS(Mastersheet!$H$2:$H$400,Mastersheet!$D$2:$D$400,$P98,Mastersheet!$C$2:$C$400,$Q98)/1000 -> 0 | H98: =SUMIFS(Mastersheet!$I$2:$I$400,Mastersheet!$D$2:$D$400,$P98,Mastersheet!$C$2:$C$400,$Q98)/1000 -> 0 | I98: =SUMIFS(Mastersheet!$J$2:$J$400,Mastersheet!$D$2:$D$400,$P98,Mastersheet!$C$2:$C$400,$Q98)/1000 -> 0 | J98: =SUMIFS(Mastersheet!$K$2:$K$400,Mastersheet!$D$2:$D$400,$P98,Mastersheet!$C$2:$C$400,$Q98)/1000 -> 0 | K98: =SUMIFS(Mastersheet!$L$2:$L$400,Mastersheet!$D$2:$D$400,$P98,Mastersheet!$C$2:$C$400,$Q98)/1000 -> 0 | L98: =SUMIFS(Mastersheet!$M$2:$M$400,Mastersheet!$D$2:$D$400,$P98,Mastersheet!$C$2:$C$400,$Q98)/1000 -> 0 | M98: =SUMIFS(Mastersheet!$N$2:$N$400,Mastersheet!$D$2:$D$400,$P98,Mastersheet!$C$2:$C$400,$Q98)/1000 -> 0 | P98: Forderungen ggue. verbundenen Unternehmen | Q98: OA | R98: POS
E99: =IF($P$99="","",SUMIFS(Mastersheet!$F$2:$F$400,Mastersheet!$A$2:$A$400,$P$99)/1000) | F99: =IF($P$99="","",SUMIFS(Mastersheet!$G$2:$G$400,Mastersheet!$A$2:$A$400,$P$99)/1000) | G99: =IF($P$99="","",SUMIFS(Mastersheet!$H$2:$H$400,Mastersheet!$A$2:$A$400,$P$99)/1000) | H99: =IF($P$99="","",SUMIFS(Mastersheet!$I$2:$I$400,Mastersheet!$A$2:$A$400,$P$99)/1000) | I99: =IF($P$99="","",SUMIFS(Mastersheet!$J$2:$J$400,Mastersheet!$A$2:$A$400,$P$99)/1000) | J99: =IF($P$99="","",SUMIFS(Mastersheet!$K$2:$K$400,Mastersheet!$A$2:$A$400,$P$99)/1000) | K99: =IF($P$99="","",SUMIFS(Mastersheet!$L$2:$L$400,Mastersheet!$A$2:$A$400,$P$99)/1000) | L99: =IF($P$99="","",SUMIFS(Mastersheet!$M$2:$M$400,Mastersheet!$A$2:$A$400,$P$99)/1000) | M99: =IF($P$99="","",SUMIFS(Mastersheet!$N$2:$N$400,Mastersheet!$A$2:$A$400,$P$99)/1000) | Q99: Account | R99: KTO
E100: =IF($P$100="","",SUMIFS(Mastersheet!$F$2:$F$400,Mastersheet!$A$2:$A$400,$P$100)/1000) | F100: =IF($P$100="","",SUMIFS(Mastersheet!$G$2:$G$400,Mastersheet!$A$2:$A$400,$P$100)/1000) | G100: =IF($P$100="","",SUMIFS(Mastersheet!$H$2:$H$400,Mastersheet!$A$2:$A$400,$P$100)/1000) | H100: =IF($P$100="","",SUMIFS(Mastersheet!$I$2:$I$400,Mastersheet!$A$2:$A$400,$P$100)/1000) | I100: =IF($P$100="","",SUMIFS(Mastersheet!$J$2:$J$400,Mastersheet!$A$2:$A$400,$P$100)/1000) | J100: =IF($P$100="","",SUMIFS(Mastersheet!$K$2:$K$400,Mastersheet!$A$2:$A$400,$P$100)/1000) | K100: =IF($P$100="","",SUMIFS(Mastersheet!$L$2:$L$400,Mastersheet!$A$2:$A$400,$P$100)/1000) | L100: =IF($P$100="","",SUMIFS(Mastersheet!$M$2:$M$400,Mastersheet!$A$2:$A$400,$P$100)/1000) | M100: =IF($P$100="","",SUMIFS(Mastersheet!$N$2:$N$400,Mastersheet!$A$2:$A$400,$P$100)/1000) | Q100: Account | R100: KTO
E101: =IF($P$101="","",SUMIFS(Mastersheet!$F$2:$F$400,Mastersheet!$A$2:$A$400,$P$101)/1000) | F101: =IF($P$101="","",SUMIFS(Mastersheet!$G$2:$G$400,Mastersheet!$A$2:$A$400,$P$101)/1000) | G101: =IF($P$101="","",SUMIFS(Mastersheet!$H$2:$H$400,Mastersheet!$A$2:$A$400,$P$101)/1000) | H101: =IF($P$101="","",SUMIFS(Mastersheet!$I$2:$I$400,Mastersheet!$A$2:$A$400,$P$101)/1000) | I101: =IF($P$101="","",SUMIFS(Mastersheet!$J$2:$J$400,Mastersheet!$A$2:$A$400,$P$101)/1000) | J101: =IF($P$101="","",SUMIFS(Mastersheet!$K$2:$K$400,Mastersheet!$A$2:$A$400,$P$101)/1000) | K101: =IF($P$101="","",SUMIFS(Mastersheet!$L$2:$L$400,Mastersheet!$A$2:$A$400,$P$101)/1000) | L101: =IF($P$101="","",SUMIFS(Mastersheet!$M$2:$M$400,Mastersheet!$A$2:$A$400,$P$101)/1000) | M101: =IF($P$101="","",SUMIFS(Mastersheet!$N$2:$N$400,Mastersheet!$A$2:$A$400,$P$101)/1000) | Q101: Account | R101: KTO
E102: =IF($P$102="","",SUMIFS(Mastersheet!$F$2:$F$400,Mastersheet!$A$2:$A$400,$P$102)/1000) | F102: =IF($P$102="","",SUMIFS(Mastersheet!$G$2:$G$400,Mastersheet!$A$2:$A$400,$P$102)/1000) | G102: =IF($P$102="","",SUMIFS(Mastersheet!$H$2:$H$400,Mastersheet!$A$2:$A$400,$P$102)/1000) | H102: =IF($P$102="","",SUMIFS(Mastersheet!$I$2:$I$400,Mastersheet!$A$2:$A$400,$P$102)/1000) | I102: =IF($P$102="","",SUMIFS(Mastersheet!$J$2:$J$400,Mastersheet!$A$2:$A$400,$P$102)/1000) | J102: =IF($P$102="","",SUMIFS(Mastersheet!$K$2:$K$400,Mastersheet!$A$2:$A$400,$P$102)/1000) | K102: =IF($P$102="","",SUMIFS(Mastersheet!$L$2:$L$400,Mastersheet!$A$2:$A$400,$P$102)/1000) | L102: =IF($P$102="","",SUMIFS(Mastersheet!$M$2:$M$400,Mastersheet!$A$2:$A$400,$P$102)/1000) | M102: =IF($P$102="","",SUMIFS(Mastersheet!$N$2:$N$400,Mastersheet!$A$2:$A$400,$P$102)/1000) | Q102: Account | R102: KTO
E103: =IF($P$103="","",SUMIFS(Mastersheet!$F$2:$F$400,Mastersheet!$A$2:$A$400,$P$103)/1000) | F103: =IF($P$103="","",SUMIFS(Mastersheet!$G$2:$G$400,Mastersheet!$A$2:$A$400,$P$103)/1000) | G103: =IF($P$103="","",SUMIFS(Mastersheet!$H$2:$H$400,Mastersheet!$A$2:$A$400,$P$103)/1000) | H103: =IF($P$103="","",SUMIFS(Mastersheet!$I$2:$I$400,Mastersheet!$A$2:$A$400,$P$103)/1000) | I103: =IF($P$103="","",SUMIFS(Mastersheet!$J$2:$J$400,Mastersheet!$A$2:$A$400,$P$103)/1000) | J103: =IF($P$103="","",SUMIFS(Mastersheet!$K$2:$K$400,Mastersheet!$A$2:$A$400,$P$103)/1000) | K103: =IF($P$103="","",SUMIFS(Mastersheet!$L$2:$L$400,Mastersheet!$A$2:$A$400,$P$103)/1000) | L103: =IF($P$103="","",SUMIFS(Mastersheet!$M$2:$M$400,Mastersheet!$A$2:$A$400,$P$103)/1000) | M103: =IF($P$103="","",SUMIFS(Mastersheet!$N$2:$N$400,Mastersheet!$A$2:$A$400,$P$103)/1000) | Q103: Account | R103: KTO
E104: =IF($P$104="","",SUMIFS(Mastersheet!$F$2:$F$400,Mastersheet!$A$2:$A$400,$P$104)/1000) | F104: =IF($P$104="","",SUMIFS(Mastersheet!$G$2:$G$400,Mastersheet!$A$2:$A$400,$P$104)/1000) | G104: =IF($P$104="","",SUMIFS(Mastersheet!$H$2:$H$400,Mastersheet!$A$2:$A$400,$P$104)/1000) | H104: =IF($P$104="","",SUMIFS(Mastersheet!$I$2:$I$400,Mastersheet!$A$2:$A$400,$P$104)/1000) | I104: =IF($P$104="","",SUMIFS(Mastersheet!$J$2:$J$400,Mastersheet!$A$2:$A$400,$P$104)/1000) | J104: =IF($P$104="","",SUMIFS(Mastersheet!$K$2:$K$400,Mastersheet!$A$2:$A$400,$P$104)/1000) | K104: =IF($P$104="","",SUMIFS(Mastersheet!$L$2:$L$400,Mastersheet!$A$2:$A$400,$P$104)/1000) | L104: =IF($P$104="","",SUMIFS(Mastersheet!$M$2:$M$400,Mastersheet!$A$2:$A$400,$P$104)/1000) | M104: =IF($P$104="","",SUMIFS(Mastersheet!$N$2:$N$400,Mastersheet!$A$2:$A$400,$P$104)/1000) | Q104: Account | R104: KTO
...

Sheet Lead CF
C4: =Cockpit!$C$4 -> Template | E4: =Cockpit!C33 -> 44561 | F4: =Cockpit!D33 -> 44926 | G4: =Cockpit!E33 -> 45291 | H4: =Cockpit!F33 -> 45657 | I4: =Cockpit!G33 -> 45808 | J4: =Cockpit!H33 -> 45808 | K4: =Cockpit!I33 -> 46022 | L4: =Cockpit!J33 -> 46387 | ... N4: =Cockpit!L33 -> 47118 | P4: Bilanzveränderungen manuell zu ergänzen
C5: ="in T"&Cockpit!$C$5 -> in TEUR | E5: IST | F5: IST | G5: IST | H5: IST | I5: =Cockpit!G34 -> LTM | J5: =Cockpit!H34 -> YTD | K5: =Cockpit!I34 -> Plan | L5: =Cockpit!J34 -> Plan | M5: =Cockpit!K34 -> Plan | N5: =Cockpit!L34 -> Plan
D6: =Cockpit!$C$4 -> Template | E6: =Cockpit!C33 -> 44561 | F6: =Cockpit!D33 -> 44926 | G6: =Cockpit!E33 -> 45291 | H6: =Cockpit!F33 -> 45657 | I6: =Cockpit!G33 -> 45808 | J6: =Cockpit!H33 -> 45808 | K6: =Cockpit!I33 -> 46022 | L6: =Cockpit!J33 -> 46387 | ... N6: =Cockpit!L33 -> 47118 | P6: Bilanzveränderungen manuell zu ergänzen
D7: ="in k"&Cockpit!$C$5 -> in kEUR | E7: =Cockpit!D34 -> IST | F7: =Cockpit!D34 -> IST | G7: =Cockpit!E34 -> IST | H7: =Cockpit!F34 -> IST | I7: =Cockpit!G34 -> LTM | J7: =Cockpit!H34 -> YTD | K7: =Cockpit!I34 -> Plan | L7: =Cockpit!J34 -> Plan | M7: =Cockpit!K34 -> Plan | N7: =Cockpit!L34 -> Plan
C9: ='Lead PL'!C146 -> EBITDA | D9: ='Lead PL'!D146 -> EBITDA | F9: ='Lead PL'!F146 -> 0 | G9: ='Lead PL'!G146 -> 0 | H9: ='Lead PL'!H146 -> 0 | I9: ='Lead PL'!I146 -> 0 | J9: ='Lead PL'!J146 -> 0 | K9: ='Lead PL'!K146 -> 0 | L9: ='Lead PL'!L146 -> 0 | M9: ='Lead PL'!M146 -> 0 | N9: ='Lead PL'!N146 -> 0
C10: ='Lead PL'!C192 -> Ertragssteuern | D10: ='Lead PL'!D192 -> Income taxes | F10: ='Lead PL'!F192 -> 0 | G10: ='Lead PL'!G201 -> 0 | H10: ='Lead PL'!H201 -> 0 | I10: ='Lead PL'!I201 -> 0 | J10: ='Lead PL'!J201 -> 0 | K10: ='Lead PL'!K201 -> 0 | L10: ='Lead PL'!L201 -> 0 | M10: ='Lead PL'!M201 -> 0 | N10: ='Lead PL'!N201 -> 0
C11: ='Lead PL'!C201 -> Sonstige Steuern | D11: ='Lead PL'!D201 -> Other taxes | F11: ='Lead PL'!F201 -> 0 | G11: ='Lead PL'!G192 -> 0 | H11: ='Lead PL'!H192 -> 0 | I11: ='Lead PL'!I192 -> 0 | J11: ='Lead PL'!J192 -> 0 | K11: ='Lead PL'!K192 -> 0 | L11: ='Lead PL'!L192 -> 0 | M11: ='Lead PL'!M192 -> 0 | N11: ='Lead PL'!N192 -> 0
C13: ="∆ "&'Lead NA'!C40 -> ∆ Vorräte | D13: ="∆ "&'Lead NA'!D40 -> ∆ Inventories | F13: =-'Lead NA'!F40+'Lead NA'!E40 -> 0 | G13: =-'Lead NA'!G40+'Lead NA'!F40 -> 0 | H13: =-'Lead NA'!H40+'Lead NA'!G40 -> 0 | J13: =-'Lead NA'!I40+'Lead NA'!H40 -> 0 | K13: =-'Lead NA'!J40+'Lead NA'!H40 -> 0 | L13: =-'Lead NA'!K40+'Lead NA'!J40 -> 0 | M13: =-'Lead NA'!L40+'Lead NA'!K40 -> 0 | N13: =-'Lead NA'!M40+'Lead NA'!L40 -> 0
C14: ="∆ "&'Lead NA'!C49 -> ∆ Forderungen aus LuL | D14: ="∆ "&'Lead NA'!D49 -> ∆ Trade receivables | F14: =-'Lead NA'!F49+'Lead NA'!E49 -> 0 | G14: =-'Lead NA'!G49+'Lead NA'!F49 -> 0 | H14: =-'Lead NA'!H49+'Lead NA'!G49 -> 0 | J14: =-'Lead NA'!I49+'Lead NA'!H49 -> 0 | K14: =-'Lead NA'!J49+'Lead NA'!H49 -> 0 | L14: =-'Lead NA'!K49+'Lead NA'!J49 -> 0 | M14: =-'Lead NA'!L49+'Lead NA'!K49 -> 0 | N14: =-'Lead NA'!M49+'Lead NA'!L49 -> 0
C15: ="∆ "&'Lead NA'!C58 -> ∆ Verbindlichkeiten aus LuL | D15: ="∆ "&'Lead NA'!D58 -> ∆ Trade payables | F15: =-'Lead NA'!F58+'Lead NA'!E58 -> 0 | G15: =-'Lead NA'!G58+'Lead NA'!F58 -> 0 | H15: =-'Lead NA'!H58+'Lead NA'!G58 -> 0 | J15: =-'Lead NA'!I58+'Lead NA'!H58 -> 0 | K15: =-'Lead NA'!J58+'Lead NA'!H58 -> 0 | L15: =-'Lead NA'!K58+'Lead NA'!J58 -> 0 | M15: =-'Lead NA'!L58+'Lead NA'!K58 -> 0 | N15: =-'Lead NA'!M58+'Lead NA'!L58 -> 0
C16: ="∆ "&'Lead NA'!C67 -> ∆ Erhaltene Anzahlungen | D16: ="∆ "&'Lead NA'!D67 -> ∆ Advance payments received | F16: =-'Lead NA'!F67+'Lead NA'!E67 -> 0 | G16: =-'Lead NA'!G67+'Lead NA'!F67 -> 0 | H16: =-'Lead NA'!H67+'Lead NA'!G67 -> 0 | J16: =-'Lead NA'!I67+'Lead NA'!H67 -> 0
C17: ="∆ "&'Lead NA'!C76 -> ∆ Dummy 1 | D17: ="∆ "&'Lead NA'!D76 -> ∆ Dummy 1 | F17: =-'Lead NA'!F76+'Lead NA'!E76 -> 0 | G17: =-'Lead NA'!G76+'Lead NA'!F76 -> 0 | H17: =-'Lead NA'!H76+'Lead NA'!G76 -> 0 | J17: =-'Lead NA'!I76+'Lead NA'!H76 -> 0 | K17: =-'Lead NA'!J76+'Lead NA'!H76 -> 0 | L17: =-'Lead NA'!K76+'Lead NA'!J76 -> 0 | M17: =-'Lead NA'!L76+'Lead NA'!K76 -> 0 | N17: =-'Lead NA'!M76+'Lead NA'!L76 -> 0
C18: ="∆ "&'Lead NA'!C77 -> ∆ Dummy 2 | D18: ="∆ "&'Lead NA'!D77 -> ∆ Dummy 2 | F18: =-'Lead NA'!F77+'Lead NA'!E77 -> 0 | G18: =-'Lead NA'!G77+'Lead NA'!F77 -> 0 | H18: =-'Lead NA'!H77+'Lead NA'!G77 -> 0 | J18: =-'Lead NA'!I77+'Lead NA'!H77 -> 0 | K18: =-'Lead NA'!J77+'Lead NA'!H77 -> 0 | L18: =-'Lead NA'!K77+'Lead NA'!J77 -> 0 | M18: =-'Lead NA'!L77+'Lead NA'!K77 -> 0 | N18: =-'Lead NA'!M77+'Lead NA'!L77 -> 0
C19: ="∆ "&'Lead NA'!C78 -> ∆ Dummy 3 | D19: ="∆ "&'Lead NA'!D78 -> ∆ Dummy 3 | F19: =-'Lead NA'!F78+'Lead NA'!E78 -> 0 | G19: =-'Lead NA'!G78+'Lead NA'!F78 -> 0 | H19: =-'Lead NA'!H78+'Lead NA'!G78 -> 0 | J19: =-'Lead NA'!I78+'Lead NA'!H78 -> 0 | K19: =-'Lead NA'!J78+'Lead NA'!H78 -> 0 | L19: =-'Lead NA'!K78+'Lead NA'!J78 -> 0 | M19: =-'Lead NA'!L78+'Lead NA'!K78 -> 0 | N19: =-'Lead NA'!M78+'Lead NA'!L78 -> 0
C20: ="∆ "&'Lead NA'!C79 -> ∆ Trade Working Capital | D20: ="∆ "&'Lead NA'!D79 -> ∆ Trade working capital | F20: =SUM(F13:F19) -> 0 | G20: =SUM(G13:G19) -> 0 | H20: =SUM(H13:H19) -> 0 | I20: =SUM(I13:I19) -> 0 | J20: =SUM(J13:J19) -> 0 | K20: =SUM(K13:K19) -> 0 | L20: =SUM(L13:L19) -> 0 | M20: =SUM(M13:M19) -> 0 | N20: =SUM(N13:N19) -> 0
C21: ="∆ "&'Lead NA'!C80 -> ∆ Sonstige Vermögensgegenstände | D21: ="∆ "&'Lead NA'!D80 -> ∆ Other assets | F21: =-'Lead NA'!F80+'Lead NA'!E80 -> 0 | G21: =-'Lead NA'!G80+'Lead NA'!F80 -> 0 | H21: =-'Lead NA'!H80+'Lead NA'!G80 -> 0 | J21: =-'Lead NA'!I80+'Lead NA'!H80 -> 0 | K21: =-'Lead NA'!J80+'Lead NA'!H80 -> 0 | L21: =-'Lead NA'!K80+'Lead NA'!J80 -> 0 | M21: =-'Lead NA'!L80+'Lead NA'!K80 -> 0 | N21: =-'Lead NA'!M80+'Lead NA'!L80 -> 0
C22: ="∆ "&'Lead NA'!C89 -> ∆ Aktive Rechnungsabgrenzungsposten | D22: ="∆ "&'Lead NA'!D89 -> ∆ Prepaid expenses | F22: =-'Lead NA'!F89+'Lead NA'!E89 -> 0 | G22: =-'Lead NA'!G89+'Lead NA'!F89 -> 0 | H22: =-'Lead NA'!H89+'Lead NA'!G89 -> 0 | J22: =-'Lead NA'!I89+'Lead NA'!H89 -> 0 | K22: =-'Lead NA'!J89+'Lead NA'!H89 -> 0 | L22: =-'Lead NA'!K89+'Lead NA'!J89 -> 0 | M22: =-'Lead NA'!L89+'Lead NA'!K89 -> 0 | N22: =-'Lead NA'!M89+'Lead NA'!L89 -> 0
C23: ="∆ "&'Lead NA'!C98 -> ∆ Forderungen gegenüber verbundenen/beteiligten Unternehmen | D23: ="∆ "&'Lead NA'!D98 -> ∆ Receivables from affiliated/ participating companies | F23: =-'Lead NA'!F98+'Lead NA'!E98 -> 0 | G23: =-'Lead NA'!G98+'Lead NA'!F98 -> 0 | H23: =-'Lead NA'!H98+'Lead NA'!G98 -> 0 | J23: =-'Lead NA'!I98+'Lead NA'!H98 -> 0
