Workbook
Name ___mds_allowwriteback___: ""
Name ___mds_asyncwriteback___: FALSE
Name ___mds_first_cell___: #REF!
Name ___mds_last_dataset_cell__: "593~5"
Name ___mds_spreading___: FALSE
Name ___mds_view_data___: #REF!
Name _14N_0Umbuchun: [2]Anlagevermögen!#REF!
Name _15N_0Umbuchun: [2]Anlagevermögen!#REF!
Name _18N__Umbuchun: [2]Anlagevermögen!#REF!
Name _3_: [2]Anlagevermögen!#REF!
Name _8_0: [2]Anlagevermögen!#REF!
Name _9_0: [2]Anlagevermögen!#REF!
Name _DAT1: [3]Exportumsätze!#REF!
Name _DAT2: [3]Exportumsätze!#REF!
Name _DAT3: [3]Exportumsätze!#REF!
Name _DAT4: [3]Exportumsätze!#REF!
Name _DAT5: [3]Exportumsätze!#REF!
Name Art: #REF!
Name base_rate: #REF!
Name base_rate: #REF!
Name base_rate_monthly: #REF!
Name base_rate_monthly: #REF!
Name BraRepKumuliert: #REF!
Name cash_bf: #REF!
Name cash_bf: #REF!
Name cash_cf: #REF!
Name cash_cf: #REF!
Name completion: #REF!
Name completion: #REF!
Name Consultant_A: #REF!
Name Consultant_B: #REF!
Name ebitda: #REF!
Name ebitda: #REF!
Name exit_cash: #REF!
Name exit_cash: #REF!
Name exit_multiple: #REF!
Name exit_multiple: #REF!
Name exit_year: #REF!
Name exit_year: #REF!
Name gc_hint_new_document: #REF!
Name instrument_1: #REF!
Name instrument_1: #REF!
Name instrument_1_amount: #REF!
Name instrument_1_amount: #REF!
Name instrument_1_bf: #REF!
Name instrument_1_bf: #REF!
Name instrument_1_cf: #REF!
Name instrument_1_cf: #REF!
Name instrument_1_custom_pmt: #REF!
Name instrument_1_custom_pmt: #REF!
Name instrument_1_int_accrual: #REF!
Name instrument_1_int_accrual: #REF!
Name instrument_1_int_pmt: #REF!
Name instrument_1_int_pmt: #REF!
Name instrument_1_int_rate: #REF!
Name instrument_1_int_rate: #REF!
Name instrument_1_rollup: #REF!
Name instrument_1_rollup: #REF!
Name instrument_1_rollup_percent: #REF!
Name instrument_1_rollup_percent: #REF!

Sheet Disclaimer
B4: ="Project: "&Cockpit!C4 -> Project: Projekt Namur
B6: Status: Working Draft
B9: Databook Financial Due Diligence
B11: BakerTilly, #city#date#
B14: Disclaimer: This Databook is confidential and has been prepared exclusively for the benefit of the Client in connection with the Transaction and may not be disclosed, quoted, used or relied on for any other purpose or by any other party than the Client without the prior written consent of BT. This Databook is made available to the Client and we consent to the disclosure, provided that the client agress to non-reliance of this work-in-progress databook. Compensation claims of the Purchaser against BT for damages caused by negligence in connection with performance of the assignment are limited to EUR 4.000.000 (in words: Euro four million) for each damage event and for all damage events in total.

Sheet Cockpit
B3: Table labels | G3: = User Input
B4: Project name | C4: Projekt Namur
B5: Currency base code | C5: EUR | G5: = technische Hilfszelle --> nicht löschen
B7: Quelle: | C7: Datenraum/ eigene Analysen
B8: Source: | C8: Virtual Data Room/ Company Information
B10: Working Group
B11: Partner
B12: Manager
B13: Senior/Assistant
B16: Timeline parameter
B17: End of first historical period | C17: 44926
B18: Number of historical periods | C18: 3
B19: Label | C19: IST | D19: Adjust according to language(DEU/ ENG)
B21: CYT Begin Date | C21: 45658 | D21: =IF(C21<(EDATE(C17,24)),"CYT Begin Date must not be prior to historical date","ok") -> ok
B22: CYT Date | C22: 46022 | D22: =IF(TEXT($C$22,"TT.MM.")="31.12.","CYT date must not be December 31, check","ok") -> CYT date must not be December 31, check
B23: Label (Last twelve months) | C23: IST | D23: Aufgrund nachträglicher Datenlieferung LTM auf IST geändert, um weitere Änderung von Verlinkungen zu vermeiden
B24: Label (Current year trading) | C24: YTD
B25: Label (Year to go) | C25: YTG
B27: Label | C27: Plan
B31: Timeline (annual for PL and CF)
B32: Counter | D32: 1 | E32: =D32+1 -> 2 | F32: =E32+1 -> 3 | G32: =F32+1 -> 4 | H32: =G32+1 -> 5 | I32: =H32+1 -> 6 | J32: =I32+1 -> 7 | K32: =J32+1 -> 8 | L32: =K32+1 -> 9
B33: Date (Auto) | C33: =EDATE($C$17,-12) -> 44561 | D33: =IF(D$32<$C$18+1,EDATE($C$33,12*D$32),IF(OR(D$32=$C$18+1,D$32=$C$18+2),$C$22,IF(D$32>$C$18+2,EDATE($C$33,(D$32-2)*12)))) -> 44926 | E33: =IF(E$32<$C$18+1,EDATE($C$33,12*E$32),IF(OR(E$32=$C$18+1,E$32=$C$18+2),$C$22,IF(E$32>$C$18+2,EDATE($C$33,(E$32-2)*12)))) -> 45291 | F33: =IF(F$32<$C$18+1,EDATE($C$33,12*F$32),IF(OR(F$32=$C$18+1,F$32=$C$18+2),$C$22,IF(F$32>$C$18+2,EDATE($C$33,(F$32-2)*12)))) -> 45657 | G33: =IF(G$32<$C$18+1,EDATE($C$33,12*G$32),IF(OR(G$32=$C$18+1,G$32=$C$18+2),$C$22,IF(G$32>$C$18+2,EDATE($C$33,(G$32-2)*12)))) -> 46022 | H33: =IF(H$32<$C$18+1,EDATE($C$33,12*H$32),IF(OR(H$32=$C$18+1,H$32=$C$18+2),$C$22,IF(H$32>$C$18+2,EDATE($C$33,(H$32-2)*12)))) -> 46022 | I33: =IF(I$32<$C$18+1,EDATE($C$33,12*I$32),IF(OR(I$32=$C$18+1,I$32=$C$18+2),$C$22,IF(I$32>$C$18+2,EDATE($C$33,(I$32-2)*12)))) -> 46022 | J33: =IF(J$32<$C$18+1,EDATE($C$33,12*J$32),IF(OR(J$32=$C$18+1,J$32=$C$18+2),$C$22,IF(J$32>$C$18+2,EDATE($C$33,(J$32-2)*12)))) -> 46387 | K33: =IF(K$32<$C$18+1,EDATE($C$33,12*K$32),IF(OR(K$32=$C$18+1,K$32=$C$18+2),$C$22,IF(K$32>$C$18+2,EDATE($C$33,(K$32-2)*12)))) -> 46752 | L33: =IF(L$32<$C$18+1,EDATE($C$33,12*L$32),IF(OR(L$32=$C$18+1,L$32=$C$18+2),$C$22,IF(L$32>$C$18+2,EDATE($C$33,(L$32-2)*12)))) -> 47118
B34: Label | C34: =$C$19 -> IST | D34: =IF(D$32<=$C$18,$C$19,IF(D$32=$C$18+1,$C$23,IF(D$32=$C$18+2,$C$24,$C$27))) -> IST | E34: =IF(E$32<=$C$18,$C$19,IF(E$32=$C$18+1,$C$23,IF(E$32=$C$18+2,$C$24,$C$27))) -> IST | F34: =IF(F$32<=$C$18,$C$19,IF(F$32=$C$18+1,$C$23,IF(F$32=$C$18+2,$C$24,$C$27))) -> IST | G34: =IF(G$32<=$C$18,$C$19,IF(G$32=$C$18+1,$C$23,IF(G$32=$C$18+2,$C$24,$C$27))) -> IST | H34: =IF(H$32<=$C$18,$C$19,IF(H$32=$C$18+1,$C$23,IF(H$32=$C$18+2,$C$24,$C$27))) -> YTD | I34: =IF(I$32<=$C$18,$C$19,IF(I$32=$C$18+1,$C$23,IF(I$32=$C$18+2,$C$24,$C$27))) -> Plan | J34: =IF(J$32<=$C$18,$C$19,IF(J$32=$C$18+1,$C$23,IF(J$32=$C$18+2,$C$24,$C$27))) -> Plan | K34: =IF(K$32<=$C$18,$C$19,IF(K$32=$C$18+1,$C$23,IF(K$32=$C$18+2,$C$24,$C$27))) -> Plan | L34: =IF(L$32<=$C$18,$C$19,IF(L$32=$C$18+1,$C$23,IF(L$32=$C$18+2,$C$24,$C$27))) -> Plan
B37: Timeline (annual for BS)
B38: Counter | D38: 1 | E38: =D38+1 -> 2 | F38: =E38+1 -> 3 | G38: =F38+1 -> 4 | H38: =G38+1 -> 5 | I38: =H38+1 -> 6 | J38: =I38+1 -> 7 | K38: =J38+1 -> 8
B39: Date | C39: =EDATE($C$17,-12) -> 44561 | D39: =IF(D$38<$C$18+1,EDATE($C$39,12*D$38),IF(D$38=$C$18+1,$C$22,IF(D$38>$C$18+1,EDATE($C$39,(D$38-1)*12)))) -> 44926 | E39: =IF(E$38<$C$18+1,EDATE($C$39,12*E$38),IF(E$38=$C$18+1,$C$22,IF(E$38>$C$18+1,EDATE($C$39,(E$38-1)*12)))) -> 45291 | F39: =IF(F$38<$C$18+1,EDATE($C$39,12*F$38),IF(F$38=$C$18+1,$C$22,IF(F$38>$C$18+1,EDATE($C$39,(F$38-1)*12)))) -> 45657 | G39: =IF(G$38<$C$18+1,EDATE($C$39,12*G$38),IF(G$38=$C$18+1,$C$22,IF(G$38>$C$18+1,EDATE($C$39,(G$38-1)*12)))) -> 46022 | H39: =IF(H$38<$C$18+1,EDATE($C$39,12*H$38),IF(H$38=$C$18+1,$C$22,IF(H$38>$C$18+1,EDATE($C$39,(H$38-1)*12)))) -> 46022 | I39: =IF(I$38<$C$18+1,EDATE($C$39,12*I$38),IF(I$38=$C$18+1,$C$22,IF(I$38>$C$18+1,EDATE($C$39,(I$38-1)*12)))) -> 46387 | J39: =IF(J$38<$C$18+1,EDATE($C$39,12*J$38),IF(J$38=$C$18+1,$C$22,IF(J$38>$C$18+1,EDATE($C$39,(J$38-1)*12)))) -> 46752 | K39: =IF(K$38<$C$18+1,EDATE($C$39,12*K$38),IF(K$38=$C$18+1,$C$22,IF(K$38>$C$18+1,EDATE($C$39,(K$38-1)*12)))) -> 47118
B40: Label | C40: =$C$19 -> IST | D40: =IF(D$38<=$C$18,$C$19,IF(D$38=$C$18+1,$C$19,$C$27)) -> IST | E40: =IF(E$38<=$C$18,$C$19,IF(E$38=$C$18+1,$C$19,$C$27)) -> IST | F40: =IF(F$38<=$C$18,$C$19,IF(F$38=$C$18+1,$C$19,$C$27)) -> IST | G40: =IF(G$38<=$C$18,$C$19,IF(G$38=$C$18+1,$C$19,$C$27)) -> IST | H40: =IF(H$38<=$C$18,$C$19,IF(H$38=$C$18+1,$C$19,$C$27)) -> Plan | I40: =IF(I$38<=$C$18,$C$19,IF(I$38=$C$18+1,$C$19,$C$27)) -> Plan | J40: =IF(J$38<=$C$18,$C$19,IF(J$38=$C$18+1,$C$19,$C$27)) -> Plan | K40: =IF(K$38<=$C$18,$C$19,IF(K$38=$C$18+1,$C$19,$C$27)) -> Plan
B43: Timeline (monthly)
B44: Counter | D44: 1 | E44: =D44+1 -> 2 | F44: =E44+1 -> 3 | G44: =F44+1 -> 4 | H44: =G44+1 -> 5 | I44: =H44+1 -> 6 | J44: =I44+1 -> 7 | K44: =J44+1 -> 8 | L44: =K44+1 -> 9 | ... CI44: =CH44+1 -> 84
B45: Date | C45: =EDATE($C$17,-12) -> 44561 | D45: =EDATE($C$45,D$44) -> 44592 | E45: =EDATE($C$45,E$44) -> 44620 | F45: =EDATE($C$45,F$44) -> 44651 | G45: =EDATE($C$45,G$44) -> 44681 | H45: =EDATE($C$45,H$44) -> 44712 | I45: =EDATE($C$45,I$44) -> 44742 | J45: =EDATE($C$45,J$44) -> 44773 | K45: =EDATE($C$45,K$44) -> 44804 | ... CI45: =EDATE($C$45,CI$44) -> 47118
B46: Label | C46: =$C$19 -> IST | D46: =IF(D$45<=$C$22,$C$19,$C$27) -> IST | E46: =IF(E$45<=$C$22,$C$19,$C$27) -> IST | F46: =IF(F$45<=$C$22,$C$19,$C$27) -> IST | G46: =IF(G$45<=$C$22,$C$19,$C$27) -> IST | H46: =IF(H$45<=$C$22,$C$19,$C$27) -> IST | I46: =IF(I$45<=$C$22,$C$19,$C$27) -> IST | J46: =IF(J$45<=$C$22,$C$19,$C$27) -> IST | K46: =IF(K$45<=$C$22,$C$19,$C$27) -> IST | ... CI46: =IF(CI$45<=$C$22,$C$19,$C$27) -> Plan

Sheet Datengrundlage
B2: Deutsch: | F2: Manuell Anpassen
B3: =Cockpit!$C$4 -> Projekt Namur | C3: =Cockpit!D33 -> 44926 | D3: =Cockpit!E33 -> 45291 | E3: =Cockpit!F33 -> 45657 | F3: =Cockpit!G33 -> 46022
B6: Heinz Meise GmbH
B7: Jahresabschlüsse (geprüft) | C7: ja | D7: ja | E7: ja | F7: -
B8: Summen- und Saldenlisten (SuSas) - monatlich | C8: nein | D8: ja | E8: ja | F8: ja
B9: Betriebswirtschaftliche Auswertungen (BWAs) - monatlich | C9: ja | D9: ja | E9: ja | F9: ja
B10: Umsatzdaten und ausgewählte KPIs | C10: ja | D10: ja | E10: ja | F10: ja
B11: Detailaufrisse und Controlling-/ERP-Auswertungen | C11: ja | D11: ja | E11: ja | F11: nein
B12: Weitere Auskünfte zu ausgewählten Sachverhalten | D12: ja
B14: Entity 2
B15: Jahresabschlüsse (ungeprüft) | C15: ja | D15: ja | E15: ja | F15: -
B16: Summen- und Saldenlisten (SuSas) - monatlich | C16: ja | D16: ja | E16: ja | F16: ja
B17: Betriebswirtschaftliche Auswertungen (BWAs) - monatlich | C17: ja | D17: ja | E17: ja | F17: ja
B18: Umsatzdaten und ausgewählte KPIs | C18: ja | D18: ja | E18: ja | F18: ja
B19: Detailaufrisse und Controlling-/ERP-Auswertungen | C19: - | D19: - | E19: - | F19: -
B20: Weitere Auskünfte zu ausgewählten Sachverhalten | D20: ja
B22: Entity 3
B23: Jahresabschlüsse (ungeprüft) | C23: ja | D23: ja | E23: ja | F23: -
B24: Summen- und Saldenlisten (SuSas) - monatlich | C24: ja | D24: ja | E24: ja | F24: ja
B25: Betriebswirtschaftliche Auswertungen (BWAs) - monatlich | C25: ja | D25: ja | E25: ja | F25: ja
B26: Umsatzdaten und ausgewählte KPIs | C26: ja | D26: ja | E26: ja | F26: ja
B27: Detailaufrisse und Controlling-/ERP-Auswertungen | C27: - | D27: - | E27: - | F27: -
B28: Weitere Auskünfte zu ausgewählten Sachverhalten | D28: ja
B30: Entity 4
B31: Jahresabschlüsse (ungeprüft) | C31: ja | D31: ja | E31: ja | F31: -
B32: Summen- und Saldenlisten (SuSas) - monatlich | C32: ja | D32: ja | E32: ja | F32: ja
B33: Betriebswirtschaftliche Auswertungen (BWAs) - monatlich | C33: ja | D33: ja | E33: ja | F33: ja
B34: Umsatzdaten und ausgewählte KPIs | C34: ja | D34: ja | E34: ja | F34: ja
B35: Detailaufrisse und Controlling-/ERP-Auswertungen | C35: - | D35: - | E35: - | F35: -
B36: Weitere Auskünfte zu ausgewählten Sachverhalten | D36: ja
B38: ="Quelle: "&Cockpit!$C$7 -> Quelle: Datenraum/ eigene Analysen

Sheet Lead >>

Sheet Lead PL
C1: Technische Zeile --> nicht löschen | D1: Technische Zeile --> nicht löschen | E1: =IFERROR(E4,E6) -> 44561 | F1: =IFERROR(F4,F6) -> 44926 | G1: =IFERROR(G4,G6) -> 45291 | H1: =IFERROR(H4,H6) -> 45657 | I1: =IFERROR(I4,I6) -> 46022 | J1: =IFERROR(J4,J6) -> 46022 | K1: =IFERROR(K4,K6) -> 46022 | L1: =IFERROR(L4,L6) -> 46387 | ... N1: =IFERROR(N4,N6) -> 47118
G3: =G9/F9-1 -> -0.083355024 | H3: =H9/G9-1 -> 0.087731686 | I3: =I9/H9-1 -> -0.099053949
C4: =Cockpit!$C$4 -> Projekt Namur | E4: =Cockpit!C33 -> 44561 | F4: =Cockpit!D33 -> 44926 | G4: =Cockpit!E33 -> 45291 | H4: =Cockpit!F33 -> 45657 | I4: =Cockpit!G33 -> 46022 | J4: =Cockpit!H33 -> 46022 | K4: =Cockpit!I33 -> 46022 | L4: =Cockpit!J33 -> 46387 | ... N4: =Cockpit!L33 -> 47118 | P4: CAGR | Q4: CAGR
C5: ="in T"&Cockpit!$C$5 -> in TEUR | E5: =Cockpit!C34 -> IST | F5: =Cockpit!D34 -> IST | G5: =Cockpit!E34 -> IST | H5: =Cockpit!F34 -> IST | I5: =Cockpit!G34 -> IST | J5: =Cockpit!H34 -> YTD | K5: =Cockpit!I34 -> Plan | L5: =Cockpit!J34 -> Plan | ... N5: =Cockpit!L34 -> Plan | P5: IST | Q5: =Cockpit!$C$27 -> Plan
D6: =Cockpit!$C$4 -> Projekt Namur | E6: =Cockpit!C33 -> 44561 | F6: =Cockpit!D33 -> 44926 | G6: =Cockpit!E33 -> 45291 | H6: =Cockpit!F33 -> 45657 | I6: =Cockpit!G33 -> 46022 | J6: =Cockpit!H33 -> 46022 | K6: =Cockpit!I33 -> 46022 | L6: =Cockpit!J33 -> 46387 | ... N6: =Cockpit!L33 -> 47118 | P6: CAGR | Q6: CAGR
D7: ="in k"&Cockpit!$C$5 -> in kEUR | E7: =Cockpit!C34 -> IST | F7: =Cockpit!D34 -> IST | G7: =Cockpit!E34 -> IST | H7: =Cockpit!F34 -> IST | I7: =Cockpit!G34 -> IST | J7: =Cockpit!H34 -> YTD | K7: =Cockpit!I34 -> Plan | L7: =Cockpit!J34 -> Plan | ... N7: =Cockpit!L34 -> Plan | P7: =Cockpit!$C$19 -> IST | Q7: =Cockpit!$C$27 -> Plan | T7: Classification BT
C9: Umsatzerlöse | D9: Revenues | F9: ='P&L (Annual Report)'!E23/1000 -> 16709.025 | G9: =-SUMIF('Trial Balance (Susa)'!D:D,"*"&$T9&"*",'Trial Balance (Susa)'!G:G)/1000 -> 15316.244 | H9: =-SUMIF('Trial Balance (Susa)'!D:D,"*"&$T9&"*",'Trial Balance (Susa)'!H:H)/1000 -> 16659.963 | I9: =-SUMIF('Trial Balance (Susa)'!D:D,"*"&$T9&"*",'Trial Balance (Susa)'!I:I)/1000 -> 15009.728 | J9: =-SUMIF('Trial Balance (Susa)'!D:D,"*"&$T9&"*",'Trial Balance (Susa)'!J:J)/1000 -> 0 | P9: =IFERROR(((H9/F9)^(1/(($H$1-$F$1)/365)))-1,"n/a") -> -0.0014671778 | Q9: =IFERROR(((N9/H9)^(1/(($N$1-$H$1)/365)))-1,"n/a") -> -1 | T9: /profit and loss/income/sales
C10: Erlöse Produktion | F10: ='P&L (Annual Report)'!E11/1000+3534.5 -> 9038.8983 | G10: =-'Trial Balance (Susa)'!G305/1000+2617 -> 9106.0935 | H10: =-'Trial Balance (Susa)'!H305/1000+4348.5 -> 11306.728 | I10: =-'Trial Balance (Susa)'!I305/1000 -> 6124.283 | T10: Produktion | V10: Check Verlinkungen der Umsatzerlöse und Umgliederung aus nicht steuerbaren Umsätzen
C11: Erlöse Handel | F11: ='P&L (Annual Report)'!E12/1000+62.6 -> 7415.4844 | G11: =-SUM('Trial Balance (Susa)'!G306)/1000+66.1 -> 6054.461 | H11: =-SUM('Trial Balance (Susa)'!H306)/1000+6 -> 5076.7472 | I11: =-SUM('Trial Balance (Susa)'!I306)/1000 -> 4016.1017 | T11: Handel
C12: Erlöse Dienstleistung | F12: =SUM(F13:F17) -> 457.76717 | G12: =SUM(G13:G17) -> 364.8482 | H12: =SUM(H13:H17) -> 452.93157 | I12: =SUM(I13:I17) -> 191.98364
C13: Erlöse Sterilisation | F13: ='P&L (Annual Report)'!E13/1000+243.5 -> 323.4889 | G13: =-SUM('Trial Balance (Susa)'!G307)/1000+172.5 -> 249.6488 | H13: =-SUM('Trial Balance (Susa)'!H307)/1000+236.8 -> 318.06137 | I13: =-SUM('Trial Balance (Susa)'!I307)/1000 -> 96.27319 | T13: Sterilisation
C14: Erlöse Wartung | F14: ='P&L (Annual Report)'!E14/1000 -> 50.2274 | G14: =-SUM('Trial Balance (Susa)'!G308)/1000 -> 64.5155 | H14: =-SUM('Trial Balance (Susa)'!H308)/1000 -> 88.5138 | I14: =-SUM('Trial Balance (Susa)'!I308)/1000 -> 63.3968 | T14: Wartung
C15: Erlöse Miete | F15: ='P&L (Annual Report)'!E15/1000 -> 42.77582 | G15: =-SUM('Trial Balance (Susa)'!G309)/1000 -> 48.32 | H15: =-SUM('Trial Balance (Susa)'!H309)/1000 -> 41.699 | I15: =-SUM('Trial Balance (Susa)'!I309)/1000 -> 28.8433 | T15: Miete
C16: Erlöse Abfallverwertung | F16: ='P&L (Annual Report)'!E16/1000 -> 2.29225 | G16: =-SUM('Trial Balance (Susa)'!G310)/1000 -> 1.3954 | H16: =-SUM('Trial Balance (Susa)'!H310)/1000 -> 3.4574 | I16: =-SUM('Trial Balance (Susa)'!I310)/1000 -> 3.0796 | T16: Abfall
C17: Sonstige Erlöse | F17: ='P&L (Annual Report)'!E7/1000+38.6 -> 38.9828 | G17: =-'Trial Balance (Susa)'!G302/1000+0.5 -> 0.9685 | H17: =-'Trial Balance (Susa)'!H302/1000+0.6 -> 1.2 | I17: =-'Trial Balance (Susa)'!I302/1000 -> 0.39075 | T17: Sonstige Dienstleistung
C18: Skonti und Boni | F18: {=SUM('P&L (Annual Report)'!E17:E22/1000)} -> -202.80217 | G18: =-('Trial Balance (Susa)'!G315+'Trial Balance (Susa)'!G316+'Trial Balance (Susa)'!G317+'Trial Balance (Susa)'!G318+'Trial Balance (Susa)'!G319)/1000 -> -207.36748 | H18: =-('Trial Balance (Susa)'!H315+'Trial Balance (Susa)'!H316+'Trial Balance (Susa)'!H317+'Trial Balance (Susa)'!H318+'Trial Balance (Susa)'!H319)/1000 -> -172.40615 | I18: =-('Trial Balance (Susa)'!I315+'Trial Balance (Susa)'!I316+'Trial Balance (Susa)'!I317+'Trial Balance (Susa)'!I318+'Trial Balance (Susa)'!I319)/1000 -> -167.08108 | T18: Skonti
C19: Bestandsveränderung | D19: Change in inventory | F19: ='P&L (Annual Report)'!E28/1000 -> -292.27995 | G19: =-SUMIF('Trial Balance (Susa)'!D:D,"*"&$T19&"*",'Trial Balance (Susa)'!G:G)/1000 -> 199.57713 | H19: =-SUMIF('Trial Balance (Susa)'!D:D,"*"&$T19&"*",'Trial Balance (Susa)'!H:H)/1000 -> 350.79514 | I19: =-SUMIF('Trial Balance (Susa)'!D:D,"*"&$T19&"*",'Trial Balance (Susa)'!I:I)/1000 -> 226.19016 | J19: =-SUMIF('Trial Balance (Susa)'!D:D,"*"&$T19&"*",'Trial Balance (Susa)'!J:J)/1000 -> 0 | P19: =IFERROR(((H19/F19)^(1/(($H$1-$F$1)/365)))-1,"n/a") -> n/a | Q19: =IFERROR(((N19/H19)^(1/(($N$1-$H$1)/365)))-1,"n/a") -> -1 | T19: /profit and loss/income/increase in inventory
C20: Aktivierte Eigenleistungen | D20: Own work capitalized | G20: =-SUMIF('Trial Balance (Susa)'!D:D,"*"&$T20&"*",'Trial Balance (Susa)'!G:G)/1000 -> 0 | H20: =-SUMIF('Trial Balance (Susa)'!D:D,"*"&$T20&"*",'Trial Balance (Susa)'!H:H)/1000 -> 0 | I20: =-SUMIF('Trial Balance (Susa)'!D:D,"*"&$T20&"*",'Trial Balance (Susa)'!I:I)/1000 -> 0 | J20: =-SUMIF('Trial Balance (Susa)'!D:D,"*"&$T20&"*",'Trial Balance (Susa)'!J:J)/1000 -> 0 | P20: =IFERROR(((H20/F20)^(1/(($H$1-$F$1)/365)))-1,"n/a") -> n/a | Q20: =IFERROR(((N20/H20)^(1/(($N$1-$H$1)/365)))-1,"n/a") -> n/a | T20: /profit and loss/income/own work capitalised
C21: Dummy 1 | D21: Dummy 1 | P21: =IFERROR(((H21/F21)^(1/(($H$1-$F$1)/365)))-1,"n/a") -> n/a | Q21: =IFERROR(((N21/H21)^(1/(($N$1-$H$1)/365)))-1,"n/a") -> n/a
C22: Dummy 2 | D22: Dummy 2 | P22: =IFERROR(((H22/F22)^(1/(($H$1-$F$1)/365)))-1,"n/a") -> n/a | Q22: =IFERROR(((N22/H22)^(1/(($N$1-$H$1)/365)))-1,"n/a") -> n/a
C23: Dummy 3 | D23: Dummy 3 | P23: =IFERROR(((H23/F23)^(1/(($H$1-$F$1)/365)))-1,"n/a") -> n/a | Q23: =IFERROR(((N23/H23)^(1/(($N$1-$H$1)/365)))-1,"n/a") -> n/a
C24: Gesamtleistung | D24: Total output | E24: =SUM(E9:E23) -> 0 | F24: =F9+F19 -> 16416.745 | G24: =G9+G19 -> 15515.821 | H24: =H9+H19 -> 17010.759 | I24: =I9+I19 -> 15235.918 | J24: =SUM(J9:J23) -> 0 | K24: =SUM(K9:K23) -> 0 | L24: =SUM(L9:L23) -> 0 | M24: =SUM(M9:M23) -> 0 | N24: =SUM(N9:N23) -> 0 | P24: =IFERROR(((H24/F24)^(1/(($H$1-$F$1)/365)))-1,"n/a") -> 0.017906198 | Q24: =IFERROR(((N24/H24)^(1/(($N$1-$H$1)/365)))-1,"n/a") -> -1
C25: Materialaufwand | D25: Cost of materials | F25: =-'P&L (Annual Report)'!E66/1000 -> -7633.1262 | G25: =-SUMIF('Trial Balance (Susa)'!D:D,"*"&$T25&"*",'Trial Balance (Susa)'!G:G)/1000 -> -8086.5024 | H25: =-SUMIF('Trial Balance (Susa)'!D:D,"*"&$T25&"*",'Trial Balance (Susa)'!H:H)/1000 -> -8397.8874 | I25: =-SUMIF('Trial Balance (Susa)'!D:D,"*"&$T25&"*",'Trial Balance (Susa)'!I:I)/1000 -> -7361.7847 | J25: =-SUMIF('Trial Balance (Susa)'!D:D,"*"&$T25&"*",'Trial Balance (Susa)'!J:J)/1000 -> 0 | P25: =IFERROR(((H25/F25)^(1/(($H$1-$F$1)/365)))-1,"n/a") -> 0.048830815 | Q25: =IFERROR(((N25/H25)^(1/(($N$1-$H$1)/365)))-1,"n/a") -> -1 | T25: /profit and loss/expense/material expense
C26: RHB-Aufwand | D26: Dummy 1 | F26: =-SUM('Trial Balance (Susa)'!E99,'Trial Balance (Susa)'!E104:E113)/1000 -> -7148.9266 | G26: =-SUM('Trial Balance (Susa)'!G99,'Trial Balance (Susa)'!G104:G113)/1000 -> -7440.4885 | H26: =-SUM('Trial Balance (Susa)'!H99,'Trial Balance (Susa)'!H104:H113)/1000 -> -7745.9163 | I26: =-SUM('Trial Balance (Susa)'!I99,'Trial Balance (Susa)'!I104:I113)/1000 -> -6854.7081 | P26: =IFERROR(((H26/F26)^(1/(($H$1-$F$1)/365)))-1,"n/a") -> 0.040859614 | Q26: =IFERROR(((N26/H26)^(1/(($N$1-$H$1)/365)))-1,"n/a") -> -1
C27: Fremdleistungen | D27: Dummy 2 | F27: =-SUM('Trial Balance (Susa)'!E100:E103)/1000 -> -484.19962 | G27: =-SUM('Trial Balance (Susa)'!G100:G103)/1000 -> -646.01391 | H27: =-SUM('Trial Balance (Susa)'!H100:H103)/1000 -> -651.97105 | I27: =-SUM('Trial Balance (Susa)'!I100:I103)/1000 -> -507.07659 | P27: =IFERROR(((H27/F27)^(1/(($H$1-$F$1)/365)))-1,"n/a") -> 0.16014844 | Q27: =IFERROR(((N27/H27)^(1/(($N$1-$H$1)/365)))-1,"n/a") -> -1
C28: Dummy 3 | D28: Dummy 3 | P28: =IFERROR(((H28/F28)^(1/(($H$1-$F$1)/365)))-1,"n/a") -> n/a | Q28: =IFERROR(((N28/H28)^(1/(($N$1-$H$1)/365)))-1,"n/a") -> n/a
C29: Rohergebnis | D29: Gross profit | E29: =SUM(E24:E28) -> 0 | F29: =SUM(F24:F28) -> 1150.4924 | G29: =SUM(G24:G28) -> -657.18405 | H29: =SUM(H24:H28) -> 214.98382 | I29: =SUM(I24:I28) -> 512.34907 | J29: =SUM(J24:J28) -> 0 | K29: =SUM(K24:K28) -> 0 | L29: =SUM(L24:L28) -> 0 | ... N29: =SUM(N24:N28) -> 0 | P29: =IFERROR(((H29/F29)^(1/(($H$1-$F$1)/365)))-1,"n/a") -> -0.56722787 | Q29: =IFERROR(((N29/H29)^(1/(($N$1-$H$1)/365)))-1,"n/a") -> -1
C30: Personalaufwand | D30: Personnel expenses | F30: =-'P&L (Annual Report)'!E96/1000 -> -3564.1972 | G30: =-SUMIF('Trial Balance (Susa)'!D:D,"*"&$T30&"*",'Trial Balance (Susa)'!G:G)/1000 -> -3758.9843 | H30: =-SUMIF('Trial Balance (Susa)'!D:D,"*"&$T30&"*",'Trial Balance (Susa)'!H:H)/1000 -> -4522.3511 | I30: =-SUMIF('Trial Balance (Susa)'!D:D,"*"&$T30&"*",'Trial Balance (Susa)'!I:I)/1000 -> -4225.827 | J30: =-SUMIF('Trial Balance (Susa)'!D:D,"*"&$T30&"*",'Trial Balance (Susa)'!J:J)/1000 -> 0 | P30: =IFERROR(((H30/F30)^(1/(($H$1-$F$1)/365)))-1,"n/a") -> 0.12623896 | Q30: =IFERROR(((N30/H30)^(1/(($N$1-$H$1)/365)))-1,"n/a") -> -1 | T30: /profit and loss/expense/personnel expense
C31: Miet- und Grundstücksaufwendungen | D31: Premise costs | F31: =-'P&L (Annual Report)'!E102/1000-'P&L (Annual Report)'!E104/1000 -> -346.10809 | G31: =-SUMIF('Trial Balance (Susa)'!D:D,"*"&$T31&"*",'Trial Balance (Susa)'!G:G)/1000 -> -341.33094 | H31: =-SUMIF('Trial Balance (Susa)'!D:D,"*"&$T31&"*",'Trial Balance (Susa)'!H:H)/1000 -> -422.98253 | I31: =-SUMIF('Trial Balance (Susa)'!D:D,"*"&$T31&"*",'Trial Balance (Susa)'!I:I)/1000 -> -349.32933 | J31: =-SUMIF('Trial Balance (Susa)'!D:D,"*"&$T31&"*",'Trial Balance (Susa)'!J:J)/1000 -> 0 | P31: =IFERROR(((H31/F31)^(1/(($H$1-$F$1)/365)))-1,"n/a") -> 0.10533967 | Q31: =IFERROR(((N31/H31)^(1/(($N$1-$H$1)/365)))-1,"n/a") -> -1 | T31: /profit and loss/expense/other expense/premise costs
C32: Reparaturen und Instandhaltungen | D32: Repair and maintenance | F32: =-'P&L (Annual Report)'!E112/1000 -> -117.49203 | G32: =-SUMIF('Trial Balance (Susa)'!D:D,"*"&$T32&"*",'Trial Balance (Susa)'!G:G)/1000 -> -124.28149 | H32: =-SUMIF('Trial Balance (Susa)'!D:D,"*"&$T32&"*",'Trial Balance (Susa)'!H:H)/1000 -> -133.31281 | I32: =-SUMIF('Trial Balance (Susa)'!D:D,"*"&$T32&"*",'Trial Balance (Susa)'!I:I)/1000 -> -112.53349 | J32: =-SUMIF('Trial Balance (Susa)'!D:D,"*"&$T32&"*",'Trial Balance (Susa)'!J:J)/1000 -> 0 | P32: =IFERROR(((H32/F32)^(1/(($H$1-$F$1)/365)))-1,"n/a") -> 0.065109385 | Q32: =IFERROR(((N32/H32)^(1/(($N$1-$H$1)/365)))-1,"n/a") -> -1 | T32: /profit and loss/expense/other expense/repair and maintenance
C33: Vertriebskosten | D33: Sales costs | F33: 0 | G33: =-SUMIF('Trial Balance (Susa)'!D:D,"*"&$T33&"*",'Trial Balance (Susa)'!G:G)/1000 -> 0 | H33: =-SUMIF('Trial Balance (Susa)'!D:D,"*"&$T33&"*",'Trial Balance (Susa)'!H:H)/1000 -> 0 | I33: =-SUMIF('Trial Balance (Susa)'!D:D,"*"&$T33&"*",'Trial Balance (Susa)'!I:I)/1000 -> 0 | J33: =-SUMIF('Trial Balance (Susa)'!D:D,"*"&$T33&"*",'Trial Balance (Susa)'!J:J)/1000 -> 0 | P33: =IFERROR(((H33/F33)^(1/(($H$1-$F$1)/365)))-1,"n/a") -> n/a | Q33: =IFERROR(((N33/H33)^(1/(($N$1-$H$1)/365)))-1,"n/a") -> n/a | T33: /profit and loss/expense/other expense/sales costs
C34: Kosten der Warenabgabe | D34: Delivery costs | F34: =-'P&L (Annual Report)'!E183/1000 -> -341.11215 | G34: =-SUMIF('Trial Balance (Susa)'!D:D,"*"&$T34&"*",'Trial Balance (Susa)'!G:G)/1000 -> -285.42781 | H34: =-SUMIF('Trial Balance (Susa)'!D:D,"*"&$T34&"*",'Trial Balance (Susa)'!H:H)/1000 -> -301.38343 | I34: =-SUMIF('Trial Balance (Susa)'!D:D,"*"&$T34&"*",'Trial Balance (Susa)'!I:I)/1000 -> -355.58784 | J34: =-SUMIF('Trial Balance (Susa)'!D:D,"*"&$T34&"*",'Trial Balance (Susa)'!J:J)/1000 -> 0 | P34: =IFERROR(((H34/F34)^(1/(($H$1-$F$1)/365)))-1,"n/a") -> -0.059956664 | Q34: =IFERROR(((N34/H34)^(1/(($N$1-$H$1)/365)))-1,"n/a") -> -1 | T34: /profit and loss/expense/other expense/delivery costs
C35: Fahrzeugkosten | D35: Vehicle costs | F35: =-'P&L (Annual Report)'!E164/1000 -> -184.66753 | G35: =-SUMIF('Trial Balance (Susa)'!D:D,"*"&$T35&"*",'Trial Balance (Susa)'!G:G)/1000 -> -194.66808 | H35: =-SUMIF('Trial Balance (Susa)'!D:D,"*"&$T35&"*",'Trial Balance (Susa)'!H:H)/1000 -> -246.06181 | I35: =-SUMIF('Trial Balance (Susa)'!D:D,"*"&$T35&"*",'Trial Balance (Susa)'!I:I)/1000 -> -239.94903 | J35: =-SUMIF('Trial Balance (Susa)'!D:D,"*"&$T35&"*",'Trial Balance (Susa)'!J:J)/1000 -> 0 | P35: =IFERROR(((H35/F35)^(1/(($H$1-$F$1)/365)))-1,"n/a") -> 0.15409504 | Q35: =IFERROR(((N35/H35)^(1/(($N$1-$H$1)/365)))-1,"n/a") -> -1 | T35: /profit and loss/expense/other expense/vehicle costs
C36: Versicherung, Beiträge und Abgaben | D36: Insurance, contributions and levies expenses | F36: =-'P&L (Annual Report)'!E108/1000 -> -62.46609 | G36: =-SUMIF('Trial Balance (Susa)'!D:D,"*"&$T36&"*",'Trial Balance (Susa)'!G:G)/1000 -> -73.2431 | H36: =-SUMIF('Trial Balance (Susa)'!D:D,"*"&$T36&"*",'Trial Balance (Susa)'!H:H)/1000 -> -69.6834 | I36: =-SUMIF('Trial Balance (Susa)'!D:D,"*"&$T36&"*",'Trial Balance (Susa)'!I:I)/1000 -> -69.77079 | J36: =-SUMIF('Trial Balance (Susa)'!D:D,"*"&$T36&"*",'Trial Balance (Susa)'!J:J)/1000 -> 0 | P36: =IFERROR(((H36/F36)^(1/(($H$1-$F$1)/365)))-1,"n/a") -> 0.056112117 | Q36: =IFERROR(((N36/H36)^(1/(($N$1-$H$1)/365)))-1,"n/a") -> -1 | T36: /profit and loss/expense/other expense/insurance contributions and levies
C37: Werbe- und Reisekosten | D37: Advertising and travel expenses | F37: =-'P&L (Annual Report)'!E178/1000 -> -140.85126 | G37: =-SUMIF('Trial Balance (Susa)'!D:D,"*"&$T37&"*",'Trial Balance (Susa)'!G:G)/1000 -> -177.41994 | H37: =-SUMIF('Trial Balance (Susa)'!D:D,"*"&$T37&"*",'Trial Balance (Susa)'!H:H)/1000 -> -154.10663 | I37: =-SUMIF('Trial Balance (Susa)'!D:D,"*"&$T37&"*",'Trial Balance (Susa)'!I:I)/1000 -> -163.61566 | J37: =-SUMIF('Trial Balance (Susa)'!D:D,"*"&$T37&"*",'Trial Balance (Susa)'!J:J)/1000 -> 0 | P37: =IFERROR(((H37/F37)^(1/(($H$1-$F$1)/365)))-1,"n/a") -> 0.045932303 | Q37: =IFERROR(((N37/H37)^(1/(($N$1-$H$1)/365)))-1,"n/a") -> -1 | T37: /profit and loss/expense/other expense/advertising and travel
C38: Sonstige betriebliche Erträge | D38: Other operating income | F38: ='P&L (Annual Report)'!E45/1000 -> 243.1056 | G38: =-SUMIF('Trial Balance (Susa)'!D:D,"*"&$T38&"*",'Trial Balance (Susa)'!G:G)/1000 -> 186.95985 | H38: =-SUMIF('Trial Balance (Susa)'!D:D,"*"&$T38&"*",'Trial Balance (Susa)'!H:H)/1000 -> 264.5716 | I38: =-SUMIF('Trial Balance (Susa)'!D:D,"*"&$T38&"*",'Trial Balance (Susa)'!I:I)/1000 -> 185.38533 | J38: =-SUMIF('Trial Balance (Susa)'!D:D,"*"&$T38&"*",'Trial Balance (Susa)'!J:J)/1000 -> 0 | P38: =IFERROR(((H38/F38)^(1/(($H$1-$F$1)/365)))-1,"n/a") -> 0.043155362 | Q38: =IFERROR(((N38/H38)^(1/(($N$1-$H$1)/365)))-1,"n/a") -> -1 | T38: /profit and loss/income/other income
C39: Sonstige betriebliche Aufwendungen | D39: Other operating expenses | F39: =-SUM('P&L (Annual Report)'!E201,'P&L (Annual Report)'!E207,'P&L (Annual Report)'!E211,'P&L (Annual Report)'!E213)/1000 -> -1023.4058 | G39: =-SUMIF('Trial Balance (Susa)'!D:D,"*"&$T39&"*",'Trial Balance (Susa)'!G:G)/1000 -> -1065.7626 | H39: =-SUMIF('Trial Balance (Susa)'!D:D,"*"&$T39&"*",'Trial Balance (Susa)'!H:H)/1000 -> -1267.2204 | I39: =-SUMIF('Trial Balance (Susa)'!D:D,"*"&$T39&"*",'Trial Balance (Susa)'!I:I)/1000 -> -1226.4219 | J39: =-SUMIF('Trial Balance (Susa)'!D:D,"*"&$T39&"*",'Trial Balance (Susa)'!J:J)/1000 -> 0 | P39: =IFERROR(((H39/F39)^(1/(($H$1-$F$1)/365)))-1,"n/a") -> 0.11259898 | Q39: =IFERROR(((N39/H39)^(1/(($N$1-$H$1)/365)))-1,"n/a") -> -1 | T39: /profit and loss/expense/other expense/other operating expense
C40: Dummy 1 | D40: Dummy 1 | P40: =IFERROR(((H40/F40)^(1/(($H$1-$F$1)/365)))-1,"n/a") -> n/a | Q40: =IFERROR(((N40/H40)^(1/(($N$1-$H$1)/365)))-1,"n/a") -> n/a
C41: Dummy 2 | D41: Dummy 2 | P41: =IFERROR(((H41/F41)^(1/(($H$1-$F$1)/365)))-1,"n/a") -> n/a | Q41: =IFERROR(((N41/H41)^(1/(($N$1-$H$1)/365)))-1,"n/a") -> n/a
C42: Dummy 3 | D42: Dummy 3 | P42: =IFERROR(((H42/F42)^(1/(($H$1-$F$1)/365)))-1,"n/a") -> n/a | Q42: =IFERROR(((N42/H42)^(1/(($N$1-$H$1)/365)))-1,"n/a") -> n/a
C43: EBITDA | D43: EBITDA | E43: =SUM(E29:E42) -> 0 | F43: =SUM(F29:F42) -> -4386.7022 | G43: =SUM(G29:G42) -> -6491.3424 | H43: =SUM(H29:H42) -> -6637.5466 | I43: =SUM(I29:I42) -> -6045.3006 | J43: =SUM(J29:J42) -> 0 | K43: =SUM(K29:K42) -> 0 | L43: =SUM(L29:L42) -> 0 | ... N43: =SUM(N29:N42) -> 0 | P43: =IFERROR(((H43/F43)^(1/(($H$1-$F$1)/365)))-1,"n/a") -> 0.22973544 | Q43: =IFERROR(((N43/H43)^(1/(($N$1-$H$1)/365)))-1,"n/a") -> -1
C44: Abschreibungen | D44: Depreciation | F44: =-'P&L (Annual Report)'!E223/1000 -> -355.3417 | G44: =-SUMIF('Trial Balance (Susa)'!D:D,"*"&$T44&"*",'Trial Balance (Susa)'!G:G)/1000 -> -324.63992 | H44: =-SUMIF('Trial Balance (Susa)'!D:D,"*"&$T44&"*",'Trial Balance (Susa)'!H:H)/1000 -> -315.71971 | I44: =-SUMIF('Trial Balance (Susa)'!D:D,"*"&$T44&"*",'Trial Balance (Susa)'!I:I)/1000 -> -268.7825 | J44: =-SUMIF('Trial Balance (Susa)'!D:D,"*"&$T44&"*",'Trial Balance (Susa)'!J:J)/1000 -> 0 | P44: =IFERROR(((H44/F44)^(1/(($H$1-$F$1)/365)))-1,"n/a") -> -0.057323069 | Q44: =IFERROR(((N44/H44)^(1/(($N$1-$H$1)/365)))-1,"n/a") -> -1 | T44: /profit and loss/expense/depreciation expense
C45: Dummy 1 | D45: Dummy 1 | P45: =IFERROR(((H45/F45)^(1/(($H$1-$F$1)/365)))-1,"n/a") -> n/a | Q45: =IFERROR(((N45/H45)^(1/(($N$1-$H$1)/365)))-1,"n/a") -> n/a
C46: Dummy 2 | D46: Dummy 2 | P46: =IFERROR(((H46/F46)^(1/(($H$1-$F$1)/365)))-1,"n/a") -> n/a | Q46: =IFERROR(((N46/H46)^(1/(($N$1-$H$1)/365)))-1,"n/a") -> n/a
C47: Dummy 3 | D47: Dummy 3 | P47: =IFERROR(((H47/F47)^(1/(($H$1-$F$1)/365)))-1,"n/a") -> n/a | Q47: =IFERROR(((N47/H47)^(1/(($N$1-$H$1)/365)))-1,"n/a") -> n/a
C48: EBIT | D48: EBIT | E48: =SUM(E43:E47) -> 0 | F48: =SUM(F43:F47) -> -4742.0439 | G48: =SUM(G43:G47) -> -6815.9823 | H48: =SUM(H43:H47) -> -6953.2663 | I48: =SUM(I43:I47) -> -6314.0831 | J48: =SUM(J43:J47) -> 0 | K48: =SUM(K43:K47) -> 0 | L48: =SUM(L43:L47) -> 0 | ... N48: =SUM(N43:N47) -> 0 | P48: =IFERROR(((H48/F48)^(1/(($H$1-$F$1)/365)))-1,"n/a") -> 0.21059243 | Q48: =IFERROR(((N48/H48)^(1/(($N$1-$H$1)/365)))-1,"n/a") -> -1
C49: Beteiligungsergebnis | D49: Investment income | G49: =-SUMIF('Trial Balance (Susa)'!D:D,"*"&$T49&"*",'Trial Balance (Susa)'!G:G)/1000 -> 0 | H49: =-SUMIF('Trial Balance (Susa)'!D:D,"*"&$T49&"*",'Trial Balance (Susa)'!H:H)/1000 -> 0 | I49: =-SUMIF('Trial Balance (Susa)'!D:D,"*"&$T49&"*",'Trial Balance (Susa)'!I:I)/1000 -> 0 | J49: =-SUMIF('Trial Balance (Susa)'!D:D,"*"&$T49&"*",'Trial Balance (Susa)'!J:J)/1000 -> 0 | P49: =IFERROR(((H49/F49)^(1/(($H$1-$F$1)/365)))-1,"n/a") -> n/a | Q49: =IFERROR(((N49/H49)^(1/(($N$1-$H$1)/365)))-1,"n/a") -> n/a | T49: /profit and loss/income/income from investments
C50: Zinserträge | D50: Interest income | F50: ='P&L (Annual Report)'!E232/1000 -> 5.33652 | G50: =-SUMIF('Trial Balance (Susa)'!D:D,"*"&$T50&"*",'Trial Balance (Susa)'!G:G)/1000 -> 4.425 | H50: =-SUMIF('Trial Balance (Susa)'!D:D,"*"&$T50&"*",'Trial Balance (Susa)'!H:H)/1000 -> 3.13466 | I50: =-SUMIF('Trial Balance (Susa)'!D:D,"*"&$T50&"*",'Trial Balance (Susa)'!I:I)/1000 -> 2.2085 | J50: =-SUMIF('Trial Balance (Susa)'!D:D,"*"&$T50&"*",'Trial Balance (Susa)'!J:J)/1000 -> 0 | P50: =IFERROR(((H50/F50)^(1/(($H$1-$F$1)/365)))-1,"n/a") -> -0.23330223 | Q50: =IFERROR(((N50/H50)^(1/(($N$1-$H$1)/365)))-1,"n/a") -> -1 | T50: /profit and loss/income/interest income
C51: Zinsaufwendungen | D51: Interest expenses | F51: =-'P&L (Annual Report)'!E235/1000 -> -9.07139 | G51: =-SUMIF('Trial Balance (Susa)'!D:D,"*"&$T51&"*",'Trial Balance (Susa)'!G:G)/1000 -> -3.69014 | H51: =-SUMIF('Trial Balance (Susa)'!D:D,"*"&$T51&"*",'Trial Balance (Susa)'!H:H)/1000 -> -3.50652 | I51: =-SUMIF('Trial Balance (Susa)'!D:D,"*"&$T51&"*",'Trial Balance (Susa)'!I:I)/1000 -> -3.84748 | J51: =-SUMIF('Trial Balance (Susa)'!D:D,"*"&$T51&"*",'Trial Balance (Susa)'!J:J)/1000 -> 0 | P51: =IFERROR(((H51/F51)^(1/(($H$1-$F$1)/365)))-1,"n/a") -> -0.37786649 | Q51: =IFERROR(((N51/H51)^(1/(($N$1-$H$1)/365)))-1,"n/a") -> -1 | T51: /profit and loss/expense/interest expense
C52: Abschreibungen auf Finanzanlagen | D52: Abschreibungn auf Finanzanlagen | F52: =-'P&L (Annual Report)'!E224/1000 -> -131.75609 | G52: =-SUMIF('Trial Balance (Susa)'!D:D,"*"&$T52&"*",'Trial Balance (Susa)'!G:G)/1000 -> -35.0785 | H52: =-SUMIF('Trial Balance (Susa)'!D:D,"*"&$T52&"*",'Trial Balance (Susa)'!H:H)/1000 -> -4.07329 | I52: =-SUMIF('Trial Balance (Susa)'!D:D,"*"&$T52&"*",'Trial Balance (Susa)'!I:I)/1000 -> -0.71 | P52: =IFERROR(((H52/F52)^(1/(($H$1-$F$1)/365)))-1,"n/a") -> -0.82375369 | Q52: =IFERROR(((N52/H52)^(1/(($N$1-$H$1)/365)))-1,"n/a") -> -1 | T52: /profit and loss/expense/depreciation on financial assets
C53: Dummy 2 | D53: Dummy 2 | P53: =IFERROR(((H53/F53)^(1/(($H$1-$F$1)/365)))-1,"n/a") -> n/a | Q53: =IFERROR(((N53/H53)^(1/(($N$1-$H$1)/365)))-1,"n/a") -> n/a
C54: Dummy 3 | D54: Dummy 3 | P54: =IFERROR(((H54/F54)^(1/(($H$1-$F$1)/365)))-1,"n/a") -> n/a | Q54: =IFERROR(((N54/H54)^(1/(($N$1-$H$1)/365)))-1,"n/a") -> n/a
C55: Finanzergebnis | D55: Financial result | E55: =SUM(E49:E54) -> 0 | F55: =SUM(F49:F54) -> -135.49096 | G55: =SUM(G49:G54) -> -34.34364 | H55: =SUM(H49:H54) -> -4.44515 | I55: =SUM(I49:I54) -> -2.34898 | J55: =SUM(J49:J54) -> 0 | K55: =SUM(K49:K54) -> 0 | L55: =SUM(L49:L54) -> 0 | ... N55: =SUM(N49:N54) -> 0 | P55: =IFERROR(((H55/F55)^(1/(($H$1-$F$1)/365)))-1,"n/a") -> -0.81844713 | Q55: =IFERROR(((N55/H55)^(1/(($N$1-$H$1)/365)))-1,"n/a") -> -1
C56: EBT | D56: EBT | E56: =E55+E48 -> 0 | F56: =F55+F48 -> -4877.5348 | G56: =G55+G48 -> -6850.3259 | H56: =H55+H48 -> -6957.7115 | I56: =I55+I48 -> -6316.4321 | J56: =J55+J48 -> 0 | K56: =K55+K48 -> 0 | L56: =L55+L48 -> 0 | ... N56: =N55+N48 -> 0 | P56: =IFERROR(((H56/F56)^(1/(($H$1-$F$1)/365)))-1,"n/a") -> 0.19406371 | Q56: =IFERROR(((N56/H56)^(1/(($N$1-$H$1)/365)))-1,"n/a") -> -1
C57: Ertragssteuern | D57: Income taxes | F57: =-'P&L (Annual Report)'!E245/1000 -> -898.38628 | G57: =-SUMIF('Trial Balance (Susa)'!D:D,"*"&$T57&"*",'Trial Balance (Susa)'!G:G)/1000 -> -390.61759 | H57: =-SUMIF('Trial Balance (Susa)'!D:D,"*"&$T57&"*",'Trial Balance (Susa)'!H:H)/1000 -> -442.12161 | I57: =-SUMIF('Trial Balance (Susa)'!D:D,"*"&$T57&"*",'Trial Balance (Susa)'!I:I)/1000 -> -333.75368 | J57: =-SUMIF('Trial Balance (Susa)'!D:D,"*"&$T57&"*",'Trial Balance (Susa)'!J:J)/1000 -> 0 | P57: =IFERROR(((H57/F57)^(1/(($H$1-$F$1)/365)))-1,"n/a") -> -0.2981409 | Q57: =IFERROR(((N57/H57)^(1/(($N$1-$H$1)/365)))-1,"n/a") -> -1 | T57: /profit and loss/expense/taxes/taxes on income and earnings
C58: Sonstige Steuern | D58: Other taxes | F58: =-'P&L (Annual Report)'!E260/1000 -> -3.077 | G58: =-SUMIF('Trial Balance (Susa)'!D:D,"*"&$T58&"*",'Trial Balance (Susa)'!G:G)/1000 -> -2.922 | H58: =-SUMIF('Trial Balance (Susa)'!D:D,"*"&$T58&"*",'Trial Balance (Susa)'!H:H)/1000 -> -3.002 | I58: =-SUMIF('Trial Balance (Susa)'!D:D,"*"&$T58&"*",'Trial Balance (Susa)'!I:I)/1000 -> -2.254 | J58: =-SUMIF('Trial Balance (Susa)'!D:D,"*"&$T58&"*",'Trial Balance (Susa)'!J:J)/1000 -> 0 | P58: =IFERROR(((H58/F58)^(1/(($H$1-$F$1)/365)))-1,"n/a") -> -0.012245707 | Q58: =IFERROR(((N58/H58)^(1/(($N$1-$H$1)/365)))-1,"n/a") -> -1 | T58: /profit and loss/expense/taxes/other taxes
C59: Jahresüberschuss | D59: Profit / Loss | E59: =SUM(E56:E58) -> 0 | F59: =SUM(F56:F58) -> -5778.9981 | G59: =SUM(G56:G58) -> -7243.8655 | H59: =SUM(H56:H58) -> -7402.8351 | I59: =SUM(I56:I58) -> -6652.4398 | J59: =SUM(J56:J58) -> 0 | K59: =SUM(K56:K58) -> 0 | L59: =SUM(L56:L58) -> 0 | ... N59: =SUM(N56:N58) -> 0 | P59: =IFERROR(((H59/F59)^(1/(($H$1-$F$1)/365)))-1,"n/a") -> 0.13161632 | Q59: =IFERROR(((N59/H59)^(1/(($N$1-$H$1)/365)))-1,"n/a") -> -1
C61: Jährliches Wachstum | D61: YoY Growth Analysis
C62: =C24 -> Gesamtleistung | D62: =D24 -> Total output | F62: =IFERROR(IF(F24/E24-1>1,">100%",IF(F24/E24-1<-1,"<100%",F24/E24-1)),"n/a") -> n/a | G62: =IFERROR(IF(G24/F24-1>1,">100%",IF(G24/F24-1<-1,"<100%",G24/F24-1)),"n/a") -> -0.054878362 | H62: =IFERROR(IF(H24/G24-1>1,">100%",IF(H24/G24-1<-1,"<100%",H24/G24-1)),"n/a") -> 0.096349263 | I62: =IFERROR(IF(I24/H24-1>1,">100%",IF(I24/H24-1<-1,"<100%",I24/H24-1)),"n/a") -> -0.10433633 | K62: =IFERROR(IF(K24/H24-1>1,">100%",IF(K24/H24-1<-1,"<100%",K24/H24-1)),"n/a") -> -1 | L62: =IFERROR(IF(L24/K24-1>1,">100%",IF(L24/K24-1<-1,"<100%",L24/K24-1)),"n/a") -> n/a | M62: =IFERROR(IF(M24/L24-1>1,">100%",IF(M24/L24-1<-1,"<100%",M24/L24-1)),"n/a") -> n/a | N62: =IFERROR(IF(N24/M24-1>1,">100%",IF(N24/M24-1<-1,"<100%",N24/M24-1)),"n/a") -> n/a
C63: =C29 -> Rohergebnis | D63: =D29 -> Gross profit | F63: =IFERROR(IF(F29/E29-1>1,">100%",IF(F29/E29-1<-1,"<100%",F29/E29-1)),"n/a") -> n/a | G63: =IFERROR(IF(G29/F29-1>1,">100%",IF(G29/F29-1<-1,"<100%",G29/F29-1)),"n/a") -> <100% | H63: =IFERROR(IF(H29/G29-1>1,">100%",IF(H29/G29-1<-1,"<100%",H29/G29-1)),"n/a") -> <100% | K63: =IFERROR(IF(K29/H29-1>1,">100%",IF(K29/H29-1<-1,"<100%",K29/H29-1)),"n/a") -> -1 | L63: =IFERROR(IF(L29/K29-1>1,">100%",IF(L29/K29-1<-1,"<100%",L29/K29-1)),"n/a") -> n/a | M63: =IFERROR(IF(M29/L29-1>1,">100%",IF(M29/L29-1<-1,"<100%",M29/L29-1)),"n/a") -> n/a | N63: =IFERROR(IF(N29/M29-1>1,">100%",IF(N29/M29-1<-1,"<100%",N29/M29-1)),"n/a") -> n/a
C64: =C43 -> EBITDA | D64: =D43 -> EBITDA | F64: =IFERROR(IF(F43/E43-1>1,">100%",IF(F43/E43-1<-1,"<100%",F43/E43-1)),"n/a") -> n/a | G64: =IFERROR(IF(G43/F43-1>1,">100%",IF(G43/F43-1<-1,"<100%",G43/F43-1)),"n/a") -> 0.47977732 | H64: =IFERROR(IF(H43/G43-1>1,">100%",IF(H43/G43-1<-1,"<100%",H43/G43-1)),"n/a") -> 0.022522958 | K64: =IFERROR(IF(K43/H43-1>1,">100%",IF(K43/H43-1<-1,"<100%",K43/H43-1)),"n/a") -> -1 | L64: =IFERROR(IF(L43/K43-1>1,">100%",IF(L43/K43-1<-1,"<100%",L43/K43-1)),"n/a") -> n/a | M64: =IFERROR(IF(M43/L43-1>1,">100%",IF(M43/L43-1<-1,"<100%",M43/L43-1)),"n/a") -> n/a | N64: =IFERROR(IF(N43/M43-1>1,">100%",IF(N43/M43-1<-1,"<100%",N43/M43-1)),"n/a") -> n/a
C65: =C59 -> Jahresüberschuss | D65: =D59 -> Profit / Loss | F65: =IFERROR(IF(F59/E59-1>1,">100%",IF(F59/E59-1<-1,"<100%",F59/E59-1)),"n/a") -> n/a | G65: =IFERROR(IF(G59/F59-1>1,">100%",IF(G59/F59-1<-1,"<100%",G59/F59-1)),"n/a") -> 0.25348121 | H65: =IFERROR(IF(H59/G59-1>1,">100%",IF(H59/G59-1<-1,"<100%",H59/G59-1)),"n/a") -> 0.021945403 | K65: =IFERROR(IF(K59/H59-1>1,">100%",IF(K59/H59-1<-1,"<100%",K59/H59-1)),"n/a") -> -1 | L65: =IFERROR(IF(L59/K59-1>1,">100%",IF(L59/K59-1<-1,"<100%",L59/K59-1)),"n/a") -> n/a | M65: =IFERROR(IF(M59/L59-1>1,">100%",IF(M59/L59-1<-1,"<100%",M59/L59-1)),"n/a") -> n/a | N65: =IFERROR(IF(N59/M59-1>1,">100%",IF(N59/M59-1<-1,"<100%",N59/M59-1)),"n/a") -> n/a
C67: ="In % der "&C24 -> In % der Gesamtleistung | D67: ="In % of "&D24 -> In % of Total output
C68: =C9 -> Umsatzerlöse | D68: =D9 -> Revenues | E68: =IFERROR(E9/E$24,"n/a") -> n/a | F68: =IFERROR(F9/F$24,"n/a") -> 1.0178038 | G68: =IFERROR(G9/G$24,"n/a") -> 0.98713719 | H68: =IFERROR(H9/H$24,"n/a") -> 0.97937804 | I68: =IFERROR(I9/I$24,"n/a") -> 0.98515415 | J68: =IFERROR(J9/J$24,"n/a") -> n/a | K68: =IFERROR(K9/K$24,"n/a") -> n/a | L68: =IFERROR(L9/L$24,"n/a") -> n/a | ... N68: =IFERROR(N9/N$24,"n/a") -> n/a
C69: =C19 -> Bestandsveränderung | D69: =D19 -> Change in inventory | E69: =IFERROR(E19/E$24,"n/a") -> n/a | F69: =IFERROR(F19/F$24,"n/a") -> -0.01780377 | G69: =IFERROR(G19/G$24,"n/a") -> 0.012862815 | H69: =IFERROR(H19/H$24,"n/a") -> 0.020621957 | I69: =IFERROR(I19/I$24,"n/a") -> 0.01484585 | J69: =IFERROR(J19/J$24,"n/a") -> n/a | K69: =IFERROR(K19/K$24,"n/a") -> n/a | L69: =IFERROR(L19/L$24,"n/a") -> n/a | ... N69: =IFERROR(N19/N$24,"n/a") -> n/a
C70: =C22 -> Dummy 2 | D70: =D22 -> Dummy 2 | E70: =IFERROR(E22/E$24,"n/a") -> n/a | F70: =IFERROR(F22/F$24,"n/a") -> 0 | G70: =IFERROR(G22/G$24,"n/a") -> 0 | H70: =IFERROR(H22/H$24,"n/a") -> 0 | I70: =IFERROR(I22/I$24,"n/a") -> 0 | J70: =IFERROR(J22/J$24,"n/a") -> n/a | K70: =IFERROR(K22/K$24,"n/a") -> n/a | L70: =IFERROR(L22/L$24,"n/a") -> n/a | ... N70: =IFERROR(N22/N$24,"n/a") -> n/a
C71: =C23 -> Dummy 3 | D71: =D23 -> Dummy 3 | E71: =IFERROR(E23/E$24,"n/a") -> n/a | F71: =IFERROR(F23/F$24,"n/a") -> 0 | G71: =IFERROR(G23/G$24,"n/a") -> 0 | H71: =IFERROR(H23/H$24,"n/a") -> 0 | I71: =IFERROR(I23/I$24,"n/a") -> 0 | J71: =IFERROR(J23/J$24,"n/a") -> n/a | K71: =IFERROR(K23/K$24,"n/a") -> n/a | L71: =IFERROR(L23/L$24,"n/a") -> n/a | ... N71: =IFERROR(N23/N$24,"n/a") -> n/a
C72: =C24 -> Gesamtleistung | D72: =D24 -> Total output | E72: =IFERROR(E24/E$24,"n/a") -> n/a | F72: =IFERROR(F24/F$24,"n/a") -> 1 | G72: =IFERROR(G24/G$24,"n/a") -> 1 | H72: =IFERROR(H24/H$24,"n/a") -> 1 | I72: =IFERROR(I24/I$24,"n/a") -> 1 | J72: =IFERROR(J24/J$24,"n/a") -> n/a | K72: =IFERROR(K24/K$24,"n/a") -> n/a | L72: =IFERROR(L24/L$24,"n/a") -> n/a | ... N72: =IFERROR(N24/N$24,"n/a") -> n/a
C73: =C25 -> Materialaufwand | D73: =D25 -> Cost of materials | E73: =IFERROR(E25/E$24,"n/a") -> n/a | F73: =IFERROR(F25/F$24,"n/a") -> -0.46495979 | G73: =IFERROR(G25/G$24,"n/a") -> -0.52117787 | H73: =IFERROR(H25/H$24,"n/a") -> -0.49368095 | I73: =IFERROR(I25/I$24,"n/a") -> -0.48318614 | J73: =IFERROR(J25/J$24,"n/a") -> n/a | K73: =IFERROR(K25/K$24,"n/a") -> n/a | L73: =IFERROR(L25/L$24,"n/a") -> n/a | ... N73: =IFERROR(N25/N$24,"n/a") -> n/a
C74: =C26 -> RHB-Aufwand | D74: =D26 -> Dummy 1 | E74: =IFERROR(E26/E$24,"n/a") -> n/a | F74: =IFERROR(F26/F$24,"n/a") -> -0.43546554 | G74: =IFERROR(G26/G$24,"n/a") -> -0.47954205 | H74: =IFERROR(H26/H$24,"n/a") -> -0.45535396 | I74: =IFERROR(I26/I$24,"n/a") -> -0.44990449 | J74: =IFERROR(J26/J$24,"n/a") -> n/a | K74: =IFERROR(K26/K$24,"n/a") -> n/a | L74: =IFERROR(L26/L$24,"n/a") -> n/a | ... N74: =IFERROR(N26/N$24,"n/a") -> n/a
C75: =C27 -> Fremdleistungen | D75: =D27 -> Dummy 2 | E75: =IFERROR(E27/E$24,"n/a") -> n/a | F75: =IFERROR(F27/F$24,"n/a") -> -0.029494253 | G75: =IFERROR(G27/G$24,"n/a") -> -0.041635819 | H75: =IFERROR(H27/H$24,"n/a") -> -0.038326983 | I75: =IFERROR(I27/I$24,"n/a") -> -0.033281656 | J75: =IFERROR(J27/J$24,"n/a") -> n/a | K75: =IFERROR(K27/K$24,"n/a") -> n/a | L75: =IFERROR(L27/L$24,"n/a") -> n/a | ... N75: =IFERROR(N27/N$24,"n/a") -> n/a
C76: =C28 -> Dummy 3 | D76: =D28 -> Dummy 3 | E76: =IFERROR(E28/E$24,"n/a") -> n/a | F76: =IFERROR(F28/F$24,"n/a") -> 0 | G76: =IFERROR(G28/G$24,"n/a") -> 0 | H76: =IFERROR(H28/H$24,"n/a") -> 0 | I76: =IFERROR(I28/I$24,"n/a") -> 0 | J76: =IFERROR(J28/J$24,"n/a") -> n/a | K76: =IFERROR(K28/K$24,"n/a") -> n/a | L76: =IFERROR(L28/L$24,"n/a") -> n/a | ... N76: =IFERROR(N28/N$24,"n/a") -> n/a
C77: =C29 -> Rohergebnis | D77: =D29 -> Gross profit | E77: =IFERROR(E29/E$24,"n/a") -> n/a | F77: =IFERROR(F29/F$24,"n/a") -> 0.070080422 | G77: =IFERROR(G29/G$24,"n/a") -> -0.042355739 | H77: =IFERROR(H29/H$24,"n/a") -> 0.012638109 | I77: =IFERROR(I29/I$24,"n/a") -> 0.033627711 | J77: =IFERROR(J29/J$24,"n/a") -> n/a | K77: =IFERROR(K29/K$24,"n/a") -> n/a | L77: =IFERROR(L29/L$24,"n/a") -> n/a | ... N77: =IFERROR(N29/N$24,"n/a") -> n/a
C78: =C30 -> Personalaufwand | D78: =D30 -> Personnel expenses | E78: =IFERROR(E30/E$24,"n/a") -> n/a | F78: =IFERROR(F30/F$24,"n/a") -> -0.21710743 | G78: =IFERROR(G30/G$24,"n/a") -> -0.24226783 | H78: =IFERROR(H30/H$24,"n/a") -> -0.2658524 | I78: =IFERROR(I30/I$24,"n/a") -> -0.27735952 | J78: =IFERROR(J30/J$24,"n/a") -> n/a | K78: =IFERROR(K30/K$24,"n/a") -> n/a | L78: =IFERROR(L30/L$24,"n/a") -> n/a | ... N78: =IFERROR(N30/N$24,"n/a") -> n/a
C79: =C31 -> Miet- und Grundstücksaufwendungen | D79: =D31 -> Premise costs | E79: =IFERROR(E31/E$24,"n/a") -> n/a | F79: =IFERROR(F31/F$24,"n/a") -> -0.021082626 | G79: =IFERROR(G31/G$24,"n/a") -> -0.021998897 | H79: =IFERROR(H31/H$24,"n/a") -> -0.024865589 | I79: =IFERROR(I31/I$24,"n/a") -> -0.022928013 | J79: =IFERROR(J31/J$24,"n/a") -> n/a | K79: =IFERROR(K31/K$24,"n/a") -> n/a | L79: =IFERROR(L31/L$24,"n/a") -> n/a | ... N79: =IFERROR(N31/N$24,"n/a") -> n/a
C80: =C32 -> Reparaturen und Instandhaltungen | D80: =D32 -> Repair and maintenance | E80: =IFERROR(E32/E$24,"n/a") -> n/a | F80: =IFERROR(F32/F$24,"n/a") -> -0.0071568409 | G80: =IFERROR(G32/G$24,"n/a") -> -0.0080099849 | H80: =IFERROR(H32/H$24,"n/a") -> -0.0078369703 | I80: =IFERROR(I32/I$24,"n/a") -> -0.0073860654 | J80: =IFERROR(J32/J$24,"n/a") -> n/a | K80: =IFERROR(K32/K$24,"n/a") -> n/a | L80: =IFERROR(L32/L$24,"n/a") -> n/a | ... N80: =IFERROR(N32/N$24,"n/a") -> n/a
C81: =C33 -> Vertriebskosten | D81: =D33 -> Sales costs | E81: =IFERROR(E33/E$24,"n/a") -> n/a | F81: =IFERROR(F33/F$24,"n/a") -> 0 | G81: =IFERROR(G33/G$24,"n/a") -> 0 | H81: =IFERROR(H33/H$24,"n/a") -> 0 | I81: =IFERROR(I33/I$24,"n/a") -> 0 | J81: =IFERROR(J33/J$24,"n/a") -> n/a | K81: =IFERROR(K33/K$24,"n/a") -> n/a | L81: =IFERROR(L33/L$24,"n/a") -> n/a | ... N81: =IFERROR(N33/N$24,"n/a") -> n/a
... C87: =C39 -> Sonstige betriebliche Aufwendungen | D87: =D39 -> Other operating expenses | E87: =IFERROR(E39/E$24,"n/a") -> n/a | F87: =IFERROR(F39/F$24,"n/a") -> -0.062339144 | G87: =IFERROR(G39/G$24,"n/a") -> -0.068688765 | H87: =IFERROR(H39/H$24,"n/a") -> -0.07449523 | I87: =IFERROR(I39/I$24,"n/a") -> -0.080495433 | J87: =IFERROR(J39/J$24,"n/a") -> n/a | K87: =IFERROR(K39/K$24,"n/a") -> n/a | L87: =IFERROR(L39/L$24,"n/a") -> n/a | ... N87: =IFERROR(N39/N$24,"n/a") -> n/a
C88: =C40 -> Dummy 1 | D88: =D40 -> Dummy 1 | E88: =IFERROR(E40/E$24,"n/a") -> n/a | F88: =IFERROR(F40/F$24,"n/a") -> 0 | G88: =IFERROR(G40/G$24,"n/a") -> 0 | H88: =IFERROR(H40/H$24,"n/a") -> 0 | I88: =IFERROR(I40/I$24,"n/a") -> 0 | J88: =IFERROR(J40/J$24,"n/a") -> n/a | K88: =IFERROR(K41/K$24,"n/a") -> n/a | L88: =IFERROR(L41/L$24,"n/a") -> n/a | M88: =IFERROR(M41/M$24,"n/a") -> n/a | N88: =IFERROR(N41/N$24,"n/a") -> n/a
C89: =C41 -> Dummy 2 | D89: =D41 -> Dummy 2 | E89: =IFERROR(E41/E$24,"n/a") -> n/a | F89: =IFERROR(F41/F$24,"n/a") -> 0 | G89: =IFERROR(G41/G$24,"n/a") -> 0 | H89: =IFERROR(H41/H$24,"n/a") -> 0 | I89: =IFERROR(I41/I$24,"n/a") -> 0 | J89: =IFERROR(J41/J$24,"n/a") -> n/a | K89: =IFERROR(K42/K$24,"n/a") -> n/a | L89: =IFERROR(L42/L$24,"n/a") -> n/a | M89: =IFERROR(M42/M$24,"n/a") -> n/a | N89: =IFERROR(N42/N$24,"n/a") -> n/a
C90: =C42 -> Dummy 3 | D90: =D42 -> Dummy 3 | E90: =IFERROR(E42/E$24,"n/a") -> n/a | F90: =IFERROR(F42/F$24,"n/a") -> 0 | G90: =IFERROR(G42/G$24,"n/a") -> 0 | H90: =IFERROR(H42/H$24,"n/a") -> 0 | I90: =IFERROR(I42/I$24,"n/a") -> 0 | J90: =IFERROR(J42/J$24,"n/a") -> n/a | K90: =IFERROR(K43/K$24,"n/a") -> n/a | L90: =IFERROR(L43/L$24,"n/a") -> n/a | M90: =IFERROR(M43/M$24,"n/a") -> n/a | N90: =IFERROR(N43/N$24,"n/a") -> n/a
C91: =C43 -> EBITDA | D91: =D43 -> EBITDA | E91: =IFERROR(E43/E$24,"n/a") -> n/a | F91: =IFERROR(F43/F$24,"n/a") -> -0.26720901 | G91: =IFERROR(G43/G$24,"n/a") -> -0.41836926 | H91: =IFERROR(H43/H$24,"n/a") -> -0.39019698 | I91: =IFERROR(I43/I$24,"n/a") -> -0.39677953 | J91: =IFERROR(J43/J$24,"n/a") -> n/a | K91: =IFERROR(K43/K$24,"n/a") -> n/a | L91: =IFERROR(L43/L$24,"n/a") -> n/a | ... N91: =IFERROR(N43/N$24,"n/a") -> n/a
C92: =C44 -> Abschreibungen | D92: =D44 -> Depreciation | E92: =IFERROR(E44/E$24,"n/a") -> n/a | F92: =IFERROR(F44/F$24,"n/a") -> -0.021645077 | G92: =IFERROR(G44/G$24,"n/a") -> -0.020923155 | H92: =IFERROR(H44/H$24,"n/a") -> -0.018560002 | I92: =IFERROR(I44/I$24,"n/a") -> -0.017641372 | J92: =IFERROR(J44/J$24,"n/a") -> n/a | K92: =IFERROR(K44/K$24,"n/a") -> n/a | L92: =IFERROR(L44/L$24,"n/a") -> n/a | ... N92: =IFERROR(N44/N$24,"n/a") -> n/a
C93: =C45 -> Dummy 1 | D93: =D45 -> Dummy 1 | E93: =IFERROR(E45/E$24,"n/a") -> n/a | F93: =IFERROR(F45/F$24,"n/a") -> 0 | G93: =IFERROR(G45/G$24,"n/a") -> 0 | H93: =IFERROR(H45/H$24,"n/a") -> 0 | I93: =IFERROR(I45/I$24,"n/a") -> 0 | J93: =IFERROR(J45/J$24,"n/a") -> n/a | K93: =IFERROR(K45/K$24,"n/a") -> n/a | L93: =IFERROR(L45/L$24,"n/a") -> n/a | ... N93: =IFERROR(N45/N$24,"n/a") -> n/a
C94: =C46 -> Dummy 2 | D94: =D46 -> Dummy 2 | E94: =IFERROR(E46/E$24,"n/a") -> n/a | F94: =IFERROR(F46/F$24,"n/a") -> 0 | G94: =IFERROR(G46/G$24,"n/a") -> 0 | H94: =IFERROR(H46/H$24,"n/a") -> 0 | I94: =IFERROR(I46/I$24,"n/a") -> 0 | J94: =IFERROR(J46/J$24,"n/a") -> n/a | K94: =IFERROR(K46/K$24,"n/a") -> n/a | L94: =IFERROR(L46/L$24,"n/a") -> n/a | ... N94: =IFERROR(N46/N$24,"n/a") -> n/a
C95: =C47 -> Dummy 3 | D95: =D47 -> Dummy 3 | E95: =IFERROR(E47/E$24,"n/a") -> n/a | F95: =IFERROR(F47/F$24,"n/a") -> 0 | G95: =IFERROR(G47/G$24,"n/a") -> 0 | H95: =IFERROR(H47/H$24,"n/a") -> 0 | I95: =IFERROR(I47/I$24,"n/a") -> 0 | J95: =IFERROR(J47/J$24,"n/a") -> n/a | K95: =IFERROR(K47/K$24,"n/a") -> n/a | L95: =IFERROR(L47/L$24,"n/a") -> n/a | ... N95: =IFERROR(N47/N$24,"n/a") -> n/a
C96: =C48 -> EBIT | D96: =D48 -> EBIT | E96: =IFERROR(E48/E$24,"n/a") -> n/a | F96: =IFERROR(F48/F$24,"n/a") -> -0.28885409 | G96: =IFERROR(G48/G$24,"n/a") -> -0.43929241 | H96: =IFERROR(H48/H$24,"n/a") -> -0.40875698 | I96: =IFERROR(I48/I$24,"n/a") -> -0.41442091 | J96: =IFERROR(J48/J$24,"n/a") -> n/a | K96: =IFERROR(K48/K$24,"n/a") -> n/a | L96: =IFERROR(L48/L$24,"n/a") -> n/a | ... N96: =IFERROR(N48/N$24,"n/a") -> n/a
C97: =C49 -> Beteiligungsergebnis | D97: =D49 -> Investment income | E97: =IFERROR(E49/E$24,"n/a") -> n/a | F97: =IFERROR(F49/F$24,"n/a") -> 0 | G97: =IFERROR(G49/G$24,"n/a") -> 0 | H97: =IFERROR(H49/H$24,"n/a") -> 0 | I97: =IFERROR(I49/I$24,"n/a") -> 0 | J97: =IFERROR(J49/J$24,"n/a") -> n/a | K97: =IFERROR(K49/K$24,"n/a") -> n/a | L97: =IFERROR(L49/L$24,"n/a") -> n/a | ... N97: =IFERROR(N49/N$24,"n/a") -> n/a
C98: =C50 -> Zinserträge | D98: =D50 -> Interest income | E98: =IFERROR(E50/E$24,"n/a") -> n/a | F98: =IFERROR(F50/F$24,"n/a") -> 0.00032506566 | G98: =IFERROR(G50/G$24,"n/a") -> 0.00028519278 | H98: =IFERROR(H50/H$24,"n/a") -> 0.00018427514 | I98: =IFERROR(I50/I$24,"n/a") -> 0.00014495352 | J98: =IFERROR(J50/J$24,"n/a") -> n/a | K98: =IFERROR(K50/K$24,"n/a") -> n/a | L98: =IFERROR(L50/L$24,"n/a") -> n/a | ... N98: =IFERROR(N50/N$24,"n/a") -> n/a
C99: =C51 -> Zinsaufwendungen | D99: =D51 -> Interest expenses | E99: =IFERROR(E51/E$24,"n/a") -> n/a | F99: =IFERROR(F51/F$24,"n/a") -> -0.00055256935 | G99: =IFERROR(G51/G$24,"n/a") -> -0.0002378308 | H99: =IFERROR(H51/H$24,"n/a") -> -0.00020613543 | I99: =IFERROR(I51/I$24,"n/a") -> -0.00025252695 | J99: =IFERROR(J51/J$24,"n/a") -> n/a | K99: =IFERROR(K51/K$24,"n/a") -> n/a | L99: =IFERROR(L51/L$24,"n/a") -> n/a | ... N99: =IFERROR(N51/N$24,"n/a") -> n/a
C100: =C52 -> Abschreibungen auf Finanzanlagen | D100: =D52 -> Abschreibungn auf Finanzanlagen | E100: =IFERROR(E52/E$24,"n/a") -> n/a | F100: =IFERROR(F52/F$24,"n/a") -> -0.0080257135 | G100: =IFERROR(G52/G$24,"n/a") -> -0.0022608214 | H100: =IFERROR(H52/H$24,"n/a") -> -0.00023945375 | I100: =IFERROR(I52/I$24,"n/a") -> -4.6600407e-05 | J100: =IFERROR(J52/J$24,"n/a") -> n/a | K100: =IFERROR(K52/K$24,"n/a") -> n/a | L100: =IFERROR(L52/L$24,"n/a") -> n/a | ... N100: =IFERROR(N52/N$24,"n/a") -> n/a
C101: =C53 -> Dummy 2 | D101: =D53 -> Dummy 2 | E101: =IFERROR(E53/E$24,"n/a") -> n/a | F101: =IFERROR(F53/F$24,"n/a") -> 0 | G101: =IFERROR(G53/G$24,"n/a") -> 0 | H101: =IFERROR(H53/H$24,"n/a") -> 0 | I101: =IFERROR(I53/I$24,"n/a") -> 0 | J101: =IFERROR(J53/J$24,"n/a") -> n/a | K101: =IFERROR(K53/K$24,"n/a") -> n/a | L101: =IFERROR(L53/L$24,"n/a") -> n/a | ... N101: =IFERROR(N53/N$24,"n/a") -> n/a
C102: =C54 -> Dummy 3 | D102: =D54 -> Dummy 3 | E102: =IFERROR(E54/E$24,"n/a") -> n/a | F102: =IFERROR(F54/F$24,"n/a") -> 0 | G102: =IFERROR(G54/G$24,"n/a") -> 0 | H102: =IFERROR(H54/H$24,"n/a") -> 0 | I102: =IFERROR(I54/I$24,"n/a") -> 0 | J102: =IFERROR(J54/J$24,"n/a") -> n/a | K102: =IFERROR(K54/K$24,"n/a") -> n/a | L102: =IFERROR(L54/L$24,"n/a") -> n/a | ... N102: =IFERROR(N54/N$24,"n/a") -> n/a
... C107: =C59 -> Jahresüberschuss | D107: =D59 -> Profit / Loss | E107: =IFERROR(E59/E$24,"n/a") -> n/a | F107: =IFERROR(F59/F$24,"n/a") -> -0.35201851 | G107: =IFERROR(G59/G$24,"n/a") -> -0.46686963 | H107: =IFERROR(H59/H$24,"n/a") -> -0.43518548 | I107: =IFERROR(I59/I$24,"n/a") -> -0.43662873 | J107: =IFERROR(J59/J$24,"n/a") -> n/a | K107: =IFERROR(K59/K$24,"n/a") -> n/a | L107: =IFERROR(L59/L$24,"n/a") -> n/a | ... N107: =IFERROR(N59/N$24,"n/a") -> n/a
C109: Steuerquote | D109: Tax rate | E109: =IFERROR(E57/E$56,"n/a") -> n/a | F109: =IFERROR(F57/F$56,"n/a") -> 0.18418859 | G109: =IFERROR(G57/G$56,"n/a") -> 0.057021752 | H109: =IFERROR(H57/H$56,"n/a") -> 0.063544114 | I109: =IFERROR(I57/I$56,"n/a") -> 0.052838956 | J109: =IFERROR(J57/J$56,"n/a") -> n/a | K109: =IFERROR(K57/K$56,"n/a") -> n/a | L109: =IFERROR(L57/L$56,"n/a") -> n/a | ... N109: =IFERROR(N57/N$56,"n/a") -> n/a
C111: ="Quelle: "&Cockpit!$C$7 -> Quelle: Datenraum/ eigene Analysen | D111: ="Source: "&Cockpit!$C$8 -> Source: Virtual Data Room/ Company Information
C113: Jahresergebnis lt. Quelldatei | D113: Profit acc. to source sheet | F113: ='P&L (Annual Report)'!E262/1000 -> 1854.1281 | G113: ='P&L (Susa)'!E299/1000 -> 842.63684 | H113: ='P&L (Susa)'!F299/1000 -> 995.0523 | I113: ='BWA Dez25'!H264/1000 -> 709.3449 | J113: ='P&L (Susa)'!G299/1000 -> 893.51867
C114: Check | D114: Check | E114: =E113-E59 -> 0 | F114: =F113-F59 -> 7633.1262 | G114: =G113-G59 -> 8086.5024 | H114: =H113-H59 -> 8397.8874 | I114: =I113-I59 -> 7361.7847 | J114: =J113-J59 -> 893.51867 | K114: =K113-K59 -> 0 | L114: =L113-L59 -> 0 | ... N114: =N113-N59 -> 0

Sheet Lead NA
C4: =Cockpit!$C$4 -> Projekt Namur | E4: =Cockpit!C39 -> 44561 | F4: =Cockpit!D39 -> 44926 | G4: =Cockpit!E39 -> 45291 | H4: =Cockpit!F39 -> 45657 | I4: =Cockpit!G39 -> 46022 | J4: =Cockpit!H39 -> 46022 | K4: =Cockpit!I39 -> 46387 | L4: =Cockpit!J39 -> 46752 | M4: =Cockpit!K39 -> 47118
C5: ="in T"&Cockpit!$C$5 -> in TEUR | E5: IST | F5: IST | G5: IST | H5: IST | I5: IST | J5: =Cockpit!H40 -> Plan | K5: =Cockpit!I40 -> Plan | L5: =Cockpit!J40 -> Plan | M5: =Cockpit!K40 -> Plan
D6: =Cockpit!$C$4 -> Projekt Namur | E6: =Cockpit!C39 -> 44561 | F6: =Cockpit!D39 -> 44926 | G6: =Cockpit!E39 -> 45291 | H6: =Cockpit!F39 -> 45657 | I6: =Cockpit!G39 -> 46022 | J6: =Cockpit!H39 -> 46022 | K6: =Cockpit!I39 -> 46387 | L6: =Cockpit!J39 -> 46752 | M6: =Cockpit!K39 -> 47118
D7: ="in k"&Cockpit!$C$5 -> in kEUR | E7: =Cockpit!C40 -> IST | F7: =Cockpit!D40 -> IST | G7: =Cockpit!E40 -> IST | H7: =Cockpit!F40 -> IST | I7: =Cockpit!G40 -> IST | J7: =Cockpit!H40 -> Plan | K7: =Cockpit!I40 -> Plan | L7: =Cockpit!J40 -> Plan | M7: =Cockpit!K40 -> Plan | P7: Classification BT
C9: Immaterielle Vermögensgegenstände | D9: Intangible assets | F9: ='Balance Sheet (Annual Report)'!E7/1000 -> 6.154 | G9: =SUMIF('Trial Balance (Susa)'!D:D,"*"&$P9&"*",'Trial Balance (Susa)'!G:G)/1000 -> 3.606 | H9: =SUMIF('Trial Balance (Susa)'!D:D,"*"&$P9&"*",'Trial Balance (Susa)'!H:H)/1000 -> 204.27617 | I9: =SUMIF('Trial Balance (Susa)'!D:D,"*"&$P9&"*",'Trial Balance (Susa)'!I:I)/1000 -> 666.00327 | P9: /fixed assets/intangible assets
C10: Sachanlagen | D10: Tangible assets | F10: ='Balance Sheet (Annual Report)'!E17/1000 -> 980.837 | G10: =SUMIF('Trial Balance (Susa)'!D:D,"*"&$P10&"*",'Trial Balance (Susa)'!G:G)/1000 -> 715.176 | H10: =SUMIF('Trial Balance (Susa)'!D:D,"*"&$P10&"*",'Trial Balance (Susa)'!H:H)/1000 -> 826.464 | I10: =SUMIF('Trial Balance (Susa)'!D:D,"*"&$P10&"*",'Trial Balance (Susa)'!I:I)/1000 -> 600.385 | P10: /fixed assets/tangible assets
C11: Finanzanlagen | D11: Financial assets | F11: ='Balance Sheet (Annual Report)'!E22/1000 -> 206.89412 | G11: =SUMIF('Trial Balance (Susa)'!D:D,"*"&$P11&"*",'Trial Balance (Susa)'!G:G)/1000 -> 182.17891 | H11: =SUMIF('Trial Balance (Susa)'!D:D,"*"&$P11&"*",'Trial Balance (Susa)'!H:H)/1000 -> 75.42562 | I11: =SUMIF('Trial Balance (Susa)'!D:D,"*"&$P11&"*",'Trial Balance (Susa)'!I:I)/1000 -> 121.96562 | P11: /fixed assets/financial assets
C12: Dummy 1 | D12: Dummy 1
C13: Dummy 2 | D13: Dummy 2
C14: Dummy 3 | D14: Dummy 3
C15: Anlagevermögen | D15: Fixed assets | E15: =SUM(E9:E14) -> 0 | F15: =SUM(F9:F14) -> 1193.8851 | G15: =SUM(G9:G14) -> 900.96091 | H15: =SUM(H9:H14) -> 1106.1658 | I15: =SUM(I9:I14) -> 1388.3539 | J15: =SUM(J9:J14) -> 0 | K15: =SUM(K9:K14) -> 0 | L15: =SUM(L9:L14) -> 0 | M15: =SUM(M9:M14) -> 0
C16: Vorräte | D16: Inventories | F16: ='Balance Sheet (Annual Report)'!E33/1000 -> 1953.4011 | G16: =SUMIF('Trial Balance (Susa)'!D:D,"*"&$P16&"*",'Trial Balance (Susa)'!G:G)/1000 -> 2652.1087 | H16: =SUMIF('Trial Balance (Susa)'!D:D,"*"&$P16&"*",'Trial Balance (Susa)'!H:H)/1000 -> 3855.8836 | I16: =SUMIF('Trial Balance (Susa)'!D:D,"*"&$P16&"*",'Trial Balance (Susa)'!I:I)/1000 -> 2912.6866 | P16: /working capital/inventory
C17: Forderungen aus LuL | D17: Trade receivables | F17: ='Balance Sheet (Annual Report)'!E37/1000 -> 1780.6561 | G17: =SUMIF('Trial Balance (Susa)'!D:D,"*"&$P17&"*",'Trial Balance (Susa)'!G:G)/1000 -> 1586.3678 | H17: =SUMIF('Trial Balance (Susa)'!D:D,"*"&$P17&"*",'Trial Balance (Susa)'!H:H)/1000 -> 1988.8014 | I17: =SUMIF('Trial Balance (Susa)'!D:D,"*"&$P17&"*",'Trial Balance (Susa)'!I:I)/1000 -> 1415.6542 | P17: /working capital/all trade receivables
C18: Verbindlichkeiten aus LuL | D18: Trade payables | F18: =-'Balance Sheet (Annual Report)'!E84/1000 -> -752.85966 | G18: =SUMIF('Trial Balance (Susa)'!D:D,"*"&$P18&"*",'Trial Balance (Susa)'!G:G)/1000-G19 -> -848.28356 | H18: =SUMIF('Trial Balance (Susa)'!D:D,"*"&$P18&"*",'Trial Balance (Susa)'!H:H)/1000-H19 -> -1220.438 | I18: =SUMIF('Trial Balance (Susa)'!D:D,"*"&$P18&"*",'Trial Balance (Susa)'!I:I)/1000-I26 -> -243.48974 | P18: /working capital/all trade payables
C19: Erhaltene Anzahlungen | D19: Advance payments received | F19: =-'Balance Sheet (Annual Report)'!E82/1000 -> -50 | G19: =SUMIF('Trial Balance (Susa)'!D:D,"*"&$P19&"*",'Trial Balance (Susa)'!G:G)/1000 -> -50 | H19: =SUMIF('Trial Balance (Susa)'!D:D,"*"&$P19&"*",'Trial Balance (Susa)'!H:H)/1000 -> -50 | I19: =SUMIF('Trial Balance (Susa)'!D:D,"*"&$P19&"*",'Trial Balance (Susa)'!I:I)/1000 -> 0 | P19: /working capital/all trade payables/advances received on orders
C20: Dummy 1 | D20: Dummy 1
C21: Dummy 2 | D21: Dummy 2
C22: Dummy 3 | D22: Dummy 3
C23: Trade Working Capital | D23: Trade working capital | E23: =SUM(E16:E22) -> 0 | F23: =SUM(F16:F22) -> 2931.1975 | G23: =SUM(G16:G22) -> 3340.1929 | H23: =SUM(H16:H22) -> 4574.247 | I23: =SUM(I16:I22) -> 4084.851 | J23: =SUM(J16:J22) -> 0 | K23: =SUM(K16:K22) -> 0 | L23: =SUM(L16:L22) -> 0 | M23: =SUM(M16:M22) -> 0
C24: Sonstige Vermögensgegenstände | D24: Other assets | F24: ='Balance Sheet (Annual Report)'!E47/1000 -> 33.1297 | G24: =SUMIF('Trial Balance (Susa)'!D:D,"*"&$P24&"*",'Trial Balance (Susa)'!G:G)/1000 -> 296.51486 | H24: =SUMIF('Trial Balance (Susa)'!D:D,"*"&$P24&"*",'Trial Balance (Susa)'!H:H)/1000 -> 313.58526 | I24: =SUMIF('Trial Balance (Susa)'!D:D,"*"&$P24&"*",'Trial Balance (Susa)'!I:I)/1000 -> 309.09184 | P24: /working capital/other working capital/other current assets
C25: Aktive Rechnungsabgrenzungsposten | D25: Prepaid expenses | F25: ='Balance Sheet (Annual Report)'!E60/1000 -> 30.21821 | G25: =SUMIF('Trial Balance (Susa)'!D:D,"*"&$P25&"*",'Trial Balance (Susa)'!G:G)/1000 -> 65.90396 | H25: =SUMIF('Trial Balance (Susa)'!D:D,"*"&$P25&"*",'Trial Balance (Susa)'!H:H)/1000 -> 62.92786 | I25: =SUMIF('Trial Balance (Susa)'!D:D,"*"&$P25&"*",'Trial Balance (Susa)'!I:I)/1000 -> 51.30145 | P25: /working capital/other working capital/prepaid expenses
C26: Geleistete Anzahlung | D26: Receivables from affiliated/ participating companies | F26: 0 | G26: 0 | H26: 0 | I26: =('Dez25 Kreditoren'!I55+'Dez25 Kreditoren'!I56)/1000 -> 180.945
C27: Dummy 2
C28: Dummy 2 | D28: Dummy 2
C29: Dummy 3 | D29: Dummy 3
C30: Sonstige Aktiva | D30: Other assets | E30: =SUM(E24:E29) -> 0 | F30: =SUM(F24:F29) -> 63.34791 | G30: =SUM(G24:G29) -> 362.41882 | H30: =SUM(H24:H29) -> 376.51312 | I30: =SUM(I24:I29) -> 541.33829 | J30: =SUM(J24:J29) -> 0 | K30: =SUM(K24:K29) -> 0 | L30: =SUM(L24:L29) -> 0 | M30: =SUM(M24:M29) -> 0
C31: Sonstige Rückstellungen | D31: Other provisions | F31: =-'Balance Sheet (Annual Report)'!E79/1000 -> -527.64378 | G31: =SUMIF('Trial Balance (Susa)'!D:D,"*"&$P31&"*",'Trial Balance (Susa)'!G:G)/1000 -> -424.9074 | H31: =SUMIF('Trial Balance (Susa)'!D:D,"*"&$P31&"*",'Trial Balance (Susa)'!H:H)/1000 -> -228.40295 | I31: =SUMIF('Trial Balance (Susa)'!D:D,"*"&$P31&"*",'Trial Balance (Susa)'!I:I)/1000 -> -428.27366 | P31: /working capital/other working capital/other provisions
C32: Sonstige Verbindlichkeiten | D32: Other liabilities | F32: =-'Balance Sheet (Annual Report)'!E109/1000 -> -448.46014 | G32: =SUMIF('Trial Balance (Susa)'!D:D,"*"&$P32&"*",'Trial Balance (Susa)'!G:G)/1000 -> -290.29441 | H32: =SUMIF('Trial Balance (Susa)'!D:D,"*"&$P32&"*",'Trial Balance (Susa)'!H:H)/1000 -> -429.13633 | I32: =SUMIF('Trial Balance (Susa)'!D:D,"*"&$P32&"*",'Trial Balance (Susa)'!I:I)/1000 -> -231.74114 | P32: /working capital/other working capital/other current liabilities
C33: Dummy 1 | D33: Tax provisions | G33: =SUMIF('Trial Balance (Susa)'!D:D,"*"&$P33&"*",'Trial Balance (Susa)'!G:G)/1000 -> 0 | H33: =SUMIF('Trial Balance (Susa)'!D:D,"*"&$P33&"*",'Trial Balance (Susa)'!H:H)/1000 -> 0 | I33: =SUMIF('Trial Balance (Susa)'!D:D,"*"&$P33&"*",'Trial Balance (Susa)'!J:J)/1000 -> 0 | P33: /working capital/other working capital/tax provisions
C34: Dummy 1 | D34: Liabilities to affiliated/ participating companies | G34: =SUMIF('Trial Balance (Susa)'!D:D,"*"&$P34&"*",'Trial Balance (Susa)'!G:G)/1000 -> 0 | H34: =SUMIF('Trial Balance (Susa)'!D:D,"*"&$P34&"*",'Trial Balance (Susa)'!H:H)/1000 -> 0 | I34: =SUMIF('Trial Balance (Susa)'!D:D,"*"&$P34&"*",'Trial Balance (Susa)'!J:J)/1000 -> 0 | P34: /working capital/other working capital/liabilities to affiliated companies
C35: Dummy 1 | D35: Liabilities to shareholders | G35: =SUMIF('Trial Balance (Susa)'!D:D,"*"&$P35&"*",'Trial Balance (Susa)'!G:G)/1000 -> 0 | H35: =SUMIF('Trial Balance (Susa)'!D:D,"*"&$P35&"*",'Trial Balance (Susa)'!H:H)/1000 -> 0 | I35: =SUMIF('Trial Balance (Susa)'!D:D,"*"&$P35&"*",'Trial Balance (Susa)'!J:J)/1000 -> 0 | P35: /working capital/other working capital/liabilities to shareholders
C36: Dummy 1 | D36: Deferred income | P36: /working capital/other working capital/deferred income
C37: Dummy 1 | D37: Dummy 1
C38: Dummy 2 | D38: Dummy 2
C39: Dummy 3 | D39: Dummy 3
C40: Sonstige Passiva | D40: Other liabilities | E40: =SUM(E31:E39) -> 0 | F40: =SUM(F31:F39) -> -976.10392 | G40: =SUM(G31:G39) -> -715.20181 | H40: =SUM(H31:H39) -> -657.53928 | I40: =SUM(I31:I39) -> -660.0148 | J40: =SUM(J31:J39) -> 0 | K40: =SUM(K31:K39) -> 0 | L40: =SUM(L31:L39) -> 0 | M40: =SUM(M31:M39) -> 0
C41: Other Working Capital | D41: Other working capital | E41: =E40+E30 -> 0 | F41: =F40+F30 -> -912.75601 | G41: =G40+G30 -> -352.78299 | H41: =H40+H30 -> -281.02616 | I41: =I40+I30 -> -118.67651 | J41: =J40+J30 -> 0 | K41: =K40+K30 -> 0 | L41: =L40+L30 -> 0 | M41: =M40+M30 -> 0
C42: Net Working Capital | D42: Net working capital | E42: =E41+E23 -> 0 | F42: =F41+F23 -> 2018.4415 | G42: =G41+G23 -> 2987.4099 | H42: =H41+H23 -> 4293.2208 | I42: =I41+I23 -> 3966.1745 | J42: =J41+J23 -> 0 | K42: =K41+K23 -> 0 | L42: =L41+L23 -> 0 | M42: =M41+M23 -> 0
C43: Liquide Mittel | D43: Cash | F43: ='Balance Sheet (Annual Report)'!E57/1000 -> 3008.3487 | G43: =SUMIF('Trial Balance (Susa)'!D:D,"*"&$P43&"*",'Trial Balance (Susa)'!G:G)/1000 -> 2715.5673 | H43: =SUMIF('Trial Balance (Susa)'!D:D,"*"&$P43&"*",'Trial Balance (Susa)'!H:H)/1000 -> 1004.0608 | I43: =SUMIF('Trial Balance (Susa)'!D:D,"*"&$P43&"*",'Trial Balance (Susa)'!I:I)/1000 -> 2026.2807 | P43: /net debt/cash and cash equivalent
C44: Verbindlichkeiten ggü.Kreditinstituten | D44: Liabilities to banks | F44: 0 | G44: =SUMIF('Trial Balance (Susa)'!D:D,"*"&$P44&"*",'Trial Balance (Susa)'!G:G)/1000 -> 0 | H44: =SUMIF('Trial Balance (Susa)'!D:D,"*"&$P44&"*",'Trial Balance (Susa)'!H:H)/1000 -> 0 | I44: =SUMIF('Trial Balance (Susa)'!D:D,"*"&$P44&"*",'Trial Balance (Susa)'!I:I)/1000 -> -19.425 | P44: /net debt/liabilities to credit institutions
C45: Pensionsrückstellungen | D45: Pension provisions | F45: =-'Balance Sheet (Annual Report)'!E70/1000 -> -201.476 | G45: =SUMIF('Trial Balance (Susa)'!D:D,"*"&$P45&"*",'Trial Balance (Susa)'!G:G)/1000 -> -192.102 | H45: =SUMIF('Trial Balance (Susa)'!D:D,"*"&$P45&"*",'Trial Balance (Susa)'!H:H)/1000 -> -182.403 | I45: =SUMIF('Trial Balance (Susa)'!D:D,"*"&$P45&"*",'Trial Balance (Susa)'!I:I)/1000 -> -171.743 | P45: /net debt/provisions for pensions and similar obligations
C46: Steuerrückstellungen | D46: Tax provisions | F46: =-'Balance Sheet (Annual Report)'!E73/1000 -> -224.92819 | G46: =SUMIF('Trial Balance (Susa)'!D:D,"*"&$P46&"*",'Trial Balance (Susa)'!G:G)/1000 -> -224.92819 | H46: =SUMIF('Trial Balance (Susa)'!D:D,"*"&$P46&"*",'Trial Balance (Susa)'!H:H)/1000 -> 0 | I46: =SUMIF('Trial Balance (Susa)'!D:D,"*"&$P46&"*",'Trial Balance (Susa)'!I:I)/1000 -> 0 | P46: /net debt/tax provisions
C47: Dummy 1 | D47: Other provisions | I47: =SUMIF('Trial Balance (Susa)'!D:D,"*"&$P47&"*",'Trial Balance (Susa)'!I:I)/1000 -> -2.3283064e-13
C48: Sonstige Wertpapiere | D48: Short-term securities | F48: 0 | G48: =SUMIF('Trial Balance (Susa)'!D:D,"*"&$P48&"*",'Trial Balance (Susa)'!G:G)/1000 -> 0 | H48: =SUMIF('Trial Balance (Susa)'!D:D,"*"&$P48&"*",'Trial Balance (Susa)'!H:H)/1000 -> 109.79175 | I48: =SUMIF('Trial Balance (Susa)'!D:D,"*"&$P48&"*",'Trial Balance (Susa)'!I:I)/1000 -> 0 | P48: /net debt/securities
C49: Netto-Finanzvermögen / -Verbindlichkeiten | D49: Net cash / Net debt | E49: =SUM(E43:E48) -> 0 | F49: =SUM(F43:F48) -> 2581.9445 | G49: =SUM(G43:G48) -> 2298.5371 | H49: =SUM(H43:H48) -> 931.44959 | I49: =SUM(I43:I48) -> 1835.1127 | J49: =SUM(J43:J48) -> 0 | K49: =SUM(K43:K48) -> 0 | L49: =SUM(L43:L48) -> 0 | M49: =SUM(M43:M48) -> 0
C50: Passive latente Steuern | D50: Deferred tax liabilities | F50: 0 | G50: =SUMIF('Trial Balance (Susa)'!D:D,"*"&$P50&"*",'Trial Balance (Susa)'!G:G)/1000 -> 0 | H50: =SUMIF('Trial Balance (Susa)'!D:D,"*"&$P50&"*",'Trial Balance (Susa)'!H:H)/1000 -> -48.876 | I50: =SUMIF('Trial Balance (Susa)'!D:D,"*"&$P50&"*",'Trial Balance (Susa)'!I:I)/1000 -> -198.336 | P50: /other/deferred tax liabilities
C51: Dummy 1 | D51: Dummy 1
C52: Dummy 2 | D52: Dummy 2
C53: Dummy 3 | D53: Dummy 3
C54: Nettovermögen (Eigenkapital) | D54: Net assets (Equity) | E54: =SUM(E50:E53)+E49+E42+E15 -> 0 | F54: =SUM(F50:F53)+F49+F42+F15 -> 5794.2711 | G54: =SUM(G50:G53)+G49+G42+G15 -> 6186.9079 | H54: =SUM(H50:H53)+H49+H42+H15 -> 6281.9602 | I54: =SUM(I50:I53)+I49+I42+I15 -> 6991.3051 | J54: =SUM(J50:J53)+J49+J42+J15 -> 0 | K54: =SUM(K50:K53)+K49+K42+K15 -> 0 | L54: =SUM(L50:L53)+L49+L42+L15 -> 0 | M54: =SUM(M50:M53)+M49+M42+M15 -> 0
C56: Equity Roll Forward | D56: Equity roll forward
C57: Nettovermögen (Periodenbeginn) | D57: Net Assets BoP | F57: =E62 -> 4820.143 | G57: =F62 -> -1838.8551 | H57: =G62 -> -9532.7207 | I57: =H62 -> -17835.556 | J57: =I62 -> -24487.996 | K57: =J62 -> -24487.996 | L57: =K62 -> -24487.996 | M57: =L62 -> -24487.996
C58: ∆ Gezeichnetes Kapital | D58: ∆ Subscriped capital | P58: manual adjustment
C59: ∆ Kapitalrücklage | D59: ∆ Capital reserves | P59: manual adjustment
C60: Gewinnausschüttung | D60: Profit distribution | F60: -880 | G60: -450 | H60: -900 | P60: manual adjustment
C61: Jahresergebnis | D61: Periodical Profit/Loss | F61: ='Lead PL'!F59 -> -5778.9981 | G61: ='Lead PL'!G59 -> -7243.8655 | H61: ='Lead PL'!H59 -> -7402.8351 | I61: ='Lead PL'!I59 -> -6652.4398 | J61: ='Lead PL'!K59 -> 0 | K61: ='Lead PL'!L59 -> 0 | L61: ='Lead PL'!M59 -> 0 | M61: ='Lead PL'!N59 -> 0
C62: Nettovermögen (Periodenende) | D62: Net Assets EoP | E62: ='Balance Sheet (Annual Report)'!D68/1000 -> 4820.143 | F62: =SUM(F57:F61) -> -1838.8551 | G62: =SUM(G57:G61) -> -9532.7207 | H62: =SUM(H57:H61) -> -17835.556 | I62: =SUM(I57:I61) -> -24487.996 | J62: =SUM(J57:J61) -> -24487.996 | K62: =SUM(K57:K61) -> -24487.996 | L62: =SUM(L57:L61) -> -24487.996 | M62: =SUM(M57:M61) -> -24487.996
C64: ="Quelle: "&Cockpit!$C$7 -> Quelle: Datenraum/ eigene Analysen | D64: ="Source: "&Cockpit!$C$8 -> Source: Virtual Data Room/ Company Information
C67: Equity roll forward | D67: Equity roll forward | F67: ='Balance Sheet (Annual Report)'!E68/1000 -> 5794.2711
C68: Check | D68: Check | F68: =F62-F54 -> -7633.1262 | G68: =G62-G54 -> -15719.629 | H68: =H62-H54 -> -24117.516 | I68: =I62-I54 -> -31479.301
C70: AKTIVA | F70: =F15+F16+F17+F30+F43+F48 -> 7999.6388 | G70: =G15+G16+G17+G30+G43+G48 -> 8217.4235 | H70: =H15+H16+H17+H30+H43+H48 -> 8441.2165 | I70: =I15+I16+I17+I30+I43+I48 -> 8284.3137 | R70: /equity/issued capital
F71: =F15/F70 -> 0.14924238 | G71: =G15/G70 -> 0.10964032 | H71: =H15/H70 -> 0.13104341 | I71: =I15/I70 -> 0.16758828 | R71: /equity/profit-loss carried forward
H72: =AVERAGE(F71:H71) -> 0.12997537 | I72: =AVERAGE(F71:I71) -> 0.1393786

Sheet Lead CF
C4: =Cockpit!$C$4 -> Projekt Namur | E4: =Cockpit!C33 -> 44561 | F4: =Cockpit!D33 -> 44926 | G4: =Cockpit!E33 -> 45291 | H4: =Cockpit!F33 -> 45657 | I4: =Cockpit!G33 -> 46022 | J4: =Cockpit!H33 -> 46022 | K4: =Cockpit!I33 -> 46022 | L4: =Cockpit!J33 -> 46387 | ... N4: =Cockpit!L33 -> 47118 | P4: Bilanzveränderungen manuell zu ergänzen
C5: ="in T"&Cockpit!$C$5 -> in TEUR | E5: IST | F5: IST | G5: IST | H5: IST | I5: =Cockpit!G34 -> IST | J5: IST | K5: =Cockpit!I34 -> Plan | L5: =Cockpit!J34 -> Plan | M5: =Cockpit!K34 -> Plan | N5: =Cockpit!L34 -> Plan
D6: =Cockpit!$C$4 -> Projekt Namur | E6: =Cockpit!C33 -> 44561 | F6: =Cockpit!D33 -> 44926 | G6: =Cockpit!E33 -> 45291 | H6: =Cockpit!F33 -> 45657 | I6: =Cockpit!G33 -> 46022 | J6: =Cockpit!H33 -> 46022 | K6: =Cockpit!I33 -> 46022 | L6: =Cockpit!J33 -> 46387 | ... N6: =Cockpit!L33 -> 47118 | P6: Bilanzveränderungen manuell zu ergänzen
D7: ="in k"&Cockpit!$C$5 -> in kEUR | E7: =Cockpit!D34 -> IST | F7: =Cockpit!D34 -> IST | G7: =Cockpit!E34 -> IST | H7: =Cockpit!F34 -> IST | I7: =Cockpit!G34 -> IST | J7: =Cockpit!H34 -> YTD | K7: =Cockpit!I34 -> Plan | L7: =Cockpit!J34 -> Plan | M7: =Cockpit!K34 -> Plan | N7: =Cockpit!L34 -> Plan
C9: ='Lead PL'!C43 -> EBITDA | D9: ='Lead PL'!D43 -> EBITDA | F9: ='Lead PL'!F43 -> -4386.7022 | G9: ='Lead PL'!G43 -> -6491.3424 | H9: ='Lead PL'!H43 -> -6637.5466 | I9: ='Lead PL'!I43 -> -6045.3006 | J9: ='Lead PL'!I43 -> -6045.3006 | K9: ='Lead PL'!K43 -> 0 | L9: ='Lead PL'!L43 -> 0 | M9: ='Lead PL'!M43 -> 0 | N9: ='Lead PL'!N43 -> 0
C10: ='Lead PL'!C57 -> Ertragssteuern | D10: ='Lead PL'!D57 -> Income taxes | F10: ='Lead PL'!F57 -> -898.38628 | G10: ='Lead PL'!G57 -> -390.61759 | H10: ='Lead PL'!H57 -> -442.12161 | I10: ='Lead PL'!I57 -> -333.75368 | J10: ='Lead PL'!I57 -> -333.75368 | K10: ='Lead PL'!K58 -> 0 | L10: ='Lead PL'!L58 -> 0 | M10: ='Lead PL'!M58 -> 0 | N10: ='Lead PL'!N58 -> 0
C11: ='Lead PL'!C58 -> Sonstige Steuern | D11: ='Lead PL'!D58 -> Other taxes | F11: ='Lead PL'!F58 -> -3.077 | G11: ='Lead PL'!G58 -> -2.922 | H11: ='Lead PL'!H58 -> -3.002 | I11: ='Lead PL'!I58 -> -2.254 | J11: ='Lead PL'!I58 -> -2.254 | K11: ='Lead PL'!K57 -> 0 | L11: ='Lead PL'!L57 -> 0 | M11: ='Lead PL'!M57 -> 0 | N11: ='Lead PL'!N57 -> 0
C12: ="∆ "&'Lead NA'!C45 -> ∆ Pensionsrückstellungen | F12: =-'Lead NA'!F45+'Lead NA'!E45 -> 201.476 | G12: =-'Lead NA'!G45+'Lead NA'!F45 -> -9.374 | H12: =-'Lead NA'!H45+'Lead NA'!G45 -> -9.699 | I12: =-NA_monthly!AX46+NA_monthly!AL46 -> -9.699 | J12: =-'Lead NA'!I45+'Lead NA'!H45 -> -10.66
C13: ="∆ "&'Lead NA'!C46 -> ∆ Steuerrückstellungen | F13: =-'Lead NA'!F46+'Lead NA'!E46 -> 224.92819 | G13: =-'Lead NA'!G46+'Lead NA'!F46 -> 0 | H13: =-'Lead NA'!H46+'Lead NA'!G46 -> -224.92819 | I13: =-NA_monthly!AX47+NA_monthly!AL47 -> -15.44608 | J13: =-'Lead NA'!I46+'Lead NA'!H46 -> 0
C14: ="∆ "&'Lead NA'!C50 -> ∆ Passive latente Steuern | G14: =-'Lead NA'!G50+'Lead NA'!F50 -> 0 | H14: =-'Lead NA'!H50+'Lead NA'!G50 -> 48.876 | I14: =-NA_monthly!AX51+NA_monthly!AL51 -> 48.876 | J14: =-'Lead NA'!I50+'Lead NA'!H50 -> 149.46
C16: ="∆ "&'Lead NA'!C16 -> ∆ Vorräte | D16: ="∆ "&'Lead NA'!D16 -> ∆ Inventories | F16: =-'Lead NA'!F16+'Lead NA'!E16 -> -1953.4011 | G16: =-'Lead NA'!G16+'Lead NA'!F16 -> -698.70757 | H16: =-'Lead NA'!H16+'Lead NA'!G16 -> -1203.775 | I16: =-NA_monthly!AX16+NA_monthly!AL16 -> -1180.3231 | J16: =-'Lead NA'!I16+'Lead NA'!H16 -> 943.19708 | K16: =-'Lead NA'!J16+'Lead NA'!H16 -> 3855.8836 | L16: =-'Lead NA'!K16+'Lead NA'!J16 -> 0 | M16: =-'Lead NA'!L16+'Lead NA'!K16 -> 0 | N16: =-'Lead NA'!M16+'Lead NA'!L16 -> 0
C17: ="∆ "&'Lead NA'!C17 -> ∆ Forderungen aus LuL | D17: ="∆ "&'Lead NA'!D17 -> ∆ Trade receivables | F17: =-'Lead NA'!F17+'Lead NA'!E17 -> -1780.6561 | G17: =-'Lead NA'!G17+'Lead NA'!F17 -> 194.28828 | H17: =-'Lead NA'!H17+'Lead NA'!G17 -> -402.43357 | I17: =-NA_monthly!AX17+NA_monthly!AL17 -> -60.55489 | J17: =-'Lead NA'!I17+'Lead NA'!H17 -> 573.14715 | K17: =-'Lead NA'!J17+'Lead NA'!H17 -> 1988.8014 | L17: =-'Lead NA'!K17+'Lead NA'!J17 -> 0 | M17: =-'Lead NA'!L17+'Lead NA'!K17 -> 0 | N17: =-'Lead NA'!M17+'Lead NA'!L17 -> 0
C18: ="∆ "&'Lead NA'!C18 -> ∆ Verbindlichkeiten aus LuL | D18: ="∆ "&'Lead NA'!D18 -> ∆ Trade payables | F18: =-'Lead NA'!F18+'Lead NA'!E18 -> 752.85966 | G18: =-'Lead NA'!G18+'Lead NA'!F18 -> 95.4239 | H18: =-'Lead NA'!H18+'Lead NA'!G18 -> 372.15445 | I18: =-NA_monthly!AX18+NA_monthly!AL18 -> -945.14974 | J18: =-'Lead NA'!I18+'Lead NA'!H18 -> -976.94827 | K18: =-'Lead NA'!J18+'Lead NA'!H18 -> -1220.438 | L18: =-'Lead NA'!K18+'Lead NA'!J18 -> 0 | M18: =-'Lead NA'!L18+'Lead NA'!K18 -> 0 | N18: =-'Lead NA'!M18+'Lead NA'!L18 -> 0
C19: ="∆ "&'Lead NA'!C19 -> ∆ Erhaltene Anzahlungen | D19: ="∆ "&'Lead NA'!D19 -> ∆ Advance payments received | F19: =-'Lead NA'!F19+'Lead NA'!E19 -> 50 | G19: =-'Lead NA'!G19+'Lead NA'!F19 -> 0 | H19: =-'Lead NA'!H19+'Lead NA'!G19 -> 0 | I19: =-NA_monthly!AX19+NA_monthly!AL19 -> -50 | J19: =-'Lead NA'!I19+'Lead NA'!H19 -> -50
C20: ="∆ "&'Lead NA'!C20 -> ∆ Dummy 1 | D20: ="∆ "&'Lead NA'!D20 -> ∆ Dummy 1 | F20: =-'Lead NA'!F20+'Lead NA'!E20 -> 0 | G20: =-'Lead NA'!G20+'Lead NA'!F20 -> 0 | H20: =-'Lead NA'!H20+'Lead NA'!G20 -> 0 | J20: =-'Lead NA'!I20+'Lead NA'!H20 -> 0 | K20: =-'Lead NA'!J20+'Lead NA'!H20 -> 0 | L20: =-'Lead NA'!K20+'Lead NA'!J20 -> 0 | M20: =-'Lead NA'!L20+'Lead NA'!K20 -> 0 | N20: =-'Lead NA'!M20+'Lead NA'!L20 -> 0
C21: ="∆ "&'Lead NA'!C21 -> ∆ Dummy 2 | D21: ="∆ "&'Lead NA'!D21 -> ∆ Dummy 2 | F21: =-'Lead NA'!F21+'Lead NA'!E21 -> 0 | G21: =-'Lead NA'!G21+'Lead NA'!F21 -> 0 | H21: =-'Lead NA'!H21+'Lead NA'!G21 -> 0 | J21: =-'Lead NA'!I21+'Lead NA'!H21 -> 0 | K21: =-'Lead NA'!J21+'Lead NA'!H21 -> 0 | L21: =-'Lead NA'!K21+'Lead NA'!J21 -> 0 | M21: =-'Lead NA'!L21+'Lead NA'!K21 -> 0 | N21: =-'Lead NA'!M21+'Lead NA'!L21 -> 0
C22: ="∆ "&'Lead NA'!C22 -> ∆ Dummy 3 | D22: ="∆ "&'Lead NA'!D22 -> ∆ Dummy 3 | F22: =-'Lead NA'!F22+'Lead NA'!E22 -> 0 | G22: =-'Lead NA'!G22+'Lead NA'!F22 -> 0 | H22: =-'Lead NA'!H22+'Lead NA'!G22 -> 0 | J22: =-'Lead NA'!I22+'Lead NA'!H22 -> 0 | K22: =-'Lead NA'!J22+'Lead NA'!H22 -> 0 | L22: =-'Lead NA'!K22+'Lead NA'!J22 -> 0 | M22: =-'Lead NA'!L22+'Lead NA'!K22 -> 0 | N22: =-'Lead NA'!M22+'Lead NA'!L22 -> 0
C23: ="∆ "&'Lead NA'!C23 -> ∆ Trade Working Capital | D23: ="∆ "&'Lead NA'!D23 -> ∆ Trade working capital | F23: =SUM(F16:F22) -> -2931.1975 | G23: =SUM(G16:G22) -> -408.99539 | H23: =SUM(H16:H22) -> -1234.0541 | I23: =SUM(I16:I22) -> -2236.0277 | J23: =SUM(J16:J22) -> 489.39596 | K23: =SUM(K16:K22) -> 4624.247 | L23: =SUM(L16:L22) -> 0 | M23: =SUM(M16:M22) -> 0 | N23: =SUM(N16:N22) -> 0
C24: ="∆ "&'Lead NA'!C24 -> ∆ Sonstige Vermögensgegenstände | D24: ="∆ "&'Lead NA'!D24 -> ∆ Other assets | F24: =-'Lead NA'!F24+'Lead NA'!E24 -> -33.1297 | G24: =-'Lead NA'!G24+'Lead NA'!F24 -> -263.38516 | H24: =-'Lead NA'!H24+'Lead NA'!G24 -> -17.0704 | I24: =-NA_monthly!AX24+NA_monthly!AL24 -> 110.73111 | J24: =-'Lead NA'!I24+'Lead NA'!H24 -> 4.49342 | K24: =-'Lead NA'!J24+'Lead NA'!H24 -> 313.58526 | L24: =-'Lead NA'!K24+'Lead NA'!J24 -> 0 | M24: =-'Lead NA'!L24+'Lead NA'!K24 -> 0 | N24: =-'Lead NA'!M24+'Lead NA'!L24 -> 0
C25: ="∆ "&'Lead NA'!C25 -> ∆ Aktive Rechnungsabgrenzungsposten | D25: ="∆ "&'Lead NA'!D25 -> ∆ Prepaid expenses | F25: =-'Lead NA'!F25+'Lead NA'!E25 -> -30.21821 | G25: =-'Lead NA'!G25+'Lead NA'!F25 -> -35.68575 | H25: =-'Lead NA'!H25+'Lead NA'!G25 -> 2.9761 | I25: =-NA_monthly!AX25+NA_monthly!AL25 -> -10.35157 | J25: =-'Lead NA'!I25+'Lead NA'!H25 -> 11.62641 | K25: =-'Lead NA'!J25+'Lead NA'!H25 -> 62.92786 | L25: =-'Lead NA'!K25+'Lead NA'!J25 -> 0 | M25: =-'Lead NA'!L25+'Lead NA'!K25 -> 0 | N25: =-'Lead NA'!M25+'Lead NA'!L25 -> 0
C26: ="∆ "&'Lead NA'!C26 -> ∆ Geleistete Anzahlung | D26: ="∆ "&'Lead NA'!D26 -> ∆ Receivables from affiliated/ participating companies | F26: =-'Lead NA'!F26+'Lead NA'!E26 -> 0 | G26: =-'Lead NA'!G26+'Lead NA'!F26 -> 0 | H26: =-'Lead NA'!H26+'Lead NA'!G26 -> 0 | J26: =-'Lead NA'!I26+'Lead NA'!H26 -> -180.945
C27: ="∆ "&'Lead NA'!C27 -> ∆ Dummy 2 | D27: ="∆ "&'Lead NA'!D27 -> ∆ | F27: =-'Lead NA'!F27+'Lead NA'!E27 -> 0 | G27: =-'Lead NA'!G27+'Lead NA'!F27 -> 0 | H27: =-'Lead NA'!H27+'Lead NA'!G27 -> 0 | J27: =-'Lead NA'!I27+'Lead NA'!H27 -> 0 | K27: =-'Lead NA'!J27+'Lead NA'!H27 -> 0 | L27: =-'Lead NA'!K27+'Lead NA'!J27 -> 0 | M27: =-'Lead NA'!L27+'Lead NA'!K27 -> 0 | N27: =-'Lead NA'!M27+'Lead NA'!L27 -> 0
C28: ="∆ "&'Lead NA'!C28 -> ∆ Dummy 2 | D28: ="∆ "&'Lead NA'!D28 -> ∆ Dummy 2 | F28: =-'Lead NA'!F28+'Lead NA'!E28 -> 0 | G28: =-'Lead NA'!G28+'Lead NA'!F28 -> 0 | H28: =-'Lead NA'!H28+'Lead NA'!G28 -> 0 | J28: =-'Lead NA'!I28+'Lead NA'!H28 -> 0 | K28: =-'Lead NA'!J28+'Lead NA'!H28 -> 0 | L28: =-'Lead NA'!K28+'Lead NA'!J28 -> 0 | M28: =-'Lead NA'!L28+'Lead NA'!K28 -> 0 | N28: =-'Lead NA'!M28+'Lead NA'!L28 -> 0
C29: ="∆ "&'Lead NA'!C29 -> ∆ Dummy 3 | D29: ="∆ "&'Lead NA'!D29 -> ∆ Dummy 3 | F29: =-'Lead NA'!F29+'Lead NA'!E29 -> 0 | G29: =-'Lead NA'!G29+'Lead NA'!F29 -> 0 | H29: =-'Lead NA'!H29+'Lead NA'!G29 -> 0 | J29: =-'Lead NA'!I29+'Lead NA'!H29 -> 0 | K29: =-'Lead NA'!J29+'Lead NA'!H29 -> 0 | L29: =-'Lead NA'!K29+'Lead NA'!J29 -> 0 | M29: =-'Lead NA'!L29+'Lead NA'!K29 -> 0 | N29: =-'Lead NA'!M29+'Lead NA'!L29 -> 0
C30: ="∆ "&'Lead NA'!C31 -> ∆ Sonstige Rückstellungen | D30: ="∆ "&'Lead NA'!D31 -> ∆ Other provisions | F30: =-'Lead NA'!F31+'Lead NA'!E31 -> 527.64378 | G30: =-'Lead NA'!G31+'Lead NA'!F31 -> -102.73638 | H30: =-'Lead NA'!H31+'Lead NA'!G31 -> -196.50445 | I30: =-NA_monthly!AX32+NA_monthly!AL32 -> 71.64589 | J30: =-'Lead NA'!I31+'Lead NA'!H31 -> 199.87071 | K30: =-'Lead NA'!J31+'Lead NA'!H31 -> -228.40295 | L30: =-'Lead NA'!K31+'Lead NA'!J31 -> 0 | M30: =-'Lead NA'!L31+'Lead NA'!K31 -> 0 | N30: =-'Lead NA'!M31+'Lead NA'!L31 -> 0
C31: ="∆ "&'Lead NA'!C32 -> ∆ Sonstige Verbindlichkeiten | D31: ="∆ "&'Lead NA'!D32 -> ∆ Other liabilities | F31: =-'Lead NA'!F32+'Lead NA'!E32 -> 448.46014 | G31: =-'Lead NA'!G32+'Lead NA'!F32 -> -158.16573 | H31: =-'Lead NA'!H32+'Lead NA'!G32 -> 138.84192 | I31: =-NA_monthly!AX33+NA_monthly!AL33 -> -103.94465 | J31: =-'Lead NA'!I32+'Lead NA'!H32 -> -197.39519 | K31: =-'Lead NA'!J32+'Lead NA'!H32 -> -429.13633 | L31: =-'Lead NA'!K32+'Lead NA'!J32 -> 0 | M31: =-'Lead NA'!L32+'Lead NA'!K32 -> 0 | N31: =-'Lead NA'!M32+'Lead NA'!L32 -> 0
C32: ="∆ "&'Lead NA'!C33 -> ∆ Dummy 1 | D32: ="∆ "&'Lead NA'!D33 -> ∆ Tax provisions | F32: =-'Lead NA'!F33+'Lead NA'!E33 -> 0 | G32: =-'Lead NA'!G33+'Lead NA'!F33 -> 0 | H32: =-'Lead NA'!H33+'Lead NA'!G33 -> 0 | J32: =-'Lead NA'!I33+'Lead NA'!H33 -> 0
C33: ="∆ "&'Lead NA'!C34 -> ∆ Dummy 1 | D33: ="∆ "&'Lead NA'!D34 -> ∆ Liabilities to affiliated/ participating companies | F33: =-'Lead NA'!F34+'Lead NA'!E34 -> 0 | G33: =-'Lead NA'!G34+'Lead NA'!F34 -> 0 | H33: =-'Lead NA'!H34+'Lead NA'!G34 -> 0 | J33: =-'Lead NA'!I34+'Lead NA'!H34 -> 0 | K33: =-'Lead NA'!J34+'Lead NA'!H34 -> 0 | L33: =-'Lead NA'!K34+'Lead NA'!J34 -> 0 | M33: =-'Lead NA'!L34+'Lead NA'!K34 -> 0 | N33: =-'Lead NA'!M34+'Lead NA'!L34 -> 0
C34: ="∆ "&'Lead NA'!C35 -> ∆ Dummy 1 | D34: ="∆ "&'Lead NA'!D35 -> ∆ Liabilities to shareholders | F34: =-'Lead NA'!F35+'Lead NA'!E35 -> 0 | G34: =-'Lead NA'!G35+'Lead NA'!F35 -> 0 | H34: =-'Lead NA'!H35+'Lead NA'!G35 -> 0 | J34: =-'Lead NA'!I35+'Lead NA'!H35 -> 0 | K34: =-'Lead NA'!J35+'Lead NA'!H35 -> 0 | L34: =-'Lead NA'!K35+'Lead NA'!J35 -> 0 | M34: =-'Lead NA'!L35+'Lead NA'!K35 -> 0 | N34: =-'Lead NA'!M35+'Lead NA'!L35 -> 0
C35: ="∆ "&'Lead NA'!C36 -> ∆ Dummy 1 | D35: ="∆ "&'Lead NA'!D36 -> ∆ Deferred income | F35: =-'Lead NA'!F36+'Lead NA'!E36 -> 0 | G35: =-'Lead NA'!G36+'Lead NA'!F36 -> 0 | H35: =-'Lead NA'!H36+'Lead NA'!G36 -> 0 | J35: =-'Lead NA'!I36+'Lead NA'!H36 -> 0
C36: ="∆ "&'Lead NA'!C37 -> ∆ Dummy 1 | D36: ="∆ "&'Lead NA'!D37 -> ∆ Dummy 1 | F36: =-'Lead NA'!F37+'Lead NA'!E37 -> 0 | G36: =-'Lead NA'!G37+'Lead NA'!F37 -> 0 | H36: =-'Lead NA'!H37+'Lead NA'!G37 -> 0 | J36: =-'Lead NA'!I37+'Lead NA'!H37 -> 0
C37: ="∆ "&'Lead NA'!C38 -> ∆ Dummy 2 | D37: ="∆ "&'Lead NA'!D38 -> ∆ Dummy 2 | F37: =-'Lead NA'!F38+'Lead NA'!E38 -> 0 | G37: =-'Lead NA'!G38+'Lead NA'!F38 -> 0 | H37: =-'Lead NA'!H38+'Lead NA'!G38 -> 0 | J37: =-'Lead NA'!I38+'Lead NA'!H38 -> 0
C38: ="∆ "&'Lead NA'!C39 -> ∆ Dummy 3 | D38: ="∆ "&'Lead NA'!D39 -> ∆ Dummy 3 | F38: =-'Lead NA'!F39+'Lead NA'!E39 -> 0 | G38: =-'Lead NA'!G39+'Lead NA'!F39 -> 0 | H38: =-'Lead NA'!H39+'Lead NA'!G39 -> 0 | J38: =-'Lead NA'!I39+'Lead NA'!H39 -> 0 | K38: =-'Lead NA'!J39+'Lead NA'!H39 -> 0 | L38: =-'Lead NA'!K39+'Lead NA'!J39 -> 0 | M38: =-'Lead NA'!L39+'Lead NA'!K39 -> 0 | N38: =-'Lead NA'!M39+'Lead NA'!L39 -> 0
C39: ="∆ "&'Lead NA'!C41 -> ∆ Other Working Capital | D39: ="∆ "&'Lead NA'!D41 -> ∆ Other working capital | F39: =SUM(F24:F38) -> 912.75601 | G39: =SUM(G24:G38) -> -559.97302 | H39: =SUM(H24:H38) -> -71.75683 | I39: =SUM(I24:I38) -> 68.08078 | J39: =SUM(J24:J38) -> -162.34965 | K39: =SUM(K24:K38) -> -281.02616 | L39: =SUM(L24:L38) -> 0 | M39: =SUM(M24:M38) -> 0 | N39: =SUM(N24:N38) -> 0
C40: Operativer Cashflow | D40: Operating cash flow | F40: =F9+SUM(F10:F11)+F23+F39 -> -7306.6069 | G40: =G9+SUM(G10:G14)+G23+G39 -> -7863.2244 | H40: =H9+SUM(H10:H14)+H23+H39 -> -8574.2324 | I40: =I9+SUM(I10:I14)+I23+I39 -> -8525.5243 | J40: =J9+SUM(J10:J14)+J23+J39 -> -5915.462 | K40: =K9+SUM(K10:K11)+K23+K39 -> 4343.2208 | L40: =L9+SUM(L10:L11)+L23+L39 -> 0 | M40: =M9+SUM(M10:M11)+M23+M39 -> 0 | N40: =N9+SUM(N10:N11)+N23+N39 -> 0
C42: CAPEX | D42: Maintenance CAPEX | F42: =-('Lead NA'!F15-'Lead NA'!E15)+'Lead PL'!F44 -> -1549.2268 | G42: =-('Lead NA'!G15-'Lead NA'!F15)+'Lead PL'!G44 -> -31.71571 | H42: =-('Lead NA'!H15-'Lead NA'!G15)+'Lead PL'!H44 -> -520.92459 | I42: =-(NA_monthly!AX15-NA_monthly!AL15)+SUM(PL_monthly!AM35:AX35) -> -334.70818 | J42: =-('Lead NA'!I15-'Lead NA'!H15)+'Lead PL'!I44 -> -550.9706
C43: Dummy 1 | D43: Expansion CAPEX | P43: Check for information regarding maintenance/ expansion or change to generally "CAPEX"
C44: Dummy 1 | D44: Dummy 1
C45: Dummy 2 | D45: Dummy 2
C46: Dummy 3 | D46: Dummy 3
C47: Cashflow Investitionen | D47: Investing cash flow | F47: =SUM(F42:F46) -> -1549.2268 | G47: =SUM(G42:G46) -> -31.71571 | H47: =SUM(H42:H46) -> -520.92459 | I47: =SUM(I42:I46) -> -334.70818 | J47: =SUM(J42:J46) -> -550.9706 | K47: =SUM(K42:K46) -> 0 | L47: =SUM(L42:L46) -> 0 | M47: =SUM(M42:M46) -> 0 | N47: =SUM(N42:N46) -> 0
C49: Free Cashflow | D49: Free Cashflow | F49: =F40+F47 -> -8855.8338 | G49: =G40+G47 -> -7894.9401 | H49: =H40+H47 -> -9095.1569 | I49: =I40+I47 -> -8860.2325 | J49: =J40+J47 -> -6466.4326
C51: ="∆ "&'Lead NA'!C44 -> ∆ Verbindlichkeiten ggü.Kreditinstituten | D51: ="∆ "&'Lead NA'!D44 -> ∆ Liabilities to banks | F51: =-'Lead NA'!F44+'Lead NA'!E44 -> 0 | G51: =-'Lead NA'!G44+'Lead NA'!F44 -> 0 | H51: =-'Lead NA'!H44+'Lead NA'!G44 -> 0 | I51: =-NA_monthly!AX45+NA_monthly!AL45 -> 19.425 | J51: =-'Lead NA'!I44+'Lead NA'!H44 -> 19.425
C52: ="∆ "&'Lead NA'!C47 -> ∆ Dummy 1
C53: ="∆ "&'Lead NA'!C47 -> ∆ Dummy 1
C54: ="∆ "&'Lead NA'!C47 -> ∆ Dummy 1 | D54: ="∆ "&'Lead NA'!D47 -> ∆ Other provisions | F54: =-'Lead NA'!F47+'Lead NA'!E47 -> 0 | G54: =-'Lead NA'!G47+'Lead NA'!F47 -> 0 | H54: =-'Lead NA'!H47+'Lead NA'!G47 -> 0 | J54: =-'Lead NA'!I47+'Lead NA'!H47 -> 2.3283064e-13
C55: ="∆ "&'Lead NA'!C48 -> ∆ Sonstige Wertpapiere | D55: ="∆ "&'Lead NA'!D48 -> ∆ Short-term securities | F55: =-'Lead NA'!F48+'Lead NA'!E48 -> 0 | G55: =-'Lead NA'!G48+'Lead NA'!F48 -> 0 | H55: =-'Lead NA'!H48+'Lead NA'!G48 -> -109.79175 | I55: =-NA_monthly!AX49+NA_monthly!AL49 -> -78.65 | J55: =-'Lead NA'!I48+'Lead NA'!H48 -> 109.79175
C56: Kapitalerhöhungen / -herabsetzungen | D56: ∆ Equity contributions
C57: ='Lead PL'!C55 -> Finanzergebnis | D57: ='Lead PL'!D55 -> Financial result | F57: ='Lead PL'!F55 -> -135.49096 | G57: ='Lead PL'!G55 -> -34.34364 | H57: ='Lead PL'!H55 -> -4.44515 | I57: ='Lead PL'!I55 -> -2.34898 | J57: ='Lead PL'!I55 -> -2.34898 | K57: ='Lead PL'!K55 -> 0 | L57: ='Lead PL'!L55 -> 0 | M57: ='Lead PL'!M55 -> 0 | N57: ='Lead PL'!N55 -> 0
C58: Gewinnausschüttung | D58: Profit distribution | F58: ='Lead NA'!F60 -> -880 | G58: ='Lead NA'!G60 -> -450 | H58: ='Lead NA'!H60 -> -900 | J58: ='Lead NA'!I60 -> 0 | K58: ='Lead NA'!J60 -> 0 | L58: ='Lead NA'!K60 -> 0 | M58: ='Lead NA'!L60 -> 0 | N58: ='Lead NA'!M60 -> 0
C59: Cashflow Finanzierung | D59: Financing cash flow | F59: =SUM(F51:F58) -> -1015.491 | G59: =SUM(G51:G58) -> -484.34364 | H59: =SUM(H51:H58) -> -1014.2369 | I59: =SUM(I51:I58) -> -61.57398 | J59: =SUM(J51:J58) -> 126.86777 | K59: =SUM(K51:K58) -> 0 | L59: =SUM(L51:L58) -> 0 | M59: =SUM(M51:M58) -> 0 | N59: =SUM(N51:N58) -> 0
C62: Veränderung Liquide Mittel | D62: Total change in cash | F62: =F49+F59 -> -9871.3247 | G62: =G49+G59 -> -8379.2837 | H62: =H49+H59 -> -10109.394 | I62: =I49+I59 -> -8921.8065 | J62: =J49+J59 -> -6339.5648 | K62: =SUM(K40,K47,K59) -> 4343.2208 | L62: =SUM(L40,L47,L59) -> 0 | M62: =SUM(M40,M47,M59) -> 0 | N62: =SUM(N40,N47,N59) -> 0
C64: Liquide Mittel (Periodenbeginn) | D64: Cash BoP | F64: =E66 -> 0 | G64: =F66 -> 3008.3487 | H64: =G66 -> -5370.9351 | I64: =NA_monthly!AL44 -> 1633.0421 | J64: =H66 -> -15480.329 | K64: =H66 -> -15480.329 | L64: =K66 -> -11137.108 | M64: =L66 -> -11137.108 | N64: =M66 -> -11137.108
C65: =C62 -> Veränderung Liquide Mittel | D65: =D62 -> Total change in cash | F65: =F62 -> -9871.3247 | G65: =G62 -> -8379.2837 | H65: =H62 -> -10109.394 | I65: =I62 -> -8921.8065 | J65: =J62 -> -6339.5648 | K65: =K62 -> 4343.2208 | L65: =L62 -> 0 | M65: =M62 -> 0 | N65: =N62 -> 0
C66: Liquide Mittel (Periodenende) | D66: Cash EoP | E66: ='Lead NA'!E43 -> 0 | F66: ='Lead NA'!F43 -> 3008.3487 | G66: =SUM(G64:G65) -> -5370.9351 | H66: =SUM(H64:H65) -> -15480.329 | I66: =SUM(I64:I65) -> -7288.7644 | J66: =SUM(J64:J65) -> -21819.894 | K66: =SUM(K64:K65) -> -11137.108 | L66: =SUM(L64:L65) -> -11137.108 | M66: =SUM(M64:M65) -> -11137.108 | N66: =SUM(N64:N65) -> -11137.108
C68: In % des EBITDA | D68: In % of EBITDA
C69: Operating cash conversion | D69: Operating cash conversion | F69: =IFERROR(F40/F$9,"n/a") -> 1.6656264 | G69: =IFERROR(G40/G$9,"n/a") -> 1.2113403 | H69: =IFERROR(H40/H$9,"n/a") -> 1.2917773 | I69: =IFERROR(I40/I$9,"n/a") -> 1.410273 | J69: =IFERROR(J40/J$9,"n/a") -> 0.97852239 | K69: =IFERROR(K40/K$9,"n/a") -> n/a | L69: =IFERROR(L40/L$9,"n/a") -> n/a | M69: =IFERROR(M40/M$9,"n/a") -> n/a | N69: =IFERROR(N40/N$9,"n/a") -> n/a
C70: Free cash conversion | D70: Free cash conversion | F70: =IFERROR((F40+F47)/F$9,"n/a") -> 2.0187907 | G70: =IFERROR((G40+G47)/G$9,"n/a") -> 1.2162261 | H70: =IFERROR((H40+H47)/H$9,"n/a") -> 1.3702588 | I70: =IFERROR((I40+I47)/I$9,"n/a") -> 1.4656397 | J70: =IFERROR((J40+J47)/J$9,"n/a") -> 1.0696627 | K70: =IFERROR((K40+K47)/K$9,"n/a") -> n/a | L70: =IFERROR((L40+L47)/L$9,"n/a") -> n/a | M70: =IFERROR((M40+M47)/M$9,"n/a") -> n/a | N70: =IFERROR((N40+N47)/N$9,"n/a") -> n/a
C72: ="Quelle: "&Cockpit!$C$7 -> Quelle: Datenraum/ eigene Analysen | D72: ="Source: "&Cockpit!$C$8 -> Source: Virtual Data Room/ Company Information
E75: 1. Periode als Ausgangspunkt auf Lead NA verknüpft
C76: Liquide Mittel Periodenende Lead NA | D76: Cash EoP Lead NA | E76: ='Lead NA'!E43 -> 0 | F76: ='Lead NA'!F43 -> 3008.3487 | G76: ='Lead NA'!G43 -> 2715.5673 | H76: ='Lead NA'!H43 -> 1004.0608 | I76: ='Lead NA'!I43 -> 2026.2807 | J76: ='Lead NA'!I43 -> 2026.2807 | K76: ='Lead NA'!J43 -> 0 | L76: ='Lead NA'!K43 -> 0 | M76: ='Lead NA'!L43 -> 0 | N76: ='Lead NA'!M43 -> 0
C77: Check | D77: Check | E77: =E76-E66 -> 0 | F77: =F76-F66 -> 0 | G77: =G76-G66 -> 8086.5024 | H77: =H76-H66 -> 16484.39 | I77: =I76-I66 -> 9315.0451 | J77: =J76-J66 -> 23846.174 | K77: =K76-K66 -> 11137.108 | L77: =L76-L66 -> 11137.108 | ... N77: =N76-N66 -> 11137.108
C79: Check TWC | D79: Check TWC | G79: =('Lead NA'!G23-'Lead NA'!F23)+G23 -> 4.5474735e-13 | H79: =('Lead NA'!H23-'Lead NA'!G23)+H23 -> 0 | I79: =-NA_monthly!AX23+NA_monthly!AL23-I23 -> 0
C81: Check OWC | D81: Check OWC | G81: =('Lead NA'!G41-'Lead NA'!F41)+G39 -> 0 | H81: =('Lead NA'!H41-'Lead NA'!G41)+H39 -> 0 | I81: =-NA_monthly!AX42+NA_monthly!AL42-I39 -> -1.1368684e-13

Sheet PL >>

Sheet PL_Top customer
C4: =Cockpit!$C$4 -> Projekt Namur | E4: =Cockpit!D33 -> 44926 | H4: =Cockpit!E33 -> 45291 | K4: =Cockpit!F33 -> 45657 | N4: =Cockpit!G33 -> 46022 | Q4: =Cockpit!H33 -> 46022
C5: ="in T"&Cockpit!$C$5 -> in TEUR | E5: # | F5: IST | H5: # | I5: IST | K5: # | L5: IST | N5: # | O5: LTM | Q5: # | R5: YTD
D6: =Cockpit!$C$4 -> Projekt Namur | E6: =Cockpit!D33 -> 44926 | H6: =Cockpit!E33 -> 45291 | K6: =Cockpit!F33 -> 45657 | N6: =Cockpit!G33 -> 46022 | Q6: =Cockpit!H33 -> 46022
D7: ="in k"&Cockpit!$C$5 -> in kEUR | E7: # | F7: Act. | H7: # | I7: Act. | K7: # | L7: Act. | N7: # | O7: LTM | Q7: # | R7: YTD
C9: Top10 Kunden pro Geschäftsjahr* | D9: TOP10 customers per fiscal year*
C10: Kunde 1 | D10: Customer 1 | K10: 1 | T10: !ACHTUNG: TOP10 des jeweiligen Jahres* hellgrau/dunkelgrün (YTD) hinterlegen und #RANG ergänzen
C11: Kunde 2 | D11: Customer 2 | K11: 2 | T11: !ACHTUNG: Basis der TOP10 Ordnung in der Fußnote aktualisieren (Standard ist Gliederung nach LTM Umsätzen)
C12: Kunde 3 | D12: Customer 3 | K12: 3
C13: Kunde 4 | D13: Customer 4 | K13: 4
C14: Kunde 5 | D14: Customer 5 | K14: 5
C15: Kunde 6 | D15: Customer 6 | K15: 6
C16: Kunde 7 | D16: Customer 7 | K16: 7
C17: Kunde 8 | D17: Customer 8 | K17: 8
C18: Kunde 9 | D18: Customer 9 | K18: 9
C19: Kunde 10 | D19: Customer 10 | K19: 10
C20: Kunde 11 | D20: Customer 11
C21: Kunde 12 | D21: Customer 12
C22: Kunde 13 | D22: Customer 13
C23: Kunde 14 | D23: Customer 14
C24: Kunde 15 | D24: Customer 15
C25: Kunde 16 | D25: Customer 16
C26: Kunde 17 | D26: Customer 17
C27: Kunde 18 | D27: Customer 18
C28: Kunde 19 | D28: Customer 19
C29: Kunde 20 | D29: Customer 20
C30: Umsatzerlöse Top Kunden | D30: Revenues Top customers | F30: =SUM(F10:F29) -> 0 | I30: =SUM(I10:I29) -> 0 | L30: =SUM(L10:L29) -> 0 | O30: =SUM(O10:O29) -> 0 | R30: =SUM(R10:R29) -> 0
C31: Sonstige Umsatzerlöse | D31: Other Revenues | F31: =F32-F30 -> 16416.745 | I31: =I32-I30 -> 15515.821 | L31: =L32-L30 -> 17010.759 | O31: =O32-O30 -> 15235.918 | R31: =R32-R30 -> 0
C32: Gesamtleistung gesamt | D32: Total output | F32: ='Lead PL'!F24 -> 16416.745 | I32: ='Lead PL'!G24 -> 15515.821 | L32: ='Lead PL'!H24 -> 17010.759 | O32: ='Lead PL'!I24 -> 15235.918 | R32: ='Lead PL'!J24 -> 0
C34: Anteil Top1 Kunde | D34: Share Top1 customer | L34: =L10/L32 -> 0 | T34: !ACHTUNG: Anteil TOP Kunden jeweils nachziehen
C35: Anteil Top5 Kunden | D35: Share Top5 customers | L35: =(L14+L10+L13+L12+L11)/L32 -> 0
C36: Anteil Top10 Kunden | D36: Share Top10 customers | L36: =(L13+L12+L19+L11+L10+L15+L17+L16+L14+L18)/L32 -> 0
C38: *Top10 Kunden des jeweiligen Jahres markiert, Gliederung basiert auf den LTM Jan23 Umsätzen | D38: *Top10 customers per each fiscal year, order is based on LTM Jan23 revenues
C40: ="Quelle: "&Cockpit!$C$7 -> Quelle: Datenraum/ eigene Analysen | D40: ="Source: "&Cockpit!$C$8 -> Source: Virtual Data Room/ Company Information
C42: Gesamleistung lt. Lead PL | D42: Total output acc. to Lead PL | F42: ='Lead PL'!F24 -> 16416.745 | I42: ='Lead PL'!G24 -> 15515.821 | L42: ='Lead PL'!H24 -> 17010.759 | O42: ='Lead PL'!I24 -> 15235.918 | R42: ='Lead PL'!J24 -> 0
C43: Check | D43: Check | F43: =F32-F42 -> 0 | I43: =I32-I42 -> 0 | L43: =L32-L42 -> 0 | O43: =O32-O42 -> 0 | R43: =R32-R42 -> 0

Sheet PL_PEX
C1: Technische Zeile --> nicht löschen | D1: Technische Zeile --> nicht löschen | F1: =IFERROR(F4,F6) -> 44926 | G1: =IFERROR(G4,G6) -> 45291 | H1: =IFERROR(H4,H6) -> 45657 | I1: =IFERROR(I4,I6) -> 46022 | J1: =IFERROR(J4,J6) -> 46022 | K1: =IFERROR(K4,K6) -> 46022 | L1: =IFERROR(L4,L6) -> 46387 | M1: =IFERROR(M4,M6) -> 46752 | N1: =IFERROR(N4,N6) -> 47118
C4: =Cockpit!$C$4 -> Projekt Namur | F4: ='Lead PL'!F4 -> 44926 | G4: ='Lead PL'!G4 -> 45291 | H4: ='Lead PL'!H4 -> 45657 | I4: ='Lead PL'!I4 -> 46022 | J4: ='Lead PL'!J4 -> 46022 | K4: ='Lead PL'!K4 -> 46022 | L4: ='Lead PL'!L4 -> 46387 | M4: ='Lead PL'!M4 -> 46752 | N4: ='Lead PL'!N4 -> 47118 | P4: ='Lead PL'!P4 -> CAGR | Q4: ='Lead PL'!Q4 -> CAGR | T4: BT Kategorisierung | V4: Kommentar BT | Y4: Heinz Meise
C5: ="in T"&Cockpit!$C$5 -> in TEUR | F5: ='Lead PL'!F5 -> IST | G5: ='Lead PL'!G5 -> IST | H5: ='Lead PL'!H5 -> IST | I5: ='Lead PL'!I5 -> IST | J5: ='Lead PL'!I5 -> IST | K5: ='Lead PL'!K5 -> Plan | L5: ='Lead PL'!L5 -> Plan | M5: ='Lead PL'!M5 -> Plan | N5: ='Lead PL'!N5 -> Plan | P5: ='Lead PL'!P5 -> IST | Q5: ='Lead PL'!Q5 -> Plan
D6: =Cockpit!$C$4 -> Projekt Namur | F6: ='Lead PL'!F6 -> 44926 | G6: ='Lead PL'!G6 -> 45291 | H6: ='Lead PL'!H6 -> 45657 | I6: ='Lead PL'!I6 -> 46022 | J6: ='Lead PL'!J6 -> 46022 | K6: ='Lead PL'!K6 -> 46022 | L6: ='Lead PL'!L6 -> 46387 | M6: ='Lead PL'!M6 -> 46752 | N6: ='Lead PL'!N6 -> 47118 | P6: ='Lead PL'!P6 -> CAGR | Q6: ='Lead PL'!Q6 -> CAGR
D7: ="in k"&Cockpit!$C$5 -> in kEUR | F7: ='Lead PL'!F7 -> IST | G7: ='Lead PL'!G7 -> IST | H7: ='Lead PL'!H7 -> IST | I7: ='Lead PL'!I7 -> IST | J7: ='Lead PL'!J7 -> YTD | K7: ='Lead PL'!K7 -> Plan | L7: ='Lead PL'!L7 -> Plan | M7: ='Lead PL'!M7 -> Plan | N7: ='Lead PL'!N7 -> Plan | P7: ='Lead PL'!P7 -> IST | Q7: ='Lead PL'!Q7 -> Plan
C9: Geschäftsführergehalt | D9: Dummy 1 | F9: =G9 -> 228 | G9: =SUMIFS('Trial Balance (Susa)'!G:G,'Trial Balance (Susa)'!$E:$E,$T9)/1000 -> 228 | H9: =SUMIFS('Trial Balance (Susa)'!H:H,'Trial Balance (Susa)'!$E:$E,$T9)/1000 -> 290.50002 | I9: 353.00004 | J9: =SUMIFS('Trial Balance (Susa)'!I:I,'Trial Balance (Susa)'!$E:$E,$T9)/1000 -> 353.00004 | P9: =IFERROR(((H9/F9)^(1/(($H$1-$F$1)/365)))-1,"n/a") -> 0.1285835 | Q9: =IFERROR(((N9/H9)^(1/(($N$1-$H$1)/365)))-1,"n/a") -> -1 | T9: GF Gehalt | V9: Tantieme f. Henze wurde in 2024 und 2025 auf falsches Konto gebucht, manuell angepasst
C10: Tantieme Geschäftsführer | F10: =G10 -> 76 | G10: =SUMIFS('Trial Balance (Susa)'!G:G,'Trial Balance (Susa)'!$E:$E,$T10)/1000 -> 76 | H10: =SUMIFS('Trial Balance (Susa)'!H:H,'Trial Balance (Susa)'!$E:$E,$T10)/1000+SUMIFS('Trial Balance (Susa)'!H:H,'Trial Balance (Susa)'!$E:$E,$T14)/1000 -> 92.757 | I10: 353.00004 | J10: =SUMIFS('Trial Balance (Susa)'!I:I,'Trial Balance (Susa)'!$E:$E,$T10)/1000+SUMIFS('Trial Balance (Susa)'!I:I,'Trial Balance (Susa)'!$E:$E,$T14)/1000 -> 88.53 | T10: GF Tantieme
C11: GF Vergütung | F11: =SUM(F9:F10) -> 304 | G11: =SUM(G9:G10) -> 304 | H11: =SUM(H9:H10) -> 383.25702 | I11: =SUM(I9:I10) -> 706.00008 | J11: =SUM(J9:J10) -> 441.53004
C13: Löhne und Gehälter | D13: Dummy 2 | F13: n/a | G13: =SUMIFS('Trial Balance (Susa)'!G:G,'Trial Balance (Susa)'!$E:$E,$T13)/1000 -> 2730.1334 | H13: =SUMIFS('Trial Balance (Susa)'!H:H,'Trial Balance (Susa)'!$E:$E,$T13)/1000 -> 3300.1118 | I13: 353.00004 | J13: =SUMIFS('Trial Balance (Susa)'!I:I,'Trial Balance (Susa)'!$E:$E,$T13)/1000 -> 2986.2051 | P13: =IFERROR(((H13/F13)^(1/(($H$1-$F$1)/365)))-1,"n/a") -> n/a | Q13: =IFERROR(((N13/H13)^(1/(($N$1-$H$1)/365)))-1,"n/a") -> -1 | T13: MA Gehalt
C14: Tantieme Mitarbeiter (MA) | D14: Dummy 3 | F14: n/a | G14: =SUMIFS('Trial Balance (Susa)'!G:G,'Trial Balance (Susa)'!$E:$E,$T14)/1000 -> 43.75 | H14: 0 | I14: 353.00004 | J14: 0 | P14: =IFERROR(((H14/F14)^(1/(($H$1-$F$1)/365)))-1,"n/a") -> n/a | Q14: =IFERROR(((N14/H14)^(1/(($N$1-$H$1)/365)))-1,"n/a") -> n/a | T14: MA Tantieme | V14: Tantieme f. Henze wurde in 2024 und 2025 auf falsches Konto gebucht, manuell angepasst Tantieme 2023 entfällt auf Reinert EUR 27.750 sowie Henze mit EUR 16.000
C15: MA - Löhne und Gehälter | D15: Wages and salaries | F15: =F17-F11 -> 2709.4677 | G15: =SUM(G13:G14) -> 2773.8834 | H15: =SUM(H13:H14) -> 3300.1118 | I15: =SUM(I13:I14) -> 706.00008 | J15: =SUM(J13:J14) -> 2986.2051 | K15: =SUM(K9:K14) -> 0 | L15: =SUM(L9:L14) -> 0 | M15: =SUM(M9:M14) -> 0 | N15: =SUM(N9:N14) -> 0 | P15: =IFERROR(((H15/F15)^(1/(($H$1-$F$1)/365)))-1,"n/a") -> 0.10347821 | Q15: =IFERROR(((N15/H15)^(1/(($N$1-$H$1)/365)))-1,"n/a") -> -1
C17: Löhne und Gehälter (Gesamt) | D17: Wages and salaries | F17: ='P&L (Annual Report)'!E89/1000 -> 3013.4677 | G17: =G11+G15 -> 3077.8834 | H17: =H11+H15 -> 3683.3689 | I17: =I11+I15 -> 1412.0002 | J17: =J11+J15 -> 3427.7351
C19: Dummy 1 | D19: Dummy 1 | P19: =IFERROR(((H19/F19)^(1/(($H$1-$F$1)/365)))-1,"n/a") -> n/a | Q19: =IFERROR(((N19/H19)^(1/(($N$1-$H$1)/365)))-1,"n/a") -> n/a
C20: Dummy 2 | D20: Dummy 2 | P20: =IFERROR(((H20/F20)^(1/(($H$1-$F$1)/365)))-1,"n/a") -> n/a | Q20: =IFERROR(((N20/H20)^(1/(($N$1-$H$1)/365)))-1,"n/a") -> n/a
C21: Dummy 3 | D21: Dummy 3 | P21: =IFERROR(((H21/F21)^(1/(($H$1-$F$1)/365)))-1,"n/a") -> n/a | Q21: =IFERROR(((N21/H21)^(1/(($N$1-$H$1)/365)))-1,"n/a") -> n/a
C22: Sozialabgaben | D22: Social security | F22: ='P&L (Annual Report)'!E95/1000 -> 550.72955 | G22: =SUMIFS('Trial Balance (Susa)'!G:G,'Trial Balance (Susa)'!$E:$E,$T22)/1000 -> 681.1009 | H22: =SUMIFS('Trial Balance (Susa)'!H:H,'Trial Balance (Susa)'!$E:$E,$T22)/1000 -> 838.9822 | I22: 353.00004 | J22: =SUMIFS('Trial Balance (Susa)'!I:I,'Trial Balance (Susa)'!$E:$E,$T22)/1000 -> 798.09191 | K22: =SUM(K19:K21) -> 0 | L22: =SUM(L19:L21) -> 0 | M22: =SUM(M19:M21) -> 0 | N22: =SUM(N19:N21) -> 0 | P22: =IFERROR(((H22/F22)^(1/(($H$1-$F$1)/365)))-1,"n/a") -> 0.23390618 | Q22: =IFERROR(((N22/H22)^(1/(($N$1-$H$1)/365)))-1,"n/a") -> -1 | T22: Sozialabgaben
C24: ='Lead PL'!C30 -> Personalaufwand | D24: ='Lead PL'!D30 -> Personnel expenses | F24: =F22+F17 -> 3564.1972 | G24: =G22+G17 -> 3758.9843 | H24: =H22+H17 -> 4522.3511 | I24: =I22+I17 -> 1765.0002 | J24: =J22+J17 -> 4225.827 | K24: =K22+K15 -> 0 | L24: =L22+L15 -> 0 | M24: =M22+M15 -> 0 | N24: =N22+N15 -> 0 | P24: =IFERROR(((H24/F24)^(1/(($H$1-$F$1)/365)))-1,"n/a") -> 0.12623896 | Q24: =IFERROR(((N24/H24)^(1/(($N$1-$H$1)/365)))-1,"n/a") -> -1
C26: ='Lead PL'!C24 -> Gesamtleistung | D26: ='Lead PL'!D24 -> Total output | F26: ='Lead PL'!F24 -> 16416.745 | G26: ='Lead PL'!G24 -> 15515.821 | H26: ='Lead PL'!H24 -> 17010.759 | I26: ='Lead PL'!I24 -> 15235.918 | J26: ='Lead PL'!I24 -> 15235.918 | K26: ='Lead PL'!K24 -> 0 | L26: ='Lead PL'!L24 -> 0 | M26: ='Lead PL'!M24 -> 0 | N26: ='Lead PL'!N24 -> 0
C28: ="in % der "&C26 -> in % der Gesamtleistung | D28: ="in % of "&D26 -> in % of Total output
C29: =C11 -> GF Vergütung | F29: =IFERROR(F11/F$26,"n/a") -> 0.018517678 | G29: =IFERROR(G11/G$26,"n/a") -> 0.019592905 | H29: =IFERROR(H11/H$26,"n/a") -> 0.022530272 | I29: =IFERROR(I11/I$26,"n/a") -> 0.046337875 | J29: =IFERROR(J11/J$26,"n/a") -> 0.028979549
C30: =C15 -> MA - Löhne und Gehälter | D30: =D15 -> Wages and salaries | F30: =IFERROR(F15/F$26,"n/a") -> 0.16504293 | G30: =IFERROR(G15/G$26,"n/a") -> 0.17877774 | H30: =IFERROR(H15/H$26,"n/a") -> 0.19400145 | I30: =IFERROR(I15/I$26,"n/a") -> 0.046337875 | J30: =IFERROR(J15/J$26,"n/a") -> 0.19599771 | K30: =IFERROR(K15/K$26,"n/a") -> n/a | L30: =IFERROR(L15/L$26,"n/a") -> n/a | M30: =IFERROR(M15/M$26,"n/a") -> n/a | N30: =IFERROR(N15/N$26,"n/a") -> n/a
C31: =C22 -> Sozialabgaben | D31: =D22 -> Social security | F31: =IFERROR(F22/F$26,"n/a") -> 0.033546818 | G31: =IFERROR(G22/G$26,"n/a") -> 0.043897188 | H31: =IFERROR(H22/H$26,"n/a") -> 0.049320681 | I31: =IFERROR(I22/I$26,"n/a") -> 0.023168937 | J31: =IFERROR(J22/J$26,"n/a") -> 0.052382264 | K31: =IFERROR(K22/K$26,"n/a") -> n/a | L31: =IFERROR(L22/L$26,"n/a") -> n/a | M31: =IFERROR(M22/M$26,"n/a") -> n/a | N31: =IFERROR(N22/N$26,"n/a") -> n/a
C32: =C24 -> Personalaufwand | D32: =D24 -> Personnel expenses | F32: =IFERROR(F24/F$26,"n/a") -> 0.21710743 | G32: =IFERROR(G24/G$26,"n/a") -> 0.24226783 | H32: =IFERROR(H24/H$26,"n/a") -> 0.2658524 | I32: =IFERROR(I24/I$26,"n/a") -> 0.11584469 | J32: =IFERROR(J24/J$26,"n/a") -> 0.27735952 | K32: =IFERROR(K24/K$26,"n/a") -> n/a | L32: =IFERROR(L24/L$26,"n/a") -> n/a | M32: =IFERROR(M24/M$26,"n/a") -> n/a | N32: =IFERROR(N24/N$26,"n/a") -> n/a
C34: Durchschnittliche Mitarbeiter | D34: Average Headcount
C35: Geschäftsführer | D35: =D9 -> Dummy 1 | F35: 1 | G35: 1 | H35: 1.5 | I35: 1 | J35: 2
C36: Mitarbeiter | D36: =D13 -> Dummy 2 | F36: =75.87-F35 -> 74.87 | G36: =70.69-G35 -> 69.69 | H36: =78.76-H35 -> 77.26 | J36: =78.36-J35 -> 76.36
D37: =D14 -> Dummy 3
C38: Anzahl FTE | D38: Total Headcount | F38: =SUM(F35:F37) -> 75.87 | G38: =SUM(G35:G37) -> 70.69 | H38: =SUM(H35:H37) -> 78.76 | I38: =SUM(I35:I37) -> 1 | J38: =SUM(J35:J37) -> 78.36 | K38: =SUM(K35:K37) -> 0 | L38: =SUM(L35:L37) -> 0 | M38: =SUM(M35:M37) -> 0 | N38: =SUM(N35:N37) -> 0
Y39: Wolfgang Henze
C40: Durchschnittlicher Personalaufwand (excl. Sozialabgaben) | D40: Average Personnel expenses
C41: =C35 -> Geschäftsführer | D41: =D9 -> Dummy 1 | F41: =IFERROR((F11)/F35,"n/a") -> 304 | G41: =IFERROR((G11)/G35,"n/a") -> 304 | H41: =IFERROR((H11)/H35,"n/a") -> 255.50468 | I41: =IFERROR((I11)/I35,"n/a") -> 706.00008 | J41: =IFERROR((J11)/J35,"n/a") -> 220.76502 | K41: =IFERROR((K9+K19)/K35,"n/a") -> n/a | L41: =IFERROR((L9+L19)/L35,"n/a") -> n/a | M41: =IFERROR((M9+M19)/M35,"n/a") -> n/a | N41: =IFERROR((N9+N19)/N35,"n/a") -> n/a
C42: =C36 -> Mitarbeiter | D42: =D13 -> Dummy 2 | F42: =IFERROR((F15)/F36,"n/a") -> 36.188963 | G42: =IFERROR((G15)/G36,"n/a") -> 39.803176 | H42: =IFERROR((H15)/H36,"n/a") -> 42.714365 | I42: =IFERROR((I15)/I36,"n/a") -> n/a | J42: =IFERROR((J15)/J36,"n/a") -> 39.106929 | K42: =IFERROR((K13+K20)/K36,"n/a") -> n/a | L42: =IFERROR((L13+L20)/L36,"n/a") -> n/a | M42: =IFERROR((M13+M20)/M36,"n/a") -> n/a | N42: =IFERROR((N13+N20)/N36,"n/a") -> n/a | T42: =_xlfn.RRI(3,F42,J42) -> 0.026185462
K43: =IFERROR((K14+K21)/K37,"n/a") -> n/a | L43: =IFERROR((L14+L21)/L37,"n/a") -> n/a | M43: =IFERROR((M14+M21)/M37,"n/a") -> n/a | N43: =IFERROR((N14+N21)/N37,"n/a") -> n/a
C44: Durchschnittlicher Personalaufwand gesamt | D44: Overall average personnel expenses | F44: =IFERROR((F17)/F38,"n/a") -> 39.71883 | G44: =IFERROR((G17)/G38,"n/a") -> 43.540577 | H44: =IFERROR((H17)/H38,"n/a") -> 46.766999 | I44: =IFERROR((I17)/I38,"n/a") -> 1412.0002 | J44: =IFERROR((J17)/J38,"n/a") -> 43.743429 | K44: =IFERROR((K15+K22)/K38,"n/a") -> n/a | L44: =IFERROR((L15+L22)/L38,"n/a") -> n/a | M44: =IFERROR((M15+M22)/M38,"n/a") -> n/a | N44: =IFERROR((N15+N22)/N38,"n/a") -> n/a
C46: Sozialversicherungsquote | D46: Social security rate | F46: =IFERROR(F22/F$17,"n/a") -> 0.18275609 | G46: =IFERROR(G22/G$17,"n/a") -> 0.22128873 | H46: =IFERROR(H22/H$17,"n/a") -> 0.22777578 | I46: =IFERROR(I22/I$17,"n/a") -> 0.25 | J46: =IFERROR(J22/J$17,"n/a") -> 0.2328336 | K46: =IFERROR(K22/K$15,"n/a") -> n/a | L46: =IFERROR(L22/L$15,"n/a") -> n/a | M46: =IFERROR(M22/M$15,"n/a") -> n/a | N46: =IFERROR(N22/N$15,"n/a") -> n/a
C48: ="Quelle: "&Cockpit!$C$7 -> Quelle: Datenraum/ eigene Analysen | D48: ="Source: "&Cockpit!$C$8 -> Source: Virtual Data Room/ Company Information
C51: Personalaufwand Lead PL | D51: Personnel expenses Lead PL | F51: ='Lead PL'!F30 -> -3564.1972 | G51: ='Lead PL'!G30 -> -3758.9843 | H51: ='Lead PL'!H30 -> -4522.3511 | I51: ='Lead PL'!I30 -> -4225.827 | J51: ='Lead PL'!I30 -> -4225.827 | K51: ='Lead PL'!K31 -> 0 | L51: ='Lead PL'!L31 -> 0 | M51: ='Lead PL'!M31 -> 0 | N51: ='Lead PL'!N31 -> 0
C52: Check | D52: Check | F52: =F51+F24 -> 0 | G52: =G51+G24 -> 0 | H52: =H51+H24 -> 0 | I52: =I51+I24 -> -2460.8268 | J52: =J51+J24 -> 0 | K52: =K51-K24 -> 0 | L52: =L51-L24 -> 0 | M52: =M51-M24 -> 0 | N52: =N51-N24 -> 0
C55: Plausibilisierung GF Gehälter
C56: Herr Heinz Meise
C57: Grundgehalt | G57: =12*19 -> 228 | H57: =12*19 -> 228 | J57: =12*19 -> 228
C58: Tantieme | G58: 76 | H58: 76 | J58: 76 | V58: Anteilig bis Juli berücksichtigt, da letzte Anpassung. Aug-Sep direkt im Net Debt berücksichtigt
C59: Summe | G59: =G57+G58 -> 304 | H59: =H57+H58 -> 304 | J59: =J57+J58 -> 304
C62: Herr Wolfgang Henze
C63: Grundgehalt (Anteilig ab Juli 24) | H63: =125/12*6 -> 62.5 | J63: =125 -> 125
C64: Tantieme | H64: 16.757 | J64: 12.53
C65: Summe | G65: =G63+G64 -> 0 | H65: =H63+H64 -> 79.257 | J65: =J63+J64 -> 137.53
C67: Gesamt GF | H67: =H59+H65 -> 383.257 | J67: =J59+J65 -> 441.53
C68: Check | H68: =H67-H11 -> -2e-05 | J68: =J67-J11 -> -4e-05

Sheet PL_oOPEX
C1: Technische Zeile --> nicht löschen | D1: Technische Zeile --> nicht löschen | F1: =IFERROR(F4,F6) -> 44926 | G1: =IFERROR(G4,G6) -> 45291 | H1: =IFERROR(H4,H6) -> 45657 | I1: =IFERROR(I4,I6) -> 46022 | J1: =IFERROR(J4,J6) -> 46022 | K1: =IFERROR(K4,K6) -> 46022 | L1: =IFERROR(L4,L6) -> 46387 | M1: =IFERROR(M4,M6) -> 46752 | N1: =IFERROR(N4,N6) -> 47118
E2: Dropdown, bei abweichender Bezeichnung unter Datenüberprüfung anpassen
C4: =Cockpit!$C$4 -> Projekt Namur | E4: Kostenart | F4: ='Lead PL'!F4 -> 44926 | G4: ='Lead PL'!G4 -> 45291 | H4: ='Lead PL'!H4 -> 45657 | I4: ='Lead PL'!I4 -> 46022 | J4: ='Lead PL'!J4 -> 46022 | K4: ='Lead PL'!K4 -> 46022 | L4: ='Lead PL'!L4 -> 46387 | M4: ='Lead PL'!M4 -> 46752 | N4: ='Lead PL'!N4 -> 47118 | P4: ='Lead PL'!P4 -> CAGR | Q4: ='Lead PL'!Q4 -> CAGR
C5: ="in T"&Cockpit!$C$5 -> in TEUR | F5: ='Lead PL'!F5 -> IST | G5: ='Lead PL'!G5 -> IST | H5: ='Lead PL'!H5 -> IST | I5: ='Lead PL'!I5 -> IST | J5: ='Lead PL'!J5 -> YTD | K5: ='Lead PL'!K5 -> Plan | L5: ='Lead PL'!L5 -> Plan | M5: ='Lead PL'!M5 -> Plan | N5: ='Lead PL'!N5 -> Plan | P5: ='Lead PL'!P5 -> IST | Q5: ='Lead PL'!Q5 -> Plan
D6: =Cockpit!$C$4 -> Projekt Namur | E6: Cost | F6: ='Lead PL'!F6 -> 44926 | G6: ='Lead PL'!G6 -> 45291 | H6: ='Lead PL'!H6 -> 45657 | I6: ='Lead PL'!I6 -> 46022 | J6: ='Lead PL'!J6 -> 46022 | K6: ='Lead PL'!K6 -> 46022 | L6: ='Lead PL'!L6 -> 46387 | M6: ='Lead PL'!M6 -> 46752 | N6: ='Lead PL'!N6 -> 47118 | P6: ='Lead PL'!P6 -> CAGR | Q6: ='Lead PL'!Q6 -> CAGR
D7: ="in k"&Cockpit!$C$5 -> in kEUR | E7: Category | F7: ='Lead PL'!F7 -> IST | G7: ='Lead PL'!G7 -> IST | H7: ='Lead PL'!H7 -> IST | I7: ='Lead PL'!I7 -> IST | J7: ='Lead PL'!J7 -> YTD | K7: ='Lead PL'!K7 -> Plan | L7: ='Lead PL'!L7 -> Plan | M7: ='Lead PL'!M7 -> Plan | N7: ='Lead PL'!N7 -> Plan | P7: ='Lead PL'!P7 -> IST | Q7: ='Lead PL'!Q7 -> Plan
C9: Aufwendungen für Lizenzen und Konzessionen | D9: Dummy 1 | F9: =-('P&L (Annual Report)'!E195)/1000 -> -466.77229 | G9: =-SUMIF('Trial Balance (Susa)'!$F:$F,"*"&$T9&"*",'Trial Balance (Susa)'!G:G)/1000 -> -312.08498 | H9: =-SUMIF('Trial Balance (Susa)'!$F:$F,"*"&$T9&"*",'Trial Balance (Susa)'!H:H)/1000 -> -527.07459 | I9: =-SUMIF('Trial Balance (Susa)'!$F:$F,"*"&$T9&"*",'Trial Balance (Susa)'!I:I)/1000 -> -537.96576 | P9: =IFERROR(((H9/F9)^(1/(($H$1-$F$1)/365)))-1,"n/a") -> 0.062545202 | Q9: =IFERROR(((N9/H9)^(1/(($N$1-$H$1)/365)))-1,"n/a") -> -1 | T9: /profit and loss/expense/other expense/AufwendungenfürLizenzenKonzessionen
C10: Rechts- und Beratungskosten | D10: Dummy 2 | F10: =-('P&L (Annual Report)'!E193)/1000 -> -246.42217 | G10: =-SUMIF('Trial Balance (Susa)'!$F:$F,"*"&$T10&"*",'Trial Balance (Susa)'!G:G)/1000 -> -306.61932 | H10: =-SUMIF('Trial Balance (Susa)'!$F:$F,"*"&$T10&"*",'Trial Balance (Susa)'!H:H)/1000 -> -323.41085 | I10: =-SUMIF('Trial Balance (Susa)'!$F:$F,"*"&$T10&"*",'Trial Balance (Susa)'!I:I)/1000 -> -303.74534 | P10: =IFERROR(((H10/F10)^(1/(($H$1-$F$1)/365)))-1,"n/a") -> 0.14539858 | Q10: =IFERROR(((N10/H10)^(1/(($N$1-$H$1)/365)))-1,"n/a") -> -1 | T10: /profit and loss/expense/other expense/RechtsBeratungskosten
C11: Personalleasing | D11: Dummy 3 | F11: =-('P&L (Annual Report)'!E185)/1000 -> -63.28483 | G11: =-SUMIF('Trial Balance (Susa)'!$F:$F,"*"&$T11&"*",'Trial Balance (Susa)'!G:G)/1000 -> -145.31952 | H11: =-SUMIF('Trial Balance (Susa)'!$F:$F,"*"&$T11&"*",'Trial Balance (Susa)'!H:H)/1000 -> -136.98034 | I11: =-SUMIF('Trial Balance (Susa)'!$F:$F,"*"&$T11&"*",'Trial Balance (Susa)'!I:I)/1000 -> -55.89724 | P11: =IFERROR(((H11/F11)^(1/(($H$1-$F$1)/365)))-1,"n/a") -> 0.47044887 | Q11: =IFERROR(((N11/H11)^(1/(($N$1-$H$1)/365)))-1,"n/a") -> -1 | T11: /profit and loss/expense/other expense/Personalleasing
C12: Betriebsbedarf | D12: Dummy 4 | F12: =-('P&L (Annual Report)'!E188+'P&L (Annual Report)'!E189+'P&L (Annual Report)'!E190+'P&L (Annual Report)'!E191+'P&L (Annual Report)'!E196+'P&L (Annual Report)'!E199)/1000 -> -102.14448 | G12: =-SUMIF('Trial Balance (Susa)'!$F:$F,"*"&$T12&"*",'Trial Balance (Susa)'!G:G)/1000 -> -85.98284 | H12: =-SUMIF('Trial Balance (Susa)'!$F:$F,"*"&$T12&"*",'Trial Balance (Susa)'!H:H)/1000 -> -96.93494 | I12: =-SUMIF('Trial Balance (Susa)'!$F:$F,"*"&$T12&"*",'Trial Balance (Susa)'!I:I)/1000 -> -96.14993 | P12: =IFERROR(((H12/F12)^(1/(($H$1-$F$1)/365)))-1,"n/a") -> -0.02579967 | Q12: =IFERROR(((N12/H12)^(1/(($N$1-$H$1)/365)))-1,"n/a") -> -1 | T12: /profit and loss/expense/other expense/Betriebsbedarf
C13: Miet- und Leasingaufwendungen | D13: Dummy 6 | F13: =-('P&L (Annual Report)'!E186+'P&L (Annual Report)'!E194)/1000 -> -19.05254 | G13: =-SUMIF('Trial Balance (Susa)'!$F:$F,"*"&$T13&"*",'Trial Balance (Susa)'!G:G)/1000 -> -40.18776 | H13: =-SUMIF('Trial Balance (Susa)'!$F:$F,"*"&$T13&"*",'Trial Balance (Susa)'!H:H)/1000 -> -50.45045 | I13: =-SUMIF('Trial Balance (Susa)'!$F:$F,"*"&$T13&"*",'Trial Balance (Susa)'!I:I)/1000 -> -107.01884 | P13: =IFERROR(((H13/F13)^(1/(($H$1-$F$1)/365)))-1,"n/a") -> 0.62617325 | Q13: =IFERROR(((N13/H13)^(1/(($N$1-$H$1)/365)))-1,"n/a") -> -1 | T13: /profit and loss/expense/other expense/MietundLeasingaufwendungen
C14: Verluste aus Anlageabgang | D14: Dummy 7 | F14: =-('P&L (Annual Report)'!E207)/1000 -> -22.238 | G14: =-SUMIF('Trial Balance (Susa)'!$F:$F,"*"&$T14&"*",'Trial Balance (Susa)'!G:G)/1000 -> -32.027 | H14: =-SUMIF('Trial Balance (Susa)'!$F:$F,"*"&$T14&"*",'Trial Balance (Susa)'!H:H)/1000 -> -38.6534 | I14: =-SUMIF('Trial Balance (Susa)'!$F:$F,"*"&$T14&"*",'Trial Balance (Susa)'!I:I)/1000 -> -9.6869 | P14: =IFERROR(((H14/F14)^(1/(($H$1-$F$1)/365)))-1,"n/a") -> 0.3178979 | Q14: =IFERROR(((N14/H14)^(1/(($N$1-$H$1)/365)))-1,"n/a") -> -1 | T14: /profit and loss/expense/other expense/VerlusteausAnlageAbgang
C15: Dummy 8 | D15: Dummy 8 | P15: =IFERROR(((H15/F15)^(1/(($H$1-$F$1)/365)))-1,"n/a") -> n/a | Q15: =IFERROR(((N15/H15)^(1/(($N$1-$H$1)/365)))-1,"n/a") -> n/a | S15: verschiedene betriebliche Kosten
C16: Dummy 9 | D16: Dummy 9 | P16: =IFERROR(((H16/F16)^(1/(($H$1-$F$1)/365)))-1,"n/a") -> n/a | Q16: =IFERROR(((N16/H16)^(1/(($N$1-$H$1)/365)))-1,"n/a") -> n/a | S16: übrige sonstige betriebliche Aufwendungen
C17: Dummy 10 | D17: Dummy 10 | P17: =IFERROR(((H17/F17)^(1/(($H$1-$F$1)/365)))-1,"n/a") -> n/a | Q17: =IFERROR(((N17/H17)^(1/(($N$1-$H$1)/365)))-1,"n/a") -> n/a
C18: Dummy 11 | D18: Dummy 11 | P18: =IFERROR(((H18/F18)^(1/(($H$1-$F$1)/365)))-1,"n/a") -> n/a | Q18: =IFERROR(((N18/H18)^(1/(($N$1-$H$1)/365)))-1,"n/a") -> n/a
C19: Dummy 12 | D19: Dummy 12 | P19: =IFERROR(((H19/F19)^(1/(($H$1-$F$1)/365)))-1,"n/a") -> n/a | Q19: =IFERROR(((N19/H19)^(1/(($N$1-$H$1)/365)))-1,"n/a") -> n/a
C20: Dummy 13 | D20: Dummy 13 | P20: =IFERROR(((H20/F20)^(1/(($H$1-$F$1)/365)))-1,"n/a") -> n/a | Q20: =IFERROR(((N20/H20)^(1/(($N$1-$H$1)/365)))-1,"n/a") -> n/a
C21: Sonstige Aufwendungen | D21: Dummy 5 | F21: =-('P&L (Annual Report)'!E184+'P&L (Annual Report)'!E212+'P&L (Annual Report)'!E192+'P&L (Annual Report)'!E187+'P&L (Annual Report)'!E197+'P&L (Annual Report)'!E198+'P&L (Annual Report)'!E211+'P&L (Annual Report)'!E200)/1000 -> -103.49151 | G21: =-SUMIF('Trial Balance (Susa)'!$F:$F,"*"&$T21&"*",'Trial Balance (Susa)'!G:G)/1000 -> -143.54115 | H21: =-SUMIF('Trial Balance (Susa)'!$F:$F,"*"&$T21&"*",'Trial Balance (Susa)'!H:H)/1000 -> -93.71581 | I21: =-SUMIF('Trial Balance (Susa)'!$F:$F,"*"&$T21&"*",'Trial Balance (Susa)'!I:I)/1000 -> -115.95785 | P21: =IFERROR(((H21/F21)^(1/(($H$1-$F$1)/365)))-1,"n/a") -> -0.048336212 | Q21: =IFERROR(((N21/H21)^(1/(($N$1-$H$1)/365)))-1,"n/a") -> -1 | T21: /profit and loss/expense/other expense/SonstigeAufwendungen
C22: Sonstige betriebliche Aufwendungen | D22: Total other operating expenses | F22: =SUM(F9:F21) -> -1023.4058 | G22: =SUM(G9:G21) -> -1065.7626 | H22: =SUM(H9:H21) -> -1267.2204 | I22: =SUM(I9:I21) -> -1226.4219 | J22: =SUM(J9:J20) -> 0 | K22: =SUM(K9:K20) -> 0 | L22: =SUM(L9:L20) -> 0 | M22: =SUM(M9:M20) -> 0 | N22: =SUM(N9:N20) -> 0 | P22: =IFERROR(((H22/F22)^(1/(($H$1-$F$1)/365)))-1,"n/a") -> 0.11259898 | Q22: =IFERROR(((N22/H22)^(1/(($N$1-$H$1)/365)))-1,"n/a") -> -1
C24: ='Lead PL'!C24 -> Gesamtleistung | D24: ='Lead PL'!D24 -> Total output | F24: ='Lead PL'!F24 -> 16416.745 | G24: ='Lead PL'!G24 -> 15515.821 | H24: ='Lead PL'!H24 -> 17010.759 | I24: ='Lead PL'!I24 -> 15235.918 | J24: ='Lead PL'!J24 -> 0 | K24: ='Lead PL'!K24 -> 0 | L24: ='Lead PL'!L24 -> 0 | M24: ='Lead PL'!M24 -> 0 | N24: ='Lead PL'!N24 -> 0
C26: davon fixe Kosten | D26: of which fixed expenses | E26: fixed | F26: =SUMIF($E$9:$E$22,$E26,F$9:F$22) -> 0 | G26: =SUMIF($E$9:$E$22,$E26,G$9:G$22) -> 0 | H26: =SUMIF($E$9:$E$22,$E26,H$9:H$22) -> 0 | I26: =SUMIF($E$9:$E$22,$E26,I$9:I$22) -> 0 | J26: =SUMIF($E$9:$E$22,$E26,J$9:J$22) -> 0 | K26: =SUMIF($E$9:$E$22,$E26,K$9:K$22) -> 0 | L26: =SUMIF($E$9:$E$22,$E26,L$9:L$22) -> 0 | M26: =SUMIF($E$9:$E$22,$E26,M$9:M$22) -> 0 | N26: =SUMIF($E$9:$E$22,$E26,N$9:N$22) -> 0 | S26: Anpassen
C27: davon variable Kosten | D27: of which variable expenses | E27: variable | F27: =SUMIF($E$9:$E$22,$E27,F$9:F$22) -> 0 | G27: =SUMIF($E$9:$E$22,$E27,G$9:G$22) -> 0 | H27: =SUMIF($E$9:$E$22,$E27,H$9:H$22) -> 0 | I27: =SUMIF($E$9:$E$22,$E27,I$9:I$22) -> 0 | J27: =SUMIF($E$9:$E$22,$E27,J$9:J$22) -> 0 | K27: =SUMIF($E$9:$E$22,$E27,K$9:K$22) -> 0 | L27: =SUMIF($E$9:$E$22,$E27,L$9:L$22) -> 0 | M27: =SUMIF($E$9:$E$22,$E27,M$9:M$22) -> 0 | N27: =SUMIF($E$9:$E$22,$E27,N$9:N$22) -> 0 | S27: Anpassen
C29: ="in % der "&C24 -> in % der Gesamtleistung | D29: ="in % of "&D24 -> in % of Total output
C30: =C9 -> Aufwendungen für Lizenzen und Konzessionen | D30: =D9 -> Dummy 1 | F30: =IFERROR(F9/F$24,"n/a") -> -0.028432695 | G30: =IFERROR(G9/G$24,"n/a") -> -0.020113985 | H30: =IFERROR(H9/H$24,"n/a") -> -0.030984779 | I30: =IFERROR(I9/I$24,"n/a") -> -0.035309047 | J30: =IFERROR(J9/J$24,"n/a") -> n/a | K30: =IFERROR(K9/K$24,"n/a") -> n/a | L30: =IFERROR(L9/L$24,"n/a") -> n/a | M30: =IFERROR(M9/M$24,"n/a") -> n/a | N30: =IFERROR(N9/N$24,"n/a") -> n/a
C31: =C10 -> Rechts- und Beratungskosten | D31: =D10 -> Dummy 2 | F31: =IFERROR(F10/F$24,"n/a") -> -0.015010416 | G31: =IFERROR(G10/G$24,"n/a") -> -0.019761721 | H31: =IFERROR(H10/H$24,"n/a") -> -0.019012136 | I31: =IFERROR(I10/I$24,"n/a") -> -0.019936136 | J31: =IFERROR(J10/J$24,"n/a") -> n/a | K31: =IFERROR(K10/K$24,"n/a") -> n/a | L31: =IFERROR(L10/L$24,"n/a") -> n/a | M31: =IFERROR(M10/M$24,"n/a") -> n/a | N31: =IFERROR(N10/N$24,"n/a") -> n/a
C32: =C11 -> Personalleasing | D32: =D11 -> Dummy 3 | F32: =IFERROR(F11/F$24,"n/a") -> -0.0038548952 | G32: =IFERROR(G11/G$24,"n/a") -> -0.0093658932 | H32: =IFERROR(H11/H$24,"n/a") -> -0.0080525709 | I32: =IFERROR(I11/I$24,"n/a") -> -0.0036687805 | J32: =IFERROR(J11/J$24,"n/a") -> n/a | K32: =IFERROR(K11/K$24,"n/a") -> n/a | L32: =IFERROR(L11/L$24,"n/a") -> n/a | M32: =IFERROR(M11/M$24,"n/a") -> n/a | N32: =IFERROR(N11/N$24,"n/a") -> n/a
C33: =C12 -> Betriebsbedarf | D33: =D12 -> Dummy 4 | F33: =IFERROR(F12/F$24,"n/a") -> -0.0062219692 | G33: =IFERROR(G12/G$24,"n/a") -> -0.0055416237 | H33: =IFERROR(H12/H$24,"n/a") -> -0.005698449 | I33: =IFERROR(I12/I$24,"n/a") -> -0.0063107407 | J33: =IFERROR(J12/J$24,"n/a") -> n/a | K33: =IFERROR(K12/K$24,"n/a") -> n/a | L33: =IFERROR(L12/L$24,"n/a") -> n/a | M33: =IFERROR(M12/M$24,"n/a") -> n/a | N33: =IFERROR(N12/N$24,"n/a") -> n/a
C34: =C13 -> Miet- und Leasingaufwendungen | D34: =D13 -> Dummy 6 | F34: =IFERROR(F13/F$24,"n/a") -> -0.0011605553 | G34: =IFERROR(G13/G$24,"n/a") -> -0.002590115 | H34: =IFERROR(H13/H$24,"n/a") -> -0.0029657966 | I34: =IFERROR(I13/I$24,"n/a") -> -0.0070241148 | J34: =IFERROR(J13/J$24,"n/a") -> n/a | K34: =IFERROR(K13/K$24,"n/a") -> n/a | L34: =IFERROR(L13/L$24,"n/a") -> n/a | M34: =IFERROR(M13/M$24,"n/a") -> n/a | N34: =IFERROR(N13/N$24,"n/a") -> n/a
C35: =C14 -> Verluste aus Anlageabgang | D35: =D14 -> Dummy 7 | F35: =IFERROR(F14/F$24,"n/a") -> -0.0013545925 | G35: =IFERROR(G14/G$24,"n/a") -> -0.0020641512 | H35: =IFERROR(H14/H$24,"n/a") -> -0.0022722914 | I35: =IFERROR(I14/I$24,"n/a") -> -0.00063579364 | J35: =IFERROR(J14/J$24,"n/a") -> n/a | K35: =IFERROR(K14/K$24,"n/a") -> n/a | L35: =IFERROR(L14/L$24,"n/a") -> n/a | M35: =IFERROR(M14/M$24,"n/a") -> n/a | N35: =IFERROR(N14/N$24,"n/a") -> n/a
C36: =C15 -> Dummy 8 | D36: =D15 -> Dummy 8 | F36: =IFERROR(F15/F$24,"n/a") -> 0 | G36: =IFERROR(G15/G$24,"n/a") -> 0 | H36: =IFERROR(H15/H$24,"n/a") -> 0 | I36: =IFERROR(I15/I$24,"n/a") -> 0 | J36: =IFERROR(J15/J$24,"n/a") -> n/a | K36: =IFERROR(K15/K$24,"n/a") -> n/a | L36: =IFERROR(L15/L$24,"n/a") -> n/a | M36: =IFERROR(M15/M$24,"n/a") -> n/a | N36: =IFERROR(N15/N$24,"n/a") -> n/a
C37: =C16 -> Dummy 9 | D37: =D16 -> Dummy 9 | F37: =IFERROR(F16/F$24,"n/a") -> 0 | G37: =IFERROR(G16/G$24,"n/a") -> 0 | H37: =IFERROR(H16/H$24,"n/a") -> 0 | I37: =IFERROR(I16/I$24,"n/a") -> 0 | J37: =IFERROR(J16/J$24,"n/a") -> n/a | K37: =IFERROR(K16/K$24,"n/a") -> n/a | L37: =IFERROR(L16/L$24,"n/a") -> n/a | M37: =IFERROR(M16/M$24,"n/a") -> n/a | N37: =IFERROR(N16/N$24,"n/a") -> n/a
C38: =C17 -> Dummy 10 | D38: =D17 -> Dummy 10 | F38: =IFERROR(F17/F$24,"n/a") -> 0 | G38: =IFERROR(G17/G$24,"n/a") -> 0 | H38: =IFERROR(H17/H$24,"n/a") -> 0 | I38: =IFERROR(I17/I$24,"n/a") -> 0 | J38: =IFERROR(J17/J$24,"n/a") -> n/a | K38: =IFERROR(K17/K$24,"n/a") -> n/a | L38: =IFERROR(L17/L$24,"n/a") -> n/a | M38: =IFERROR(M17/M$24,"n/a") -> n/a | N38: =IFERROR(N17/N$24,"n/a") -> n/a
C39: =C18 -> Dummy 11 | D39: =D18 -> Dummy 11 | F39: =IFERROR(F18/F$24,"n/a") -> 0 | G39: =IFERROR(G18/G$24,"n/a") -> 0 | H39: =IFERROR(H18/H$24,"n/a") -> 0 | I39: =IFERROR(I18/I$24,"n/a") -> 0 | J39: =IFERROR(J18/J$24,"n/a") -> n/a | K39: =IFERROR(K18/K$24,"n/a") -> n/a | L39: =IFERROR(L18/L$24,"n/a") -> n/a | M39: =IFERROR(M18/M$24,"n/a") -> n/a | N39: =IFERROR(N18/N$24,"n/a") -> n/a
C40: =C19 -> Dummy 12 | D40: =D19 -> Dummy 12 | F40: =IFERROR(F19/F$24,"n/a") -> 0 | G40: =IFERROR(G19/G$24,"n/a") -> 0 | H40: =IFERROR(H19/H$24,"n/a") -> 0 | I40: =IFERROR(I19/I$24,"n/a") -> 0 | J40: =IFERROR(J19/J$24,"n/a") -> n/a | K40: =IFERROR(K19/K$24,"n/a") -> n/a | L40: =IFERROR(L19/L$24,"n/a") -> n/a | M40: =IFERROR(M19/M$24,"n/a") -> n/a | N40: =IFERROR(N19/N$24,"n/a") -> n/a
C41: =C20 -> Dummy 13 | D41: =D20 -> Dummy 13 | F41: =IFERROR(F20/F$24,"n/a") -> 0 | G41: =IFERROR(G20/G$24,"n/a") -> 0 | H41: =IFERROR(H20/H$24,"n/a") -> 0 | I41: =IFERROR(I20/I$24,"n/a") -> 0 | J41: =IFERROR(J20/J$24,"n/a") -> n/a | K41: =IFERROR(K20/K$24,"n/a") -> n/a | L41: =IFERROR(L20/L$24,"n/a") -> n/a | M41: =IFERROR(M20/M$24,"n/a") -> n/a | N41: =IFERROR(N20/N$24,"n/a") -> n/a
... C43: =C22 -> Sonstige betriebliche Aufwendungen | D43: =D22 -> Total other operating expenses | F43: =IFERROR(F22/F$24,"n/a") -> -0.062339144 | G43: =IFERROR(G22/G$24,"n/a") -> -0.068688765 | H43: =IFERROR(H22/H$24,"n/a") -> -0.07449523 | I43: =IFERROR(I22/I$24,"n/a") -> -0.080495433 | J43: =IFERROR(J22/J$24,"n/a") -> n/a | K43: =IFERROR(K22/K$24,"n/a") -> n/a | L43: =IFERROR(L22/L$24,"n/a") -> n/a | M43: =IFERROR(M22/M$24,"n/a") -> n/a | N43: =IFERROR(N22/N$24,"n/a") -> n/a
C45: fixe Kosten | D45: fixed expenses | F45: =IFERROR(F26/F$24,"n/a") -> 0 | G45: =IFERROR(G26/G$24,"n/a") -> 0 | H45: =IFERROR(H26/H$24,"n/a") -> 0 | I45: =IFERROR(I26/I$24,"n/a") -> 0 | J45: =IFERROR(J26/J$24,"n/a") -> n/a | K45: =IFERROR(K26/K$24,"n/a") -> n/a | L45: =IFERROR(L26/L$24,"n/a") -> n/a | M45: =IFERROR(M26/M$24,"n/a") -> n/a | N45: =IFERROR(N26/N$24,"n/a") -> n/a
C46: variable Kosten | D46: variable expenses | F46: =IFERROR(F27/F$24,"n/a") -> 0 | G46: =IFERROR(G27/G$24,"n/a") -> 0 | H46: =IFERROR(H27/H$24,"n/a") -> 0 | I46: =IFERROR(I27/I$24,"n/a") -> 0 | J46: =IFERROR(J27/J$24,"n/a") -> n/a | K46: =IFERROR(K27/K$24,"n/a") -> n/a | L46: =IFERROR(L27/L$24,"n/a") -> n/a | M46: =IFERROR(M27/M$24,"n/a") -> n/a | N46: =IFERROR(N27/N$24,"n/a") -> n/a
C48: ="Quelle: "&Cockpit!$C$7 -> Quelle: Datenraum/ eigene Analysen | D48: ="Source: "&Cockpit!$C$8 -> Source: Virtual Data Room/ Company Information
C51: Gesamtaufwand (bis EBITDA) Lead PL | D51: Total expenses (until EBITDA) Lead PL | F51: ='Lead PL'!F39 -> -1023.4058 | G51: ='Lead PL'!G39 -> -1065.7626 | H51: ='Lead PL'!H39 -> -1267.2204 | I51: ='Lead PL'!I39 -> -1226.4219 | J51: ='Lead PL'!J38 -> 0 | K51: ='Lead PL'!K38 -> 0 | L51: ='Lead PL'!L38 -> 0 | M51: ='Lead PL'!M38 -> 0 | N51: ='Lead PL'!N38 -> 0
C52: Check | D52: Check | F52: =F51-F22 -> 0 | G52: =G51-G22 -> 0 | H52: =H51-H22 -> 0 | I52: =I51-I22 -> 0 | J52: =J51-J22 -> 0 | K52: =K51-K22 -> 0 | L52: =L51-L22 -> 0 | M52: =M51-M22 -> 0 | N52: =N51-N22 -> 0
C54: Verteilung fix/variabel | D54: Distribution fixed/variable
C55: Check | D55: Check | F55: =SUM(F26:F27)-F22 -> 1023.4058 | G55: =SUM(G26:G27)-G22 -> 1065.7626 | H55: =SUM(H26:H27)-H22 -> 1267.2204 | I55: =SUM(I26:I27)-I22 -> 1226.4219 | J55: =SUM(J26:J27)-J22 -> 0 | K55: =SUM(K26:K27)-K22 -> 0 | L55: =SUM(L26:L27)-L22 -> 0 | M55: =SUM(M26:M27)-M22 -> 0 | N55: =SUM(N26:N27)-N22 -> 0

Sheet PL_YTD
C5: =Cockpit!$C$4 -> Projekt Namur | E5: ='Lead PL'!H6 -> 45657 | J5: ='Lead PL'!K6 -> 46022
E6: =Cockpit!$C$24 -> YTD | F6: =Cockpit!$C$25 -> YTG | G6: =Cockpit!$C$19 -> IST | H6: YTD in % | J6: =Cockpit!$C$24 -> YTD | K6: =F6 -> YTG | L6: =Cockpit!$I$34 -> Plan | M6: YTD in %
C7: ="in T"&Cockpit!$C$5 -> in TEUR | E7: =EDATE(J7,-12) -> 45657 | F7: =EDATE(K7,-12) -> 45657 | G7: =F7 -> 45657 | H7: des GJ | J7: ='Lead PL'!J4 -> 46022 | K7: =$J7 -> 46022 | L7: =K7 -> 46022 | M7: des GJ
D8: =Cockpit!$C$4 -> Projekt Namur | E8: ='Lead PL'!H6 -> 45657 | J8: ='Lead PL'!K6 -> 46022
E9: =Cockpit!$C$24 -> YTD | F9: =Cockpit!$C$25 -> YTG | G9: =Cockpit!$C$19 -> IST | H9: YTD in % | J9: =Cockpit!$C$24 -> YTD | K9: =F9 -> YTG | L9: =Cockpit!$I$34 -> Plan | M9: YTD in %
D10: ="in k"&Cockpit!$C$5 -> in kEUR | E10: =EDATE(J10,-12) -> 45657 | F10: =EDATE(K10,-12) -> 45657 | G10: =F10 -> 45657 | H10: of FY | J10: ='Lead PL'!J6 -> 46022 | K10: =$J10 -> 46022 | L10: =K10 -> 46022 | M10: of FY | P10: Classification BT
C12: ='Lead PL'!C9 -> Umsatzerlöse | D12: ='Lead PL'!D9 -> Revenues | E12: =E13+E14+E15+E16+E22 -> 12729.947 | F12: =G12-E12 -> 3930.0168 | G12: ='Lead PL'!H9 -> 16659.963 | H12: =IFERROR(E12/G12,"n/a") -> 0.76410411 | J12: =J13+J14+J15+J16+J22 -> 11495.738 | K12: =L12-J12 -> -11495.738 | M12: =IFERROR(J12/L12,"n/a") -> n/a
C13: Steuerfreie/nicht steuerbare Umsätze | E13: =-SUMIF('Trial Balance (Susa)'!$F:$F,"*"&$P13&"*",'Trial Balance (Susa)'!AE:AE)/1000 -> 3342.6303 | F13: =G13-E13 -> #REF! | G13: ='Lead PL'!#REF! -> #REF! | H13: =IFERROR(E13/G13,"n/a") -> n/a | J13: =-SUMIF('Trial Balance (Susa)'!$F:$F,"*"&$P13&"*",'Trial Balance (Susa)'!AQ:AQ)/1000 -> 3585.218 | K13: =L13-J13 -> -3585.218 | M13: =IFERROR(J13/L13,"n/a") -> n/a | P13: SteuerfreiNichtSteuerbar
C14: Erlöse Produktion | E14: =-SUMIF('Trial Balance (Susa)'!$F:$F,"*"&$P14&"*",'Trial Balance (Susa)'!AE:AE)/1000 -> 5266.9981 | F14: =G14-E14 -> 6039.7302 | G14: ='Lead PL'!H10 -> 11306.728 | H14: =IFERROR(E14/G14,"n/a") -> 0.46582866 | J14: =-SUMIF('Trial Balance (Susa)'!$F:$F,"*"&$P14&"*",'Trial Balance (Susa)'!AQ:AQ)/1000 -> 4848.8322 | K14: =L14-J14 -> -4848.8322 | M14: =IFERROR(J14/L14,"n/a") -> n/a | P14: Produktion
C15: Erlöse Handel | E15: =-SUMIF('Trial Balance (Susa)'!$F:$F,"*"&$P15&"*",'Trial Balance (Susa)'!AE:AE)/1000 -> 4075.4113 | F15: =G15-E15 -> 1001.3359 | G15: ='Lead PL'!H11 -> 5076.7472 | H15: =IFERROR(E15/G15,"n/a") -> 0.80276034 | J15: =-SUMIF('Trial Balance (Susa)'!$F:$F,"*"&$P15&"*",'Trial Balance (Susa)'!AQ:AQ)/1000 -> 3033.9223 | K15: =L15-J15 -> -3033.9223 | M15: =IFERROR(J15/L15,"n/a") -> n/a | P15: Handel
C16: Erlöse Dienstleistung | E16: =SUM(E17:E21) -> 175.5124 | F16: =G16-E16 -> 277.41917 | G16: ='Lead PL'!H12 -> 452.93157 | H16: =IFERROR(E16/G16,"n/a") -> 0.38750313 | J16: =SUM(J17:J21) -> 152.69066 | K16: =L16-J16 -> -152.69066 | M16: =IFERROR(J16/L16,"n/a") -> n/a
C17: Erlöse Sterilisation | E17: =-SUMIF('Trial Balance (Susa)'!$F:$F,"*"&$P17&"*",'Trial Balance (Susa)'!AE:AE)/1000 -> 64.5578 | F17: =G17-E17 -> 253.50357 | G17: ='Lead PL'!H13 -> 318.06137 | H17: =IFERROR(E17/G17,"n/a") -> 0.20297278 | J17: =-SUMIF('Trial Balance (Susa)'!$F:$F,"*"&$P17&"*",'Trial Balance (Susa)'!AQ:AQ)/1000 -> 73.31951 | K17: =L17-J17 -> -73.31951 | M17: =IFERROR(J17/L17,"n/a") -> n/a | P17: Sterilisation
C18: Erlöse Wartung | E18: =-SUMIF('Trial Balance (Susa)'!$F:$F,"*"&$P18&"*",'Trial Balance (Susa)'!AE:AE)/1000 -> 77.3138 | F18: =G18-E18 -> 11.2 | G18: ='Lead PL'!H14 -> 88.5138 | H18: =IFERROR(E18/G18,"n/a") -> 0.87346606 | J18: =-SUMIF('Trial Balance (Susa)'!$F:$F,"*"&$P18&"*",'Trial Balance (Susa)'!AQ:AQ)/1000 -> 56.6608 | K18: =L18-J18 -> -56.6608 | M18: =IFERROR(J18/L18,"n/a") -> n/a | P18: Wartung
C19: Erlöse Miete | E19: =-SUMIF('Trial Balance (Susa)'!$F:$F,"*"&$P19&"*",'Trial Balance (Susa)'!AE:AE)/1000 -> 30.619 | F19: =G19-E19 -> 11.08 | G19: ='Lead PL'!H15 -> 41.699 | H19: =IFERROR(E19/G19,"n/a") -> 0.73428619 | J19: =-SUMIF('Trial Balance (Susa)'!$F:$F,"*"&$P19&"*",'Trial Balance (Susa)'!AQ:AQ)/1000 -> 19.77 | K19: =L19-J19 -> -19.77 | M19: =IFERROR(J19/L19,"n/a") -> n/a | P19: Miete
C20: Erlöse Abfallverwertung | E20: =-SUMIF('Trial Balance (Susa)'!$F:$F,"*"&$P20&"*",'Trial Balance (Susa)'!AE:AE)/1000 -> 2.5893 | F20: =G20-E20 -> 0.8681 | G20: ='Lead PL'!H16 -> 3.4574 | H20: =IFERROR(E20/G20,"n/a") -> 0.74891537 | J20: =-SUMIF('Trial Balance (Susa)'!$F:$F,"*"&$P20&"*",'Trial Balance (Susa)'!AQ:AQ)/1000 -> 2.6271 | K20: =L20-J20 -> -2.6271 | M20: =IFERROR(J20/L20,"n/a") -> n/a | P20: Abfall
C21: Sonstige Erlöse | E21: =-SUMIF('Trial Balance (Susa)'!$F:$F,"*"&$P21&"*",'Trial Balance (Susa)'!AE:AE)/1000 -> 0.4325 | F21: =G21-E21 -> 0.7675 | G21: ='Lead PL'!H17 -> 1.2 | H21: =IFERROR(E21/G21,"n/a") -> 0.36041667 | J21: =-SUMIF('Trial Balance (Susa)'!$F:$F,"*"&$P21&"*",'Trial Balance (Susa)'!AQ:AQ)/1000 -> 0.31325 | K21: =L21-J21 -> -0.31325 | M21: =IFERROR(J21/L21,"n/a") -> n/a | P21: Sonstige Dienstleistung
C22: Skonti und Boni | E22: =-SUMIF('Trial Balance (Susa)'!$F:$F,"*"&$P22&"*",'Trial Balance (Susa)'!AE:AE)/1000 -> -130.60544 | F22: =G22-E22 -> -41.80071 | G22: ='Lead PL'!H18 -> -172.40615 | H22: =IFERROR(E22/G22,"n/a") -> 0.75754513 | J22: =-SUMIF('Trial Balance (Susa)'!$F:$F,"*"&$P22&"*",'Trial Balance (Susa)'!AQ:AQ)/1000 -> -124.92524 | K22: =L22-J22 -> 124.92524 | M22: =IFERROR(J22/L22,"n/a") -> n/a | P22: Skonti
C23: ='Lead PL'!C19 -> Bestandsveränderung | D23: ='Lead PL'!D19 -> Change in inventory | E23: =-SUMIF('Trial Balance (Susa)'!$D:$D,"*"&$P23&"*",'Trial Balance (Susa)'!AE:AE)/1000 -> 109.90872 | F23: =G23-E23 -> 240.88642 | G23: ='Lead PL'!H19 -> 350.79514 | H23: =IFERROR(E23/G23,"n/a") -> 0.31331312 | J23: =-SUMIF('Trial Balance (Susa)'!$D:$D,"*"&$P23&"*",'Trial Balance (Susa)'!AQ:AQ)/1000 -> 0 | K23: =L23-J23 -> 0 | M23: =IFERROR(J23/L23,"n/a") -> n/a | P23: /profit and loss/income/increase in inventory
C24: ='Lead PL'!C20 -> Aktivierte Eigenleistungen | D24: ='Lead PL'!D20 -> Own work capitalized | F24: =G24-E24 -> 0 | H24: =IFERROR(E24/G24,"n/a") -> n/a | K24: =L24-J24 -> 0 | M24: =IFERROR(J24/L24,"n/a") -> n/a | P24: /profit and loss/income/own work capitalised
C25: ='Lead PL'!C21 -> Dummy 1 | D25: ='Lead PL'!D21 -> Dummy 1 | F25: =G25-E25 -> 0 | H25: =IFERROR(E25/G25,"n/a") -> n/a | K25: =L25-J25 -> 0 | M25: =IFERROR(J25/L25,"n/a") -> n/a
C26: ='Lead PL'!C22 -> Dummy 2 | D26: ='Lead PL'!D22 -> Dummy 2 | F26: =G26-E26 -> 0 | H26: =IFERROR(E26/G26,"n/a") -> n/a | K26: =L26-J26 -> 0 | M26: =IFERROR(J26/L26,"n/a") -> n/a
C27: ='Lead PL'!C23 -> Dummy 3 | D27: ='Lead PL'!D23 -> Dummy 3 | F27: =G27-E27 -> 0 | H27: =IFERROR(E27/G27,"n/a") -> n/a | K27: =L27-J27 -> 0 | M27: =IFERROR(J27/L27,"n/a") -> n/a
C28: ='Lead PL'!C24 -> Gesamtleistung | D28: ='Lead PL'!D24 -> Total output | E28: =E12+E23 -> 12839.855 | F28: =G28-E28 -> 4170.9032 | G28: =G12+G23 -> 17010.759 | H28: =IFERROR(E28/G28,"n/a") -> 0.75480792 | J28: =J12+J23 -> 11495.738 | K28: =L28-J28 -> -11495.738 | L28: =SUM(L12:L27) -> 0 | M28: =IFERROR(J28/L28,"n/a") -> n/a
C29: ='Lead PL'!C25 -> Materialaufwand | D29: ='Lead PL'!D25 -> Cost of materials | E29: =-SUMIF('Trial Balance (Susa)'!$D:$D,"*"&$P29&"*",'Trial Balance (Susa)'!AE:AE)/1000 -> -7716.4573 | F29: =G29-E29 -> -681.43012 | G29: ='Lead PL'!H25 -> -8397.8874 | H29: =IFERROR(E29/G29,"n/a") -> 0.91885696 | J29: =-SUMIF('Trial Balance (Susa)'!$D:$D,"*"&$P29&"*",'Trial Balance (Susa)'!AQ:AQ)/1000 -> -5256.4678 | K29: =L29-J29 -> 5256.4678 | M29: =IFERROR(J29/L29,"n/a") -> n/a | P29: /profit and loss/expense/material expense
C30: ='Lead PL'!C26 -> RHB-Aufwand | D30: ='Lead PL'!D26 -> Dummy 1 | F30: =G30-E30 -> 0 | H30: =IFERROR(E30/G30,"n/a") -> n/a | K30: =L30-J30 -> 0 | M30: =IFERROR(J30/L30,"n/a") -> n/a
C31: ='Lead PL'!C27 -> Fremdleistungen | D31: ='Lead PL'!D27 -> Dummy 2 | F31: =G31-E31 -> 0 | H31: =IFERROR(E31/G31,"n/a") -> n/a | K31: =L31-J31 -> 0 | M31: =IFERROR(J31/L31,"n/a") -> n/a
C32: ='Lead PL'!C28 -> Dummy 3 | D32: ='Lead PL'!D28 -> Dummy 3 | F32: =G32-E32 -> 0 | H32: =IFERROR(E32/G32,"n/a") -> n/a | K32: =L32-J32 -> 0 | M32: =IFERROR(J32/L32,"n/a") -> n/a
C33: ='Lead PL'!C29 -> Rohergebnis | D33: ='Lead PL'!D29 -> Gross profit | E33: =SUM(E28:E32) -> 5123.3981 | F33: =G33-E33 -> 3489.4731 | G33: =SUM(G28:G32) -> 8612.8712 | H33: =IFERROR(E33/G33,"n/a") -> 0.59485367 | J33: =SUM(J28:J32) -> 6239.2701 | K33: =L33-J33 -> -6239.2701 | L33: =SUM(L28:L32) -> 0 | M33: =IFERROR(J33/L33,"n/a") -> n/a
C34: ='Lead PL'!C30 -> Personalaufwand | D34: ='Lead PL'!D30 -> Personnel expenses | E34: =-SUMIF('Trial Balance (Susa)'!$D:$D,"*"&$P34&"*",'Trial Balance (Susa)'!AE:AE)/1000 -> -3374.9749 | F34: =G34-E34 -> -1147.3761 | G34: ='Lead PL'!H30 -> -4522.3511 | H34: =IFERROR(E34/G34,"n/a") -> 0.7462877 | J34: =-SUMIF('Trial Balance (Susa)'!$D:$D,"*"&$P34&"*",'Trial Balance (Susa)'!AQ:AQ)/1000 -> -3218.9178 | K34: =L34-J34 -> 3218.9178 | M34: =IFERROR(J34/L34,"n/a") -> n/a | P34: /profit and loss/expense/personnel expense
C35: ='Lead PL'!C31 -> Miet- und Grundstücksaufwendungen | D35: ='Lead PL'!D31 -> Premise costs | E35: =-SUMIF('Trial Balance (Susa)'!$D:$D,"*"&$P35&"*",'Trial Balance (Susa)'!AE:AE)/1000 -> -316.8258 | F35: =G35-E35 -> -106.15673 | G35: ='Lead PL'!H31 -> -422.98253 | H35: =IFERROR(E35/G35,"n/a") -> 0.7490281 | J35: =-SUMIF('Trial Balance (Susa)'!$D:$D,"*"&$P35&"*",'Trial Balance (Susa)'!AQ:AQ)/1000 -> -263.52974 | K35: =L35-J35 -> 263.52974 | M35: =IFERROR(J35/L35,"n/a") -> n/a | P35: /profit and loss/expense/other expense/premise costs
C36: ='Lead PL'!C32 -> Reparaturen und Instandhaltungen | D36: ='Lead PL'!D32 -> Repair and maintenance | E36: =-SUMIF('Trial Balance (Susa)'!$D:$D,"*"&$P36&"*",'Trial Balance (Susa)'!AE:AE)/1000 -> -96.05455 | F36: =G36-E36 -> -37.25826 | G36: ='Lead PL'!H32 -> -133.31281 | H36: =IFERROR(E36/G36,"n/a") -> 0.72052003 | J36: =-SUMIF('Trial Balance (Susa)'!$D:$D,"*"&$P36&"*",'Trial Balance (Susa)'!AQ:AQ)/1000 -> -80.49878 | K36: =L36-J36 -> 80.49878 | M36: =IFERROR(J36/L36,"n/a") -> n/a | P36: /profit and loss/expense/other expense/repair and maintenance
C37: ='Lead PL'!C33 -> Vertriebskosten | D37: ='Lead PL'!D33 -> Sales costs | E37: =-SUMIF('Trial Balance (Susa)'!$D:$D,"*"&$P37&"*",'Trial Balance (Susa)'!AE:AE)/1000 -> 0 | F37: =G37-E37 -> 0 | G37: ='Lead PL'!H33 -> 0 | H37: =IFERROR(E37/G37,"n/a") -> n/a | J37: =-SUMIF('Trial Balance (Susa)'!$D:$D,"*"&$P37&"*",'Trial Balance (Susa)'!AQ:AQ)/1000 -> 0 | K37: =L37-J37 -> 0 | M37: =IFERROR(J37/L37,"n/a") -> n/a | P37: /profit and loss/expense/other expense/sales costs
C38: ='Lead PL'!C34 -> Kosten der Warenabgabe | D38: ='Lead PL'!D34 -> Delivery costs | E38: =-SUMIF('Trial Balance (Susa)'!$D:$D,"*"&$P38&"*",'Trial Balance (Susa)'!AE:AE)/1000 -> -221.88585 | F38: =G38-E38 -> -79.49758 | G38: ='Lead PL'!H34 -> -301.38343 | H38: =IFERROR(E38/G38,"n/a") -> 0.73622445 | J38: =-SUMIF('Trial Balance (Susa)'!$D:$D,"*"&$P38&"*",'Trial Balance (Susa)'!AQ:AQ)/1000 -> -271.42434 | K38: =L38-J38 -> 271.42434 | M38: =IFERROR(J38/L38,"n/a") -> n/a | P38: /profit and loss/expense/other expense/delivery costs
C39: ='Lead PL'!C35 -> Fahrzeugkosten | D39: ='Lead PL'!D35 -> Vehicle costs | E39: =-SUMIF('Trial Balance (Susa)'!$D:$D,"*"&$P39&"*",'Trial Balance (Susa)'!AE:AE)/1000 -> -182.0933 | F39: =G39-E39 -> -63.96851 | G39: ='Lead PL'!H35 -> -246.06181 | H39: =IFERROR(E39/G39,"n/a") -> 0.74003073 | J39: =-SUMIF('Trial Balance (Susa)'!$D:$D,"*"&$P39&"*",'Trial Balance (Susa)'!AQ:AQ)/1000 -> -171.83902 | K39: =L39-J39 -> 171.83902 | M39: =IFERROR(J39/L39,"n/a") -> n/a | P39: /profit and loss/expense/other expense/vehicle costs
C40: ='Lead PL'!C36 -> Versicherung, Beiträge und Abgaben | D40: ='Lead PL'!D36 -> Insurance, contributions and levies expenses | E40: =-SUMIF('Trial Balance (Susa)'!$D:$D,"*"&$P40&"*",'Trial Balance (Susa)'!AE:AE)/1000 -> -54.90961 | F40: =G40-E40 -> -14.77379 | G40: ='Lead PL'!H36 -> -69.6834 | H40: =IFERROR(E40/G40,"n/a") -> 0.78798695 | J40: =-SUMIF('Trial Balance (Susa)'!$D:$D,"*"&$P40&"*",'Trial Balance (Susa)'!AQ:AQ)/1000 -> -63.03017 | K40: =L40-J40 -> 63.03017 | M40: =IFERROR(J40/L40,"n/a") -> n/a | P40: /profit and loss/expense/other expense/insurance contributions and levies
C41: ='Lead PL'!C37 -> Werbe- und Reisekosten | D41: ='Lead PL'!D37 -> Advertising and travel expenses | E41: =-SUMIF('Trial Balance (Susa)'!$D:$D,"*"&$P41&"*",'Trial Balance (Susa)'!AE:AE)/1000 -> -104.88799 | F41: =G41-E41 -> -49.21864 | G41: ='Lead PL'!H37 -> -154.10663 | H41: =IFERROR(E41/G41,"n/a") -> 0.68061958 | J41: =-SUMIF('Trial Balance (Susa)'!$D:$D,"*"&$P41&"*",'Trial Balance (Susa)'!AQ:AQ)/1000 -> -85.08739 | K41: =L41-J41 -> 85.08739 | M41: =IFERROR(J41/L41,"n/a") -> n/a | P41: /profit and loss/expense/other expense/advertising and travel
C42: ='Lead PL'!C38 -> Sonstige betriebliche Erträge | D42: ='Lead PL'!D38 -> Other operating income | E42: =-SUMIF('Trial Balance (Susa)'!$D:$D,"*"&$P42&"*",'Trial Balance (Susa)'!AE:AE)/1000 -> 200.9248 | F42: =G42-E42 -> 63.6468 | G42: ='Lead PL'!H38 -> 264.5716 | H42: =IFERROR(E42/G42,"n/a") -> 0.7594345 | J42: =-SUMIF('Trial Balance (Susa)'!$D:$D,"*"&$P42&"*",'Trial Balance (Susa)'!AQ:AQ)/1000 -> 130.83662 | K42: =L42-J42 -> -130.83662 | M42: =IFERROR(J42/L42,"n/a") -> n/a | P42: /profit and loss/income/other income
C43: ='Lead PL'!C39 -> Sonstige betriebliche Aufwendungen | D43: ='Lead PL'!D39 -> Other operating expenses | E43: =-SUMIF('Trial Balance (Susa)'!$D:$D,"*"&$P43&"*",'Trial Balance (Susa)'!AE:AE)/1000 -> -736.83693 | F43: =G43-E43 -> -530.38345 | G43: ='Lead PL'!H39 -> -1267.2204 | H43: =IFERROR(E43/G43,"n/a") -> 0.58145919 | J43: =-SUMIF('Trial Balance (Susa)'!$D:$D,"*"&$P43&"*",'Trial Balance (Susa)'!AQ:AQ)/1000 -> -777.20689 | K43: =L43-J43 -> 777.20689 | M43: =IFERROR(J43/L43,"n/a") -> n/a | P43: /profit and loss/expense/other expense/other operating expense
C44: ='Lead PL'!C40 -> Dummy 1 | D44: ='Lead PL'!D40 -> Dummy 1 | F44: =G44-E44 -> 0 | H44: =IFERROR(E44/G44,"n/a") -> n/a | K44: =L44-J44 -> 0 | M44: =IFERROR(J44/L44,"n/a") -> n/a
C45: ='Lead PL'!C41 -> Dummy 2 | D45: ='Lead PL'!D41 -> Dummy 2 | F45: =G45-E45 -> 0 | H45: =IFERROR(E45/G45,"n/a") -> n/a | K45: =L45-J45 -> 0 | M45: =IFERROR(J45/L45,"n/a") -> n/a
C46: ='Lead PL'!C42 -> Dummy 3 | D46: ='Lead PL'!D42 -> Dummy 3 | F46: =G46-E46 -> 0 | H46: =IFERROR(E46/G46,"n/a") -> n/a | K46: =L46-J46 -> 0 | M46: =IFERROR(J46/L46,"n/a") -> n/a
C47: ='Lead PL'!C43 -> EBITDA | D47: ='Lead PL'!D43 -> EBITDA | E47: =SUM(E33:E46) -> 235.8539 | F47: =G47-E47 -> 1524.4869 | G47: =SUM(G33:G46) -> 1760.3408 | H47: =IFERROR(E47/G47,"n/a") -> 0.13398196 | J47: =SUM(J33:J46) -> 1438.5726 | K47: =L47-J47 -> -1438.5726 | L47: =SUM(L33:L46) -> 0 | M47: =IFERROR(J47/L47,"n/a") -> n/a
C48: ='Lead PL'!C44 -> Abschreibungen | D48: ='Lead PL'!D44 -> Depreciation | E48: =-SUMIF('Trial Balance (Susa)'!$D:$D,"*"&$P48&"*",'Trial Balance (Susa)'!AE:AE)/1000 -> -229.30187 | F48: =G48-E48 -> -86.41784 | G48: ='Lead PL'!H44 -> -315.71971 | H48: =IFERROR(E48/G48,"n/a") -> 0.72628304 | J48: =-SUMIF('Trial Balance (Susa)'!$D:$D,"*"&$P48&"*",'Trial Balance (Susa)'!AQ:AQ)/1000 -> -208.41796 | K48: =L48-J48 -> 208.41796 | M48: =IFERROR(J48/L48,"n/a") -> n/a | P48: /profit and loss/expense/depreciation expense
C49: ='Lead PL'!C45 -> Dummy 1 | D49: ='Lead PL'!D45 -> Dummy 1 | F49: =G49-E49 -> 0 | H49: =IFERROR(E49/G49,"n/a") -> n/a | K49: =L49-J49 -> 0 | M49: =IFERROR(J49/L49,"n/a") -> n/a
C50: ='Lead PL'!C46 -> Dummy 2 | D50: ='Lead PL'!D46 -> Dummy 2 | F50: =G50-E50 -> 0 | H50: =IFERROR(E50/G50,"n/a") -> n/a | K50: =L50-J50 -> 0 | M50: =IFERROR(J50/L50,"n/a") -> n/a
C51: ='Lead PL'!C47 -> Dummy 3 | D51: ='Lead PL'!D47 -> Dummy 3 | F51: =G51-E51 -> 0 | H51: =IFERROR(E51/G51,"n/a") -> n/a | K51: =L51-J51 -> 0 | M51: =IFERROR(J51/L51,"n/a") -> n/a
C52: ='Lead PL'!C48 -> EBIT | D52: ='Lead PL'!D48 -> EBIT | E52: =SUM(E47:E51) -> 6.55203 | F52: =G52-E52 -> 1438.069 | G52: =SUM(G47:G51) -> 1444.6211 | H52: =IFERROR(E52/G52,"n/a") -> 0.0045354662 | J52: =SUM(J47:J51) -> 1230.1547 | K52: =L52-J52 -> -1230.1547 | L52: =SUM(L47:L51) -> 0 | M52: =IFERROR(J52/L52,"n/a") -> n/a
C53: ='Lead PL'!C49 -> Beteiligungsergebnis | D53: ='Lead PL'!D49 -> Investment income | E53: =-SUMIF('Trial Balance (Susa)'!$D:$D,"*"&$P53&"*",'Trial Balance (Susa)'!AE:AE)/1000 -> 0 | F53: =G53-E53 -> 0 | G53: ='Lead PL'!H49 -> 0 | H53: =IFERROR(E53/G53,"n/a") -> n/a | J53: =-SUMIF('Trial Balance (Susa)'!$D:$D,"*"&$P53&"*",'Trial Balance (Susa)'!AQ:AQ)/1000 -> 0 | K53: =L53-J53 -> 0 | M53: =IFERROR(J53/L53,"n/a") -> n/a | P53: /profit and loss/income/income from investments
C54: ='Lead PL'!C50 -> Zinserträge | D54: ='Lead PL'!D50 -> Interest income | E54: =-SUMIF('Trial Balance (Susa)'!$D:$D,"*"&$P54&"*",'Trial Balance (Susa)'!AE:AE)/1000 -> 3.13242 | F54: =G54-E54 -> 0.00224 | G54: ='Lead PL'!H50 -> 3.13466 | H54: =IFERROR(E54/G54,"n/a") -> 0.99928541 | J54: =-SUMIF('Trial Balance (Susa)'!$D:$D,"*"&$P54&"*",'Trial Balance (Susa)'!AQ:AQ)/1000 -> 2.20626 | K54: =L54-J54 -> -2.20626 | M54: =IFERROR(J54/L54,"n/a") -> n/a | P54: /profit and loss/income/interest income
C55: ='Lead PL'!C51 -> Zinsaufwendungen | D55: ='Lead PL'!D51 -> Interest expenses | E55: =-SUMIF('Trial Balance (Susa)'!$D:$D,"*"&$P55&"*",'Trial Balance (Susa)'!AE:AE)/1000 -> 0 | F55: =G55-E55 -> -3.50652 | G55: ='Lead PL'!H51 -> -3.50652 | H55: =IFERROR(E55/G55,"n/a") -> 0 | J55: =-SUMIF('Trial Balance (Susa)'!$D:$D,"*"&$P55&"*",'Trial Balance (Susa)'!AQ:AQ)/1000 -> -0.21145 | K55: =L55-J55 -> 0.21145 | M55: =IFERROR(J55/L55,"n/a") -> n/a | P55: /profit and loss/expense/interest expense
C56: ='Lead PL'!C52 -> Abschreibungen auf Finanzanlagen | D56: ='Lead PL'!D52 -> Abschreibungn auf Finanzanlagen | E56: =-SUMIF('Trial Balance (Susa)'!$D:$D,"*"&$P56&"*",'Trial Balance (Susa)'!AE:AE)/1000 -> 0 | F56: =G56-E56 -> -4.07329 | G56: ='Lead PL'!H52 -> -4.07329 | H56: =IFERROR(E56/G56,"n/a") -> 0 | J56: =-SUMIF('Trial Balance (Susa)'!$D:$D,"*"&$P56&"*",'Trial Balance (Susa)'!AQ:AQ)/1000 -> 0 | K56: =L56-J56 -> 0 | M56: =IFERROR(J56/L56,"n/a") -> n/a | P56: /profit and loss/expense/depreciation on financial assets
C57: ='Lead PL'!C53 -> Dummy 2 | D57: ='Lead PL'!D53 -> Dummy 2 | F57: =G57-E57 -> 0 | H57: =IFERROR(E57/G57,"n/a") -> n/a | K57: =L57-J57 -> 0 | M57: =IFERROR(J57/L57,"n/a") -> n/a
C58: ='Lead PL'!C54 -> Dummy 3 | D58: ='Lead PL'!D54 -> Dummy 3 | F58: =G58-E58 -> 0 | H58: =IFERROR(E58/G58,"n/a") -> n/a | K58: =L58-J58 -> 0 | M58: =IFERROR(J58/L58,"n/a") -> n/a
C59: ='Lead PL'!C55 -> Finanzergebnis | D59: ='Lead PL'!D55 -> Financial result | E59: =SUM(E53:E58) -> 3.13242 | F59: =G59-E59 -> -7.57757 | G59: =SUM(G53:G58) -> -4.44515 | H59: =IFERROR(E59/G59,"n/a") -> -0.70468263 | J59: =SUM(J53:J58) -> 1.99481 | K59: =L59-J59 -> -1.99481 | L59: =SUM(L53:L58) -> 0 | M59: =IFERROR(J59/L59,"n/a") -> n/a
C60: ='Lead PL'!C56 -> EBT | D60: ='Lead PL'!D56 -> EBT | E60: =E59+E52 -> 9.68445 | F60: =G60-E60 -> 1430.4915 | G60: =G59+G52 -> 1440.1759 | H60: =IFERROR(E60/G60,"n/a") -> 0.006724491 | J60: =J59+J52 -> 1232.1495 | K60: =L60-J60 -> -1232.1495 | L60: =L59+L52 -> 0 | M60: =IFERROR(J60/L60,"n/a") -> n/a
C61: ='Lead PL'!C57 -> Ertragssteuern | D61: ='Lead PL'!D57 -> Income taxes | E61: =-SUMIF('Trial Balance (Susa)'!$D:$D,"*"&$P61&"*",'Trial Balance (Susa)'!AE:AE)/1000 -> -384.7391 | F61: =G61-E61 -> -57.38251 | G61: ='Lead PL'!H57 -> -442.12161 | H61: =IFERROR(E61/G61,"n/a") -> 0.87021103 | J61: =-SUMIF('Trial Balance (Susa)'!$D:$D,"*"&$P61&"*",'Trial Balance (Susa)'!AQ:AQ)/1000 -> -333.51971 | K61: =L61-J61 -> 333.51971 | M61: =IFERROR(J61/L61,"n/a") -> n/a | P61: /profit and loss/expense/taxes/taxes on income and earnings
C62: ='Lead PL'!C58 -> Sonstige Steuern | D62: ='Lead PL'!D58 -> Other taxes | E62: =-SUMIF('Trial Balance (Susa)'!$D:$D,"*"&$P62&"*",'Trial Balance (Susa)'!AE:AE)/1000 -> -2.972 | F62: =G62-E62 -> -0.03 | G62: ='Lead PL'!H58 -> -3.002 | H62: =IFERROR(E62/G62,"n/a") -> 0.99000666 | J62: =-SUMIF('Trial Balance (Susa)'!$D:$D,"*"&$P62&"*",'Trial Balance (Susa)'!AQ:AQ)/1000 -> -2.484 | K62: =L62-J62 -> 2.484 | M62: =IFERROR(J62/L62,"n/a") -> n/a | P62: /profit and loss/expense/taxes/other taxes
C63: ='Lead PL'!C59 -> Jahresüberschuss | D63: ='Lead PL'!D59 -> Profit / Loss | E63: =SUM(E60:E62) -> -378.02665 | F63: =G63-E63 -> 1373.0789 | G63: =SUM(G60:G62) -> 995.0523 | H63: =IFERROR(E63/G63,"n/a") -> -0.37990631 | J63: =SUM(J60:J62) -> 896.14577 | K63: =L63-J63 -> -896.14577 | L63: =SUM(L60:L62) -> 0 | M63: =IFERROR(J63/L63,"n/a") -> n/a
C65: ="In % der "&C28 -> In % der Gesamtleistung | D65: ="In % of "&D28 -> In % of Total output
C66: =C12 -> Umsatzerlöse | D66: =D12 -> Revenues | E66: =IFERROR(E12/E$28,"n/a") -> 0.99144003 | F66: =IFERROR(F12/F$28,"n/a") -> 0.94224598 | G66: =IFERROR(G12/G$28,"n/a") -> 0.97937804 | J66: =IFERROR(J12/J$28,"n/a") -> 1 | K66: =IFERROR(K12/K$28,"n/a") -> 1 | L66: =IFERROR(L12/L$28,"n/a") -> n/a
C67: =C23 -> Bestandsveränderung | D67: =D23 -> Change in inventory | E67: =IFERROR(E23/E$28,"n/a") -> 0.0085599656 | F67: =IFERROR(F23/F$28,"n/a") -> 0.057754018 | G67: =IFERROR(G23/G$28,"n/a") -> 0.020621957 | J67: =IFERROR(J23/J$28,"n/a") -> 0 | K67: =IFERROR(K23/K$28,"n/a") -> 0 | L67: =IFERROR(L23/L$28,"n/a") -> n/a
C68: =C24 -> Aktivierte Eigenleistungen | D68: =D24 -> Own work capitalized | E68: =IFERROR(E25/E$28,"n/a") -> 0 | F68: =IFERROR(F25/F$28,"n/a") -> 0 | G68: =IFERROR(G25/G$28,"n/a") -> 0 | J68: =IFERROR(J25/J$28,"n/a") -> 0 | K68: =IFERROR(K25/K$28,"n/a") -> 0 | L68: =IFERROR(L25/L$28,"n/a") -> n/a
C69: =C26 -> Dummy 2 | D69: =D26 -> Dummy 2 | E69: =IFERROR(E26/E$28,"n/a") -> 0 | F69: =IFERROR(F26/F$28,"n/a") -> 0 | G69: =IFERROR(G26/G$28,"n/a") -> 0 | J69: =IFERROR(J26/J$28,"n/a") -> 0 | K69: =IFERROR(K26/K$28,"n/a") -> 0 | L69: =IFERROR(L26/L$28,"n/a") -> n/a
C70: =C27 -> Dummy 3 | D70: =D27 -> Dummy 3 | E70: =IFERROR(E27/E$28,"n/a") -> 0 | F70: =IFERROR(F27/F$28,"n/a") -> 0 | G70: =IFERROR(G27/G$28,"n/a") -> 0 | J70: =IFERROR(J27/J$28,"n/a") -> 0 | K70: =IFERROR(K27/K$28,"n/a") -> 0 | L70: =IFERROR(L27/L$28,"n/a") -> n/a
C71: =C28 -> Gesamtleistung | D71: =D28 -> Total output | E71: =IFERROR(E28/E$28,"n/a") -> 1 | F71: =IFERROR(F28/F$28,"n/a") -> 1 | G71: =IFERROR(G28/G$28,"n/a") -> 1 | J71: =IFERROR(J28/J$28,"n/a") -> 1 | K71: =IFERROR(K28/K$28,"n/a") -> 1 | L71: =IFERROR(L28/L$28,"n/a") -> n/a
C72: =C29 -> Materialaufwand | D72: =D29 -> Cost of materials | E72: =IFERROR(E29/E$28,"n/a") -> -0.60097696 | F72: =IFERROR(F29/F$28,"n/a") -> -0.16337711 | G72: =IFERROR(G29/G$28,"n/a") -> -0.49368095 | J72: =IFERROR(J29/J$28,"n/a") -> -0.45725362 | K72: =IFERROR(K29/K$28,"n/a") -> -0.45725362 | L72: =IFERROR(L29/L$28,"n/a") -> n/a
C73: =C30 -> RHB-Aufwand | D73: =D30 -> Dummy 1 | E73: =IFERROR(E30/E$28,"n/a") -> 0 | F73: =IFERROR(F30/F$28,"n/a") -> 0 | G73: =IFERROR(G30/G$28,"n/a") -> 0 | J73: =IFERROR(J30/J$28,"n/a") -> 0 | K73: =IFERROR(K30/K$28,"n/a") -> 0 | L73: =IFERROR(L30/L$28,"n/a") -> n/a
C74: =C31 -> Fremdleistungen | D74: =D31 -> Dummy 2 | E74: =IFERROR(E31/E$28,"n/a") -> 0 | F74: =IFERROR(F31/F$28,"n/a") -> 0 | G74: =IFERROR(G31/G$28,"n/a") -> 0 | J74: =IFERROR(J31/J$28,"n/a") -> 0 | K74: =IFERROR(K31/K$28,"n/a") -> 0 | L74: =IFERROR(L31/L$28,"n/a") -> n/a
C75: =C32 -> Dummy 3 | D75: =D32 -> Dummy 3 | E75: =IFERROR(E32/E$28,"n/a") -> 0 | F75: =IFERROR(F32/F$28,"n/a") -> 0 | G75: =IFERROR(G32/G$28,"n/a") -> 0 | J75: =IFERROR(J32/J$28,"n/a") -> 0 | K75: =IFERROR(K32/K$28,"n/a") -> 0 | L75: =IFERROR(L32/L$28,"n/a") -> n/a
C76: =C33 -> Rohergebnis | D76: =D33 -> Gross profit | E76: =IFERROR(E33/E$28,"n/a") -> 0.39902304 | F76: =IFERROR(F33/F$28,"n/a") -> 0.83662289 | G76: =IFERROR(G33/G$28,"n/a") -> 0.50631905 | J76: =IFERROR(J33/J$28,"n/a") -> 0.54274638 | K76: =IFERROR(K33/K$28,"n/a") -> 0.54274638 | L76: =IFERROR(L33/L$28,"n/a") -> n/a
C77: =C34 -> Personalaufwand | D77: =D34 -> Personnel expenses | E77: =IFERROR(E34/E$28,"n/a") -> -0.26285148 | F77: =IFERROR(F34/F$28,"n/a") -> -0.27509056 | G77: =IFERROR(G34/G$28,"n/a") -> -0.2658524 | J77: =IFERROR(J34/J$28,"n/a") -> -0.28000967 | K77: =IFERROR(K34/K$28,"n/a") -> -0.28000967 | L77: =IFERROR(L34/L$28,"n/a") -> n/a
C78: =C35 -> Miet- und Grundstücksaufwendungen | D78: =D35 -> Premise costs | E78: =IFERROR(E35/E$28,"n/a") -> -0.024675185 | F78: =IFERROR(F35/F$28,"n/a") -> -0.025451736 | G78: =IFERROR(G35/G$28,"n/a") -> -0.024865589 | J78: =IFERROR(J35/J$28,"n/a") -> -0.022924126 | K78: =IFERROR(K35/K$28,"n/a") -> -0.022924126 | L78: =IFERROR(L35/L$28,"n/a") -> n/a
C79: =C36 -> Reparaturen und Instandhaltungen | D79: =D36 -> Repair and maintenance | E79: =IFERROR(E36/E$28,"n/a") -> -0.0074809682 | F79: =IFERROR(F36/F$28,"n/a") -> -0.0089328996 | G79: =IFERROR(G36/G$28,"n/a") -> -0.0078369703 | J79: =IFERROR(J36/J$28,"n/a") -> -0.0070024892 | K79: =IFERROR(K36/K$28,"n/a") -> -0.0070024892 | L79: =IFERROR(L36/L$28,"n/a") -> n/a
C80: =C37 -> Vertriebskosten | D80: =D37 -> Sales costs | E80: =IFERROR(E37/E$28,"n/a") -> 0 | F80: =IFERROR(F37/F$28,"n/a") -> 0 | G80: =IFERROR(G37/G$28,"n/a") -> 0 | J80: =IFERROR(J37/J$28,"n/a") -> 0 | K80: =IFERROR(K37/K$28,"n/a") -> 0 | L80: =IFERROR(L37/L$28,"n/a") -> n/a
... C106: =C63 -> Jahresüberschuss | D106: =D63 -> Profit / Loss | E106: =IFERROR(E63/E$28,"n/a") -> -0.02944166 | F106: =IFERROR(F63/F$28,"n/a") -> 0.32920422 | G106: =IFERROR(G63/G$28,"n/a") -> 0.058495469 | J106: =IFERROR(J63/J$28,"n/a") -> 0.07795461 | K106: =IFERROR(K63/K$28,"n/a") -> 0.07795461 | L106: =IFERROR(L63/L$28,"n/a") -> n/a
C108: ="Quelle: "&Cockpit!$C$7 -> Quelle: Datenraum/ eigene Analysen | D108: ="Source: "&Cockpit!$C$8 -> Source: Virtual Data Room/ Company Information
C112: Jahresergebnis Lead PL | D112: P/L Check | G112: ='Lead PL'!H59 -> -7402.8351 | J112: ='Lead PL'!J59 -> 0 | L112: ='Lead PL'!K59 -> 0
C113: Check | D113: Check | G113: =G112-G63 -> -8397.8874 | J113: =J112-J63 -> -896.14577 | L113: =L112-L63 -> 0

Sheet PL_QoE
C4: =Cockpit!$C$4 -> Projekt Namur | F4: ='Lead PL'!F4 -> 44926 | G4: ='Lead PL'!G4 -> 45291 | H4: ='Lead PL'!H4 -> 45657 | I4: ='Lead PL'!I4 -> 46022 | J4: ='Lead PL'!J4 -> 46022 | K4: ='Lead PL'!K4 -> 46022 | L4: ='Lead PL'!L4 -> 46387 | M4: ='Lead PL'!M4 -> 46752 | N4: ='Lead PL'!N4 -> 47118
C5: ="in T"&Cockpit!$C$5 -> in TEUR | E5: Ref. | F5: ='Lead PL'!F5 -> IST | G5: ='Lead PL'!G5 -> IST | H5: ='Lead PL'!H5 -> IST | I5: ='Lead PL'!I5 -> IST | J5: ='Lead PL'!J5 -> YTD | K5: ='Lead PL'!K5 -> Plan | L5: ='Lead PL'!L5 -> Plan | M5: ='Lead PL'!M5 -> Plan | N5: ='Lead PL'!N5 -> Plan | T5: Kommentar BT
D6: =Cockpit!$C$4 -> Projekt Namur | F6: ='Lead PL'!F6 -> 44926 | G6: ='Lead PL'!G6 -> 45291 | H6: ='Lead PL'!H6 -> 45657 | I6: ='Lead PL'!I6 -> 46022 | J6: ='Lead PL'!J6 -> 46022 | K6: ='Lead PL'!K6 -> 46022 | L6: ='Lead PL'!L6 -> 46387 | M6: ='Lead PL'!M6 -> 46752 | N6: ='Lead PL'!N6 -> 47118
D7: ="in k"&Cockpit!$C$5 -> in kEUR | E7: Ref. | F7: ='Lead PL'!F7 -> IST | G7: ='Lead PL'!G7 -> IST | H7: ='Lead PL'!H7 -> IST | I7: ='Lead PL'!I7 -> IST | J7: ='Lead PL'!J7 -> YTD | K7: ='Lead PL'!K7 -> Plan | L7: ='Lead PL'!L7 -> Plan | M7: ='Lead PL'!M7 -> Plan | N7: ='Lead PL'!N7 -> Plan | Q7: Classification BT | T7: Kommentar BT
C9: Reported EBITDA | D9: Reported EBITDA | F9: ='Lead PL'!F43 -> -4386.7022 | G9: ='Lead PL'!G43 -> -6491.3424 | H9: ='Lead PL'!H43 -> -6637.5466 | I9: ='Lead PL'!I43 -> -6045.3006 | J9: ='Lead PL'!J43 -> 0 | K9: ='Lead PL'!K43 -> 0 | L9: ='Lead PL'!L43 -> 0 | M9: ='Lead PL'!M43 -> 0 | N9: ='Lead PL'!N43 -> 0
C11: Normalisierungsanpassungen Management | D11: Mgmt normalization adjustments
C12: Firmenjubiläum | D12: Dummy 1 | E12: 1 | F12: 0 | G12: =-'Management Bereinigung 2024'!AW28/1000 -> 32.30675 | H12: 0 | I12: 0 | T12: 2023: Kto. 4641 Kosten Firmenjubiläum
C13: Karenzentschädigung Herr Reinert | D13: Dummy 2 | E13: =E12+1 -> 2 | F13: 0 | G13: 0 | H13: =(10*6.76498)*1.11 -> 75.091278 | I13: 0 | T13: 2024: Kto. 4120 Reinert Karenzentschädigung 10 x 6.764,98 EUR
C14: Geschäftsführergehalt | E14: =E13+1 -> 3 | F14: =(12*19+76)*1.11 -> 337.44 | G14: =(12*19+76)*1.11 -> 337.44 | H14: =(12*19+76)*1.11 -> 337.44 | I14: =(12*19+76)*1.11 -> 337.44 | T14: Kto. 4124/4126 GesGF Heinz Meise Gehalt 12 x 19.000,00 EUR + Tantieme 76.000,00 (aktueller GF kann die alleinige Geschäftsführung übernehmen); Sozialabgaben (und sonstiges) pauschal 11% (insb. Sonstiges: z.B. Privater Range Rover)
C15: Rechts- und Beratungskosten 8P (MDR) | E15: =E14+1 -> 4 | F15: 0 | G15: 64.5 | H15: 10 | I15: 0 | T15: 2023-2024: Kto. 4950 Beratungskosten 8P
C16: Rechts- und Beratungskosten Brandenburg&Partner (MDR) | E16: =E15 -> 4 | F16: 0 | G16: 0 | H16: =142.2025 -> 142.2025 | I16: 0 | T16: 2023-2024: Kto. 4950 Beratungskosten 8P + Brandenburg&Partner (MDR)
C17: Rechts- und Beratungskosten Normec bup GmbH (MDR) | E17: =E16 -> 4 | F17: 0 | G17: 0 | H17: 0 | I17: 99.035
C18: Doppelzahlung Reisekosten & Berufsgenossenschaft | E18: =E17+1 -> 5 | F18: =-'Management Bereinigung 2025'!AS32/1000 -> 5.51704 | G18: =2.80403+2.36825 -> 5.17228 | H18: 5.17489 | I18: 0 | T18: 2023: Kto. 2300 Ausb.TNT Doppelzahlung aus 2020/Reisek.Vorjahre (2.804,03) & Berufsgenossenschaft 2021/2022 (2.368,25); 2024: Kto. 2300 Berufsgenossenschaft 2021-2023 (5.174,89)
C19: Verluste aus Verkauf von Finanzanlagen | D19: Dummy 3 | E19: =E18+1 -> 6 | F19: =-'Management Bereinigung 2024'!AV34/1000 -> 0 | G19: =-'Management Bereinigung 2024'!AW34/1000 -> 0 | H19: =SUMIF('Trial Balance (Susa)'!$E:$E,"*"&$Q19&"*",'Trial Balance (Susa)'!H:H)/1000 -> 21.8304 | I19: =-(-34174.9+40095.46)/1000 -> -5.92056 | Q19: /btadjustment/QOE/AbgangFinanzanlagen | T19: 2024: Kto. 2312 Abgänge Finanzanlagen Restbuchw. BV abzgl. Kto. 8818 Erlöse Verkäufe Finanzanlagen BV; 2025: Kto. 2312/2317/2325 Abgänge Finanzanlagen (34.174.90), Kto. 2715/8818/8838 Erlöse Verkäufe Finanzanlagen (40.095,46)
C20: SIHK Beitrag 2022 | E20: =E19+1 -> 7 | F20: 0 | G20: 0 | H20: 0 | I20: =8.178242+2.36288 -> 10.541122
C21: Ausbuchung geleistete Anzahlung Medvital | E21: =E20+1 -> 8 | F21: 0 | G21: 0 | H21: 0 | I21: 50 | T21: 2025: Medvital geleistete Anzahlung Ausbuchung (50 TEUR)
C22: =C11 & " Gesamt" -> Normalisierungsanpassungen Management Gesamt | D22: =D11 -> Mgmt normalization adjustments | F22: =SUM(F12:F21) -> 342.95704 | G22: =SUM(G12:G21) -> 439.41903 | H22: =SUM(H12:H21) -> 591.73907 | I22: =SUM(I12:I21) -> 491.09556 | J22: =SUM(J12:J19) -> 0 | K22: =SUM(K12:K19) -> 0 | L22: =SUM(L12:L19) -> 0 | M22: =SUM(M12:M19) -> 0 | N22: =SUM(N12:N19) -> 0
C23: Management normalisiertes EBITDA | D23: Management normalized EBITDA | F23: =F22+F9 -> -4043.7451 | G23: =G22+G9 -> -6051.9234 | H23: =H22+H9 -> -6045.8076 | I23: =I22+I9 -> -5554.2051 | J23: =J22+J9 -> 0 | K23: =K22+K9 -> 0 | L23: =L22+L9 -> 0 | M23: =M22+M9 -> 0 | N23: =N22+N9 -> 0
C25: Normalisierungsanpassungen BT | D25: BT normalization adjustments
A27: sbE | C27: Erträge aus Herabsetzung von EWB | F27: =-SUMIF('P&L (Annual Report)'!$I:$I,$Q27,'P&L (Annual Report)'!E:E)/1000 -> -4.784 | G27: =SUMIF('Trial Balance (Susa)'!$E:$E,"*"&$Q27&"*",'Trial Balance (Susa)'!G:G)/1000 -> -6.3 | H27: =SUMIF('Trial Balance (Susa)'!$E:$E,"*"&$Q27&"*",'Trial Balance (Susa)'!H:H)/1000 -> -27.177 | I27: =SUMIF('Trial Balance (Susa)'!$E:$E,"*"&$Q27&"*",'Trial Balance (Susa)'!I:I)/1000 -> 0 | Q27: /btadjustment/QOE/HerabsetzungEWB
A28: sbA | C28: Aufwendungen EWB | F28: =SUMIF('P&L (Annual Report)'!$I:$I,$Q28,'P&L (Annual Report)'!E:E)/1000 -> 6.3 | G28: =SUMIF('Trial Balance (Susa)'!$E:$E,"*"&$Q28&"*",'Trial Balance (Susa)'!G:G)/1000 -> 27.177 | H28: =SUMIF('Trial Balance (Susa)'!$E:$E,"*"&$Q28&"*",'Trial Balance (Susa)'!H:H)/1000 -> 0 | I28: =SUMIF('Trial Balance (Susa)'!$E:$E,"*"&$Q28&"*",'Trial Balance (Susa)'!I:I)/1000 -> 0 | Q28: /btadjustment/QOE/EinstellungEWB | T28: In 2024 gab es keine EWB? Forderungen checken (Frage zu EWB gestellt)
C29: EWB Gesamt | E29: =E21+1 -> 9 | F29: =SUM(F27:F28) -> 1.516 | G29: =SUM(G27:G28) -> 20.877 | H29: =SUM(H27:H28) -> -27.177 | I29: =SUM(I27:I28) -> 0
A31: sbE | C31: Betriebs-/periodenfremde Erträge | F31: =-SUMIF('P&L (Annual Report)'!$I:$I,$Q31,'P&L (Annual Report)'!E:E)/1000 -> -92.67746 | G31: =SUMIF('Trial Balance (Susa)'!$E:$E,"*"&$Q31&"*",'Trial Balance (Susa)'!G:G)/1000 -> -19.86614 | H31: =SUMIF('Trial Balance (Susa)'!$E:$E,"*"&$Q31&"*",'Trial Balance (Susa)'!H:H)/1000 -> -0.30611 | I31: =SUMIF('Trial Balance (Susa)'!$E:$E,"*"&$Q31&"*",'Trial Balance (Susa)'!I:I)/1000 -> -2.44288 | Q31: /btadjustment/QOE/betriebsundperiodenfremd
C32: Betriebs-/periodenfremde Aufwendungen | F32: n.q. | G32: n.q. | H32: n.q. | I32: n.q.
C33: Betriebs/-periodenfremde Erträge/Aufw. | E33: =E29+1 -> 10 | F33: =SUM(F31:F32) -> -92.67746 | G33: =SUM(G31:G32) -> -19.86614 | H33: =SUM(H31:H32) -> -0.30611 | I33: =SUM(I31:I32) -> -2.44288
A35: sbE | C35: Verluste aus Verkauf von Finanzanlagen | F35: ='P&L (Annual Report)'!E203 -> 0 | G35: =SUMIF('Trial Balance (Susa)'!$E:$E,"*"&$Q35&"*",'Trial Balance (Susa)'!G:G)/1000 -> 0 | H35: 0 | Q35: /btadjustment/QOE/AbgangFinanzanlagen
A36: sbE | C36: Zuschreibungen Finanzanlagen | F36: =-SUMIF('P&L (Annual Report)'!$I:$I,$Q36,'P&L (Annual Report)'!E:E)/1000 -> 0 | G36: =SUMIF('Trial Balance (Susa)'!$E:$E,"*"&$Q36&"*",'Trial Balance (Susa)'!G:G)/1000 -> -10.16329 | H36: =SUMIF('Trial Balance (Susa)'!$E:$E,"*"&$Q36&"*",'Trial Balance (Susa)'!H:H)/1000 -> 0 | I36: =SUMIF('Trial Balance (Susa)'!$E:$E,"*"&$Q36&"*",'Trial Balance (Susa)'!I:I)/1000 -> 0 | Q36: /btadjustment/QOE/ZuschreibungenFinanz
C37: Aufw./Erträge aus Finanzanlagen | E37: =E33+1 -> 11 | F37: =SUM(F35:F36) -> 0 | G37: =SUM(G35:G36) -> -10.16329 | H37: =SUM(H35:H36) -> 0 | I37: =SUM(I35:I36) -> 0
C39: Rechts- und Beratungskosten adesso SE (MDR) | E39: =E37+1 -> 12 | F39: 0 | G39: 0 | H39: 0 | I39: 17.73408 | T39: Unterstützung unserer QM-Abt. hinsichtlich Dokumentenerstellung für die MDR ( Medical Device Regulation )
C40: Rechts- und Beratungskosten (MDR) | E40: =E39+1 -> 13 | F40: 0 | G40: 0 | H40: 0 | I40: -50
C42: =C25& " Gesamt" -> Normalisierungsanpassungen BT Gesamt | D42: =D25 -> BT normalization adjustments | F42: =F29+F33+F39+F40 -> -91.16146 | G42: =G29+G33+G39+G40 -> 1.01086 | H42: =H29+H33+H39+H40 -> -27.48311 | I42: =I29+I33+I39+I40 -> -34.7088
C43: BT normalisiertes EBITDA I | D43: BT normalized EBITDA I | F43: =F42+F23 -> -4134.9066 | G43: =G42+G23 -> -6050.9125 | H43: =H42+H23 -> -6073.2907 | I43: =I42+I23 -> -5588.9139 | J43: =J42+J23 -> 0 | K43: =K42+K23 -> 0 | L43: =L42+L23 -> 0 | M43: =M42+M23 -> 0 | N43: =N42+N23 -> 0
C45: Pro forma Anpassungen BT | D45: BT pro forma adjustments
C46: Miete für Betriebsgebäude | D46: Dummy 1 | E46: =E40+1 -> 14 | F46: n.q. | G46: n.q. | H46: n.q. | I46: n.q. | J46: n.q. | T46: Neue Miete?
C47: Geschäftsführergehalt | D47: Dummy 3 | E47: =E46+1 -> 15 | T47: Mit Legal/Tax sprechen bzgl. Fremdüblichkeit
C48: Geschäftsführergehalt (Beratervertrag) | E48: =E47 -> 15 | F48: -150 | G48: -150 | H48: -150 | I48: -150
C49: Geschäftsführer Herr Henze | E49: =E48+1 -> 16 | F49: -50 | G49: -50 | H49: -50 | I49: -50
C50: Buchhaltung/ Kaufmännischer Leiter | E50: =E49+1 -> 17 | F50: -70 | G50: -70 | H50: -70 | I50: -70
C51: Post-Transaktions-Anpassungen | F51: =SUM(F46:F50) -> -270 | G51: =SUM(G46:G50) -> -270 | H51: =SUM(H46:H50) -> -270 | I51: =SUM(I46:I50) -> -270
C53: Kündigung Lieferantenvertrag | D53: Dummy 1 | E53: =E50+1 -> 18 | F53: n.q. | G53: n.q. | H53: n.q. | I53: n.q. | J53: n.q.
C54: =C45 & " Gesamt" -> Pro forma Anpassungen BT Gesamt | D54: =D45 -> BT pro forma adjustments | F54: =SUM(F51:F53) -> -270 | G54: =SUM(G51:G53) -> -270 | H54: =SUM(H51:H53) -> -270 | I54: =SUM(I51:I53) -> -270 | J54: =SUM(J53:J53) -> 0 | K54: =SUM(K53:K53) -> 0 | L54: =SUM(L53:L53) -> 0 | M54: =SUM(M53:M53) -> 0 | N54: =SUM(N53:N53) -> 0
C55: BT normalisiertes EBITDA II | D55: BT normalized EBITDA II | F55: =F54+F43 -> -4404.9066 | G55: =G54+G43 -> -6320.9125 | H55: =H54+H43 -> -6343.2907 | I55: =I54+I43 -> -5858.9139 | J55: =J54+J43 -> 0 | K55: =K54+K43 -> 0 | L55: =L54+L43 -> 0 | M55: =M54+M43 -> 0 | N55: =N54+N43 -> 0
C57: ='Lead PL'!C24 -> Gesamtleistung | D57: ='Lead PL'!D24 -> Total output | F57: ='Lead PL'!F24 -> 16416.745 | G57: ='Lead PL'!G24 -> 15515.821 | H57: ='Lead PL'!H24 -> 17010.759 | I57: ='Lead PL'!I24 -> 15235.918 | J57: ='Lead PL'!J24 -> 0 | K57: ='Lead PL'!K24 -> 0 | L57: ='Lead PL'!L24 -> 0 | M57: ='Lead PL'!M24 -> 0 | N57: ='Lead PL'!N24 -> 0
C59: Other items to be considered | D59: Other items to be considered
C60: COVID19-Effekt | D60: Dummy 3 | E60: =E53+1 -> 19 | F60: n.q. | G60: 0 | H60: 0 | I60: 0
C61: Dummy 3 | D61: Dummy 3 | Q61: /btadjustment/QOE/other items_3
C62: BT - other items to be considered | D62: BT - other items to be considered | F62: =SUM(F60:F61) -> 0 | G62: =SUM(G60:G61) -> 0 | H62: =SUM(H60:H61) -> 0 | I62: =SUM(I60:I61) -> 0 | J62: =SUM(J50:J61) -> 0 | K62: =SUM(K50:K61) -> 0 | L62: =SUM(L50:L61) -> 0 | M62: =SUM(M50:M61) -> 0 | N62: =SUM(N50:N61) -> 0
C64: ="in % der "&C57 -> in % der Gesamtleistung | D64: ="in % of "&D57 -> in % of Total output
C65: =C9 -> Reported EBITDA | D65: =D9 -> Reported EBITDA | F65: =IFERROR(F9/F$57,"n/a") -> -0.26720901 | G65: =IFERROR(G9/G$57,"n/a") -> -0.41836926 | H65: =IFERROR(H9/H$57,"n/a") -> -0.39019698 | I65: =IFERROR(I9/I$57,"n/a") -> -0.39677953 | J65: =IFERROR(J9/J$57,"n/a") -> n/a | K65: =IFERROR(K9/K$57,"n/a") -> n/a | L65: =IFERROR(L9/L$57,"n/a") -> n/a | M65: =IFERROR(M9/M$57,"n/a") -> n/a | N65: =IFERROR(N9/N$57,"n/a") -> n/a
C66: =C23 -> Management normalisiertes EBITDA | D66: =D23 -> Management normalized EBITDA | F66: =IFERROR(F23/F$57,"n/a") -> -0.24631833 | G66: =IFERROR(G23/G$57,"n/a") -> -0.39004855 | H66: =IFERROR(H23/H$57,"n/a") -> -0.35541081 | I66: =IFERROR(I23/I$57,"n/a") -> -0.36454678 | J66: =IFERROR(J23/J$57,"n/a") -> n/a | K66: =IFERROR(K23/K$57,"n/a") -> n/a | L66: =IFERROR(L23/L$57,"n/a") -> n/a | M66: =IFERROR(M23/M$57,"n/a") -> n/a | N66: =IFERROR(N23/N$57,"n/a") -> n/a
C67: =C43 -> BT normalisiertes EBITDA I | D67: =D43 -> BT normalized EBITDA I | F67: =IFERROR(F43/F$57,"n/a") -> -0.25187128 | G67: =IFERROR(G43/G$57,"n/a") -> -0.3899834 | H67: =IFERROR(H43/H$57,"n/a") -> -0.35702644 | I67: =IFERROR(I43/I$57,"n/a") -> -0.36682487 | J67: =IFERROR(J43/J$57,"n/a") -> n/a | K67: =IFERROR(K43/K$57,"n/a") -> n/a | L67: =IFERROR(L43/L$57,"n/a") -> n/a | M67: =IFERROR(M43/M$57,"n/a") -> n/a | N67: =IFERROR(N43/N$57,"n/a") -> n/a
C68: =C55 -> BT normalisiertes EBITDA II | D68: =D55 -> BT normalized EBITDA II | F68: =IFERROR(F55/F$57,"n/a") -> -0.26831791 | G68: =IFERROR(G55/G$57,"n/a") -> -0.40738499 | H68: =IFERROR(H55/H$57,"n/a") -> -0.37289875 | I68: =IFERROR(I55/I$57,"n/a") -> -0.38454616 | J68: =IFERROR(J55/J$57,"n/a") -> n/a | K68: =IFERROR(K55/K$57,"n/a") -> n/a | L68: =IFERROR(L55/L$57,"n/a") -> n/a | M68: =IFERROR(M55/M$57,"n/a") -> n/a | N68: =IFERROR(N55/N$57,"n/a") -> n/a
C70: ="Quelle: "&Cockpit!$C$7 -> Quelle: Datenraum/ eigene Analysen | D70: ="Source: "&Cockpit!$C$8 -> Source: Virtual Data Room/ Company Information
C73: EBITDA Lead PL | D73: EBITDA Lead PL | F73: ='Lead PL'!F43 -> -4386.7022 | G73: ='Lead PL'!G43 -> -6491.3424 | H73: ='Lead PL'!H43 -> -6637.5466 | I73: ='Lead PL'!I43 -> -6045.3006 | J73: ='Lead PL'!J43 -> 0 | K73: ='Lead PL'!K43 -> 0 | L73: ='Lead PL'!L43 -> 0 | M73: ='Lead PL'!M43 -> 0 | N73: ='Lead PL'!N43 -> 0
C74: Check | D74: Check | F74: =F73-F9 -> 0 | G74: =G73-G9 -> 0 | H74: =H73-H9 -> 0 | I74: =I73-I9 -> 0 | J74: =J73-J9 -> 0 | K74: =K73-K9 -> 0 | L74: =L73-L9 -> 0 | M74: =M73-M9 -> 0 | N74: =N73-N9 -> 0

Sheet PL_monthly
AE2: =-(NA_monthly!AX15-NA_monthly!AL15)+SUM(PL_monthly!AM35:AX35) -> -334.70818
S3: =SUM(PL_monthly!G9:R9) -> 1087.9522
C4: =Cockpit!$C$4 -> Projekt Namur | F4: =Cockpit!D45 -> 44592 | G4: =Cockpit!E45 -> 44620 | H4: =Cockpit!F45 -> 44651 | I4: =Cockpit!G45 -> 44681 | J4: =Cockpit!H45 -> 44712 | K4: =Cockpit!I45 -> 44742 | L4: =Cockpit!J45 -> 44773 | M4: =Cockpit!K45 -> 44804 | ... CK4: =Cockpit!CI45 -> 47118
C5: ="in T"&Cockpit!$C$5 -> in TEUR | F5: =Cockpit!D46 -> IST | G5: =Cockpit!E46 -> IST | H5: =Cockpit!F46 -> IST | I5: =Cockpit!G46 -> IST | J5: =Cockpit!H46 -> IST | K5: =Cockpit!I46 -> IST | L5: =Cockpit!J46 -> IST | M5: =Cockpit!K46 -> IST | ... CK5: =Cockpit!CI46 -> Plan
D6: =Cockpit!$C$4 -> Projekt Namur | F6: =Cockpit!D45 -> 44592 | G6: =Cockpit!E45 -> 44620 | H6: =Cockpit!F45 -> 44651 | I6: =Cockpit!G45 -> 44681 | J6: =Cockpit!H45 -> 44712 | K6: =Cockpit!I45 -> 44742 | L6: =Cockpit!J45 -> 44773 | M6: =Cockpit!K45 -> 44804 | ... CK6: =Cockpit!CI45 -> 47118
D7: ="in k"&Cockpit!$C$5 -> in kEUR | F7: =Cockpit!D46 -> IST | G7: =Cockpit!E46 -> IST | H7: =Cockpit!F46 -> IST | I7: =Cockpit!G46 -> IST | J7: =Cockpit!H46 -> IST | K7: =Cockpit!I46 -> IST | L7: =Cockpit!J46 -> IST | M7: =Cockpit!K46 -> IST | ... CK7: =Cockpit!CI46 -> Plan | CN7: Classification BT
C9: ='Lead PL'!C9 -> Umsatzerlöse | D9: ='Lead PL'!D9 -> Revenues | R9: =-SUMIF('Trial Balance (Susa)'!$D:$D,"*"&$CN9&"*",'Trial Balance (Susa)'!K:K)/1000 -> 1087.9522 | S9: =-SUMIF('Trial Balance (Susa)'!$D:$D,"*"&$CN9&"*",'Trial Balance (Susa)'!L:L)/1000-R9 -> 1215.6508 | T9: =-SUMIF('Trial Balance (Susa)'!$D:$D,"*"&$CN9&"*",'Trial Balance (Susa)'!M:M)/1000-SUM($R9:S9) -> 1445.9008 | U9: =-SUMIF('Trial Balance (Susa)'!$D:$D,"*"&$CN9&"*",'Trial Balance (Susa)'!N:N)/1000-SUM($R9:T9) -> 1326.2849 | V9: =-SUMIF('Trial Balance (Susa)'!$D:$D,"*"&$CN9&"*",'Trial Balance (Susa)'!O:O)/1000-SUM($R9:U9) -> 1200.1293 | W9: =-SUMIF('Trial Balance (Susa)'!$D:$D,"*"&$CN9&"*",'Trial Balance (Susa)'!P:P)/1000-SUM($R9:V9) -> 1229.5316 | X9: =-SUMIF('Trial Balance (Susa)'!$D:$D,"*"&$CN9&"*",'Trial Balance (Susa)'!Q:Q)/1000-SUM($R9:W9) -> 1218.0431 | Y9: =-SUMIF('Trial Balance (Susa)'!$D:$D,"*"&$CN9&"*",'Trial Balance (Susa)'!R:R)/1000-SUM($R9:X9) -> 1357.9237 | Z9: =-SUMIF('Trial Balance (Susa)'!$D:$D,"*"&$CN9&"*",'Trial Balance (Susa)'!S:S)/1000-SUM($R9:Y9) -> 1298.7723 | AA9: =-SUMIF('Trial Balance (Susa)'!$D:$D,"*"&$CN9&"*",'Trial Balance (Susa)'!T:T)/1000-SUM($R9:Z9) -> 1083.6379 | AB9: =-SUMIF('Trial Balance (Susa)'!$D:$D,"*"&$CN9&"*",'Trial Balance (Susa)'!U:U)/1000-SUM($R9:AA9) -> 1323.5492 | AC9: =-SUMIF('Trial Balance (Susa)'!$D:$D,"*"&$CN9&"*",'Trial Balance (Susa)'!V:V)/1000-SUM($R9:AB9) -> 1528.8678 | AD9: =-SUMIF('Trial Balance (Susa)'!$D:$D,"*"&$CN9&"*",'Trial Balance (Susa)'!W:W)/1000 -> 1340.9038 | AE9: =-SUMIF('Trial Balance (Susa)'!$D:$D,"*"&$CN9&"*",'Trial Balance (Susa)'!X:X)/1000-SUM($AD9:AD9) -> 1375.6855 | AF9: =-SUMIF('Trial Balance (Susa)'!$D:$D,"*"&$CN9&"*",'Trial Balance (Susa)'!Y:Y)/1000-SUM($AD9:AE9) -> 1659.5218 | AG9: =-SUMIF('Trial Balance (Susa)'!$D:$D,"*"&$CN9&"*",'Trial Balance (Susa)'!Z:Z)/1000-SUM($AD9:AF9) -> 1332.6841 | AH9: =-SUMIF('Trial Balance (Susa)'!$D:$D,"*"&$CN9&"*",'Trial Balance (Susa)'!AA:AA)/1000-SUM($AD9:AG9) -> 1745.2056 | AI9: =-SUMIF('Trial Balance (Susa)'!$D:$D,"*"&$CN9&"*",'Trial Balance (Susa)'!AB:AB)/1000-SUM($AD9:AH9) -> 1098.1648 | AJ9: =-SUMIF('Trial Balance (Susa)'!$D:$D,"*"&$CN9&"*",'Trial Balance (Susa)'!AC:AC)/1000-SUM($AD9:AI9) -> 1488.1723 | AK9: =-SUMIF('Trial Balance (Susa)'!$D:$D,"*"&$CN9&"*",'Trial Balance (Susa)'!AD:AD)/1000-SUM($AD9:AJ9) -> 1264.4617 | AL9: =-SUMIF('Trial Balance (Susa)'!$D:$D,"*"&$CN9&"*",'Trial Balance (Susa)'!AE:AE)/1000-SUM($AD9:AK9) -> 1422.5578 | AM9: =-SUMIF('Trial Balance (Susa)'!$D:$D,"*"&$CN9&"*",'Trial Balance (Susa)'!AF:AF)/1000-SUM($AD9:AL9) -> 1334.7222 | AN9: =-SUMIF('Trial Balance (Susa)'!$D:$D,"*"&$CN9&"*",'Trial Balance (Susa)'!AG:AG)/1000-SUM($AD9:AM9) -> 1322.4554 | AO9: =-SUMIF('Trial Balance (Susa)'!$D:$D,"*"&$CN9&"*",'Trial Balance (Susa)'!AH:AH)/1000-SUM($AD9:AN9) -> 1275.4285 | AP9: =-SUMIF('Trial Balance (Susa)'!$D:$D,"*"&$CN9&"*",'Trial Balance (Susa)'!AI:AI)/1000 -> 1354.935 | AQ9: =-SUMIF('Trial Balance (Susa)'!$D:$D,"*"&$CN9&"*",'Trial Balance (Susa)'!AJ:AJ)/1000-SUM($AP9:AP9) -> 1472.3399 | AR9: =-SUMIF('Trial Balance (Susa)'!$D:$D,"*"&$CN9&"*",'Trial Balance (Susa)'!AK:AK)/1000-SUM($AP9:AQ9) -> 1118.1143 | AS9: =-SUMIF('Trial Balance (Susa)'!$D:$D,"*"&$CN9&"*",'Trial Balance (Susa)'!AL:AL)/1000-SUM($AP9:AR9) -> 1362.9075 | AT9: =-SUMIF('Trial Balance (Susa)'!$D:$D,"*"&$CN9&"*",'Trial Balance (Susa)'!AM:AM)/1000-SUM($AP9:AS9) -> 1513.972 | AU9: =-SUMIF('Trial Balance (Susa)'!$D:$D,"*"&$CN9&"*",'Trial Balance (Susa)'!AN:AN)/1000-SUM($AP9:AT9) -> 1056.3678 | AV9: =-SUMIF('Trial Balance (Susa)'!$D:$D,"*"&$CN9&"*",'Trial Balance (Susa)'!AO:AO)/1000-SUM($AP9:AU9) -> 1111.3172 | AW9: =-SUMIF('Trial Balance (Susa)'!$D:$D,"*"&$CN9&"*",'Trial Balance (Susa)'!AP:AP)/1000-SUM($AP9:AV9) -> 1378.9363 | AX9: =-SUMIF('Trial Balance (Susa)'!$D:$D,"*"&$CN9&"*",'Trial Balance (Susa)'!AQ:AQ)/1000-SUM($AP9:AW9) -> 1124.221 | AY9: =-SUMIF('Trial Balance (Susa)'!$D:$D,"*"&$CN9&"*",'Trial Balance (Susa)'!AR:AR)/1000-SUM($AP9:AX9) -> 1212.3275 | AZ9: =-SUMIF('Trial Balance (Susa)'!$D:$D,"*"&$CN9&"*",'Trial Balance (Susa)'!AS:AS)/1000-SUM($AP9:AY9) -> 1193.4928 | BA9: =-SUMIF('Trial Balance (Susa)'!$D:$D,"*"&$CN9&"*",'Trial Balance (Susa)'!AT:AT)/1000-SUM($AP9:AZ9) -> 1110.7971 | CN9: /profit and loss/income/sales
C10: ='Lead PL'!C19 -> Bestandsveränderung | D10: ='Lead PL'!D19 -> Change in inventory | R10: =-SUMIF('Trial Balance (Susa)'!$D:$D,"*"&$CN10&"*",'Trial Balance (Susa)'!K:K)/1000 -> 0 | S10: =-SUMIF('Trial Balance (Susa)'!$D:$D,"*"&$CN10&"*",'Trial Balance (Susa)'!L:L)/1000-R10 -> 0 | T10: =-SUMIF('Trial Balance (Susa)'!$D:$D,"*"&$CN10&"*",'Trial Balance (Susa)'!M:M)/1000-SUM($R10:S10) -> 0 | U10: =-SUMIF('Trial Balance (Susa)'!$D:$D,"*"&$CN10&"*",'Trial Balance (Susa)'!N:N)/1000-SUM($R10:T10) -> 0 | V10: =-SUMIF('Trial Balance (Susa)'!$D:$D,"*"&$CN10&"*",'Trial Balance (Susa)'!O:O)/1000-SUM($R10:U10) -> 0 | W10: =-SUMIF('Trial Balance (Susa)'!$D:$D,"*"&$CN10&"*",'Trial Balance (Susa)'!P:P)/1000-SUM($R10:V10) -> 141.02733 | X10: =-SUMIF('Trial Balance (Susa)'!$D:$D,"*"&$CN10&"*",'Trial Balance (Susa)'!Q:Q)/1000-SUM($R10:W10) -> 0 | Y10: =-SUMIF('Trial Balance (Susa)'!$D:$D,"*"&$CN10&"*",'Trial Balance (Susa)'!R:R)/1000-SUM($R10:X10) -> 0 | Z10: =-SUMIF('Trial Balance (Susa)'!$D:$D,"*"&$CN10&"*",'Trial Balance (Susa)'!S:S)/1000-SUM($R10:Y10) -> 20.01299 | AA10: =-SUMIF('Trial Balance (Susa)'!$D:$D,"*"&$CN10&"*",'Trial Balance (Susa)'!T:T)/1000-SUM($R10:Z10) -> 0 | AB10: =-SUMIF('Trial Balance (Susa)'!$D:$D,"*"&$CN10&"*",'Trial Balance (Susa)'!U:U)/1000-SUM($R10:AA10) -> 0 | AC10: =-SUMIF('Trial Balance (Susa)'!$D:$D,"*"&$CN10&"*",'Trial Balance (Susa)'!V:V)/1000-SUM($R10:AB10) -> 38.53681 | AD10: =-SUMIF('Trial Balance (Susa)'!$D:$D,"*"&$CN10&"*",'Trial Balance (Susa)'!W:W)/1000 -> 0 | AE10: =-SUMIF('Trial Balance (Susa)'!$D:$D,"*"&$CN10&"*",'Trial Balance (Susa)'!X:X)/1000-SUM($AD10:AD10) -> 0 | AF10: =-SUMIF('Trial Balance (Susa)'!$D:$D,"*"&$CN10&"*",'Trial Balance (Susa)'!Y:Y)/1000-SUM($AD10:AE10) -> 0 | AG10: =-SUMIF('Trial Balance (Susa)'!$D:$D,"*"&$CN10&"*",'Trial Balance (Susa)'!Z:Z)/1000-SUM($AD10:AF10) -> 0 | AH10: =-SUMIF('Trial Balance (Susa)'!$D:$D,"*"&$CN10&"*",'Trial Balance (Susa)'!AA:AA)/1000-SUM($AD10:AG10) -> 0 | AI10: =-SUMIF('Trial Balance (Susa)'!$D:$D,"*"&$CN10&"*",'Trial Balance (Susa)'!AB:AB)/1000-SUM($AD10:AH10) -> 109.90872 | AJ10: =-SUMIF('Trial Balance (Susa)'!$D:$D,"*"&$CN10&"*",'Trial Balance (Susa)'!AC:AC)/1000-SUM($AD10:AI10) -> 0 | AK10: =-SUMIF('Trial Balance (Susa)'!$D:$D,"*"&$CN10&"*",'Trial Balance (Susa)'!AD:AD)/1000-SUM($AD10:AJ10) -> 0 | AL10: =-SUMIF('Trial Balance (Susa)'!$D:$D,"*"&$CN10&"*",'Trial Balance (Susa)'!AE:AE)/1000-SUM($AD10:AK10) -> 0 | AM10: =-SUMIF('Trial Balance (Susa)'!$D:$D,"*"&$CN10&"*",'Trial Balance (Susa)'!AF:AF)/1000-SUM($AD10:AL10) -> 0 | AN10: =-SUMIF('Trial Balance (Susa)'!$D:$D,"*"&$CN10&"*",'Trial Balance (Susa)'!AG:AG)/1000-SUM($AD10:AM10) -> 0 | AO10: =-SUMIF('Trial Balance (Susa)'!$D:$D,"*"&$CN10&"*",'Trial Balance (Susa)'!AH:AH)/1000-SUM($AD10:AN10) -> 240.88642 | AP10: =-SUMIF('Trial Balance (Susa)'!$D:$D,"*"&$CN10&"*",'Trial Balance (Susa)'!AI:AI)/1000 -> 0 | AQ10: =-SUMIF('Trial Balance (Susa)'!$D:$D,"*"&$CN10&"*",'Trial Balance (Susa)'!AJ:AJ)/1000-SUM($AP10:AP10) -> 0 | AR10: =-SUMIF('Trial Balance (Susa)'!$D:$D,"*"&$CN10&"*",'Trial Balance (Susa)'!AK:AK)/1000-SUM($AP10:AQ10) -> 0 | AS10: =-SUMIF('Trial Balance (Susa)'!$D:$D,"*"&$CN10&"*",'Trial Balance (Susa)'!AL:AL)/1000-SUM($AP10:AR10) -> 0 | AT10: =-SUMIF('Trial Balance (Susa)'!$D:$D,"*"&$CN10&"*",'Trial Balance (Susa)'!AM:AM)/1000-SUM($AP10:AS10) -> 0 | AU10: =-SUMIF('Trial Balance (Susa)'!$D:$D,"*"&$CN10&"*",'Trial Balance (Susa)'!AN:AN)/1000-SUM($AP10:AT10) -> 0 | AV10: =-SUMIF('Trial Balance (Susa)'!$D:$D,"*"&$CN10&"*",'Trial Balance (Susa)'!AO:AO)/1000-SUM($AP10:AU10) -> 0 | AW10: =-SUMIF('Trial Balance (Susa)'!$D:$D,"*"&$CN10&"*",'Trial Balance (Susa)'!AP:AP)/1000-SUM($AP10:AV10) -> 0 | AX10: =-SUMIF('Trial Balance (Susa)'!$D:$D,"*"&$CN10&"*",'Trial Balance (Susa)'!AQ:AQ)/1000-SUM($AP10:AW10) -> 0 | AY10: =-SUMIF('Trial Balance (Susa)'!$D:$D,"*"&$CN10&"*",'Trial Balance (Susa)'!AR:AR)/1000-SUM($AP10:AX10) -> 0 | AZ10: =-SUMIF('Trial Balance (Susa)'!$D:$D,"*"&$CN10&"*",'Trial Balance (Susa)'!AS:AS)/1000-SUM($AP10:AY10) -> 0 | BA10: =-SUMIF('Trial Balance (Susa)'!$D:$D,"*"&$CN10&"*",'Trial Balance (Susa)'!AT:AT)/1000-SUM($AP10:AZ10) -> 226.19016 | CN10: /profit and loss/income/increase in inventory
C11: ='Lead PL'!C20 -> Aktivierte Eigenleistungen | D11: ='Lead PL'!D20 -> Own work capitalized | CN11: /profit and loss/income/own work capitalised
C12: ='Lead PL'!C21 -> Dummy 1 | D12: ='Lead PL'!D21 -> Dummy 1
C13: ='Lead PL'!C22 -> Dummy 2 | D13: ='Lead PL'!D22 -> Dummy 2
C14: ='Lead PL'!C23 -> Dummy 3 | D14: ='Lead PL'!D23 -> Dummy 3
C15: ='Lead PL'!C24 -> Gesamtleistung | D15: ='Lead PL'!D24 -> Total output | F15: =SUM(F9:F14) -> 0 | G15: =SUM(G9:G14) -> 0 | H15: =SUM(H9:H14) -> 0 | I15: =SUM(I9:I14) -> 0 | J15: =SUM(J9:J14) -> 0 | K15: =SUM(K9:K14) -> 0 | L15: =SUM(L9:L14) -> 0 | M15: =SUM(M9:M14) -> 0 | ... CK15: =SUM(CK9:CK14) -> 0
C16: ='Lead PL'!C25 -> Materialaufwand | D16: ='Lead PL'!D25 -> Cost of materials | R16: =-SUMIF('Trial Balance (Susa)'!$D:$D,"*"&$CN16&"*",'Trial Balance (Susa)'!K:K)/1000 -> -694.43766 | S16: =-SUMIF('Trial Balance (Susa)'!$D:$D,"*"&$CN16&"*",'Trial Balance (Susa)'!L:L)/1000-R16 -> -918.26469 | T16: =-SUMIF('Trial Balance (Susa)'!$D:$D,"*"&$CN16&"*",'Trial Balance (Susa)'!M:M)/1000-SUM($R16:S16) -> -986.22682 | U16: =-SUMIF('Trial Balance (Susa)'!$D:$D,"*"&$CN16&"*",'Trial Balance (Susa)'!N:N)/1000-SUM($R16:T16) -> -658.53136 | V16: =-SUMIF('Trial Balance (Susa)'!$D:$D,"*"&$CN16&"*",'Trial Balance (Susa)'!O:O)/1000-SUM($R16:U16) -> -944.96867 | W16: =-SUMIF('Trial Balance (Susa)'!$D:$D,"*"&$CN16&"*",'Trial Balance (Susa)'!P:P)/1000-SUM($R16:V16) -> 60.98294 | X16: =-SUMIF('Trial Balance (Susa)'!$D:$D,"*"&$CN16&"*",'Trial Balance (Susa)'!Q:Q)/1000-SUM($R16:W16) -> -721.89017 | Y16: =-SUMIF('Trial Balance (Susa)'!$D:$D,"*"&$CN16&"*",'Trial Balance (Susa)'!R:R)/1000-SUM($R16:X16) -> -502.11796 | Z16: =-SUMIF('Trial Balance (Susa)'!$D:$D,"*"&$CN16&"*",'Trial Balance (Susa)'!S:S)/1000-SUM($R16:Y16) -> -706.97924 | AA16: =-SUMIF('Trial Balance (Susa)'!$D:$D,"*"&$CN16&"*",'Trial Balance (Susa)'!T:T)/1000-SUM($R16:Z16) -> -510.89214 | AB16: =-SUMIF('Trial Balance (Susa)'!$D:$D,"*"&$CN16&"*",'Trial Balance (Susa)'!U:U)/1000-SUM($R16:AA16) -> -427.10223 | AC16: =-SUMIF('Trial Balance (Susa)'!$D:$D,"*"&$CN16&"*",'Trial Balance (Susa)'!V:V)/1000-SUM($R16:AB16) -> -1076.0744 | AD16: =-SUMIF('Trial Balance (Susa)'!$D:$D,"*"&$CN16&"*",'Trial Balance (Susa)'!W:W)/1000 -> -702.71268 | AE16: =-SUMIF('Trial Balance (Susa)'!$D:$D,"*"&$CN16&"*",'Trial Balance (Susa)'!X:X)/1000-SUM($AD16:AD16) -> -513.43489 | AF16: =-SUMIF('Trial Balance (Susa)'!$D:$D,"*"&$CN16&"*",'Trial Balance (Susa)'!Y:Y)/1000-SUM($AD16:AE16) -> -623.84022 | AG16: =-SUMIF('Trial Balance (Susa)'!$D:$D,"*"&$CN16&"*",'Trial Balance (Susa)'!Z:Z)/1000-SUM($AD16:AF16) -> -648.25692 | AH16: =-SUMIF('Trial Balance (Susa)'!$D:$D,"*"&$CN16&"*",'Trial Balance (Susa)'!AA:AA)/1000-SUM($AD16:AG16) -> -1067.9753 | AI16: =-SUMIF('Trial Balance (Susa)'!$D:$D,"*"&$CN16&"*",'Trial Balance (Susa)'!AB:AB)/1000-SUM($AD16:AH16) -> -829.13193 | AJ16: =-SUMIF('Trial Balance (Susa)'!$D:$D,"*"&$CN16&"*",'Trial Balance (Susa)'!AC:AC)/1000-SUM($AD16:AI16) -> -1669.2757 | AK16: =-SUMIF('Trial Balance (Susa)'!$D:$D,"*"&$CN16&"*",'Trial Balance (Susa)'!AD:AD)/1000-SUM($AD16:AJ16) -> -494.91564 | AL16: =-SUMIF('Trial Balance (Susa)'!$D:$D,"*"&$CN16&"*",'Trial Balance (Susa)'!AE:AE)/1000-SUM($AD16:AK16) -> -1166.914 | AM16: =-SUMIF('Trial Balance (Susa)'!$D:$D,"*"&$CN16&"*",'Trial Balance (Susa)'!AF:AF)/1000-SUM($AD16:AL16) -> -353.45835 | AN16: =-SUMIF('Trial Balance (Susa)'!$D:$D,"*"&$CN16&"*",'Trial Balance (Susa)'!AG:AG)/1000-SUM($AD16:AM16) -> -589.53628 | AO16: =-SUMIF('Trial Balance (Susa)'!$D:$D,"*"&$CN16&"*",'Trial Balance (Susa)'!AH:AH)/1000-SUM($AD16:AN16) -> 261.56451 | AP16: =-SUMIF('Trial Balance (Susa)'!$D:$D,"*"&$CN16&"*",'Trial Balance (Susa)'!AI:AI)/1000 -> -666.35807 | AQ16: =-SUMIF('Trial Balance (Susa)'!$D:$D,"*"&$CN16&"*",'Trial Balance (Susa)'!AJ:AJ)/1000-SUM($AP16:AP16) -> -853.88634 | AR16: =-SUMIF('Trial Balance (Susa)'!$D:$D,"*"&$CN16&"*",'Trial Balance (Susa)'!AK:AK)/1000-SUM($AP16:AQ16) -> -664.77471 | AS16: =-SUMIF('Trial Balance (Susa)'!$D:$D,"*"&$CN16&"*",'Trial Balance (Susa)'!AL:AL)/1000-SUM($AP16:AR16) -> -703.46014 | AT16: =-SUMIF('Trial Balance (Susa)'!$D:$D,"*"&$CN16&"*",'Trial Balance (Susa)'!AM:AM)/1000-SUM($AP16:AS16) -> -701.22723 | AU16: =-SUMIF('Trial Balance (Susa)'!$D:$D,"*"&$CN16&"*",'Trial Balance (Susa)'!AN:AN)/1000-SUM($AP16:AT16) -> -291.10538 | AV16: =-SUMIF('Trial Balance (Susa)'!$D:$D,"*"&$CN16&"*",'Trial Balance (Susa)'!AO:AO)/1000-SUM($AP16:AU16) -> -506.23966 | AW16: =-SUMIF('Trial Balance (Susa)'!$D:$D,"*"&$CN16&"*",'Trial Balance (Susa)'!AP:AP)/1000-SUM($AP16:AV16) -> -446.51855 | AX16: =-SUMIF('Trial Balance (Susa)'!$D:$D,"*"&$CN16&"*",'Trial Balance (Susa)'!AQ:AQ)/1000-SUM($AP16:AW16) -> -422.89771 | AY16: =-SUMIF('Trial Balance (Susa)'!$D:$D,"*"&$CN16&"*",'Trial Balance (Susa)'!AR:AR)/1000-SUM($AP16:AX16) -> -378.50554 | AZ16: =-SUMIF('Trial Balance (Susa)'!$D:$D,"*"&$CN16&"*",'Trial Balance (Susa)'!AS:AS)/1000-SUM($AP16:AY16) -> -736.21119 | BA16: =-SUMIF('Trial Balance (Susa)'!$D:$D,"*"&$CN16&"*",'Trial Balance (Susa)'!AT:AT)/1000-SUM($AP16:AZ16) -> -990.60017 | CN16: /profit and loss/expense/material expense
C17: ='Lead PL'!C26 -> RHB-Aufwand | D17: ='Lead PL'!D26 -> Dummy 1
C18: ='Lead PL'!C27 -> Fremdleistungen | D18: ='Lead PL'!D27 -> Dummy 2
C19: ='Lead PL'!C28 -> Dummy 3 | D19: ='Lead PL'!D28 -> Dummy 3
C20: ='Lead PL'!C29 -> Rohergebnis | D20: ='Lead PL'!D29 -> Gross profit | F20: =SUM(F15:F19) -> 0 | G20: =SUM(G15:G19) -> 0 | H20: =SUM(H15:H19) -> 0 | I20: =SUM(I15:I19) -> 0 | J20: =SUM(J15:J19) -> 0 | K20: =SUM(K15:K19) -> 0 | L20: =SUM(L15:L19) -> 0 | M20: =SUM(M15:M19) -> 0 | ... CK20: =SUM(CK15:CK19) -> 0
C21: ='Lead PL'!C30 -> Personalaufwand | D21: ='Lead PL'!D30 -> Personnel expenses | R21: =-SUMIF('Trial Balance (Susa)'!$D:$D,"*"&$CN21&"*",'Trial Balance (Susa)'!K:K)/1000 -> -294.62902 | S21: =-SUMIF('Trial Balance (Susa)'!$D:$D,"*"&$CN21&"*",'Trial Balance (Susa)'!L:L)/1000-R21 -> -251.95002 | T21: =-SUMIF('Trial Balance (Susa)'!$D:$D,"*"&$CN21&"*",'Trial Balance (Susa)'!M:M)/1000-SUM($R21:S21) -> -275.8747 | U21: =-SUMIF('Trial Balance (Susa)'!$D:$D,"*"&$CN21&"*",'Trial Balance (Susa)'!N:N)/1000-SUM($R21:T21) -> -273.98507 | V21: =-SUMIF('Trial Balance (Susa)'!$D:$D,"*"&$CN21&"*",'Trial Balance (Susa)'!O:O)/1000-SUM($R21:U21) -> -306.27277 | W21: =-SUMIF('Trial Balance (Susa)'!$D:$D,"*"&$CN21&"*",'Trial Balance (Susa)'!P:P)/1000-SUM($R21:V21) -> -351.39617 | X21: =-SUMIF('Trial Balance (Susa)'!$D:$D,"*"&$CN21&"*",'Trial Balance (Susa)'!Q:Q)/1000-SUM($R21:W21) -> -295.89089 | Y21: =-SUMIF('Trial Balance (Susa)'!$D:$D,"*"&$CN21&"*",'Trial Balance (Susa)'!R:R)/1000-SUM($R21:X21) -> -274.84541 | Z21: =-SUMIF('Trial Balance (Susa)'!$D:$D,"*"&$CN21&"*",'Trial Balance (Susa)'!S:S)/1000-SUM($R21:Y21) -> -337.60095 | AA21: =-SUMIF('Trial Balance (Susa)'!$D:$D,"*"&$CN21&"*",'Trial Balance (Susa)'!T:T)/1000-SUM($R21:Z21) -> -331.69483 | AB21: =-SUMIF('Trial Balance (Susa)'!$D:$D,"*"&$CN21&"*",'Trial Balance (Susa)'!U:U)/1000-SUM($R21:AA21) -> -342.47146 | AC21: =-SUMIF('Trial Balance (Susa)'!$D:$D,"*"&$CN21&"*",'Trial Balance (Susa)'!V:V)/1000-SUM($R21:AB21) -> -422.37297 | AD21: =-SUMIF('Trial Balance (Susa)'!$D:$D,"*"&$CN21&"*",'Trial Balance (Susa)'!W:W)/1000 -> -337.82957 | AE21: =-SUMIF('Trial Balance (Susa)'!$D:$D,"*"&$CN21&"*",'Trial Balance (Susa)'!X:X)/1000-SUM($AD21:AD21) -> -340.19396 | AF21: =-SUMIF('Trial Balance (Susa)'!$D:$D,"*"&$CN21&"*",'Trial Balance (Susa)'!Y:Y)/1000-SUM($AD21:AE21) -> -365.80621 | AG21: =-SUMIF('Trial Balance (Susa)'!$D:$D,"*"&$CN21&"*",'Trial Balance (Susa)'!Z:Z)/1000-SUM($AD21:AF21) -> -366.03587 | AH21: =-SUMIF('Trial Balance (Susa)'!$D:$D,"*"&$CN21&"*",'Trial Balance (Susa)'!AA:AA)/1000-SUM($AD21:AG21) -> -384.84101 | AI21: =-SUMIF('Trial Balance (Susa)'!$D:$D,"*"&$CN21&"*",'Trial Balance (Susa)'!AB:AB)/1000-SUM($AD21:AH21) -> -401.95188 | AJ21: =-SUMIF('Trial Balance (Susa)'!$D:$D,"*"&$CN21&"*",'Trial Balance (Susa)'!AC:AC)/1000-SUM($AD21:AI21) -> -408.64079 | AK21: =-SUMIF('Trial Balance (Susa)'!$D:$D,"*"&$CN21&"*",'Trial Balance (Susa)'!AD:AD)/1000-SUM($AD21:AJ21) -> -388.09949 | AL21: =-SUMIF('Trial Balance (Susa)'!$D:$D,"*"&$CN21&"*",'Trial Balance (Susa)'!AE:AE)/1000-SUM($AD21:AK21) -> -381.57617 | AM21: =-SUMIF('Trial Balance (Susa)'!$D:$D,"*"&$CN21&"*",'Trial Balance (Susa)'!AF:AF)/1000-SUM($AD21:AL21) -> -392.60759 | AN21: =-SUMIF('Trial Balance (Susa)'!$D:$D,"*"&$CN21&"*",'Trial Balance (Susa)'!AG:AG)/1000-SUM($AD21:AM21) -> -360.62585 | AO21: =-SUMIF('Trial Balance (Susa)'!$D:$D,"*"&$CN21&"*",'Trial Balance (Susa)'!AH:AH)/1000-SUM($AD21:AN21) -> -394.14266 | AP21: =-SUMIF('Trial Balance (Susa)'!$D:$D,"*"&$CN21&"*",'Trial Balance (Susa)'!AI:AI)/1000 -> -354.7783 | AQ21: =-SUMIF('Trial Balance (Susa)'!$D:$D,"*"&$CN21&"*",'Trial Balance (Susa)'!AJ:AJ)/1000-SUM($AP21:AP21) -> -342.09086 | AR21: =-SUMIF('Trial Balance (Susa)'!$D:$D,"*"&$CN21&"*",'Trial Balance (Susa)'!AK:AK)/1000-SUM($AP21:AQ21) -> -361.47042 | AS21: =-SUMIF('Trial Balance (Susa)'!$D:$D,"*"&$CN21&"*",'Trial Balance (Susa)'!AL:AL)/1000-SUM($AP21:AR21) -> -364.21122 | AT21: =-SUMIF('Trial Balance (Susa)'!$D:$D,"*"&$CN21&"*",'Trial Balance (Susa)'!AM:AM)/1000-SUM($AP21:AS21) -> -356.70311 | AU21: =-SUMIF('Trial Balance (Susa)'!$D:$D,"*"&$CN21&"*",'Trial Balance (Susa)'!AN:AN)/1000-SUM($AP21:AT21) -> -349.05644 | AV21: =-SUMIF('Trial Balance (Susa)'!$D:$D,"*"&$CN21&"*",'Trial Balance (Susa)'!AO:AO)/1000-SUM($AP21:AU21) -> -403.34928 | AW21: =-SUMIF('Trial Balance (Susa)'!$D:$D,"*"&$CN21&"*",'Trial Balance (Susa)'!AP:AP)/1000-SUM($AP21:AV21) -> -338.51617 | AX21: =-SUMIF('Trial Balance (Susa)'!$D:$D,"*"&$CN21&"*",'Trial Balance (Susa)'!AQ:AQ)/1000-SUM($AP21:AW21) -> -348.74197 | AY21: =-SUMIF('Trial Balance (Susa)'!$D:$D,"*"&$CN21&"*",'Trial Balance (Susa)'!AR:AR)/1000-SUM($AP21:AX21) -> -348.89501 | AZ21: =-SUMIF('Trial Balance (Susa)'!$D:$D,"*"&$CN21&"*",'Trial Balance (Susa)'!AS:AS)/1000-SUM($AP21:AY21) -> -320.30164 | BA21: =-SUMIF('Trial Balance (Susa)'!$D:$D,"*"&$CN21&"*",'Trial Balance (Susa)'!AT:AT)/1000-SUM($AP21:AZ21) -> -337.71261 | CN21: /profit and loss/expense/personnel expense
C22: ='Lead PL'!C31 -> Miet- und Grundstücksaufwendungen | D22: ='Lead PL'!D31 -> Premise costs | R22: =-SUMIF('Trial Balance (Susa)'!$D:$D,"*"&$CN22&"*",'Trial Balance (Susa)'!K:K)/1000 -> -27.2161 | S22: =-SUMIF('Trial Balance (Susa)'!$D:$D,"*"&$CN22&"*",'Trial Balance (Susa)'!L:L)/1000-R22 -> -27.80861 | T22: =-SUMIF('Trial Balance (Susa)'!$D:$D,"*"&$CN22&"*",'Trial Balance (Susa)'!M:M)/1000-SUM($R22:S22) -> -30.1826 | U22: =-SUMIF('Trial Balance (Susa)'!$D:$D,"*"&$CN22&"*",'Trial Balance (Susa)'!N:N)/1000-SUM($R22:T22) -> -21.31338 | V22: =-SUMIF('Trial Balance (Susa)'!$D:$D,"*"&$CN22&"*",'Trial Balance (Susa)'!O:O)/1000-SUM($R22:U22) -> -27.23192 | W22: =-SUMIF('Trial Balance (Susa)'!$D:$D,"*"&$CN22&"*",'Trial Balance (Susa)'!P:P)/1000-SUM($R22:V22) -> -32.24401 | X22: =-SUMIF('Trial Balance (Susa)'!$D:$D,"*"&$CN22&"*",'Trial Balance (Susa)'!Q:Q)/1000-SUM($R22:W22) -> -26.99516 | Y22: =-SUMIF('Trial Balance (Susa)'!$D:$D,"*"&$CN22&"*",'Trial Balance (Susa)'!R:R)/1000-SUM($R22:X22) -> -28.25488 | Z22: =-SUMIF('Trial Balance (Susa)'!$D:$D,"*"&$CN22&"*",'Trial Balance (Susa)'!S:S)/1000-SUM($R22:Y22) -> -27.74758 | AA22: =-SUMIF('Trial Balance (Susa)'!$D:$D,"*"&$CN22&"*",'Trial Balance (Susa)'!T:T)/1000-SUM($R22:Z22) -> -27.1669 | AB22: =-SUMIF('Trial Balance (Susa)'!$D:$D,"*"&$CN22&"*",'Trial Balance (Susa)'!U:U)/1000-SUM($R22:AA22) -> -27.32267 | AC22: =-SUMIF('Trial Balance (Susa)'!$D:$D,"*"&$CN22&"*",'Trial Balance (Susa)'!V:V)/1000-SUM($R22:AB22) -> -37.84713 | AD22: =-SUMIF('Trial Balance (Susa)'!$D:$D,"*"&$CN22&"*",'Trial Balance (Susa)'!W:W)/1000 -> -25.75353 | AE22: =-SUMIF('Trial Balance (Susa)'!$D:$D,"*"&$CN22&"*",'Trial Balance (Susa)'!X:X)/1000-SUM($AD22:AD22) -> -33.27989 | AF22: =-SUMIF('Trial Balance (Susa)'!$D:$D,"*"&$CN22&"*",'Trial Balance (Susa)'!Y:Y)/1000-SUM($AD22:AE22) -> -41.53512 | AG22: =-SUMIF('Trial Balance (Susa)'!$D:$D,"*"&$CN22&"*",'Trial Balance (Susa)'!Z:Z)/1000-SUM($AD22:AF22) -> -43.1463 | AH22: =-SUMIF('Trial Balance (Susa)'!$D:$D,"*"&$CN22&"*",'Trial Balance (Susa)'!AA:AA)/1000-SUM($AD22:AG22) -> -42.9353 | AI22: =-SUMIF('Trial Balance (Susa)'!$D:$D,"*"&$CN22&"*",'Trial Balance (Susa)'!AB:AB)/1000-SUM($AD22:AH22) -> -34.61969 | AJ22: =-SUMIF('Trial Balance (Susa)'!$D:$D,"*"&$CN22&"*",'Trial Balance (Susa)'!AC:AC)/1000-SUM($AD22:AI22) -> -31.49121 | AK22: =-SUMIF('Trial Balance (Susa)'!$D:$D,"*"&$CN22&"*",'Trial Balance (Susa)'!AD:AD)/1000-SUM($AD22:AJ22) -> -32.2745 | AL22: =-SUMIF('Trial Balance (Susa)'!$D:$D,"*"&$CN22&"*",'Trial Balance (Susa)'!AE:AE)/1000-SUM($AD22:AK22) -> -31.79026 | AM22: =-SUMIF('Trial Balance (Susa)'!$D:$D,"*"&$CN22&"*",'Trial Balance (Susa)'!AF:AF)/1000-SUM($AD22:AL22) -> -30.79647 | AN22: =-SUMIF('Trial Balance (Susa)'!$D:$D,"*"&$CN22&"*",'Trial Balance (Susa)'!AG:AG)/1000-SUM($AD22:AM22) -> -31.19332 | AO22: =-SUMIF('Trial Balance (Susa)'!$D:$D,"*"&$CN22&"*",'Trial Balance (Susa)'!AH:AH)/1000-SUM($AD22:AN22) -> -44.16694 | AP22: =-SUMIF('Trial Balance (Susa)'!$D:$D,"*"&$CN22&"*",'Trial Balance (Susa)'!AI:AI)/1000 -> -25.13871 | AQ22: =-SUMIF('Trial Balance (Susa)'!$D:$D,"*"&$CN22&"*",'Trial Balance (Susa)'!AJ:AJ)/1000-SUM($AP22:AP22) -> -30.70871 | AR22: =-SUMIF('Trial Balance (Susa)'!$D:$D,"*"&$CN22&"*",'Trial Balance (Susa)'!AK:AK)/1000-SUM($AP22:AQ22) -> -25.31899 | AS22: =-SUMIF('Trial Balance (Susa)'!$D:$D,"*"&$CN22&"*",'Trial Balance (Susa)'!AL:AL)/1000-SUM($AP22:AR22) -> -27.53055 | AT22: =-SUMIF('Trial Balance (Susa)'!$D:$D,"*"&$CN22&"*",'Trial Balance (Susa)'!AM:AM)/1000-SUM($AP22:AS22) -> -29.15301 | AU22: =-SUMIF('Trial Balance (Susa)'!$D:$D,"*"&$CN22&"*",'Trial Balance (Susa)'!AN:AN)/1000-SUM($AP22:AT22) -> -31.01767 | AV22: =-SUMIF('Trial Balance (Susa)'!$D:$D,"*"&$CN22&"*",'Trial Balance (Susa)'!AO:AO)/1000-SUM($AP22:AU22) -> -36.82897 | AW22: =-SUMIF('Trial Balance (Susa)'!$D:$D,"*"&$CN22&"*",'Trial Balance (Susa)'!AP:AP)/1000-SUM($AP22:AV22) -> -29.16012 | AX22: =-SUMIF('Trial Balance (Susa)'!$D:$D,"*"&$CN22&"*",'Trial Balance (Susa)'!AQ:AQ)/1000-SUM($AP22:AW22) -> -28.67301 | AY22: =-SUMIF('Trial Balance (Susa)'!$D:$D,"*"&$CN22&"*",'Trial Balance (Susa)'!AR:AR)/1000-SUM($AP22:AX22) -> -28.5043 | AZ22: =-SUMIF('Trial Balance (Susa)'!$D:$D,"*"&$CN22&"*",'Trial Balance (Susa)'!AS:AS)/1000-SUM($AP22:AY22) -> -29.09974 | BA22: =-SUMIF('Trial Balance (Susa)'!$D:$D,"*"&$CN22&"*",'Trial Balance (Susa)'!AT:AT)/1000-SUM($AP22:AZ22) -> -28.19555 | CN22: /profit and loss/expense/other expense/premise costs
C23: ='Lead PL'!C32 -> Reparaturen und Instandhaltungen | D23: ='Lead PL'!D32 -> Repair and maintenance | R23: =-SUMIF('Trial Balance (Susa)'!$D:$D,"*"&$CN23&"*",'Trial Balance (Susa)'!K:K)/1000 -> -4.13929 | S23: =-SUMIF('Trial Balance (Susa)'!$D:$D,"*"&$CN23&"*",'Trial Balance (Susa)'!L:L)/1000-R23 -> -11.56364 | T23: =-SUMIF('Trial Balance (Susa)'!$D:$D,"*"&$CN23&"*",'Trial Balance (Susa)'!M:M)/1000-SUM($R23:S23) -> -12.4817 | U23: =-SUMIF('Trial Balance (Susa)'!$D:$D,"*"&$CN23&"*",'Trial Balance (Susa)'!N:N)/1000-SUM($R23:T23) -> -10.06513 | V23: =-SUMIF('Trial Balance (Susa)'!$D:$D,"*"&$CN23&"*",'Trial Balance (Susa)'!O:O)/1000-SUM($R23:U23) -> -8.47959 | W23: =-SUMIF('Trial Balance (Susa)'!$D:$D,"*"&$CN23&"*",'Trial Balance (Susa)'!P:P)/1000-SUM($R23:V23) -> -4.70396 | X23: =-SUMIF('Trial Balance (Susa)'!$D:$D,"*"&$CN23&"*",'Trial Balance (Susa)'!Q:Q)/1000-SUM($R23:W23) -> -12.9846 | Y23: =-SUMIF('Trial Balance (Susa)'!$D:$D,"*"&$CN23&"*",'Trial Balance (Susa)'!R:R)/1000-SUM($R23:X23) -> -5.37672 | Z23: =-SUMIF('Trial Balance (Susa)'!$D:$D,"*"&$CN23&"*",'Trial Balance (Susa)'!S:S)/1000-SUM($R23:Y23) -> -12.09036 | AA23: =-SUMIF('Trial Balance (Susa)'!$D:$D,"*"&$CN23&"*",'Trial Balance (Susa)'!T:T)/1000-SUM($R23:Z23) -> -3.55726 | AB23: =-SUMIF('Trial Balance (Susa)'!$D:$D,"*"&$CN23&"*",'Trial Balance (Susa)'!U:U)/1000-SUM($R23:AA23) -> -13.37528 | AC23: =-SUMIF('Trial Balance (Susa)'!$D:$D,"*"&$CN23&"*",'Trial Balance (Susa)'!V:V)/1000-SUM($R23:AB23) -> -25.46396 | AD23: =-SUMIF('Trial Balance (Susa)'!$D:$D,"*"&$CN23&"*",'Trial Balance (Susa)'!W:W)/1000 -> -7.78703 | AE23: =-SUMIF('Trial Balance (Susa)'!$D:$D,"*"&$CN23&"*",'Trial Balance (Susa)'!X:X)/1000-SUM($AD23:AD23) -> -10.2227 | AF23: =-SUMIF('Trial Balance (Susa)'!$D:$D,"*"&$CN23&"*",'Trial Balance (Susa)'!Y:Y)/1000-SUM($AD23:AE23) -> -10.29589 | AG23: =-SUMIF('Trial Balance (Susa)'!$D:$D,"*"&$CN23&"*",'Trial Balance (Susa)'!Z:Z)/1000-SUM($AD23:AF23) -> -15.56641 | AH23: =-SUMIF('Trial Balance (Susa)'!$D:$D,"*"&$CN23&"*",'Trial Balance (Susa)'!AA:AA)/1000-SUM($AD23:AG23) -> -10.10177 | AI23: =-SUMIF('Trial Balance (Susa)'!$D:$D,"*"&$CN23&"*",'Trial Balance (Susa)'!AB:AB)/1000-SUM($AD23:AH23) -> -10.91146 | AJ23: =-SUMIF('Trial Balance (Susa)'!$D:$D,"*"&$CN23&"*",'Trial Balance (Susa)'!AC:AC)/1000-SUM($AD23:AI23) -> -11.18316 | AK23: =-SUMIF('Trial Balance (Susa)'!$D:$D,"*"&$CN23&"*",'Trial Balance (Susa)'!AD:AD)/1000-SUM($AD23:AJ23) -> -10.88208 | AL23: =-SUMIF('Trial Balance (Susa)'!$D:$D,"*"&$CN23&"*",'Trial Balance (Susa)'!AE:AE)/1000-SUM($AD23:AK23) -> -9.10405 | AM23: =-SUMIF('Trial Balance (Susa)'!$D:$D,"*"&$CN23&"*",'Trial Balance (Susa)'!AF:AF)/1000-SUM($AD23:AL23) -> -17.16772 | AN23: =-SUMIF('Trial Balance (Susa)'!$D:$D,"*"&$CN23&"*",'Trial Balance (Susa)'!AG:AG)/1000-SUM($AD23:AM23) -> -6.05882 | AO23: =-SUMIF('Trial Balance (Susa)'!$D:$D,"*"&$CN23&"*",'Trial Balance (Susa)'!AH:AH)/1000-SUM($AD23:AN23) -> -14.03172 | AP23: =-SUMIF('Trial Balance (Susa)'!$D:$D,"*"&$CN23&"*",'Trial Balance (Susa)'!AI:AI)/1000 -> -8.31209 | AQ23: =-SUMIF('Trial Balance (Susa)'!$D:$D,"*"&$CN23&"*",'Trial Balance (Susa)'!AJ:AJ)/1000-SUM($AP23:AP23) -> -8.77184 | AR23: =-SUMIF('Trial Balance (Susa)'!$D:$D,"*"&$CN23&"*",'Trial Balance (Susa)'!AK:AK)/1000-SUM($AP23:AQ23) -> -16.1505 | AS23: =-SUMIF('Trial Balance (Susa)'!$D:$D,"*"&$CN23&"*",'Trial Balance (Susa)'!AL:AL)/1000-SUM($AP23:AR23) -> -12.62275 | AT23: =-SUMIF('Trial Balance (Susa)'!$D:$D,"*"&$CN23&"*",'Trial Balance (Susa)'!AM:AM)/1000-SUM($AP23:AS23) -> -10.92641 | AU23: =-SUMIF('Trial Balance (Susa)'!$D:$D,"*"&$CN23&"*",'Trial Balance (Susa)'!AN:AN)/1000-SUM($AP23:AT23) -> -5.39061 | AV23: =-SUMIF('Trial Balance (Susa)'!$D:$D,"*"&$CN23&"*",'Trial Balance (Susa)'!AO:AO)/1000-SUM($AP23:AU23) -> -11.06676 | AW23: =-SUMIF('Trial Balance (Susa)'!$D:$D,"*"&$CN23&"*",'Trial Balance (Susa)'!AP:AP)/1000-SUM($AP23:AV23) -> -0.93763 | AX23: =-SUMIF('Trial Balance (Susa)'!$D:$D,"*"&$CN23&"*",'Trial Balance (Susa)'!AQ:AQ)/1000-SUM($AP23:AW23) -> -6.32019 | AY23: =-SUMIF('Trial Balance (Susa)'!$D:$D,"*"&$CN23&"*",'Trial Balance (Susa)'!AR:AR)/1000-SUM($AP23:AX23) -> -22.3189 | AZ23: =-SUMIF('Trial Balance (Susa)'!$D:$D,"*"&$CN23&"*",'Trial Balance (Susa)'!AS:AS)/1000-SUM($AP23:AY23) -> -7.35032 | BA23: =-SUMIF('Trial Balance (Susa)'!$D:$D,"*"&$CN23&"*",'Trial Balance (Susa)'!AT:AT)/1000-SUM($AP23:AZ23) -> -2.36549 | CN23: /profit and loss/expense/other expense/repair and maintenance
C24: ='Lead PL'!C33 -> Vertriebskosten | D24: ='Lead PL'!D33 -> Sales costs | R24: =-SUMIF('Trial Balance (Susa)'!$D:$D,"*"&$CN24&"*",'Trial Balance (Susa)'!K:K)/1000 -> 0 | S24: =-SUMIF('Trial Balance (Susa)'!$D:$D,"*"&$CN24&"*",'Trial Balance (Susa)'!L:L)/1000-R24 -> 0 | T24: =-SUMIF('Trial Balance (Susa)'!$D:$D,"*"&$CN24&"*",'Trial Balance (Susa)'!M:M)/1000-SUM($R24:S24) -> 0 | U24: =-SUMIF('Trial Balance (Susa)'!$D:$D,"*"&$CN24&"*",'Trial Balance (Susa)'!N:N)/1000-SUM($R24:T24) -> 0 | V24: =-SUMIF('Trial Balance (Susa)'!$D:$D,"*"&$CN24&"*",'Trial Balance (Susa)'!O:O)/1000-SUM($R24:U24) -> 0 | W24: =-SUMIF('Trial Balance (Susa)'!$D:$D,"*"&$CN24&"*",'Trial Balance (Susa)'!P:P)/1000-SUM($R24:V24) -> 0 | X24: =-SUMIF('Trial Balance (Susa)'!$D:$D,"*"&$CN24&"*",'Trial Balance (Susa)'!Q:Q)/1000-SUM($R24:W24) -> 0 | Y24: =-SUMIF('Trial Balance (Susa)'!$D:$D,"*"&$CN24&"*",'Trial Balance (Susa)'!R:R)/1000-SUM($R24:X24) -> 0 | Z24: =-SUMIF('Trial Balance (Susa)'!$D:$D,"*"&$CN24&"*",'Trial Balance (Susa)'!S:S)/1000-SUM($R24:Y24) -> 0 | AA24: =-SUMIF('Trial Balance (Susa)'!$D:$D,"*"&$CN24&"*",'Trial Balance (Susa)'!T:T)/1000-SUM($R24:Z24) -> 0 | AB24: =-SUMIF('Trial Balance (Susa)'!$D:$D,"*"&$CN24&"*",'Trial Balance (Susa)'!U:U)/1000-SUM($R24:AA24) -> 0 | AC24: =-SUMIF('Trial Balance (Susa)'!$D:$D,"*"&$CN24&"*",'Trial Balance (Susa)'!V:V)/1000-SUM($R24:AB24) -> 0 | AD24: =-SUMIF('Trial Balance (Susa)'!$D:$D,"*"&$CN24&"*",'Trial Balance (Susa)'!W:W)/1000 -> 0 | AE24: =-SUMIF('Trial Balance (Susa)'!$D:$D,"*"&$CN24&"*",'Trial Balance (Susa)'!X:X)/1000-SUM($AD24:AD24) -> 0 | AF24: =-SUMIF('Trial Balance (Susa)'!$D:$D,"*"&$CN24&"*",'Trial Balance (Susa)'!Y:Y)/1000-SUM($AD24:AE24) -> 0 | AG24: =-SUMIF('Trial Balance (Susa)'!$D:$D,"*"&$CN24&"*",'Trial Balance (Susa)'!Z:Z)/1000-SUM($AD24:AF24) -> 0 | AH24: =-SUMIF('Trial Balance (Susa)'!$D:$D,"*"&$CN24&"*",'Trial Balance (Susa)'!AA:AA)/1000-SUM($AD24:AG24) -> 0 | AI24: =-SUMIF('Trial Balance (Susa)'!$D:$D,"*"&$CN24&"*",'Trial Balance (Susa)'!AB:AB)/1000-SUM($AD24:AH24) -> 0 | AJ24: =-SUMIF('Trial Balance (Susa)'!$D:$D,"*"&$CN24&"*",'Trial Balance (Susa)'!AC:AC)/1000-SUM($AD24:AI24) -> 0 | AK24: =-SUMIF('Trial Balance (Susa)'!$D:$D,"*"&$CN24&"*",'Trial Balance (Susa)'!AD:AD)/1000-SUM($AD24:AJ24) -> 0 | AL24: =-SUMIF('Trial Balance (Susa)'!$D:$D,"*"&$CN24&"*",'Trial Balance (Susa)'!AE:AE)/1000-SUM($AD24:AK24) -> 0 | AM24: =-SUMIF('Trial Balance (Susa)'!$D:$D,"*"&$CN24&"*",'Trial Balance (Susa)'!AF:AF)/1000-SUM($AD24:AL24) -> 0 | AN24: =-SUMIF('Trial Balance (Susa)'!$D:$D,"*"&$CN24&"*",'Trial Balance (Susa)'!AG:AG)/1000-SUM($AD24:AM24) -> 0 | AO24: =-SUMIF('Trial Balance (Susa)'!$D:$D,"*"&$CN24&"*",'Trial Balance (Susa)'!AH:AH)/1000-SUM($AD24:AN24) -> 0 | AP24: =-SUMIF('Trial Balance (Susa)'!$D:$D,"*"&$CN24&"*",'Trial Balance (Susa)'!AI:AI)/1000 -> 0 | AQ24: =-SUMIF('Trial Balance (Susa)'!$D:$D,"*"&$CN24&"*",'Trial Balance (Susa)'!AJ:AJ)/1000-SUM($AP24:AP24) -> 0 | AR24: =-SUMIF('Trial Balance (Susa)'!$D:$D,"*"&$CN24&"*",'Trial Balance (Susa)'!AK:AK)/1000-SUM($AP24:AQ24) -> 0 | AS24: =-SUMIF('Trial Balance (Susa)'!$D:$D,"*"&$CN24&"*",'Trial Balance (Susa)'!AL:AL)/1000-SUM($AP24:AR24) -> 0 | AT24: =-SUMIF('Trial Balance (Susa)'!$D:$D,"*"&$CN24&"*",'Trial Balance (Susa)'!AM:AM)/1000-SUM($AP24:AS24) -> 0 | AU24: =-SUMIF('Trial Balance (Susa)'!$D:$D,"*"&$CN24&"*",'Trial Balance (Susa)'!AN:AN)/1000-SUM($AP24:AT24) -> 0 | AV24: =-SUMIF('Trial Balance (Susa)'!$D:$D,"*"&$CN24&"*",'Trial Balance (Susa)'!AO:AO)/1000-SUM($AP24:AU24) -> 0 | AW24: =-SUMIF('Trial Balance (Susa)'!$D:$D,"*"&$CN24&"*",'Trial Balance (Susa)'!AP:AP)/1000-SUM($AP24:AV24) -> 0 | AX24: =-SUMIF('Trial Balance (Susa)'!$D:$D,"*"&$CN24&"*",'Trial Balance (Susa)'!AQ:AQ)/1000-SUM($AP24:AW24) -> 0 | AY24: =-SUMIF('Trial Balance (Susa)'!$D:$D,"*"&$CN24&"*",'Trial Balance (Susa)'!AR:AR)/1000-SUM($AP24:AX24) -> 0 | AZ24: =-SUMIF('Trial Balance (Susa)'!$D:$D,"*"&$CN24&"*",'Trial Balance (Susa)'!AS:AS)/1000-SUM($AP24:AY24) -> 0 | BA24: =-SUMIF('Trial Balance (Susa)'!$D:$D,"*"&$CN24&"*",'Trial Balance (Susa)'!AT:AT)/1000-SUM($AP24:AZ24) -> 0 | CN24: /profit and loss/expense/other expense/sales costs
C25: ='Lead PL'!C34 -> Kosten der Warenabgabe | D25: ='Lead PL'!D34 -> Delivery costs | R25: =-SUMIF('Trial Balance (Susa)'!$D:$D,"*"&$CN25&"*",'Trial Balance (Susa)'!K:K)/1000 -> -25.05148 | S25: =-SUMIF('Trial Balance (Susa)'!$D:$D,"*"&$CN25&"*",'Trial Balance (Susa)'!L:L)/1000-R25 -> -25.84616 | T25: =-SUMIF('Trial Balance (Susa)'!$D:$D,"*"&$CN25&"*",'Trial Balance (Susa)'!M:M)/1000-SUM($R25:S25) -> -25.53212 | U25: =-SUMIF('Trial Balance (Susa)'!$D:$D,"*"&$CN25&"*",'Trial Balance (Susa)'!N:N)/1000-SUM($R25:T25) -> -32.32235 | V25: =-SUMIF('Trial Balance (Susa)'!$D:$D,"*"&$CN25&"*",'Trial Balance (Susa)'!O:O)/1000-SUM($R25:U25) -> -18.07578 | W25: =-SUMIF('Trial Balance (Susa)'!$D:$D,"*"&$CN25&"*",'Trial Balance (Susa)'!P:P)/1000-SUM($R25:V25) -> -29.25595 | X25: =-SUMIF('Trial Balance (Susa)'!$D:$D,"*"&$CN25&"*",'Trial Balance (Susa)'!Q:Q)/1000-SUM($R25:W25) -> -26.16698 | Y25: =-SUMIF('Trial Balance (Susa)'!$D:$D,"*"&$CN25&"*",'Trial Balance (Susa)'!R:R)/1000-SUM($R25:X25) -> -30.84593 | Z25: =-SUMIF('Trial Balance (Susa)'!$D:$D,"*"&$CN25&"*",'Trial Balance (Susa)'!S:S)/1000-SUM($R25:Y25) -> -26.32689 | AA25: =-SUMIF('Trial Balance (Susa)'!$D:$D,"*"&$CN25&"*",'Trial Balance (Susa)'!T:T)/1000-SUM($R25:Z25) -> -92.22927 | AB25: =-SUMIF('Trial Balance (Susa)'!$D:$D,"*"&$CN25&"*",'Trial Balance (Susa)'!U:U)/1000-SUM($R25:AA25) -> -26.16788 | AC25: =-SUMIF('Trial Balance (Susa)'!$D:$D,"*"&$CN25&"*",'Trial Balance (Susa)'!V:V)/1000-SUM($R25:AB25) -> 72.39298 | AD25: =-SUMIF('Trial Balance (Susa)'!$D:$D,"*"&$CN25&"*",'Trial Balance (Susa)'!W:W)/1000 -> -21.16626 | AE25: =-SUMIF('Trial Balance (Susa)'!$D:$D,"*"&$CN25&"*",'Trial Balance (Susa)'!X:X)/1000-SUM($AD25:AD25) -> -25.22316 | AF25: =-SUMIF('Trial Balance (Susa)'!$D:$D,"*"&$CN25&"*",'Trial Balance (Susa)'!Y:Y)/1000-SUM($AD25:AE25) -> -27.5588 | AG25: =-SUMIF('Trial Balance (Susa)'!$D:$D,"*"&$CN25&"*",'Trial Balance (Susa)'!Z:Z)/1000-SUM($AD25:AF25) -> -24.66354 | AH25: =-SUMIF('Trial Balance (Susa)'!$D:$D,"*"&$CN25&"*",'Trial Balance (Susa)'!AA:AA)/1000-SUM($AD25:AG25) -> -25.54879 | AI25: =-SUMIF('Trial Balance (Susa)'!$D:$D,"*"&$CN25&"*",'Trial Balance (Susa)'!AB:AB)/1000-SUM($AD25:AH25) -> -25.39537 | AJ25: =-SUMIF('Trial Balance (Susa)'!$D:$D,"*"&$CN25&"*",'Trial Balance (Susa)'!AC:AC)/1000-SUM($AD25:AI25) -> -22.78573 | AK25: =-SUMIF('Trial Balance (Susa)'!$D:$D,"*"&$CN25&"*",'Trial Balance (Susa)'!AD:AD)/1000-SUM($AD25:AJ25) -> -23.34709 | AL25: =-SUMIF('Trial Balance (Susa)'!$D:$D,"*"&$CN25&"*",'Trial Balance (Susa)'!AE:AE)/1000-SUM($AD25:AK25) -> -26.19711 | AM25: =-SUMIF('Trial Balance (Susa)'!$D:$D,"*"&$CN25&"*",'Trial Balance (Susa)'!AF:AF)/1000-SUM($AD25:AL25) -> -29.00054 | AN25: =-SUMIF('Trial Balance (Susa)'!$D:$D,"*"&$CN25&"*",'Trial Balance (Susa)'!AG:AG)/1000-SUM($AD25:AM25) -> -25.26801 | AO25: =-SUMIF('Trial Balance (Susa)'!$D:$D,"*"&$CN25&"*",'Trial Balance (Susa)'!AH:AH)/1000-SUM($AD25:AN25) -> -25.22903 | AP25: =-SUMIF('Trial Balance (Susa)'!$D:$D,"*"&$CN25&"*",'Trial Balance (Susa)'!AI:AI)/1000 -> -28.31583 | AQ25: =-SUMIF('Trial Balance (Susa)'!$D:$D,"*"&$CN25&"*",'Trial Balance (Susa)'!AJ:AJ)/1000-SUM($AP25:AP25) -> -33.93054 | AR25: =-SUMIF('Trial Balance (Susa)'!$D:$D,"*"&$CN25&"*",'Trial Balance (Susa)'!AK:AK)/1000-SUM($AP25:AQ25) -> -36.18775 | AS25: =-SUMIF('Trial Balance (Susa)'!$D:$D,"*"&$CN25&"*",'Trial Balance (Susa)'!AL:AL)/1000-SUM($AP25:AR25) -> -30.88778 | AT25: =-SUMIF('Trial Balance (Susa)'!$D:$D,"*"&$CN25&"*",'Trial Balance (Susa)'!AM:AM)/1000-SUM($AP25:AS25) -> -35.15344 | AU25: =-SUMIF('Trial Balance (Susa)'!$D:$D,"*"&$CN25&"*",'Trial Balance (Susa)'!AN:AN)/1000-SUM($AP25:AT25) -> -27.58053 | AV25: =-SUMIF('Trial Balance (Susa)'!$D:$D,"*"&$CN25&"*",'Trial Balance (Susa)'!AO:AO)/1000-SUM($AP25:AU25) -> -25.76325 | AW25: =-SUMIF('Trial Balance (Susa)'!$D:$D,"*"&$CN25&"*",'Trial Balance (Susa)'!AP:AP)/1000-SUM($AP25:AV25) -> -28.22268 | AX25: =-SUMIF('Trial Balance (Susa)'!$D:$D,"*"&$CN25&"*",'Trial Balance (Susa)'!AQ:AQ)/1000-SUM($AP25:AW25) -> -25.38254 | AY25: =-SUMIF('Trial Balance (Susa)'!$D:$D,"*"&$CN25&"*",'Trial Balance (Susa)'!AR:AR)/1000-SUM($AP25:AX25) -> -29.76069 | AZ25: =-SUMIF('Trial Balance (Susa)'!$D:$D,"*"&$CN25&"*",'Trial Balance (Susa)'!AS:AS)/1000-SUM($AP25:AY25) -> -25.20366 | BA25: =-SUMIF('Trial Balance (Susa)'!$D:$D,"*"&$CN25&"*",'Trial Balance (Susa)'!AT:AT)/1000-SUM($AP25:AZ25) -> -29.19915 | CN25: /profit and loss/expense/other expense/delivery costs
